Workbook

Sheet Summary
A1: SAI LIFE SCIENCES LIMITED | Integrated Three-Statement Model | FY2024A - FY2035E
A2: All figures in INR million unless stated (Rs 1 crore = Rs 10 million). Fiscal year ends 31 March. FY2024A-FY2026A = reported consolidated Ind AS. FY2027E-FY2035E = analyst estimates. Single base case. BLUE = hardcoded input BLACK = formula GREEN = cross-sheet link.
A5: QUARTERLY UPDATE CHECKLIST (everything below lives on the Revenue_Model sheet in blue cells)
A6: 1. Segment revenue. Roll reported CRO and CDMO revenue in section A forward one year. Both come straight off page 21 and page 24 of the quarterly investor deck.
A7: 2. DRIVERS 1 and 2 - CRO. Net billable FTE additions, and revenue per FTE growth. Then glance at the implied USD rate per FTE underneath; if it leaves the USD 55-90k band, one of the two is wrong.
A8: 3. DRIVERS 3 and 4 - commercial CDMO. Net new commercial molecules (the deck gives the count directly), and growth in revenue per commercial molecule. Remember driver 4 embeds the dilution from newly qualified molecules, which earn far less in year one than the portfolio average.
A9: 4. DRIVER 5 - development CDMO. A single growth rate covering pre-clinical through Phase III, validation, process R&D and tech transfer. Sanity-check it against the disclosed programme counts in section F.
A10: 5. DRIVER 6 - capacity. KL commissioned in the year. Then check the revenue-per-effective-KL flag; if it reads REVIEW, the model is forecasting output the plant cannot make.
A11: 6. Costs and capex sit on the Schedules sheet. Update the capex plan, the CDMO material ratio, wage growth and headcount additions from the call. Everything else flows.
A12: 7. Finish on the Sources_Checks sheet. The master check must read ALL CHECKS OK before you circulate anything.
A15: KEY FINANCIAL SUMMARY
B16: INR mn | C16: FY2024A | D16: FY2025A | E16: FY2026A | F16: FY2027E | G16: FY2028E | H16: FY2029E | I16: FY2030E | J16: FY2031E | K16: FY2032E | L16: FY2033E | M16: FY2034E | N16: FY2035E | P16: Source / basis
A17: Revenue from operations | B17: INR mn | C17: =Statements!C6 -> 14651.78 | D17: =Statements!D6 -> 16945.7 | E17: =Statements!E6 -> 21924.92 | F17: =Statements!F6 -> 25155.942 | G17: =Statements!G6 -> 28557.44 | H17: =Statements!H6 -> 32501.745 | I17: =Statements!I6 -> 36659.531 | J17: =Statements!J6 -> 41035.764 | ... N17: =Statements!N6 -> 62332.848
A18: Revenue growth (%) | B18: % | D18: =D17/C17-1 -> 0.15656255 | E18: =E17/D17-1 -> 0.29383383 | F18: =F17/E17-1 -> 0.14736755 | G18: =G17/F17-1 -> 0.13521648 | H18: =H17/G17-1 -> 0.13811832 | I18: =I17/H17-1 -> 0.12792501 | J18: =J17/I17-1 -> 0.11937505 | K18: =K17/J17-1 -> 0.121102 | ... N18: =N17/M17-1 -> 0.099548835
A19: CRO / Discovery revenue | B19: INR mn | C19: =Revenue_Model!C17 -> 4970 | D19: =Revenue_Model!D17 -> 6260 | E19: =Revenue_Model!E17 -> 7750 | F19: =Revenue_Model!F17 -> 8900.6064 | G19: =Revenue_Model!G17 -> 10058.487 | H19: =Revenue_Model!H17 -> 11261.4 | I19: =Revenue_Model!I17 -> 12449.618 | J19: =Revenue_Model!J17 -> 13635.75 | ... N19: =Revenue_Model!N17 -> 18008.098
A20: CDMO / CMC revenue | B20: INR mn | C20: =Revenue_Model!C39 -> 9680 | D20: =Revenue_Model!D39 -> 10680 | E20: =Revenue_Model!E39 -> 14170 | F20: =Revenue_Model!F39 -> 16255.335 | G20: =Revenue_Model!G39 -> 18498.952 | H20: =Revenue_Model!H39 -> 21240.345 | I20: =Revenue_Model!I39 -> 24209.913 | J20: =Revenue_Model!J39 -> 27400.015 | ... N20: =Revenue_Model!N39 -> 44324.749
A21: CRO mix (%) | B21: % | C21: =C19/C17 -> 0.33920793 | D21: =D19/D17 -> 0.36941525 | E21: =E19/E17 -> 0.35347905 | F21: =F19/F17 -> 0.35381726 | G21: =G19/G17 -> 0.3522195 | H21: =H19/H17 -> 0.34648601 | I21: =I19/I17 -> 0.33960112 | J21: =J19/J17 -> 0.3322894 | ... N21: =N19/N17 -> 0.28890223
A22: CDMO mix (%) | B22: % | C22: =C20/C17 -> 0.66067058 | D22: =D20/D17 -> 0.63024838 | E22: =E20/E17 -> 0.64629654 | F22: =F20/F17 -> 0.64618274 | G22: =G20/G17 -> 0.6477805 | H22: =H20/H17 -> 0.65351399 | I22: =I20/I17 -> 0.66039888 | J22: =J20/J17 -> 0.6677106 | ... N22: =N20/N17 -> 0.71109777
A23: Material margin (%) | B23: % | C23: =Statements!C9 -> 0.6957844 | D23: =Statements!D9 -> 0.72514325 | E23: =Statements!E9 -> 0.73961501 | F23: =Statements!F9 -> 0.73260701 | G23: =Statements!G9 -> 0.73538256 | H23: =Statements!H9 -> 0.73701608 | I23: =Statements!I9 -> 0.73640911 | J23: =Statements!J9 -> 0.73571187 | ... N23: =Statements!N9 -> 0.72658141
A24: EBITDA | B24: INR mn | C24: =Statements!C13 -> 3001.15 | D24: =Statements!D13 -> 4247.37 | E24: =Statements!E13 -> 6611.77 | F24: =Statements!F13 -> 6733.4559 | G24: =Statements!G13 -> 7497.83 | H24: =Statements!H13 -> 8572.4128 | I24: =Statements!I13 -> 9686.0861 | J24: =Statements!J13 -> 10861.099 | ... N24: =Statements!N13 -> 16921.48
A25: EBITDA margin (%) | B25: % | C25: =Statements!C14 -> 0.20483177 | D25: =Statements!D14 -> 0.25064589 | E25: =Statements!E14 -> 0.30156416 | F25: =Statements!F14 -> 0.26766861 | G25: =Statements!G14 -> 0.2625526 | H25: =Statements!H14 -> 0.26375239 | I25: =Statements!I14 -> 0.2642174 | J25: =Statements!J14 -> 0.26467398 | ... N25: =Statements!N14 -> 0.27146971
A26: EBIT | B26: INR mn | C26: =Statements!C16 -> 1806.79 | D26: =Statements!D16 -> 2861.64 | E26: =Statements!E16 -> 4943.22 | F26: =Statements!F16 -> 4322.2061 | G26: =Statements!G16 -> 4322.3286 | H26: =Statements!H16 -> 4804.1125 | I26: =Statements!I16 -> 5515.7981 | J26: =Statements!J16 -> 6347.0032 | ... N26: =Statements!N16 -> 11195.364
A27: Profit after tax | B27: INR mn | C27: =Statements!C26 -> 828.09 | D27: =Statements!D26 -> 1701.32 | E27: =Statements!E26 -> 3489.1 | F27: =Statements!F26 -> 3060.1782 | G27: =Statements!G26 -> 2642.015 | H27: =Statements!H26 -> 2709.0214 | I27: =Statements!I26 -> 3105.3765 | J27: =Statements!J26 -> 3628.3951 | ... N27: =Statements!N26 -> 7422.383
A28: PAT margin (%) | B28: % | C28: =Statements!C27 -> 0.056518048 | D28: =Statements!D27 -> 0.10039833 | E28: =Statements!E27 -> 0.15913855 | F28: =Statements!F27 -> 0.12164832 | G28: =Statements!G27 -> 0.092515823 | H28: =Statements!H27 -> 0.083350028 | I28: =Statements!I27 -> 0.084708571 | J28: =Statements!J27 -> 0.088420314 | ... N28: =Statements!N27 -> 0.11907659
A29: Diluted EPS | B29: INR | C29: =Statements!C30 -> 4.5300328 | D29: =Statements!D30 -> 8.609919 | E29: =Statements!E30 -> 16.430119 | F29: =Statements!F30 -> 14.275882 | G29: =Statements!G30 -> 12.211199 | H29: =Statements!H30 -> 12.406216 | I29: =Statements!I30 -> 14.092287 | J29: =Statements!J30 -> 16.317661 | ... N29: =Statements!N30 -> 32.220798
A30: EPS growth (%) | B30: % | D30: =D29/C29-1 -> 0.90063061 | E30: =E29/D29-1 -> 0.90827795 | F30: =F29/E29-1 -> -0.13111507 | G30: =G29/F29-1 -> -0.14462738 | H30: =H29/G29-1 -> 0.015970351 | I30: =I29/H29-1 -> 0.13590537 | J30: =J29/I29-1 -> 0.1579143 | K30: =K29/J29-1 -> 0.21100402 | ... N30: =N29/M29-1 -> 0.17690435
A31: Capex | B31: INR mn | C31: =Schedules!C52 -> 1816.9 | D31: =Schedules!D52 -> 3692.8 | E31: =Schedules!E52 -> 5929.61 | F31: =Schedules!F52 -> 12000 | G31: =Schedules!G52 -> 8500 | H31: =Schedules!H52 -> 7000 | I31: =Schedules!I52 -> 7500 | J31: =Schedules!J52 -> 7000 | ... N31: =Schedules!N52 -> 7500
A32: Capex (% of revenue) | B32: % | C32: =Schedules!C53 -> 0.12400541 | D32: =Schedules!D53 -> 0.21791959 | E32: =Schedules!E53 -> 0.2704507 | F32: =Schedules!F53 -> 0.47702448 | G32: =Schedules!G53 -> 0.29764573 | H32: =Schedules!H53 -> 0.21537305 | I32: =Schedules!I53 -> 0.20458527 | J32: =Schedules!J53 -> 0.17058291 | ... N32: =Schedules!N53 -> 0.12032179
A33: Cash flow from operations | B33: INR mn | C33: =Statements!C80 -> 2630.87 | D33: =Statements!D80 -> 3140.45 | E33: =Statements!E80 -> 5091.33 | F33: =Statements!F80 -> 5755.271 | G33: =Statements!G80 -> 4908.9222 | H33: =Statements!H80 -> 6379.7585 | I33: =Statements!I80 -> 7729.0276 | J33: =Statements!J80 -> 8510.7345 | ... N33: =Statements!N80 -> 12973.793
A34: Free cash flow (CFO less capex) | B34: INR mn | C34: =Statements!C106 -> 813.97 | D34: =Statements!D106 -> -552.35 | E34: =Statements!E106 -> -838.28 | F34: =Statements!F106 -> -6244.729 | G34: =Statements!G106 -> -3591.0778 | H34: =Statements!H106 -> -620.24153 | I34: =Statements!I106 -> 229.02761 | J34: =Statements!J106 -> 1510.7345 | ... N34: =Statements!N106 -> 5473.7932
A35: Net debt / (net cash) | B35: INR mn | C35: =Schedules!C138 -> 5513.63 | D35: =Schedules!D138 -> -3352.46 | E35: =Schedules!E138 -> -627.38 | F35: =Schedules!F138 -> 6188.9163 | G35: =Schedules!G138 -> 10860.339 | H35: =Schedules!H138 -> 12926.281 | I35: =Schedules!I138 -> 14317.128 | J35: =Schedules!J138 -> 14566.022 | ... N35: =Schedules!N138 -> 6539.6827
A36: Net debt / EBITDA | B36: x | C36: =Schedules!C139 -> 1.8371724 | D36: =Schedules!D139 -> -0.78930256 | E36: =Schedules!E139 -> -0.094888358 | F36: =Schedules!F139 -> 0.91912926 | G36: =Schedules!G139 -> 1.4484643 | H36: =Schedules!H139 -> 1.5078929 | I36: =Schedules!I139 -> 1.4781129 | J36: =Schedules!J139 -> 1.3411186 | ... N36: =Schedules!N139 -> 0.38647226
A37: ROCE (%) | B37: % | D37: =Statements!D107 -> 0.14517628 | E37: =Statements!E107 -> 0.20444257 | F37: =Statements!F107 -> 0.14003124 | G37: =Statements!G107 -> 0.1086802 | H37: =Statements!H107 -> 0.10405787 | I37: =Statements!I107 -> 0.10778728 | J37: =Statements!J107 -> 0.11386566 | K37: =Statements!K107 -> 0.12456335 | ... N37: =Statements!N107 -> 0.15346056
A38: ROE (%) | B38: % | D38: =Statements!D108 -> 0.10963887 | E38: =Statements!E108 -> 0.15130391 | F38: =Statements!F108 -> 0.11566624 | G38: =Statements!G108 -> 0.089593039 | H38: =Statements!H108 -> 0.083747255 | I38: =Statements!I108 -> 0.087624027 | J38: =Statements!J108 -> 0.093050879 | K38: =Statements!K108 -> 0.10259547 | ... N38: =Statements!N108 -> 0.12112921
A40: KEY OPERATING ASSUMPTIONS
A41: Billable discovery FTEs | B41: count | C41: =Revenue_Model!C13 -> 1127 | D41: =Revenue_Model!D13 -> 1161 | E41: =Revenue_Model!E13 -> 1313 | F41: =Revenue_Model!F13 -> 1443 | G41: =Revenue_Model!G13 -> 1568 | H41: =Revenue_Model!H13 -> 1688 | I41: =Revenue_Model!I13 -> 1803 | J41: =Revenue_Model!J13 -> 1908 | ... N41: =Revenue_Model!N13 -> 2228
A42: Revenue per billable discovery FTE | B42: INR mn | C42: =Revenue_Model!C15 -> 4.4099379 | D42: =Revenue_Model!D15 -> 5.3919035 | E42: =Revenue_Model!E15 -> 5.9025133 | F42: =Revenue_Model!F15 -> 6.1681264 | G42: =Revenue_Model!G15 -> 6.4148515 | H42: =Revenue_Model!H15 -> 6.6714455 | I42: =Revenue_Model!I15 -> 6.9049461 | J42: =Revenue_Model!J15 -> 7.1466193 | ... N42: =Revenue_Model!N15 -> 8.0826295
A43: Installed GMP capacity | B43: KL | C43: =Revenue_Model!C46 -> 475 | D43: =Revenue_Model!D46 -> 609 | E43: =Revenue_Model!E46 -> 700 | F43: =Revenue_Model!F46 -> 925 | G43: =Revenue_Model!G46 -> 1150 | H43: =Revenue_Model!H46 -> 1250 | I43: =Revenue_Model!I46 -> 1400 | J43: =Revenue_Model!J46 -> 1500 | ... N43: =Revenue_Model!N46 -> 2100
A44: Effective revenue-generating capacity | B44: KL | C44: =Revenue_Model!C47 -> 475 | D44: =Revenue_Model!D47 -> 515.2 | E44: =Revenue_Model!E47 -> 636.3 | F44: =Revenue_Model!F47 -> 767.5 | G44: =Revenue_Model!G47 -> 992.5 | H44: =Revenue_Model!H47 -> 1180 | I44: =Revenue_Model!I47 -> 1295 | J44: =Revenue_Model!J47 -> 1430 | ... N44: =Revenue_Model!N47 -> 2030
A45: Total employees | B45: count | C45: =Schedules!C10 -> 3345 | D45: =Schedules!D10 -> 3401 | E45: =Schedules!E10 -> 3800 | F45: =Schedules!F10 -> 4120 | G45: =Schedules!G10 -> 4420 | H45: =Schedules!H10 -> 4700 | I45: =Schedules!I10 -> 4960 | J45: =Schedules!J10 -> 5200 | ... N45: =Schedules!N10 -> 5960
A46: Revenue per employee | B46: INR mn | C46: =Schedules!C91 -> 4.3802033 | D46: =Schedules!D91 -> 4.982564 | E46: =Schedules!E91 -> 5.7697158 | F46: =Schedules!F91 -> 6.1058111 | G46: =Schedules!G91 -> 6.4609592 | H46: =Schedules!H91 -> 6.9152649 | I46: =Schedules!I91 -> 7.3910345 | J46: =Schedules!J91 -> 7.8914931 | ... N46: =Schedules!N91 -> 10.458531
A47: Fixed asset turnover (net PP&E + CWIP) | B47: x | C47: =Schedules!C92 -> 1.4180286 | D47: =Schedules!D92 -> 1.2940904 | E47: =Schedules!E92 -> 1.2147665 | F47: =Schedules!F92 -> 0.90312032 | G47: =Schedules!G92 -> 0.85266253 | H47: =Schedules!H92 -> 0.87655498 | I47: =Schedules!I92 -> 0.89927658 | J47: =Schedules!J92 -> 0.94036406 | ... N47: =Schedules!N92 -> 1.14713
A48: Net working capital days | B48: days | C48: =Schedules!C114 -> 124.62003 | D48: =Schedules!D114 -> 103.47414 | E48: =Schedules!E114 -> 96.333549 | F48: =Schedules!F114 -> 84.640036 | G48: =Schedules!G114 -> 96.888311 | H48: =Schedules!H114 -> 100.36673 | I48: =Schedules!I114 -> 98.926189 | J48: =Schedules!J114 -> 99.356686 | ... N48: =Schedules!N114 -> 99.806103
A50: KEY MOLECULE AND PIPELINE ASSUMPTIONS
A51: Commercial molecules | B51: count | C51: =Revenue_Model!C31 -> 26 | D51: =Revenue_Model!D31 -> 30 | E51: =Revenue_Model!E31 -> 34 | F51: =Revenue_Model!F31 -> 36 | G51: =Revenue_Model!G31 -> 38 | H51: =Revenue_Model!H31 -> 41 | I51: =Revenue_Model!I31 -> 44 | J51: =Revenue_Model!J31 -> 47 | ... N51: =Revenue_Model!N31 -> 63
A52: Phase III / pre-registration molecules (disclosed, history) | B52: count | C52: =Revenue_Model!C67 -> 5 | D52: =Revenue_Model!D67 -> 6 | E52: =Revenue_Model!E67 -> 11
A53: Top-4 identified commercial molecules - revenue | B53: INR mn | C53: =Revenue_Model!C64 -> 2292 | D53: =Revenue_Model!D64 -> 2412 | E53: =Revenue_Model!E64 -> 3308 | F53: =Revenue_Model!F64 -> 3835.3341 | G53: =Revenue_Model!G64 -> 4412.765 | H53: =Revenue_Model!H64 -> 5165.8382 | I53: =Revenue_Model!I64 -> 5987.3324 | J53: =Revenue_Model!J64 -> 6875.2266 | ... N53: =Revenue_Model!N64 -> 11911.124
A54: Top-4 as % of CDMO revenue | B54: % | C54: =Revenue_Model!C65 -> 0.23677686 | D54: =Revenue_Model!D65 -> 0.2258427 | E54: =Revenue_Model!E65 -> 0.23345095 | F54: =Revenue_Model!F65 -> 0.23594309 | G54: =Revenue_Model!G65 -> 0.23854134 | H54: =Revenue_Model!H65 -> 0.24320877 | I54: =Revenue_Model!I65 -> 0.24730912 | J54: =Revenue_Model!J65 -> 0.25092054 | ... N54: =Revenue_Model!N65 -> 0.268724
A55: Commercial manufacturing revenue | B55: INR mn | C55: =Revenue_Model!C34 -> 5730 | D55: =Revenue_Model!D34 -> 6030 | E55: =Revenue_Model!E34 -> 8270 | F55: =Revenue_Model!F34 -> 9588.3353 | G55: =Revenue_Model!G34 -> 11031.912 | H55: =Revenue_Model!H34 -> 12914.595 | I55: =Revenue_Model!I34 -> 14968.331 | J55: =Revenue_Model!J34 -> 17188.067 | ... N55: =Revenue_Model!N34 -> 29777.809
A56: Revenue per commercial molecule | B56: INR mn | C56: =Revenue_Model!C33 -> 220.38462 | D56: =Revenue_Model!D33 -> 201 | E56: =Revenue_Model!E33 -> 243.23529 | F56: =Revenue_Model!F33 -> 266.34265 | G56: =Revenue_Model!G33 -> 290.31349 | H56: =Revenue_Model!H33 -> 314.99013 | I56: =Revenue_Model!I33 -> 340.18934 | J56: =Revenue_Model!J33 -> 365.70354 | ... N56: =Revenue_Model!N33 -> 472.66364
A57: Development revenue | B57: INR mn | C57: =Revenue_Model!C37 -> 3950 | D57: =Revenue_Model!D37 -> 4650 | E57: =Revenue_Model!E37 -> 5900 | F57: =Revenue_Model!F37 -> 6667 | G57: =Revenue_Model!G37 -> 7467.04 | H57: =Revenue_Model!H37 -> 8325.7496 | I57: =Revenue_Model!I37 -> 9241.5821 | J57: =Revenue_Model!J37 -> 10211.948 | ... N57: =Revenue_Model!N37 -> 14546.94
A59: HISTORICAL AND FORECAST CAGRs
A60: Period | C60: Revenue | D60: CRO | E60: CDMO | F60: EBITDA | G60: PAT | H60: EPS
A61: FY2024A - FY2026A (historical, 2 years) | C61: =(E17/C17)^(1/2)-1 -> 0.22327419 | D61: =(E19/C19)^(1/2)-1 -> 0.24874182 | E61: =(E20/C20)^(1/2)-1 -> 0.20989379 | F61: =(E24/C24)^(1/2)-1 -> 0.4842772 | G61: =(E27/C27)^(1/2)-1 -> 1.0526643 | H61: =(E29/C29)^(1/2)-1 -> 0.90445044
A62: FY2025A - FY2030E (guidance window, 5 years) | C62: =(I17/D17)^(1/5)-1 -> 0.16687807 | D62: =(I19/D19)^(1/5)-1 -> 0.14740394 | E62: =(I20/D20)^(1/5)-1 -> 0.17783484 | F62: =(I24/D24)^(1/5)-1 -> 0.17924935 | G62: =(I27/D27)^(1/5)-1 -> 0.12788715 | H62: =(I29/D29)^(1/5)-1 -> 0.10356136
A63: FY2026A - FY2031E (5 years) | C63: =(J17/E17)^(1/5)-1 -> 0.13356102 | D63: =(J19/E19)^(1/5)-1 -> 0.11963241 | E63: =(J20/E20)^(1/5)-1 -> 0.14097516 | F63: =(J24/E24)^(1/5)-1 -> 0.10436137 | G63: =(J27/E27)^(1/5)-1 -> 0.0078600532 | H63: =(J29/E29)^(1/5)-1 -> -0.0013726816
A64: FY2026A - FY2035E (full forecast, 9 years) | C64: =(N17/E17)^(1/9)-1 -> 0.12310377 | D64: =(N19/E19)^(1/9)-1 -> 0.098209328 | E64: =(N20/E20)^(1/9)-1 -> 0.13509109 | F64: =(N24/E24)^(1/9)-1 -> 0.11006072 | G64: =(N27/E27)^(1/9)-1 -> 0.087490695 | H64: =(N29/E29)^(1/9)-1 -> 0.077704038
A66: MAJOR MODEL CONCLUSIONS
A67: 1. REVENUE. The bottom-up build produces an FY2025-FY2030 revenue CAGR of about 17%, inside management's stated 15-20% window, and about 13% across the full FY2026-FY2035 forecast as the base scales. FY2027 growth of roughly 14% is deliberately below the 29% delivered in FY2026, because the first 225 KL of new capacity only lands in H2 and management has guided that H2 FY2027 will be stronger than H1.
A68: 2. MARGIN. The model produces an EBITDA margin of 26.6% in FY2027 rising to about 28% by FY2035, below the 28-30% guidance through the investment years. This is a deliberate analyst position, not a modelling artefact. FY2026's reported 30.2% was flattered by two items assumed not to repeat: a net credit-loss REVERSAL of Rs 239mn (worth 110bp) and an FX gain of Rs 300mn (140bp). On a clean basis FY2026 was roughly 27.7%, and the model grows modestly from there.
A69: 3. FY2027-FY2028 IS AN INVESTMENT TROUGH, NOT A BREAK IN THE STORY. EPS falls from Rs 16.4 in FY2026 to Rs 14.0 and then Rs 12.0, and does not regain the FY2026 level until FY2031. Capex more than doubles to Rs 1,200 Cr, depreciation and interest step up, and site overhead is carried before the revenue arrives. ROCE dips from 20% to around 11% before recovering to the mid-teens.
A70: 4. GROWTH IS CAPACITY-GATED THROUGH FY2028. Installed capacity runs 700 to 925 to 1,150 KL, and the model explicitly phases each block through qualification, customer audit and validation rather than treating the commissioning date as the revenue start date. Commercial revenue per effective KL therefore FALLS in FY2027 and FY2028 - that under-absorption is the margin story.
A71: 5. FUNDING IS COMFORTABLE. Free cash flow is negative for three years and cumulative FY2027-FY2029 outflow is roughly Rs 10,600mn, funded by incremental debt. Net debt to EBITDA peaks at about 1.5x in FY2029 and de-levers thereafter. This is consistent with management's comment that the ratio would remain 'fairly healthy'.
A72: 6. THE BALANCE SHEET RISK IS CONTRACT ASSETS, NOT LEVERAGE. Unbilled revenue runs at roughly 100 days of sales and is the largest single working capital item. FY2025 already required a Rs 347mn loss allowance against doubtful contract assets. Ten days of deterioration is worth roughly Rs 700mn of cash at FY2027 revenue.
A73: 7. CRO HAS LITTLE OPERATING LEVERAGE BY CONSTRUCTION. It is an FTE business: cutting headcount cuts CRO revenue close to one-for-one, so margin expansion in this model comes almost entirely from CDMO scale and mix, not from the discovery business.
A74: 8. MOLECULE ECONOMICS ARE THE WEAKEST EVIDENCED LAYER. Sai discloses neither molecule names nor customers and management explicitly declined to on the Q4FY26 call. The model therefore does not attempt a bottom-up molecule build; top-4 concentration is carried as a single memo line at 40% of commercial revenue. Treat it as illustrative, not as identified revenue.
A75: 9. HOW THE REVENUE MODEL IS BUILT. Six drivers, base case only. CRO is billable FTEs times revenue per FTE. CDMO is commercial molecules times revenue per molecule, plus a single development growth rate. Capacity is a cross-check, not a driver. Everything a quarterly update needs sits in six blue rows on the Revenue_Model sheet.

Sheet Revenue_Model
A1: SHEET 2 | REVENUE MODEL
A2: SIX forecast drivers, all in blue. CRO = billable FTEs x revenue per FTE. CDMO = commercial molecules x revenue per molecule, plus development revenue. Capacity is a cross-check, not a driver. Single base case.
B3: INR mn | C3: FY2024A | D3: FY2025A | E3: FY2026A | F3: FY2027E | G3: FY2028E | H3: FY2029E | I3: FY2030E | J3: FY2031E | K3: FY2032E | L3: FY2033E | M3: FY2034E | N3: FY2035E | P3: Source / basis
A5: A. REPORTED SEGMENT REVENUE (anchor - refresh from the quarterly deck)
A6: CRO / Discovery Services - reported | B6: INR mn | C6: 4970 | D6: 6260 | E6: 7750 | P6: Q4FY26 investor presentation p.21 - Discovery revenue FY22-FY26 (Rs Cr x 10). REPORTED FACT.
A7: CDMO / CMC Services - reported | B7: INR mn | C7: 9680 | D7: 10680 | E7: 14170 | P7: Q4FY26 investor presentation p.24 - CMC revenue FY22-FY26 (Rs Cr x 10). REPORTED FACT.
A8: Revenue from operations - audited | B8: INR mn | C8: 14651.78 | D8: 16945.7 | E8: 21924.92 | P8: FY25 Annual Report p.179 (FY24 & FY25); audited FY26 consolidated results filed 14-May-2026. REPORTED FACT.
A9: Rounding on segment disclosure (Rs Cr granularity) | B9: INR mn | C9: =C8-C6-C7 -> 1.78 | D9: =D8-D6-D7 -> 5.7 | E9: =E8-E6-E7 -> 4.92 | P9: Segments are disclosed in Rs Cr only; the residual is carried so the build ties exactly to audited revenue.
A11: B. CRO / DISCOVERY = BILLABLE FTEs x REVENUE PER FTE [ DRIVERS 1 and 2 ]
A12: DRIVER 1 Net billable FTE additions | B12: count | F12: 130 | G12: 125 | H12: 120 | I12: 115 | J12: 105 | K12: 95 | L12: 85 | M12: 75 | N12: 65 | P12: Implied historical additions: +34 in FY25, +152 in FY26.
A13: Billable discovery FTEs | B13: count | C13: 1127 | D13: 1161 | E13: 1313 | F13: =E13+F12 -> 1443 | G13: =F13+G12 -> 1568 | H13: =G13+H12 -> 1688 | I13: =H13+I12 -> 1803 | J13: =I13+J12 -> 1908 | K13: =J13+K12 -> 2003 | L13: =K13+L12 -> 2088 | M13: =L13+M12 -> 2163 | N13: =M13+N12 -> 2228 | P13: ANALYST ESTIMATE. Sai discloses 2,605 scientists of 3,401 employees at FY25 but does NOT split them between Discovery and CMC - management declined the split on the Q4FY26 call. Utilisation is embedded here rather than modelled separately. History is calibrated so the implied FTE rate sits inside observed Indian discovery rate cards.
A14: DRIVER 2 Revenue per FTE - growth | B14: % | F14: 0.045 | G14: 0.04 | H14: 0.04 | I14: 0.035 | J14: 0.035 | K14: 0.035 | L14: 0.03 | M14: 0.03 | N14: 0.03 | P14: Contractual escalation, mix shift toward integrated / biology / DMPK work, and FX. Implied history: FY25 +22.3%, FY26 +9.5%.
A15: Revenue per billable FTE | B15: INR mn | C15: =C6/C13 -> 4.4099379 | D15: =D6/D13 -> 5.3919035 | E15: =E6/E13 -> 5.9025133 | F15: =E15*(1+F14) -> 6.1681264 | G15: =F15*(1+G14) -> 6.4148515 | H15: =G15*(1+H14) -> 6.6714455 | I15: =H15*(1+I14) -> 6.9049461 | J15: =I15*(1+J14) -> 7.1466193 | K15: =J15*(1+K14) -> 7.3967509 | L15: =K15*(1+L14) -> 7.6186535 | M15: =L15*(1+M14) -> 7.8472131 | N15: =M15*(1+N14) -> 8.0826295 | P15: History derived (reported CRO revenue / billable FTEs).
A16: CROSS-CHECK: implied rate per FTE (USD 000 @ INR 84/USD) | B16: USD k | C16: =C15*1000/84 -> 52.499261 | D16: =D15*1000/84 -> 64.189328 | E16: =E15*1000/84 -> 70.268016 | F16: =F15*1000/84 -> 73.430077 | G16: =G15*1000/84 -> 76.36728 | H16: =H15*1000/84 -> 79.421971 | I16: =I15*1000/84 -> 82.20174 | J16: =J15*1000/84 -> 85.078801 | ... N16: =N15*1000/84 -> 96.221779 | P16: Indian discovery rate cards typically run USD 55k-90k for med-chem and biology FTEs.
A17: CRO / Discovery revenue | B17: INR mn | C17: =C13*C15 -> 4970 | D17: =D13*D15 -> 6260 | E17: =E13*E15 -> 7750 | F17: =F13*F15 -> 8900.6064 | G17: =G13*G15 -> 10058.487 | H17: =H13*H15 -> 11261.4 | I17: =I13*I15 -> 12449.618 | J17: =J13*J15 -> 13635.75 | ... N17: =N13*N15 -> 18008.098
A18: check: engine vs reported (history) - must be nil | B18: INR mn | C18: =C17-C6 -> 0 | D18: =D17-D6 -> 0 | E18: =E17-E6 -> 0
A19: CRO growth (%) | B19: % | D19: =D17/C17-1 -> 0.25955734 | E19: =E17/D17-1 -> 0.23801917 | F19: =F17/E17-1 -> 0.14846535 | G19: =G17/F17-1 -> 0.13009009 | H19: =H17/G17-1 -> 0.11959184 | I19: =I17/H17-1 -> 0.10551244 | J19: =J17/I17-1 -> 0.095274542 | K19: =K17/J17-1 -> 0.086533019 | ... N19: =N17/M17-1 -> 0.060952381
A20: CRO bridge (volume / price - foots exactly)
A21: Opening CRO revenue | B21: INR mn | D21: =C17 -> 4970 | E21: =D17 -> 6260 | F21: =E17 -> 7750 | G21: =F17 -> 8900.6064 | H21: =G17 -> 10058.487 | I21: =H17 -> 11261.4 | J21: =I17 -> 12449.618 | K21: =J17 -> 13635.75 | ... N21: =M17 -> 16973.522
A22: + FTE additions (volume) | B22: INR mn | D22: =(D13-C13)*C15 -> 149.93789 | E22: =(E13-D13)*D15 -> 819.56934 | F22: =(F13-E13)*E15 -> 767.32673 | G22: =(G13-F13)*F15 -> 771.0158 | H22: =(H13-G13)*G15 -> 769.78218 | I22: =(I13-H13)*H15 -> 767.21624 | J22: =(J13-I13)*I15 -> 725.01934 | K22: =(K13-J13)*J15 -> 678.92883 | ... N22: =(N13-M13)*M15 -> 510.06885
A23: + Rate, service mix and FX (price) | B23: INR mn | D23: =D13*(D15-C15) -> 1140.0621 | E23: =E13*(E15-D15) -> 670.43066 | F23: =F13*(F15-E15) -> 383.2797 | G23: =G13*(G15-F15) -> 386.86489 | H23: =H13*(H15-G15) -> 433.13077 | I23: =I13*(I15-H15) -> 421.00157 | J23: =J13*(J15-I15) -> 461.1123 | K23: =K13*(K15-J15) -> 501.01374 | ... N23: =N13*(N15-M15) -> 524.50772
A24: = Closing CRO revenue | B24: INR mn | D24: =D21+D22+D23 -> 6260 | E24: =E21+E22+E23 -> 7750 | F24: =F21+F22+F23 -> 8900.6064 | G24: =G21+G22+G23 -> 10058.487 | H24: =H21+H22+H23 -> 11261.4 | I24: =I21+I22+I23 -> 12449.618 | J24: =J21+J22+J23 -> 13635.75 | K24: =K21+K22+K23 -> 14815.692 | ... N24: =N21+N22+N23 -> 18008.098
A25: check: bridge vs CRO revenue - must be nil | B25: INR mn | D25: =D24-D17 -> 0 | E25: =E24-E17 -> 0 | F25: =F24-F17 -> 0 | G25: =G24-G17 -> 0 | H25: =H24-H17 -> 0 | I25: =I24-I17 -> 0 | J25: =J24-J17 -> 0 | K25: =K24-K17 -> 0 | ... N25: =N24-N17 -> 0
A27: C. CDMO / CMC = COMMERCIAL MANUFACTURING + DEVELOPMENT [ DRIVERS 3, 4 and 5 ]
A28: Two mutually exclusive and collectively exhaustive buckets. Commercial is a molecule count times an average revenue per molecule; development is everything pre-commercial, forecast as a growth rate because Sai does not disclose revenue by development stage.
A29: C1. Commercial manufacturing
A30: DRIVER 3 Net new commercial molecules (qualifications less exits) | B30: count | D30: 4 | E30: 4 | F30: 2 | G30: 2 | H30: 3 | I30: 3 | J30: 3 | K30: 4 | L30: 4 | M30: 4 | N30: 4 | P30: REPORTED: FY26 added 4 commercial molecules, 30 to 34 (Q4FY26 call), with two additional large-pharma commercial supply qualifications received. Forecast is net of assumed de-listings and customer in-sourcing.
A31: Commercial molecules | B31: count | C31: 26 | D31: 30 | E31: 34 | F31: =E31+F30 -> 36 | G31: =F31+G30 -> 38 | H31: =G31+H30 -> 41 | I31: =H31+I30 -> 44 | J31: =I31+J30 -> 47 | K31: =J31+K30 -> 51 | L31: =K31+L30 -> 55 | M31: =L31+M30 -> 59 | N31: =M31+N30 -> 63 | P31: REPORTED: FY25 = 30, FY26 = 34 (Q4FY26 deck p.15 and call). FY24 = ANALYST ESTIMATE.
A32: DRIVER 4 Revenue per commercial molecule - growth | B32: % | F32: 0.095 | G32: 0.09 | H32: 0.085 | I32: 0.08 | J32: 0.075 | K32: 0.07 | L32: 0.07 | M32: 0.065 | N32: 0.06 | P32: Embeds BOTH underlying volume and price growth on the existing portfolio AND the maturation of newly qualified molecules, which earn roughly Rs 110mn in year one against a portfolio average of Rs 243mn. Implied history: FY24 220.4, FY25 201.0, FY26 243.2 - the FY25 dip is the disclosed customer destocking on a commercial intermediate.
A33: Revenue per commercial molecule | B33: INR mn | C33: =C34/C31 -> 220.38462 | D33: =D34/D31 -> 201 | E33: =E34/E31 -> 243.23529 | F33: =E33*(1+F32) -> 266.34265 | G33: =F33*(1+G32) -> 290.31349 | H33: =G33*(1+H32) -> 314.99013 | I33: =H33*(1+I32) -> 340.18934 | J33: =I33*(1+J32) -> 365.70354 | K33: =J33*(1+K32) -> 391.30279 | L33: =K33*(1+L32) -> 418.69399 | M33: =L33*(1+M32) -> 445.9091 | N33: =M33*(1+N32) -> 472.66364 | P33: History derived. This is the single most important CDMO number in the model - watch it against the count.
A34: Commercial manufacturing revenue | B34: INR mn | C34: 5730 | D34: 6030 | E34: 8270 | F34: =F33*F31 -> 9588.3353 | G34: =G33*G31 -> 11031.912 | H34: =H33*H31 -> 12914.595 | I34: =I33*I31 -> 14968.331 | J34: =J33*J31 -> 17188.067 | K34: =K33*K31 -> 19956.442 | L34: =L33*L31 -> 23028.169 | M34: =M33*M31 -> 26308.637 | N34: =N33*N31 -> 29777.809 | P34: History is the balancing figure so the two buckets tie exactly to reported CDMO revenue. ANALYST ESTIMATE of the split between commercial and development - Sai does not disclose it.
A35: C2. Development (pre-clinical, Phase I-III, validation, process R&D and tech transfer)
A36: DRIVER 5 Development revenue - growth | B36: % | F36: 0.13 | G36: 0.12 | H36: 0.115 | I36: 0.11 | J36: 0.105 | K36: 0.1 | L36: 0.095 | M36: 0.09 | N36: 0.085 | P36: Forecast as a growth rate, not a programme count, because Sai discloses programme counts but never revenue per programme. Implied history: +17.7% FY25, +26.9% FY26. Includes the dedicated large-pharma development FTE teams management flagged on the Q4FY26 call.
A37: Development revenue | B37: INR mn | C37: 3950 | D37: 4650 | E37: 5900 | F37: =E37*(1+F36) -> 6667 | G37: =F37*(1+G36) -> 7467.04 | H37: =G37*(1+H36) -> 8325.7496 | I37: =H37*(1+I36) -> 9241.5821 | J37: =I37*(1+J36) -> 10211.948 | K37: =J37*(1+K36) -> 11233.143 | L37: =K37*(1+L36) -> 12300.292 | M37: =L37*(1+M36) -> 13407.318 | N37: =M37*(1+N36) -> 14546.94 | P37: Residual of reported CDMO revenue less commercial manufacturing. ANALYST ESTIMATE.
A38: C3. CDMO revenue
A39: CDMO / CMC revenue | B39: INR mn | C39: =C34+C37 -> 9680 | D39: =D34+D37 -> 10680 | E39: =E34+E37 -> 14170 | F39: =F34+F37 -> 16255.335 | G39: =G34+G37 -> 18498.952 | H39: =H34+H37 -> 21240.345 | I39: =I34+I37 -> 24209.913 | J39: =J34+J37 -> 27400.015 | ... N39: =N34+N37 -> 44324.749
A40: check: buckets vs reported (history) - must be nil | B40: INR mn | C40: =C39-C7 -> 0 | D40: =D39-D7 -> 0 | E40: =E39-E7 -> 0
A41: CDMO growth (%) | B41: % | D41: =D39/C39-1 -> 0.10330579 | E41: =E39/D39-1 -> 0.32677903 | F41: =F39/E39-1 -> 0.14716551 | G41: =G39/F39-1 -> 0.13802343 | H41: =H39/G39-1 -> 0.14819177 | I41: =I39/H39-1 -> 0.1398079 | J41: =J39/I39-1 -> 0.1317684 | K41: =K39/J39-1 -> 0.13830542 | ... N41: =N39/M39-1 -> 0.11604391
A42: Commercial as % of CDMO | B42: % | C42: =C34/C39 -> 0.59194215 | D42: =D34/D39 -> 0.56460674 | E42: =E34/E39 -> 0.58362738 | F42: =F34/F39 -> 0.58985774 | G42: =G34/G39 -> 0.59635336 | H42: =H34/H39 -> 0.60802192 | I42: =I34/I39 -> 0.61827281 | J42: =J34/J39 -> 0.62730136 | ... N42: =N34/N39 -> 0.67180999
A44: D. MANUFACTURING CAPACITY (cross-check, deliberately NOT a revenue driver) [ DRIVER 6 ]
A45: DRIVER 6 Capacity commissioned in year | B45: KL | C45: 0 | D45: 134 | E45: 91 | F45: 225 | G45: 225 | H45: 100 | I45: 150 | J45: 100 | K45: 150 | L45: 200 | M45: 150 | N45: 100 | P45: FY26 +91 KL: Bidar Unit IV PB-11 Phase II, Q1FY26, taking total to ~700 KL (Q1FY26 release, 8-Aug-2025). FY27 and FY28 +225 KL each: the 700 to 1,150 KL Bidar expansion (Q4FY26 call). FY29 onward, including the second Hyderabad site, is an ANALYST ASSUMPTION sized to keep revenue per KL credible.
A46: Installed GMP capacity | B46: KL | C46: 475 | D46: 609 | E46: 700 | F46: =E46+F45 -> 925 | G46: =F46+G45 -> 1150 | H46: =G46+H45 -> 1250 | I46: =H46+I45 -> 1400 | J46: =I46+J45 -> 1500 | K46: =J46+K45 -> 1650 | L46: =K46+L45 -> 1850 | M46: =L46+M45 -> 2000 | N46: =M46+N45 -> 2100 | P46: REPORTED: 475 KL in 2023 and ~700 KL in 2025 (Q3FY26 deck p.27); 1,150 KL by FY28 (Q4FY26 call). FY25 = 609 KL DERIVED.
A47: Effective revenue-generating capacity | B47: KL | C47: =C46-C45*(1-$C$62) -> 475 | D47: =D46-D45*(1-$C$62) -> 515.2 | E47: =E46-E45*(1-$C$62) -> 636.3 | F47: =F46-F45*(1-$C$62) -> 767.5 | G47: =G46-G45*(1-$C$62) -> 992.5 | H47: =H46-H45*(1-$C$62) -> 1180 | I47: =I46-I45*(1-$C$62) -> 1295 | J47: =J46-J45*(1-$C$62) -> 1430 | ... N47: =N46-N45*(1-$C$62) -> 2030 | P47: Commissioning date is not the revenue start date. A new block is only partly productive in year one while it is qualified, audited by customers and run through validation batches; assumed fully productive from year two.
A48: CROSS-CHECK: commercial revenue per effective KL | B48: INR mn/KL | C48: =C34/C47 -> 12.063158 | D48: =D34/D47 -> 11.704193 | E48: =E34/E47 -> 12.997014 | F48: =F34/F47 -> 12.492945 | G48: =G34/G47 -> 11.115277 | H48: =H34/H47 -> 10.944572 | I48: =I34/I47 -> 11.558557 | J48: =J34/J47 -> 12.019627 | ... N48: =N34/N47 -> 14.668872 | P48: If this climbs fast, the model is forecasting output the plant cannot physically make.
A49: yoy change in revenue intensity | B49: % | D49: =D48/C48-1 -> -0.029757162 | E49: =E48/D48-1 -> 0.11045798 | F49: =F48/E48-1 -> -0.038783445 | G49: =G48/F48-1 -> -0.11027568 | H49: =H48/G48-1 -> -0.015357661 | I49: =I48/H48-1 -> 0.056099444 | J49: =J48/I48-1 -> 0.03988994 | K49: =K48/J48-1 -> 0.074641603 | ... N49: =N48/M48-1 -> 0.056592636
A50: FLAG if intensity growth exceeds 10% p.a. | D50: =IF(D49>0.1,"REVIEW","ok") -> ok | E50: =IF(E49>0.1,"REVIEW","ok") -> REVIEW | F50: =IF(F49>0.1,"REVIEW","ok") -> ok | G50: =IF(G49>0.1,"REVIEW","ok") -> ok | H50: =IF(H49>0.1,"REVIEW","ok") -> ok | I50: =IF(I49>0.1,"REVIEW","ok") -> ok | J50: =IF(J49>0.1,"REVIEW","ok") -> ok | K50: =IF(K49>0.1,"REVIEW","ok") -> ok | ... N50: =IF(N49>0.1,"REVIEW","ok") -> ok
A52: E. TOTAL REVENUE AND RECONCILIATION
A53: Revenue from operations | B53: INR mn | C53: =C17+C39+C9 -> 14651.78 | D53: =D17+D39+D9 -> 16945.7 | E53: =E17+E39+E9 -> 21924.92 | F53: =F17+F39 -> 25155.942 | G53: =G17+G39 -> 28557.44 | H53: =H17+H39 -> 32501.745 | I53: =I17+I39 -> 36659.531 | J53: =J17+J39 -> 41035.764 | K53: =K17+K39 -> 46005.277 | L53: =L17+L39 -> 51236.209 | M53: =M17+M39 -> 56689.476 | N53: =N17+N39 -> 62332.848
A54: Revenue growth (%) | B54: % | D54: =D53/C53-1 -> 0.15656255 | E54: =E53/D53-1 -> 0.29383383 | F54: =F53/E53-1 -> 0.14736755 | G54: =G53/F53-1 -> 0.13521648 | H54: =H53/G53-1 -> 0.13811832 | I54: =I53/H53-1 -> 0.12792501 | J54: =J53/I53-1 -> 0.11937505 | K54: =K53/J53-1 -> 0.121102 | ... N54: =N53/M53-1 -> 0.099548835
A55: CRO share of revenue (%) | B55: % | C55: =C17/C53 -> 0.33920793 | D55: =D17/D53 -> 0.36941525 | E55: =E17/E53 -> 0.35347905 | F55: =F17/F53 -> 0.35381726 | G55: =G17/G53 -> 0.3522195 | H55: =H17/H53 -> 0.34648601 | I55: =I17/I53 -> 0.33960112 | J55: =J17/J53 -> 0.3322894 | ... N55: =N17/N53 -> 0.28890223
A56: CDMO share of revenue (%) | B56: % | C56: =C39/C53 -> 0.66067058 | D56: =D39/D53 -> 0.63024838 | E56: =E39/E53 -> 0.64629654 | F56: =F39/F53 -> 0.64618274 | G56: =G39/G53 -> 0.6477805 | H56: =H39/H53 -> 0.65351399 | I56: =I39/I53 -> 0.66039888 | J56: =J39/J53 -> 0.6677106 | ... N56: =N39/N53 -> 0.71109777
A57: CHECK: total revenue vs audited (history) - must be nil | B57: INR mn | C57: =C53-C8 -> 0 | D57: =D53-D8 -> 0 | E57: =E53-E8 -> 0
A58: Forward 5-year revenue CAGR from this year | B58: % | C58: =(H53/C53)^(1/5)-1 -> 0.1727441 | D58: =(I53/D53)^(1/5)-1 -> 0.16687807 | E58: =(J53/E53)^(1/5)-1 -> 0.13356102 | F58: =(K53/F53)^(1/5)-1 -> 0.12832293 | G58: =(L53/G53)^(1/5)-1 -> 0.12401355 | H58: =(M53/H53)^(1/5)-1 -> 0.11768431 | I58: =(N53/I53)^(1/5)-1 -> 0.11200314
A59: FLAG: FY25-base 5yr CAGR vs the 15-20% guidance | D59: =IF(AND(D58>=0.15,D58<=0.2),"WITHIN GUIDANCE","OUTSIDE 15-20% GUIDANCE - review") -> WITHIN GUIDANCE
A61: F. FIXED ASSUMPTIONS AND DISCLOSED PORTFOLIO DATA (set once, not forecast year by year)
A62: Share of newly commissioned capacity productive in year one | B62: % | C62: 0.3 | P62: ANALYST ASSUMPTION - qualification, customer audit and validation batches absorb most of year one. Single cell, applied to every year.
A63: Top-4 commercial molecules as a share of commercial revenue | B63: % | C63: 0.4 | P63: Sai discloses no molecule names or customers and management explicitly declined to on the Q4FY26 call. Anchored on disclosed FY26 concentration: top-1 customer 12% of group revenue, top-5 37%, top-10 54%. Memo only - does not drive revenue. CONFIDENCE: LOW.
A64: memo: top-4 identified commercial molecules | B64: INR mn | C64: =C34*$C$63 -> 2292 | D64: =D34*$C$63 -> 2412 | E64: =E34*$C$63 -> 3308 | F64: =F34*$C$63 -> 3835.3341 | G64: =G34*$C$63 -> 4412.765 | H64: =H34*$C$63 -> 5165.8382 | I64: =I34*$C$63 -> 5987.3324 | J64: =J34*$C$63 -> 6875.2266 | ... N64: =N34*$C$63 -> 11911.124
A65: memo: top-4 as % of CDMO revenue | B65: % | C65: =C64/C39 -> 0.23677686 | D65: =D64/D39 -> 0.2258427 | E65: =E64/E39 -> 0.23345095 | F65: =F64/F39 -> 0.23594309 | G65: =G64/G39 -> 0.23854134 | H65: =H64/H39 -> 0.24320877 | I65: =I64/I39 -> 0.24730912 | J65: =J64/J39 -> 0.25092054 | ... N65: =N64/N39 -> 0.268724
A66: Disclosed portfolio counts (history only - track them, they do not drive revenue)
A67: Phase III / pre-registration molecules | B67: count | C67: 5 | D67: 6 | E67: 11 | P67: REPORTED: FY25 = 6 (Q3FY26 deck p.13), FY26 = 11 (Q4FY26 deck p.15 and call). FY24 = ANALYST ESTIMATE. The leading indicator for the commercial molecule count two to four years out.
A68: Early-phase development programmes | B68: count | C68: 150 | D68: 160 | E68: 155 | P68: REPORTED: FY25 = 160 (Q3FY26 deck p.19), FY26 = 155 (Q4FY26 deck p.24 and call). FY24 = ANALYST ESTIMATE.
A69: CROSS-CHECK: development revenue per active programme | B69: INR mn | C69: =C37/(C67+C68) -> 25.483871 | D69: =D37/(D67+D68) -> 28.012048 | E69: =E37/(E67+E68) -> 35.542169 | P69: History: 25.5 / 28.0 / 35.5 INR mn per active development programme. Update the counts each quarter and check that the implied intensity is not running away from you.
A70: New modalities (% of group revenue) | B70: % | C70: 0.03 | D70: 0.07 | E70: 0.04 | P70: REPORTED: FY22 4%, FY23 3%, FY24 3%, FY25 7%, FY26 4% (Q4FY26 deck p.25). Lumpy because new-modality work is campaign-driven, not commercial. Memo only.

Sheet Statements
A1: SHEET 3 | INCOME STATEMENT, BALANCE SHEET AND CASH FLOW STATEMENT
A2: Consolidated, Ind AS, INR million. FY2024A-FY2026A are hardcoded from the audited financial statements. FY2027E-FY2035E are fully formula-driven from the Revenue_Model and Schedules sheets.
B3: INR mn | C3: FY2024A | D3: FY2025A | E3: FY2026A | F3: FY2027E | G3: FY2028E | H3: FY2029E | I3: FY2030E | J3: FY2031E | K3: FY2032E | L3: FY2033E | M3: FY2034E | N3: FY2035E | P3: Source / basis
A5: I. CONSOLIDATED INCOME STATEMENT
A6: Revenue from operations | B6: INR mn | C6: =Schedules!C6 -> 14651.78 | D6: =Schedules!D6 -> 16945.7 | E6: =Schedules!E6 -> 21924.92 | F6: =Schedules!F6 -> 25155.942 | G6: =Schedules!G6 -> 28557.44 | H6: =Schedules!H6 -> 32501.745 | I6: =Schedules!I6 -> 36659.531 | J6: =Schedules!J6 -> 41035.764 | ... N6: =Schedules!N6 -> 62332.848
A7: Cost of materials, chemicals & reagents (net of WIP) | B7: INR mn | C7: =-Schedules!C19 -> -4457.3 | D7: =-Schedules!D19 -> -4657.64 | E7: =-Schedules!E19 -> -5708.92 | F7: =-Schedules!F19 -> -6726.5226 | G7: =-Schedules!G19 -> -7556.7966 | H7: =-Schedules!H19 -> -8547.4362 | I7: =-Schedules!I19 -> -9663.1183 | J7: =-Schedules!J19 -> -10845.265 | ... N7: =-Schedules!N19 -> -17042.96
A8: Material margin | B8: INR mn | C8: =C6+C7 -> 10194.48 | D8: =D6+D7 -> 12288.06 | E8: =E6+E7 -> 16216 | F8: =F6+F7 -> 18429.419 | G8: =G6+G7 -> 21000.643 | H8: =H6+H7 -> 23954.309 | I8: =I6+I7 -> 26996.413 | J8: =J6+J7 -> 30190.499 | ... N8: =N6+N7 -> 45289.888
A9: Material margin (%) | B9: % | C9: =C8/C6 -> 0.6957844 | D9: =D8/D6 -> 0.72514325 | E9: =E8/E6 -> 0.73961501 | F9: =F8/F6 -> 0.73260701 | G9: =G8/G6 -> 0.73538256 | H9: =H8/H6 -> 0.73701608 | I9: =I8/I6 -> 0.73640911 | J9: =J8/J6 -> 0.73571187 | ... N9: =N8/N6 -> 0.72658141
A10: Employee benefits expense | B10: INR mn | C10: =-Schedules!C27 -> -4949.05 | D10: =-Schedules!D27 -> -5491.18 | E10: =-Schedules!E27 -> -6830.55 | F10: =-Schedules!F27 -> -7961.1858 | G10: =-Schedules!G27 -> -9155.8274 | H10: =-Schedules!H27 -> -10417.343 | I10: =-Schedules!I27 -> -11741.188 | J10: =-Schedules!J27 -> -13109.415 | ... N10: =-Schedules!N27 -> -18879.685
A11: Other operating expenses | B11: INR mn | C11: =-Schedules!C40 -> -2390.54 | D11: =-Schedules!D40 -> -2740.27 | E11: =-Schedules!E40 -> -3073.86 | F11: =-Schedules!F40 -> -3936.0251 | G11: =-Schedules!G40 -> -4575.4451 | H11: =-Schedules!H40 -> -5224.567 | I11: =-Schedules!I40 -> -5862.415 | J11: =-Schedules!J40 -> -6548.2712 | ... N11: =-Schedules!N40 -> -9987.3862
A12: Net foreign exchange gain / (loss) | B12: INR mn | C12: =Schedules!C44 -> 146.26 | D12: =Schedules!D44 -> 190.76 | E12: =Schedules!E44 -> 300.18 | F12: =Schedules!F44 -> 201.24753 | G12: =Schedules!G44 -> 228.45952 | H12: =Schedules!H44 -> 260.01396 | I12: =Schedules!I44 -> 293.27625 | J12: =Schedules!J44 -> 328.28611 | ... N12: =Schedules!N44 -> 498.66278
A13: EBITDA | B13: INR mn | C13: =C8+C10+C11+C12 -> 3001.15 | D13: =D8+D10+D11+D12 -> 4247.37 | E13: =E8+E10+E11+E12 -> 6611.77 | F13: =F8+F10+F11+F12 -> 6733.4559 | G13: =G8+G10+G11+G12 -> 7497.83 | H13: =H8+H10+H11+H12 -> 8572.4128 | I13: =I8+I10+I11+I12 -> 9686.0861 | J13: =J8+J10+J11+J12 -> 10861.099 | ... N13: =N8+N10+N11+N12 -> 16921.48
A14: EBITDA margin (%) | B14: % | C14: =C13/C6 -> 0.20483177 | D14: =D13/D6 -> 0.25064589 | E14: =E13/E6 -> 0.30156416 | F14: =F13/F6 -> 0.26766861 | G14: =G13/G6 -> 0.2625526 | H14: =H13/H6 -> 0.26375239 | I14: =I13/I6 -> 0.2642174 | J14: =J13/J6 -> 0.26467398 | ... N14: =N13/N6 -> 0.27146971
A15: Depreciation and amortisation | B15: INR mn | C15: =-Schedules!C88 -> -1194.36 | D15: =-Schedules!D88 -> -1385.73 | E15: =-Schedules!E88 -> -1668.55 | F15: =-Schedules!F88 -> -2411.2497 | G15: =-Schedules!G88 -> -3175.5013 | H15: =-Schedules!H88 -> -3768.3003 | I15: =-Schedules!I88 -> -4170.2881 | J15: =-Schedules!J88 -> -4514.0958 | ... N15: =-Schedules!N88 -> -5726.1158
A16: EBIT | B16: INR mn | C16: =C13+C15 -> 1806.79 | D16: =D13+D15 -> 2861.64 | E16: =E13+E15 -> 4943.22 | F16: =F13+F15 -> 4322.2061 | G16: =G13+G15 -> 4322.3286 | H16: =H13+H15 -> 4804.1125 | I16: =I13+I15 -> 5515.7981 | J16: =J13+J15 -> 6347.0032 | ... N16: =N13+N15 -> 11195.364
A17: EBIT margin (%) | B17: % | C17: =C16/C6 -> 0.12331539 | D17: =D16/D6 -> 0.16887116 | E17: =E16/E6 -> 0.22546126 | F17: =F16/F6 -> 0.17181651 | G17: =G16/G6 -> 0.15135561 | H17: =H16/H6 -> 0.14781091 | I17: =I16/I6 -> 0.15046014 | J17: =J16/J6 -> 0.15467004 | ... N17: =N16/N6 -> 0.17960617
A18: Other income (interest and investment income) | B18: INR mn | C18: =Schedules!C136 -> 144.65 | D18: =Schedules!D136 -> 177.03 | E18: =Schedules!E136 -> 191.1 | F18: =Schedules!F136 -> 78.9315 | G18: =Schedules!G136 -> 83.896123 | H18: =Schedules!H136 -> 91.842405 | I18: =Schedules!I136 -> 100.83828 | J18: =Schedules!J136 -> 110.31242 | ... N18: =Schedules!N136 -> 155.31222
A19: Finance costs | B19: INR mn | C19: =-Schedules!C131 -> -859.1 | D19: =-Schedules!D131 -> -761.64 | E19: =-Schedules!E131 -> -392.39 | F19: =-Schedules!F131 -> -293.51595 | G19: =-Schedules!G131 -> -859.89587 | H19: =-Schedules!H131 -> -1259.6847 | I19: =-Schedules!I131 -> -1448.3458 | J19: =-Schedules!J131 -> -1586.9866 | ... N19: =-Schedules!N131 -> -1387.7462
A20: Profit before exceptional items and tax | B20: INR mn | C20: =C16+C18+C19 -> 1092.34 | D20: =D16+D18+D19 -> 2277.03 | E20: =E16+E18+E19 -> 4741.93 | F20: =F16+F18+F19 -> 4107.6217 | G20: =G16+G18+G19 -> 3546.3289 | H20: =H16+H18+H19 -> 3636.2703 | I20: =I16+I18+I19 -> 4168.2906 | J20: =J16+J18+J19 -> 4870.3291 | ... N20: =N16+N18+N19 -> 9962.9302
A21: Exceptional items | B21: INR mn | C21: =Schedules!C142 -> 0 | D21: =Schedules!D142 -> 0 | E21: =Schedules!E142 -> -80.01 | F21: =Schedules!F142 -> 0 | G21: =Schedules!G142 -> 0 | H21: =Schedules!H142 -> 0 | I21: =Schedules!I142 -> 0 | J21: =Schedules!J142 -> 0 | ... N21: =Schedules!N142 -> 0
A22: Profit before tax | B22: INR mn | C22: =C20+C21 -> 1092.34 | D22: =D20+D21 -> 2277.03 | E22: =E20+E21 -> 4661.92 | F22: =F20+F21 -> 4107.6217 | G22: =G20+G21 -> 3546.3289 | H22: =H20+H21 -> 3636.2703 | I22: =I20+I21 -> 4168.2906 | J22: =J20+J21 -> 4870.3291 | ... N22: =N20+N21 -> 9962.9302
A23: Current tax | B23: INR mn | C23: =-Schedules!C150 -> -77.57 | D23: =-Schedules!D150 -> -338.44 | E23: =-Schedules!E150 -> -884.02 | F23: =-Schedules!F150 -> -817.00595 | G23: =-Schedules!G150 -> -723.45109 | H23: =-Schedules!H150 -> -760.34412 | I23: =-Schedules!I150 -> -892.84784 | J23: =-Schedules!J150 -> -1068.0632 | ... N23: =-Schedules!N150 -> -2286.4925
A24: Deferred tax | B24: INR mn | C24: =-Schedules!C149 -> -186.68 | D24: =-Schedules!D149 -> -237.27 | E24: =-Schedules!E149 -> -288.8 | F24: =-Schedules!F149 -> -230.43758 | G24: =-Schedules!G149 -> -180.86277 | H24: =-Schedules!H149 -> -166.90481 | I24: =-Schedules!I149 -> -170.06626 | J24: =-Schedules!J149 -> -173.87075 | ... N24: =-Schedules!N149 -> -254.05472
A25: Total tax expense | B25: INR mn | C25: =C23+C24 -> -264.25 | D25: =D23+D24 -> -575.71 | E25: =E23+E24 -> -1172.82 | F25: =F23+F24 -> -1047.4435 | G25: =G23+G24 -> -904.31387 | H25: =H23+H24 -> -927.24892 | I25: =I23+I24 -> -1062.9141 | J25: =J23+J24 -> -1241.9339 | ... N25: =N23+N24 -> -2540.5472
A26: Profit after tax | B26: INR mn | C26: =C22+C25 -> 828.09 | D26: =D22+D25 -> 1701.32 | E26: =E22+E25 -> 3489.1 | F26: =F22+F25 -> 3060.1782 | G26: =G22+G25 -> 2642.015 | H26: =H22+H25 -> 2709.0214 | I26: =I22+I25 -> 3105.3765 | J26: =J22+J25 -> 3628.3951 | ... N26: =N22+N25 -> 7422.383
A27: PAT margin (%) | B27: % | C27: =C26/C6 -> 0.056518048 | D27: =D26/D6 -> 0.10039833 | E27: =E26/E6 -> 0.15913855 | F27: =F26/F6 -> 0.12164832 | G27: =G26/G6 -> 0.092515823 | H27: =H26/H6 -> 0.083350028 | I27: =I26/I6 -> 0.084708571 | J27: =J26/J6 -> 0.088420314 | ... N27: =N26/N6 -> 0.11907659
A28: Effective tax rate (%) | B28: % | C28: =-C25/C22 -> 0.24191186 | D28: =-D25/D22 -> 0.25283374 | E28: =-E25/E22 -> 0.25157446 | F28: =-F25/F22 -> 0.255 | G28: =-G25/G22 -> 0.255 | H28: =-H25/H22 -> 0.255 | I28: =-I25/I22 -> 0.255 | J28: =-J25/J22 -> 0.255 | ... N28: =-N25/N22 -> 0.255
A29: Diluted weighted average shares | B29: mn | C29: =Schedules!C169 -> 182.8 | D29: =Schedules!D169 -> 197.6 | E29: =Schedules!E169 -> 212.36 | F29: =Schedules!F169 -> 214.36 | G29: =Schedules!G169 -> 216.36 | H29: =Schedules!H169 -> 218.36 | I29: =Schedules!I169 -> 220.36 | J29: =Schedules!J169 -> 222.36 | ... N29: =Schedules!N169 -> 230.36
A30: Diluted EPS | B30: INR | C30: =C26/C29 -> 4.5300328 | D30: =D26/D29 -> 8.609919 | E30: =E26/E29 -> 16.430119 | F30: =F26/F29 -> 14.275882 | G30: =G26/G29 -> 12.211199 | H30: =H26/H29 -> 12.406216 | I30: =I26/I29 -> 14.092287 | J30: =J26/J29 -> 16.317661 | ... N30: =N26/N29 -> 32.220798
A31: CHECK: PAT vs audited (history) - must be nil | B31: INR mn | C31: =C26-828.09 -> 0 | D31: =D26-1701.32 -> 0 | E31: =E26-3489.1 -> 0
A33: II. CONSOLIDATED BALANCE SHEET
A34: Assets
A35: Property, plant and equipment | B35: INR mn | C35: =Schedules!C76 -> 9263.55 | D35: =Schedules!D76 -> 11850.12 | E35: =Schedules!E76 -> 15344.14 | F35: =Schedules!F76 -> 23174.474 | G35: =Schedules!G76 -> 30840.077 | H35: =Schedules!H76 -> 35236.208 | I35: =Schedules!I76 -> 38791.205 | J35: =Schedules!J76 -> 41931.917 | ... N35: =Schedules!N76 -> 52509.961
A36: Right-of-use assets | B36: INR mn | C36: =Schedules!C81 -> 2397.13 | D36: =Schedules!D81 -> 2923.44 | E36: =Schedules!E81 -> 2743.01 | F36: =Schedules!F81 -> 2617.4406 | G36: =Schedules!G81 -> 2556.8096 | H36: =Schedules!H81 -> 2557.4587 | I36: =Schedules!I81 -> 2612.0519 | J36: =Schedules!J81 -> 2714.5283 | ... N36: =Schedules!N81 -> 3557.8716
A37: Capital work-in-progress | B37: INR mn | C37: =Schedules!C69 -> 1068.95 | D37: =Schedules!D69 -> 1244.56 | E37: =Schedules!E69 -> 2704.53 | F37: =Schedules!F69 -> 4680 | G37: =Schedules!G69 -> 2652 | H37: =Schedules!H69 -> 1842.75 | I37: =Schedules!I69 -> 1974.375 | J37: =Schedules!J69 -> 1706.25 | ... N37: =Schedules!N69 -> 1828.125
A38: Intangible assets | B38: INR mn | C38: =Schedules!C64 -> 137.73 | D38: =Schedules!D64 -> 108.56 | E38: =Schedules!E64 -> 61.17 | F38: =Schedules!F64 -> 281.7126 | G38: =Schedules!G64 -> 385.48583 | H38: =Schedules!H64 -> 437.17895 | I38: =Schedules!I64 -> 487.24958 | J38: =Schedules!J64 -> 516.55467 | ... N38: =Schedules!N64 -> 611.21475
A39: Other non-current assets | B39: INR mn | C39: =Schedules!C175 -> 432.86 | D39: =Schedules!D175 -> 427.96 | E39: =Schedules!E175 -> 1303.25 | F39: =Schedules!F175 -> 1257.7971 | G39: =Schedules!G175 -> 1370.7571 | H39: =Schedules!H175 -> 1495.0803 | I39: =Schedules!I175 -> 1649.6789 | J39: =Schedules!J175 -> 1805.5736 | ... N39: =Schedules!N175 -> 2493.3139
A40: Total non-current assets | B40: INR mn | C40: =C35+C36+C37+C38+C39 -> 13300.22 | D40: =D35+D36+D37+D38+D39 -> 16554.64 | E40: =E35+E36+E37+E38+E39 -> 22156.1 | F40: =F35+F36+F37+F38+F39 -> 32011.425 | G40: =G35+G36+G37+G38+G39 -> 37805.13 | H40: =H35+H36+H37+H38+H39 -> 41568.676 | I40: =I35+I36+I37+I38+I39 -> 45514.56 | J40: =J35+J36+J37+J38+J39 -> 48674.824 | ... N40: =N35+N36+N37+N38+N39 -> 61000.486
A41: Inventories | B41: INR mn | C41: =Schedules!C97 -> 874.43 | D41: =Schedules!D97 -> 1188.65 | E41: =Schedules!E97 -> 1509.68 | F41: =Schedules!F97 -> 1750.7388 | G41: =Schedules!G97 -> 1946.1339 | H41: =Schedules!H97 -> 2177.8399 | I41: =Schedules!I97 -> 2435.6353 | J41: =Schedules!J97 -> 2703.888 | ... N41: =Schedules!N97 -> 4202.3736
A42: Trade receivables | B42: INR mn | C42: =Schedules!C99 -> 2561.84 | D42: =Schedules!D99 -> 3547.83 | E42: =Schedules!E99 -> 3736.23 | F42: =Schedules!F99 -> 4273.0641 | G42: =Schedules!G99 -> 4850.8527 | H42: =Schedules!H99 -> 5431.7985 | I42: =Schedules!I99 -> 6126.6613 | J42: =Schedules!J99 -> 6745.6051 | ... N42: =Schedules!N99 -> 10246.495
A43: Other current assets (mainly contract assets) | B43: INR mn | C43: =Schedules!C101 -> 3632.11 | D43: =Schedules!D101 -> 4873.57 | E43: =Schedules!E101 -> 6241.05 | F43: =Schedules!F101 -> 7029.8796 | G43: =Schedules!G101 -> 7823.956 | H43: =Schedules!H101 -> 8726.4959 | I43: =Schedules!I101 -> 9641.9588 | J43: =Schedules!J101 -> 10680.541 | ... N43: =Schedules!N101 -> 15711.293
A44: Other financial assets (current) | B44: INR mn | C44: =Schedules!C103 -> 794.76 | D44: =Schedules!D103 -> 796.24 | E44: =Schedules!E103 -> 1039.71 | F44: =Schedules!F103 -> 1171.6466 | G44: =Schedules!G103 -> 1330.0725 | H44: =Schedules!H103 -> 1513.7799 | I44: =Schedules!I103 -> 1707.4302 | J44: =Schedules!J103 -> 1911.2548 | ... N44: =Schedules!N103 -> 2903.1737
A45: Bank deposits and current investments | B45: INR mn | C45: =Schedules!C132 -> 1351.43 | D45: =Schedules!D132 -> 3727.63 | E45: =Schedules!E132 -> 759.49 | F45: =Schedules!F132 -> 797.4645 | G45: =Schedules!G132 -> 837.33772 | H45: =Schedules!H132 -> 879.20461 | I45: =Schedules!I132 -> 923.16484 | J45: =Schedules!J132 -> 969.32308 | ... N45: =Schedules!N132 -> 1178.2183
A46: Cash and cash equivalents | B46: INR mn | C46: =Schedules!C137 -> 236.57 | D46: =Schedules!D137 -> 911.19 | E46: =Schedules!E137 -> 819.14 | F46: =Schedules!F137 -> 880.45796 | G46: =Schedules!G137 -> 999.51038 | H46: =Schedules!H137 -> 1137.5611 | I46: =Schedules!I137 -> 1283.0836 | J46: =Schedules!J137 -> 1436.2517 | ... N46: =Schedules!N137 -> 2181.6497
A47: Total current assets | B47: INR mn | C47: =C41+C42+C43+C44+C45+C46 -> 9451.14 | D47: =D41+D42+D43+D44+D45+D46 -> 15045.11 | E47: =E41+E42+E43+E44+E45+E46 -> 14105.3 | F47: =F41+F42+F43+F44+F45+F46 -> 15903.251 | G47: =G41+G42+G43+G44+G45+G46 -> 17787.863 | H47: =H41+H42+H43+H44+H45+H46 -> 19866.68 | I47: =I41+I42+I43+I44+I45+I46 -> 22117.934 | J47: =J41+J42+J43+J44+J45+J46 -> 24446.864 | ... N47: =N41+N42+N43+N44+N45+N46 -> 36423.204
A48: TOTAL ASSETS | B48: INR mn | C48: =C40+C47 -> 22751.36 | D48: =D40+D47 -> 31599.75 | E48: =E40+E47 -> 36261.4 | F48: =F40+F47 -> 47914.676 | G48: =G40+G47 -> 55592.993 | H48: =H40+H47 -> 61435.356 | I48: =I40+I47 -> 67632.494 | J48: =J40+J47 -> 73121.688 | ... N48: =N40+N47 -> 97423.69
A49: Equity and liabilities
A50: Equity share capital | B50: INR mn | C50: =Schedules!C161 -> 180.5 | D50: =Schedules!D161 -> 208.41 | E50: =Schedules!E161 -> 211.78 | F50: =Schedules!F161 -> 214.78 | G50: =Schedules!G161 -> 217.78 | H50: =Schedules!H161 -> 220.78 | I50: =Schedules!I161 -> 223.78 | J50: =Schedules!J161 -> 226.78 | ... N50: =Schedules!N161 -> 238.78
A51: Other equity | B51: INR mn | C51: =Schedules!C166 -> 9570.94 | D51: =Schedules!D166 -> 21075.13 | E51: =Schedules!E166 -> 24625.1 | F51: =Schedules!F166 -> 27862.278 | G51: =Schedules!G166 -> 30683.293 | H51: =Schedules!H166 -> 33573.315 | I51: =Schedules!I166 -> 36861.691 | J51: =Schedules!J166 -> 40675.086 | ... N51: =Schedules!N166 -> 64846.984
A52: Total equity | B52: INR mn | C52: =C50+C51 -> 9751.44 | D52: =D50+D51 -> 21283.54 | E52: =E50+E51 -> 24836.88 | F52: =F50+F51 -> 28077.058 | G52: =G50+G51 -> 30901.073 | H52: =H50+H51 -> 33794.095 | I52: =I50+I51 -> 37085.471 | J52: =J50+J51 -> 40901.866 | ... N52: =N50+N51 -> 65085.764
A53: Borrowings - non-current | B53: INR mn | C53: =Schedules!C128-Schedules!C129 -> 2772.46 | D53: =Schedules!D128-Schedules!D129 -> 0 | E53: =Schedules!E128-Schedules!E129 -> 205.04 | F53: =Schedules!F128-Schedules!F129 -> 6255.699 | G53: =Schedules!G128-Schedules!G129 -> 10280.989 | H53: =Schedules!H128-Schedules!H129 -> 12152.539 | I53: =Schedules!I128-Schedules!I129 -> 13469.481 | J53: =Schedules!J128-Schedules!J129 -> 13842.997 | ... N53: =Schedules!N128-Schedules!N129 -> 7949.6255
A54: Lease liabilities - non-current | B54: INR mn | C54: =Schedules!C85-Schedules!C86 -> 1757.21 | D54: =Schedules!D85-Schedules!D86 -> 1646.87 | E54: =Schedules!E85-Schedules!E86 -> 1276.2 | F54: =Schedules!F85-Schedules!F86 -> 1147.2875 | G54: =Schedules!G85-Schedules!G86 -> 1082.5427 | H54: =Schedules!H85-Schedules!H86 -> 1069.1211 | I54: =Schedules!I85-Schedules!I86 -> 1094.9972 | J54: =Schedules!J85-Schedules!J86 -> 1151.4348 | ... N54: =Schedules!N85-Schedules!N86 -> 1604.6932
A55: Deferred tax liabilities (net of DTA within other assets) | B55: INR mn | C55: =Schedules!C154 -> 862.66 | D55: =Schedules!D154 -> 1110.36 | E55: =Schedules!E154 -> 1283.32 | F55: =Schedules!F154 -> 1513.7576 | G55: =Schedules!G154 -> 1694.6203 | H55: =Schedules!H154 -> 1861.5252 | I55: =Schedules!I154 -> 2031.5914 | J55: =Schedules!J154 -> 2205.4622 | ... N55: =Schedules!N154 -> 3073.4689
A56: Provisions - non-current | B56: INR mn | C56: =Schedules!C112 -> 172.949 | D56: =Schedules!D112 -> 211.8106 | E56: =Schedules!E112 -> 324.5948 | F56: =Schedules!F112 -> 370.19514 | G56: =Schedules!G112 -> 425.74597 | H56: =Schedules!H112 -> 484.40645 | I56: =Schedules!I112 -> 545.96523 | J56: =Schedules!J112 -> 609.58779 | ... N56: =Schedules!N112 -> 877.90533
A57: Total non-current liabilities | B57: INR mn | C57: =C53+C54+C55+C56 -> 5565.279 | D57: =D53+D54+D55+D56 -> 2969.0406 | E57: =E53+E54+E55+E56 -> 3089.1548 | F57: =F53+F54+F55+F56 -> 9286.9392 | G57: =G53+G54+G55+G56 -> 13483.898 | H57: =H53+H54+H55+H56 -> 15567.592 | I57: =I53+I54+I55+I56 -> 17142.035 | J57: =J53+J54+J55+J56 -> 17809.482 | ... N57: =N53+N54+N55+N56 -> 13505.693
A58: Borrowings - current | B58: INR mn | C58: =Schedules!C129 -> 4329.17 | D58: =Schedules!D129 -> 1286.36 | E58: =Schedules!E129 -> 746.21 | F58: =Schedules!F129 -> 1611.1398 | G58: =Schedules!G129 -> 2416.1978 | H58: =Schedules!H129 -> 2790.5078 | I58: =Schedules!I129 -> 3053.8962 | J58: =Schedules!J129 -> 3128.5994 | ... N58: =Schedules!N129 -> 1949.9251
A59: Lease liabilities - current | B59: INR mn | C59: =Schedules!C86 -> 417.76 | D59: =Schedules!D86 -> 590.58 | E59: =Schedules!E86 -> 657.07 | F59: =Schedules!F86 -> 591.02688 | G59: =Schedules!G86 -> 557.6735 | H59: =Schedules!H86 -> 550.75937 | I59: =Schedules!I86 -> 564.08947 | J59: =Schedules!J86 -> 593.16339 | ... N59: =Schedules!N86 -> 826.66012
A60: Trade payables | B60: INR mn | C60: =Schedules!C105 -> 1384.7 | D60: =Schedules!D105 -> 3225.08 | E60: =Schedules!E105 -> 2853.38 | F60: =Schedules!F105 -> 3225.0451 | G60: =Schedules!G105 -> 3623.1217 | H60: =Schedules!H105 -> 4098.0859 | I60: =Schedules!I105 -> 4633.0019 | J60: =Schedules!J105 -> 5199.7847 | ... N60: =Schedules!N105 -> 8171.282
A61: Other financial liabilities (current) | B61: INR mn | C61: =Schedules!C107 -> 330.86 | D61: =Schedules!D107 -> 754.44 | E61: =Schedules!E107 -> 1636.78 | F61: =Schedules!F107 -> 2640 | G61: =Schedules!G107 -> 1870 | H61: =Schedules!H107 -> 1540 | I61: =Schedules!I107 -> 1650 | J61: =Schedules!J107 -> 1540 | ... N61: =Schedules!N107 -> 1650
A62: Other current liabilities | B62: INR mn | C62: =Schedules!C109 -> 866.15 | D62: =Schedules!D109 -> 1281.19 | E62: =Schedules!E109 -> 1726.38 | F62: =Schedules!F109 -> 1929.7709 | G62: =Schedules!G109 -> 2190.7077 | H62: =Schedules!H109 -> 2493.2846 | I62: =Schedules!I109 -> 2812.238 | J62: =Schedules!J109 -> 3147.949 | ... N62: =Schedules!N109 -> 4781.6979
A63: Provisions - current | B63: INR mn | C63: =Schedules!C111-Schedules!C112 -> 106.001 | D63: =Schedules!D111-Schedules!D112 -> 129.8194 | E63: =Schedules!E111-Schedules!E112 -> 198.9452 | F63: =Schedules!F111-Schedules!F112 -> 226.89379 | G63: =Schedules!G111-Schedules!G112 -> 260.94108 | H63: =Schedules!H111-Schedules!H112 -> 296.89428 | I63: =Schedules!I111-Schedules!I112 -> 334.62385 | J63: =Schedules!J111-Schedules!J112 -> 373.61833 | ... N63: =Schedules!N111-Schedules!N112 -> 538.07101
A64: Current tax liabilities (net) | B64: INR mn | C64: =Schedules!C152 -> 0 | D64: =Schedules!D152 -> 79.7 | E64: =Schedules!E152 -> 516.6 | F64: =Schedules!F152 -> 326.80238 | G64: =Schedules!G152 -> 289.38044 | H64: =Schedules!H152 -> 304.13765 | I64: =Schedules!I152 -> 357.13914 | J64: =Schedules!J152 -> 427.22527 | ... N64: =Schedules!N152 -> 914.597
A65: Total current liabilities | B65: INR mn | C65: =C58+C59+C60+C61+C62+C63+C64 -> 7434.641 | D65: =D58+D59+D60+D61+D62+D63+D64 -> 7347.1694 | E65: =E58+E59+E60+E61+E62+E63+E64 -> 8335.3652 | F65: =F58+F59+F60+F61+F62+F63+F64 -> 10550.679 | G65: =G58+G59+G60+G61+G62+G63+G64 -> 11208.022 | H65: =H58+H59+H60+H61+H62+H63+H64 -> 12073.669 | I65: =I58+I59+I60+I61+I62+I63+I64 -> 13404.989 | J65: =J58+J59+J60+J61+J62+J63+J64 -> 14410.34 | ... N65: =N58+N59+N60+N61+N62+N63+N64 -> 18832.233
A66: TOTAL EQUITY AND LIABILITIES | B66: INR mn | C66: =C52+C57+C65 -> 22751.36 | D66: =D52+D57+D65 -> 31599.75 | E66: =E52+E57+E65 -> 36261.4 | F66: =F52+F57+F65 -> 47914.676 | G66: =G52+G57+G65 -> 55592.993 | H66: =H52+H57+H65 -> 61435.356 | I66: =I52+I57+I65 -> 67632.494 | J66: =J52+J57+J65 -> 73121.688 | ... N66: =N52+N57+N65 -> 97423.69
A67: CHECK: balance sheet balances - must be nil | B67: INR mn | C67: =C48-C66 -> 0 | D67: =D48-D66 -> 0 | E67: =E48-E66 -> 0 | F67: =F48-F66 -> 0 | G67: =G48-G66 -> 0 | H67: =H48-H66 -> 0 | I67: =I48-I66 -> 0 | J67: =J48-J66 -> 0 | ... N67: =N48-N66 -> 0
A69: III. CONSOLIDATED CASH FLOW STATEMENT (indirect method)
A70: Cash flow from operating activities
A71: Profit before tax | B71: INR mn | C71: =C22 -> 1092.34 | D71: =D22 -> 2277.03 | E71: =E22 -> 4661.92 | F71: =F22 -> 4107.6217 | G71: =G22 -> 3546.3289 | H71: =H22 -> 3636.2703 | I71: =I22 -> 4168.2906 | J71: =J22 -> 4870.3291 | ... N71: =N22 -> 9962.9302
A72: Add: depreciation and amortisation | B72: INR mn | C72: =Schedules!C88 -> 1194.36 | D72: =Schedules!D88 -> 1385.73 | E72: =Schedules!E88 -> 1668.55 | F72: =Schedules!F88 -> 2411.2497 | G72: =Schedules!G88 -> 3175.5013 | H72: =Schedules!H88 -> 3768.3003 | I72: =Schedules!I88 -> 4170.2881 | J72: =Schedules!J88 -> 4514.0958 | ... N72: =Schedules!N88 -> 5726.1158
A73: Add: finance costs | B73: INR mn | C73: =Schedules!C131 -> 859.1 | D73: =Schedules!D131 -> 761.64 | E73: =Schedules!E131 -> 392.39 | F73: =Schedules!F131 -> 293.51595 | G73: =Schedules!G131 -> 859.89587 | H73: =Schedules!H131 -> 1259.6847 | I73: =Schedules!I131 -> 1448.3458 | J73: =Schedules!J131 -> 1586.9866 | ... N73: =Schedules!N131 -> 1387.7462
A74: Add: share-based payments and other non-cash items | B74: INR mn | C74: 142.19 | D74: 418.93 | E74: -313.21 | F74: =Schedules!F162 -> 30 | G74: =Schedules!G162 -> 32 | H74: =Schedules!H162 -> 34 | I74: =Schedules!I162 -> 36 | J74: =Schedules!J162 -> 38 | K74: =Schedules!K162 -> 40 | L74: =Schedules!L162 -> 42 | M74: =Schedules!M162 -> 44 | N74: =Schedules!N162 -> 46 | P74: History = equity-settled share-based payments, loss allowances, CWIP written off, unrealised FX and loss on disposal, per the consolidated cash flow statement. Forecast = share-based payments only (credit losses are already expensed in other operating expenses and settle through working capital).
A75: Less: interest and investment income | B75: INR mn | C75: =-Schedules!C134 -> -135.97 | D75: =-Schedules!D134 -> -175.65 | E75: =-Schedules!E134 -> -191.1 | F75: =-Schedules!F134 -> -78.9315 | G75: =-Schedules!G134 -> -83.896123 | H75: =-Schedules!H134 -> -91.842405 | I75: =-Schedules!I134 -> -100.83828 | J75: =-Schedules!J134 -> -110.31242 | ... N75: =-Schedules!N134 -> -155.31222
A76: Operating cash flow before working capital changes | B76: INR mn | C76: =C71+C72+C73+C74+C75 -> 3152.02 | D76: =D71+D72+D73+D74+D75 -> 4667.68 | E76: =E71+E72+E73+E74+E75 -> 6218.55 | F76: =F71+F72+F73+F74+F75 -> 6763.4559 | G76: =G71+G72+G73+G74+G75 -> 7529.83 | H76: =H71+H72+H73+H74+H75 -> 8606.4128 | I76: =I71+I72+I73+I74+I75 -> 9722.0861 | J76: =J71+J72+J73+J74+J75 -> 10899.099 | ... N76: =N71+N72+N73+N74+N75 -> 16967.48
A77: (Increase) / decrease in net working capital | B77: INR mn | C77: -306.04 | D77: -1332.73 | E77: -706.41 | F77: =Schedules!F115 -> -46.834159 | G77: =Schedules!G115 -> -1747.0747 | H77: =Schedules!H115 -> -1356.7443 | I77: =Schedules!I115 -> -998.61356 | J77: =Schedules!J115 -> -1234.4927 | K77: =Schedules!K115 -> -1370.795 | L77: =Schedules!L115 -> -1226.8514 | M77: =Schedules!M115 -> -1594.0118 | N77: =Schedules!N115 -> -1682.372 | P77: History = the sum of the working capital movements disclosed in the consolidated cash flow statement.
A78: Movement in other non-current assets | B78: INR mn | C78: -76.38 | D78: 21.81 | E78: -31.54 | F78: =-(Schedules!F175-Schedules!E175) -> 45.452914 | G78: =-(Schedules!G175-Schedules!F175) -> -112.96001 | H78: =-(Schedules!H175-Schedules!G175) -> -124.32317 | I78: =-(Schedules!I175-Schedules!H175) -> -154.59862 | J78: =-(Schedules!J175-Schedules!I175) -> -155.89473 | K78: =-(Schedules!K175-Schedules!J175) -> -172.6533 | L78: =-(Schedules!L175-Schedules!K175) -> -173.69386 | M78: =-(Schedules!M175-Schedules!L175) -> -172.34774 | N78: =-(Schedules!N175-Schedules!M175) -> -169.04538
A79: Income taxes paid | B79: INR mn | C79: =-Schedules!C153 -> -138.73 | D79: =-Schedules!D153 -> -216.31 | E79: =-Schedules!E153 -> -389.27 | F79: =-Schedules!F153 -> -1006.8036 | G79: =-Schedules!G153 -> -760.87304 | H79: =-Schedules!H153 -> -745.58691 | I79: =-Schedules!I153 -> -839.84635 | J79: =-Schedules!J153 -> -997.97703 | ... N79: =-Schedules!N153 -> -2142.2694
A80: NET CASH FROM OPERATING ACTIVITIES | B80: INR mn | C80: =C76+C77+C78+C79 -> 2630.87 | D80: =D76+D77+D78+D79 -> 3140.45 | E80: =E76+E77+E78+E79 -> 5091.33 | F80: =F76+F77+F78+F79 -> 5755.271 | G80: =G76+G77+G78+G79 -> 4908.9222 | H80: =H76+H77+H78+H79 -> 6379.7585 | I80: =I76+I77+I78+I79 -> 7729.0276 | J80: =J76+J77+J78+J79 -> 8510.7345 | ... N80: =N76+N77+N78+N79 -> 12973.793
A81: check: vs reported CFO (history) - must be nil | B81: INR mn | C81: =C80-2630.87 -> 0 | D81: =D80-3140.45 -> 0 | E81: =E80-5091.33 -> 0
A82: Cash flow from investing activities
A83: Purchase of PP&E, intangibles and CWIP | B83: INR mn | C83: =-Schedules!C52 -> -1816.9 | D83: =-Schedules!D52 -> -3692.8 | E83: =-Schedules!E52 -> -5929.61 | F83: =-Schedules!F52 -> -12000 | G83: =-Schedules!G52 -> -8500 | H83: =-Schedules!H52 -> -7000 | I83: =-Schedules!I52 -> -7500 | J83: =-Schedules!J52 -> -7000 | ... N83: =-Schedules!N52 -> -7500
A84: Proceeds from sale of PP&E | B84: INR mn | C84: 8.53 | D84: 4.77 | E84: 5.18 | F84: =Schedules!F75 -> 15 | G84: =Schedules!G75 -> 15 | H84: =Schedules!H75 -> 15 | I84: =Schedules!I75 -> 15 | J84: =Schedules!J75 -> 15 | K84: =Schedules!K75 -> 15 | L84: =Schedules!L75 -> 15 | M84: =Schedules!M75 -> 15 | N84: =Schedules!N75 -> 15 | P84: Per the consolidated cash flow statement.
A85: Movement in bank deposits and current investments | B85: INR mn | C85: -237.19 | D85: -1837.73 | E85: 1745.64 | F85: =-(Schedules!F132-Schedules!E132) -> -37.9745 | G85: =-(Schedules!G132-Schedules!F132) -> -39.873225 | H85: =-(Schedules!H132-Schedules!G132) -> -41.866886 | I85: =-(Schedules!I132-Schedules!H132) -> -43.960231 | J85: =-(Schedules!J132-Schedules!I132) -> -46.158242 | K85: =-(Schedules!K132-Schedules!J132) -> -48.466154 | L85: =-(Schedules!L132-Schedules!K132) -> -50.889462 | M85: =-(Schedules!M132-Schedules!L132) -> -53.433935 | N85: =-(Schedules!N132-Schedules!M132) -> -56.105632 | P85: History = movement in other bank balances, corporate deposits, mutual funds and investments in other entities.
A86: Interest income received | B86: INR mn | C86: 121.75 | D86: 159.11 | E86: 224.68 | F86: =Schedules!F134 -> 78.9315 | G86: =Schedules!G134 -> 83.896123 | H86: =Schedules!H134 -> 91.842405 | I86: =Schedules!I134 -> 100.83828 | J86: =Schedules!J134 -> 110.31242 | K86: =Schedules!K134 -> 120.27874 | L86: =Schedules!L134 -> 131.3987 | M86: =Schedules!M134 -> 143.0973 | N86: =Schedules!N134 -> 155.31222
A87: NET CASH USED IN INVESTING ACTIVITIES | B87: INR mn | C87: =C83+C84+C85+C86 -> -1923.81 | D87: =D83+D84+D85+D86 -> -5366.65 | E87: =E83+E84+E85+E86 -> -3954.11 | F87: =F83+F84+F85+F86 -> -11944.043 | G87: =G83+G84+G85+G86 -> -8440.9771 | H87: =H83+H84+H85+H86 -> -6935.0245 | I87: =I83+I84+I85+I86 -> -7428.1219 | J87: =J83+J84+J85+J86 -> -6920.8458 | ... N87: =N83+N84+N85+N86 -> -7385.7934
A88: Cash flow from financing activities
A89: Proceeds from borrowings | B89: INR mn | C89: 998.93 | D89: 534.08 | E89: 255.04 | F89: =Schedules!F126 -> 7074.1304 | G89: =Schedules!G126 -> 6141.4878 | H89: =Schedules!H126 -> 4362.0575 | I89: =Schedules!I126 -> 4070.8381 | J89: =Schedules!J126 -> 3202.1156 | K89: =Schedules!K126 -> 2320.8542 | L89: =Schedules!L126 -> 1922.5168 | M89: =Schedules!M126 -> 417.40131 | N89: =Schedules!N126 -> 0
A90: Repayment of borrowings | B90: INR mn | C90: -667.28 | D90: -6238.3 | E90: -588.9 | F90: =-Schedules!F124+Schedules!F127 -> -158.54167 | G90: =-Schedules!G124+Schedules!G127 -> -1311.1398 | H90: =-Schedules!H124+Schedules!H127 -> -2116.1978 | I90: =-Schedules!I124+Schedules!I127 -> -2490.5078 | J90: =-Schedules!J124+Schedules!J127 -> -2753.8962 | K90: =-Schedules!K124+Schedules!K127 -> -2828.5994 | L90: =-Schedules!L124+Schedules!L127 -> -2743.9752 | M90: =-Schedules!M124+Schedules!M127 -> -2607.0654 | N90: =-Schedules!N124+Schedules!N127 -> -3553.178
A91: Repayment of lease liabilities - principal | B91: INR mn | C91: =-Schedules!C84 -> -441.05 | D91: =-Schedules!D84 -> -510.64 | E91: =-Schedules!E84 -> -615.52 | F91: =-Schedules!F84 -> -521.9829 | G91: =-Schedules!G84 -> -469.34487 | H91: =-Schedules!H84 -> -442.85837 | I91: =-Schedules!I84 -> -437.36774 | J91: =-Schedules!J84 -> -447.9534 | ... N91: =-Schedules!N84 -> -599.55766
A92: Repayment of lease liabilities - interest | B92: INR mn | C92: =-Schedules!C83 -> -253.53 | D92: =-Schedules!D83 -> -248.98 | E92: =-Schedules!E83 -> -232.17 | F92: =-Schedules!F83 -> -212.6597 | G92: =-Schedules!G83 -> -191.21458 | H92: =-Schedules!H83 -> -180.42378 | I92: =-Schedules!I83 -> -178.18686 | J92: =-Schedules!J83 -> -182.49953 | ... N92: =-Schedules!N83 -> -244.26423
A93: Interest paid on borrowings | B93: INR mn | C93: -599.73 | D93: -525.12 | E93: -107.7 | F93: =-Schedules!F123 -> -80.85625 | G93: =-Schedules!G123 -> -668.6813 | H93: =-Schedules!H123 -> -1079.2609 | I93: =-Schedules!I123 -> -1270.159 | J93: =-Schedules!J123 -> -1404.487 | K93: =-Schedules!K123 -> -1442.5857 | L93: =-Schedules!L123 -> -1399.4273 | M93: =-Schedules!M123 -> -1329.6034 | N93: =-Schedules!N123 -> -1143.4819 | P93: History per the consolidated cash flow statement (net of borrowing costs capitalised).
A94: Proceeds from issue of equity shares (net of issue costs) | B94: INR mn | C94: 9.67 | D94: 10003.22 | E94: 52.45 | F94: =Schedules!F159 -> 150 | G94: =Schedules!G159 -> 150 | H94: =Schedules!H159 -> 150 | I94: =Schedules!I159 -> 150 | J94: =Schedules!J159 -> 150 | K94: =Schedules!K159 -> 150 | L94: =Schedules!L159 -> 150 | M94: =Schedules!M159 -> 150 | N94: =Schedules!N159 -> 150 | P94: FY25 includes the IPO fresh issue of Rs 9,500mn net of transaction costs.
A95: Dividend paid | B95: INR mn | C95: =-Schedules!C164 -> 0 | D95: =-Schedules!D164 -> 0 | E95: =-Schedules!E164 -> 0 | F95: =-Schedules!F164 -> 0 | G95: =-Schedules!G164 -> 0 | H95: =-Schedules!H164 -> 0 | I95: =-Schedules!I164 -> 0 | J95: =-Schedules!J164 -> 0 | ... N95: =-Schedules!N164 -> 0
A96: NET CASH FROM / (USED IN) FINANCING ACTIVITIES | B96: INR mn | C96: =C89+C90+C91+C92+C93+C94+C95 -> -952.99 | D96: =D89+D90+D91+D92+D93+D94+D95 -> 3014.26 | E96: =E89+E90+E91+E92+E93+E94+E95 -> -1236.8 | F96: =F89+F90+F91+F92+F93+F94+F95 -> 6250.0899 | G96: =G89+G90+G91+G92+G93+G94+G95 -> 3651.1073 | H96: =H89+H90+H91+H92+H93+H94+H95 -> 693.31671 | I96: =I89+I90+I91+I92+I93+I94+I95 -> -155.38316 | J96: =J89+J90+J91+J92+J93+J94+J95 -> -1436.7205 | ... N96: =N89+N90+N91+N92+N93+N94+N95 -> -5390.4818
A97: Cash reconciliation
A98: Net increase / (decrease) in cash | B98: INR mn | C98: =C80+C87+C96 -> -245.93 | D98: =D80+D87+D96 -> 788.06 | E98: =E80+E87+E96 -> -99.58 | F98: =F80+F87+F96 -> 61.317961 | G98: =G80+G87+G96 -> 119.05242 | H98: =H80+H87+H96 -> 138.05069 | I98: =I80+I87+I96 -> 145.52251 | J98: =J80+J87+J96 -> 153.16816 | ... N98: =N80+N87+N96 -> 197.518
A99: Effect of exchange differences on cash | B99: INR mn | C99: 10.33 | D99: 2.78 | E99: 8.2 | F99: 0 | G99: 0 | H99: 0 | I99: 0 | J99: 0 | K99: 0 | L99: 0 | M99: 0 | N99: 0
A100: Cash and cash equivalents - opening | B100: INR mn | C100: 355.29 | D100: 119.69 | E100: 910.52 | F100: =Schedules!E137 -> 819.14 | G100: =Schedules!F137 -> 880.45796 | H100: =Schedules!G137 -> 999.51038 | I100: =Schedules!H137 -> 1137.5611 | J100: =Schedules!I137 -> 1283.0836 | K100: =Schedules!J137 -> 1436.2517 | L100: =Schedules!K137 -> 1610.1847 | M100: =Schedules!L137 -> 1793.2673 | N100: =Schedules!M137 -> 1984.1317
A101: Cash and cash equivalents - closing | B101: INR mn | C101: =C100+C98+C99 -> 119.69 | D101: =D100+D98+D99 -> 910.53 | E101: =E100+E98+E99 -> 819.14 | F101: =F100+F98+F99 -> 880.45796 | G101: =G100+G98+G99 -> 999.51038 | H101: =H100+H98+H99 -> 1137.5611 | I101: =I100+I98+I99 -> 1283.0836 | J101: =J100+J98+J99 -> 1436.2517 | ... N101: =N100+N98+N99 -> 2181.6497
A102: CHECK: closing cash vs balance sheet - must be nil | B102: INR mn | F102: =F101-F46 -> 0 | G102: =G101-G46 -> 0 | H102: =H101-H46 -> 0 | I102: =I101-I46 -> 0 | J102: =J101-J46 -> 0 | K102: =K101-K46 -> 0 | L102: =L101-L46 -> 0 | M102: =M101-M46 -> 0 | N102: =N101-N46 -> 0
A103: Note: for FY2025A the statutory cash flow closing balance (910.52) differs from the balance sheet cash line (911.19) by a 0.67 book overdraft reclassification; historical statements are presented as reported.
...

Sheet Schedules
A1: SHEET 4 | SUPPORTING SCHEDULES
A2: Cost build, PP&E and capex, working capital, debt and interest, tax, equity and share count. Every forecast line in the Statements sheet is driven from this sheet.
B3: INR mn | C3: FY2024A | D3: FY2025A | E3: FY2026A | F3: FY2027E | G3: FY2028E | H3: FY2029E | I3: FY2030E | J3: FY2031E | K3: FY2032E | L3: FY2033E | M3: FY2034E | N3: FY2035E | P3: Source / basis
A5: 0. DRIVERS IMPORTED FROM THE REVENUE MODEL
A6: Revenue from operations | B6: INR mn | C6: =Revenue_Model!C53 -> 14651.78 | D6: =Revenue_Model!D53 -> 16945.7 | E6: =Revenue_Model!E53 -> 21924.92 | F6: =Revenue_Model!F53 -> 25155.942 | G6: =Revenue_Model!G53 -> 28557.44 | H6: =Revenue_Model!H53 -> 32501.745 | I6: =Revenue_Model!I53 -> 36659.531 | J6: =Revenue_Model!J53 -> 41035.764 | ... N6: =Revenue_Model!N53 -> 62332.848
A7: CRO / Discovery revenue | B7: INR mn | C7: =Revenue_Model!C17 -> 4970 | D7: =Revenue_Model!D17 -> 6260 | E7: =Revenue_Model!E17 -> 7750 | F7: =Revenue_Model!F17 -> 8900.6064 | G7: =Revenue_Model!G17 -> 10058.487 | H7: =Revenue_Model!H17 -> 11261.4 | I7: =Revenue_Model!I17 -> 12449.618 | J7: =Revenue_Model!J17 -> 13635.75 | ... N7: =Revenue_Model!N17 -> 18008.098
A8: CDMO / CMC revenue | B8: INR mn | C8: =Revenue_Model!C39 -> 9680 | D8: =Revenue_Model!D39 -> 10680 | E8: =Revenue_Model!E39 -> 14170 | F8: =Revenue_Model!F39 -> 16255.335 | G8: =Revenue_Model!G39 -> 18498.952 | H8: =Revenue_Model!H39 -> 21240.345 | I8: =Revenue_Model!I39 -> 24209.913 | J8: =Revenue_Model!J39 -> 27400.015 | ... N8: =Revenue_Model!N39 -> 44324.749
A9: Net group headcount additions <-- INPUT | B9: count | F9: 320 | G9: 300 | H9: 280 | I9: 260 | J9: 240 | K9: 220 | L9: 200 | M9: 180 | N9: 160 | P9: FY26 net addition was approximately +400. Additions taper so headcount growth runs below revenue growth - that is what produces employee-cost operating leverage.
A10: Total employees (period end) | B10: count | C10: 3345 | D10: 3401 | E10: 3800 | F10: =E10+F9 -> 4120 | G10: =F10+G9 -> 4420 | H10: =G10+H9 -> 4700 | I10: =H10+I9 -> 4960 | J10: =I10+J9 -> 5200 | K10: =J10+K9 -> 5420 | L10: =K10+L9 -> 5620 | M10: =L10+M9 -> 5800 | N10: =M10+N9 -> 5960 | P10: FY25: 3,401 permanent employees (FY25 Annual Report p.33). FY26: 3,800+ (Q4FY26 deck p.15). FY24: ANALYST ESTIMATE derived from FY24 employee cost divided by FY25 average cost deflated by the disclosed 9.12% salary increase.
A11: Installed GMP capacity | B11: KL | C11: =Revenue_Model!C46 -> 475 | D11: =Revenue_Model!D46 -> 609 | E11: =Revenue_Model!E46 -> 700 | F11: =Revenue_Model!F46 -> 925 | G11: =Revenue_Model!G46 -> 1150 | H11: =Revenue_Model!H46 -> 1250 | I11: =Revenue_Model!I46 -> 1400 | J11: =Revenue_Model!J46 -> 1500 | ... N11: =Revenue_Model!N46 -> 2100
A12: Capacity commissioned in year | B12: KL | C12: =Revenue_Model!C45 -> 0 | D12: =Revenue_Model!D45 -> 134 | E12: =Revenue_Model!E45 -> 91 | F12: =Revenue_Model!F45 -> 225 | G12: =Revenue_Model!G45 -> 225 | H12: =Revenue_Model!H45 -> 100 | I12: =Revenue_Model!I45 -> 150 | J12: =Revenue_Model!J45 -> 100 | ... N12: =Revenue_Model!N45 -> 100
A14: 1. COST AND MARGIN SCHEDULE
A15: 1a. Material, chemicals and reagents (net of change in WIP)
A16: Reported material cost, net of WIP movement | B16: INR mn | C16: 4457.3 | D16: 4657.64 | E16: 5708.92 | P16: FY25 AR p.179 and FY26 audited results: cost of material, chemicals & reagents consumed plus changes in inventories of WIP. REPORTED FACT.
A17: CRO consumables ratio (% of CRO revenue) | B17: % | C17: 0.08 | D17: 0.08 | E17: 0.08 | F17: 0.08 | G17: 0.08 | H17: 0.08 | I17: 0.08 | J17: 0.08 | K17: 0.08 | L17: 0.08 | M17: 0.08 | N17: 0.08 | P17: ANALYST ASSUMPTION - discovery work is labour-intensive; reagents and consumables run at a high single-digit percentage of revenue.
A18: CDMO material ratio (% of CDMO revenue) | B18: % | C18: =(C16-C7*C17)/C8 -> 0.4193905 | D18: =(D16-D7*D17)/D8 -> 0.38921723 | E18: =(E16-E7*E17)/E8 -> 0.35913338 | F18: 0.37 | G18: 0.365 | H18: 0.36 | I18: 0.358 | J18: 0.356 | K18: 0.355 | L18: 0.354 | M18: 0.353 | N18: 0.352 | P18: History derived so total material cost ties to the audited number: 41.9% FY24, 38.9% FY25, 35.9% FY26. FY27 normalises upward because FY26 benefited from a Rs 34 Cr destocking provision reversal; thereafter mix and scale drive a slow decline.
A19: Material cost | B19: INR mn | C19: =C8*C18+C7*C17 -> 4457.3 | D19: =D8*D18+D7*D17 -> 4657.64 | E19: =E8*E18+E7*E17 -> 5708.92 | F19: =F8*F18+F7*F17 -> 6726.5226 | G19: =G8*G18+G7*G17 -> 7556.7966 | H19: =H8*H18+H7*H17 -> 8547.4362 | I19: =I8*I18+I7*I17 -> 9663.1183 | J19: =J8*J18+J7*J17 -> 10845.265 | ... N19: =N8*N18+N7*N17 -> 17042.96
A20: check: vs reported (history) - must be nil | B20: INR mn | C20: =C19-C16 -> 0 | D20: =D19-D16 -> 0 | E20: =E19-E16 -> 0
A21: Material margin | B21: INR mn | C21: =C6-C19 -> 10194.48 | D21: =D6-D19 -> 12288.06 | E21: =E6-E19 -> 16216 | F21: =F6-F19 -> 18429.419 | G21: =G6-G19 -> 21000.643 | H21: =H6-H19 -> 23954.309 | I21: =I6-I19 -> 26996.413 | J21: =J6-J19 -> 30190.499 | ... N21: =N6-N19 -> 45289.888
A22: Material margin (%) | B22: % | C22: =C21/C6 -> 0.6957844 | D22: =D21/D6 -> 0.72514325 | E22: =E21/E6 -> 0.73961501 | F22: =F21/F6 -> 0.73260701 | G22: =G21/G6 -> 0.73538256 | H22: =H21/H6 -> 0.73701608 | I22: =I21/I6 -> 0.73640911 | J22: =J21/J6 -> 0.73571187 | ... N22: =N21/N6 -> 0.72658141 | P22: Company discloses material margin of 72.5% in FY25 and 74.0% in FY26 (Q4FY26 deck p.10) - the build reproduces both.
A23: 1b. Employee benefits expense
A24: Reported employee benefits expense | B24: INR mn | C24: 4949.05 | D24: 5491.18 | E24: 6830.55 | P24: FY25 AR p.179 note 31; FY26 audited results. REPORTED FACT.
A25: Average cost per employee - growth (%) | B25: % | F25: 0.075 | G25: 0.072 | H25: 0.07 | I25: 0.068 | J25: 0.065 | K25: 0.062 | L25: 0.06 | M25: 0.058 | N25: 0.055 | P25: ANALYST ASSUMPTION. FY25 average salary increase for non-managerial staff was 9.12% (FY25 AR p.60); mix effects from senior scientific and leadership hiring add to base wage inflation.
A26: Average cost per employee | B26: INR mn | C26: =C24/C10 -> 1.4795366 | D26: =D24/D10 -> 1.6145781 | E26: =E24/E10 -> 1.7975132 | F26: =E26*(1+F25) -> 1.9323266 | G26: =F26*(1+G25) -> 2.0714542 | H26: =G26*(1+H25) -> 2.216456 | I26: =H26*(1+I25) -> 2.367175 | J26: =I26*(1+J25) -> 2.5210413 | K26: =J26*(1+K25) -> 2.6773459 | L26: =K26*(1+L25) -> 2.8379866 | M26: =L26*(1+M25) -> 3.0025899 | N26: =M26*(1+N25) -> 3.1677323 | P26: History derived. FY24 1.48, FY25 1.61, FY26 1.80 INR mn per employee.
A27: Employee benefits expense | B27: INR mn | C27: =C10*C26 -> 4949.05 | D27: =D10*D26 -> 5491.18 | E27: =E10*E26 -> 6830.55 | F27: =F10*F26 -> 7961.1858 | G27: =G10*G26 -> 9155.8274 | H27: =H10*H26 -> 10417.343 | I27: =I10*I26 -> 11741.188 | J27: =J10*J26 -> 13109.415 | ... N27: =N10*N26 -> 18879.685
A28: check: vs reported (history) - must be nil | B28: INR mn | C28: =C27-C24 -> 0 | D28: =D27-D24 -> 0 | E28: =E27-E24 -> 0
A29: Employee cost (% of revenue) | B29: % | C29: =C27/C6 -> 0.33777807 | D29: =D27/D6 -> 0.32404563 | E29: =E27/E6 -> 0.31154276 | F29: =F27/F6 -> 0.31647337 | G29: =G27/G6 -> 0.32061093 | H29: =H27/H6 -> 0.32051642 | I29: =I27/I6 -> 0.32027654 | J29: =J27/J6 -> 0.31946316 | ... N29: =N27/N6 -> 0.302885
A30: 1c. Other operating expenses
A31: Reported other expenses | B31: INR mn | C31: 2390.54 | D31: 2740.27 | E31: 3073.86 | P31: FY25 AR p.179 note 34; FY26 audited results. REPORTED FACT.
A32: Production & facility overhead - reported / estimated (history) | B32: INR mn | C32: 1322.67 | D32: 1404.59 | E32: 1942.5 | P32: FY24 and FY25 are the sum of power and fuel, stores and spares and repairs and maintenance per note 34. FY26 is apportioned pro-rata to the growth in other expenses excluding credit losses, because the FY26 annual report is not yet published. ANALYST ESTIMATE for FY26.
A33: Production & facility overhead - variable (% of CDMO revenue) | B33: % | C33: 0.0888 | D33: 0.0855 | E33: 0.0891 | F33: 0.0891 | G33: 0.0891 | H33: 0.0891 | I33: 0.0891 | J33: 0.0891 | K33: 0.0891 | L33: 0.0891 | M33: 0.0891 | N33: 0.0891 | P33: Variable element of site overhead - power, fuel and consumable spares that flow with production volume.
A34: Production & facility overhead - fixed (INR mn per installed KL) | B34: INR mn/KL | C34: =(C32-C8*C33)/(C11-C12/2) -> 0.97491789 | D34: =(D32-D8*D33)/(D11-D12/2) -> 0.90673432 | E34: =(E32-E8*E33)/(E11-E12/2) -> 1.0388892 | F34: =E34*1.01 -> 1.0492781 | G34: =F34*1.01 -> 1.0597709 | H34: =G34*1.01 -> 1.0703686 | I34: =H34*1.01 -> 1.0810723 | J34: =I34*1.01 -> 1.091883 | K34: =J34*1.01 -> 1.1028019 | L34: =K34*1.01 -> 1.1138299 | M34: =L34*1.01 -> 1.1249682 | N34: =M34*1.01 -> 1.1362178 | P34: Derived for history so the bucket ties exactly. Fixed site overhead - minimum demand charges, plant maintenance, EHS. Captures under-absorption when new blocks are commissioned ahead of revenue. Escalated 1% p.a., reflecting scale efficiency and the shift of the Bidar site to 100% renewable power.
A35: Production & facility overhead | B35: INR mn | C35: =C8*C33+(C11-C12/2)*C34 -> 1322.67 | D35: =D8*D33+(D11-D12/2)*D34 -> 1404.59 | E35: =E8*E33+(E11-E12/2)*E34 -> 1942.5 | F35: =F8*F33+(F11-F12/2)*F34 -> 2300.8888 | G35: =G8*G33+(G11-G12/2)*G34 -> 2747.769 | H35: =H8*H33+(H11-H12/2)*H34 -> 3176.9571 | I35: =I8*I33+(I11-I12/2)*I34 -> 3589.5241 | J35: =J8*J33+(J11-J12/2)*J34 -> 4024.5717 | ... N35: =N8*N33+(N11-N12/2)*N34 -> 6278.5817 | P35: Fixed overhead is charged on AVERAGE installed capacity for the year, so a block commissioned mid-year carries only half a year of site cost.
A36: Corporate, selling, freight, travel & technology (% of revenue) | B36: % | C36: =(C31-C35-C38)/C6 -> 0.06167783 | D36: =(D31-D35-D38)/D6 -> 0.058497436 | E36: =(E31-E35-E38)/E6 -> 0.062512885 | F36: 0.0605 | G36: 0.0595 | H36: 0.0585 | I36: 0.0575 | J36: 0.057 | K36: 0.0565 | L36: 0.056 | M36: 0.0555 | N36: 0.055 | P36: Legal and professional, travel, freight, insurance, membership, communication and IT. Derived for history so the build ties exactly (6.2% FY24, 5.9% FY25, 6.3% FY26). Scenario lever L_opex is added to this ratio in the forecast.
A37: Corporate, selling and other expenses | B37: INR mn | C37: =C6*C36 -> 903.69 | D37: =D6*D36 -> 991.28 | E37: =E6*E36 -> 1370.59 | F37: =F6*F36 -> 1521.9345 | G37: =G6*G36 -> 1699.1677 | H37: =H6*H36 -> 1901.3521 | I37: =I6*I36 -> 2107.923 | J37: =J6*J36 -> 2339.0386 | ... N37: =N6*N36 -> 3428.3066
A38: Credit loss allowance / bad debts (net) | B38: INR mn | C38: 164.18 | D38: 344.4 | E38: -239.23 | P38: FY24 and FY25 from note 34 (loss allowance on receivables and contract assets, bad debts, CWIP written off). FY26 is a NET REVERSAL as the destocked commercial product resumed shipment. REPORTED / DERIVED.
A39: Normalised credit loss (% of revenue) | B39: % | F39: 0.0045 | G39: 0.0045 | H39: 0.0045 | I39: 0.0045 | J39: 0.0045 | K39: 0.0045 | L39: 0.0045 | M39: 0.0045 | N39: 0.0045 | P39: ANALYST ASSUMPTION - normalised through the cycle. FY24 1.1%, FY25 2.0%, FY26 (1.1)% actual.
A40: Other operating expenses | B40: INR mn | C40: =C35+C37+C38 -> 2390.54 | D40: =D35+D37+D38 -> 2740.27 | E40: =E35+E37+E38 -> 3073.86 | F40: =F35+F37+F6*F39 -> 3936.0251 | G40: =G35+G37+G6*G39 -> 4575.4451 | H40: =H35+H37+H6*H39 -> 5224.567 | I40: =I35+I37+I6*I39 -> 5862.415 | J40: =J35+J37+J6*J39 -> 6548.2712 | K40: =K35+K37+K6*K39 -> 7322.2269 | L40: =L35+L37+L6*L39 -> 8196.7588 | M40: =M35+M37+M6*M39 -> 9105.6238 | N40: =N35+N37+N6*N39 -> 9987.3862
A41: check: vs reported (history) - must be nil | B41: INR mn | C41: =C40-C31 -> 0 | D41: =D40-D31 -> 0 | E41: =E40-E31 -> 0
A42: 1d. EBITDA
A43: Net FX gain (% of revenue) | B43: % | C43: =C44/C6 -> 0.0099824049 | D43: =D44/D6 -> 0.011257133 | E43: =E44/E6 -> 0.01369127 | F43: 0.008 | G43: 0.008 | H43: 0.008 | I43: 0.008 | J43: 0.008 | K43: 0.008 | L43: 0.008 | M43: 0.008 | N43: 0.008 | P43: History: 1.00% FY24, 1.13% FY25, 1.37% FY26. Roughly 97% of revenue is exported, so realised hedging and translation gains have been persistent. Forecast at a deliberately conservative 0.8% - below every historical year - because forecasting FX gains flatters the margin.
A44: Net foreign exchange gain / (loss) | B44: INR mn | C44: 146.26 | D44: 190.76 | E44: 300.18 | F44: =F6*F43 -> 201.24753 | G44: =G6*G43 -> 228.45952 | H44: =H6*H43 -> 260.01396 | I44: =I6*I43 -> 293.27625 | J44: =J6*J43 -> 328.28611 | K44: =K6*K43 -> 368.04222 | L44: =L6*L43 -> 409.88967 | M44: =M6*M43 -> 453.51581 | N44: =N6*N43 -> 498.66278 | P44: FY24 146.26 and FY25 190.76 from note 28 (other income). FY26 300.18 derived as other income less interest income and the FVTPL gain, and reconciles to the Rs 30 Cr FX gain in the Q4FY26 deck EBITDA bridge. The company includes net FX within EBITDA, so the model follows that definition and shows EBITDA excluding FX as a memo line.
A45: EBITDA (company definition, includes net FX) | B45: INR mn | C45: =C6-C19-C27-C40+C44 -> 3001.15 | D45: =D6-D19-D27-D40+D44 -> 4247.37 | E45: =E6-E19-E27-E40+E44 -> 6611.77 | F45: =F6-F19-F27-F40+F44 -> 6733.4559 | G45: =G6-G19-G27-G40+G44 -> 7497.83 | H45: =H6-H19-H27-H40+H44 -> 8572.4128 | I45: =I6-I19-I27-I40+I44 -> 9686.0861 | J45: =J6-J19-J27-J40+J44 -> 10861.099 | ... N45: =N6-N19-N27-N40+N44 -> 16921.48
A46: EBITDA margin (%) | B46: % | C46: =C45/C6 -> 0.20483177 | D46: =D45/D6 -> 0.25064589 | E46: =E45/E6 -> 0.30156416 | F46: =F45/F6 -> 0.26766861 | G46: =G45/G6 -> 0.2625526 | H46: =H45/H6 -> 0.26375239 | I46: =I45/I6 -> 0.2642174 | J46: =J45/J6 -> 0.26467398 | ... N46: =N45/N6 -> 0.27146971 | P46: Reported: 20.5% FY24, 25.1% FY25, 30.2% FY26. Guidance 28-30% (Q4FY26 call).
A47: memo: EBITDA excluding net FX | B47: INR mn | C47: =C45-C44 -> 2854.89 | D47: =D45-D44 -> 4056.61 | E47: =E45-E44 -> 6311.59 | F47: =F45-F44 -> 6532.2083 | G47: =G45-G44 -> 7269.3705 | H47: =H45-H44 -> 8312.3989 | I47: =I45-I44 -> 9392.8099 | J47: =J45-J44 -> 10532.813 | ... N47: =N45-N44 -> 16422.817
A48: memo: EBITDA margin excluding net FX (%) | B48: % | C48: =C47/C6 -> 0.19484936 | D48: =D47/D6 -> 0.23938875 | E48: =E47/E6 -> 0.28787289 | F48: =F47/F6 -> 0.25966861 | G48: =G47/G6 -> 0.2545526 | H48: =H47/H6 -> 0.25575239 | I48: =I47/I6 -> 0.2562174 | J48: =J47/J6 -> 0.25667398 | ... N48: =N47/N6 -> 0.26346971
A49: FLAG: EBITDA margin vs 28-30% guidance | F49: =IF(F46<0.28,"BELOW GUIDANCE",IF(F46>0.305,"ABOVE GUIDANCE","in range")) -> BELOW GUIDANCE | G49: =IF(G46<0.28,"BELOW GUIDANCE",IF(G46>0.305,"ABOVE GUIDANCE","in range")) -> BELOW GUIDANCE | H49: =IF(H46<0.28,"BELOW GUIDANCE",IF(H46>0.305,"ABOVE GUIDANCE","in range")) -> BELOW GUIDANCE | I49: =IF(I46<0.28,"BELOW GUIDANCE",IF(I46>0.305,"ABOVE GUIDANCE","in range")) -> BELOW GUIDANCE | J49: =IF(J46<0.28,"BELOW GUIDANCE",IF(J46>0.305,"ABOVE GUIDANCE","in range")) -> BELOW GUIDANCE | K49: =IF(K46<0.28,"BELOW GUIDANCE",IF(K46>0.305,"ABOVE GUIDANCE","in range")) -> BELOW GUIDANCE | L49: =IF(L46<0.28,"BELOW GUIDANCE",IF(L46>0.305,"ABOVE GUIDANCE","in range")) -> BELOW GUIDANCE | M49: =IF(M46<0.28,"BELOW GUIDANCE",IF(M46>0.305,"ABOVE GUIDANCE","in range")) -> BELOW GUIDANCE | N49: =IF(N46<0.28,"BELOW GUIDANCE",IF(N46>0.305,"ABOVE GUIDANCE","in range")) -> BELOW GUIDANCE
A51: 2. PP&E, CAPEX, CWIP AND DEPRECIATION SCHEDULE
A52: Capex (cash, incl. capital advances & creditors) <-- INPUT | B52: INR mn | C52: 1816.9 | D52: 3692.8 | E52: 5929.61 | F52: 12000 | G52: 8500 | H52: 7000 | I52: 7500 | J52: 7000 | K52: 7000 | L52: 8000 | M52: 7500 | N52: 7500 | P52: History = purchase of PP&E and intangibles per the consolidated cash flow statement; company-stated FY26 capex was Rs 633 Cr. FY27 = Rs 1,200 Cr, the midpoint of the guided Rs 1,100-1,300 Cr (Q4FY26 call). FY28 onward is an ANALYST ASSUMPTION reflecting completion of the 1,150 KL programme and a second Hyderabad site.
A53: Capex (% of revenue) | B53: % | C53: =C52/C6 -> 0.12400541 | D53: =D52/D6 -> 0.21791959 | E53: =E52/E6 -> 0.2704507 | F53: =F52/F6 -> 0.47702448 | G53: =G52/G6 -> 0.29764573 | H53: =H52/H6 -> 0.21537305 | I53: =I52/I6 -> 0.20458527 | J53: =J52/J6 -> 0.17058291 | ... N53: =N52/N6 -> 0.12032179
A54: Maintenance capex (% of revenue) | B54: % | C54: 0.035 | D54: 0.035 | E54: 0.035 | F54: 0.035 | G54: 0.035 | H54: 0.035 | I54: 0.035 | J54: 0.035 | K54: 0.035 | L54: 0.035 | M54: 0.035 | N54: 0.035 | P54: ANALYST ASSUMPTION - routine replacement, compliance and EHS spend.
A55: of which: maintenance capex | B55: INR mn | C55: =MIN(C52,C6*C54) -> 512.8123 | D55: =MIN(D52,D6*D54) -> 593.0995 | E55: =MIN(E52,E6*E54) -> 767.3722 | F55: =MIN(F52,F6*F54) -> 880.45796 | G55: =MIN(G52,G6*G54) -> 999.51038 | H55: =MIN(H52,H6*H54) -> 1137.5611 | I55: =MIN(I52,I6*I54) -> 1283.0836 | J55: =MIN(J52,J6*J54) -> 1436.2517 | ... N55: =MIN(N52,N6*N54) -> 2181.6497
A56: of which: growth capex | B56: INR mn | C56: =C52-C55 -> 1304.0877 | D56: =D52-D55 -> 3099.7005 | E56: =E52-E55 -> 5162.2378 | F56: =F52-F55 -> 11119.542 | G56: =G52-G55 -> 7500.4896 | H56: =H52-H55 -> 5862.4389 | I56: =I52-I55 -> 6216.9164 | J56: =J52-J55 -> 5563.7483 | ... N56: =N52-N55 -> 5318.3503
A57: CDMO share of capex (%) | B57: % | C57: 0.65 | D57: 0.65 | E57: 0.62 | F57: 0.7 | G57: 0.68 | H57: 0.66 | I57: 0.66 | J57: 0.65 | K57: 0.65 | L57: 0.65 | M57: 0.65 | N57: 0.65 | P57: REPORTED: FY26 62% CDMO / 38% CRO; FY27 guided 70% CDMO / 30% CRO on the deck and 65/35 on the call (Q4FY26 deck p.7). FY24-25 ANALYST ESTIMATE.
A58: of which: CDMO / manufacturing capex | B58: INR mn | C58: =C52*C57 -> 1180.985 | D58: =D52*D57 -> 2400.32 | E58: =E52*E57 -> 3676.3582 | F58: =F52*F57 -> 8400 | G58: =G52*G57 -> 5780 | H58: =H52*H57 -> 4620 | I58: =I52*I57 -> 4950 | J58: =J52*J57 -> 4550 | ... N58: =N52*N57 -> 4875
A59: of which: CRO / R&D capex | B59: INR mn | C59: =C52-C58 -> 635.915 | D59: =D52-D58 -> 1292.48 | E59: =E52-E58 -> 2253.2518 | F59: =F52-F58 -> 3600 | G59: =G52-G58 -> 2720 | H59: =H52-H58 -> 2380 | I59: =I52-I58 -> 2550 | J59: =J52-J58 -> 2450 | ... N59: =N52-N58 -> 2625
A60: 2a. Intangible assets
A61: Intangible additions (% of capex) | B61: % | F61: 0.025 | G61: 0.025 | H61: 0.025 | I61: 0.025 | J61: 0.025 | K61: 0.025 | L61: 0.025 | M61: 0.025 | N61: 0.025 | P61: ANALYST ASSUMPTION - software, digital and AI tooling. Management confirmed AI tools are capitalised (Q4FY26 call).
A62: Intangible additions | B62: INR mn | E62: 19.16 | F62: =F52*F61 -> 300 | G62: =G52*G61 -> 212.5 | H62: =H52*H61 -> 175 | I62: =I52*I61 -> 187.5 | J62: =J52*J61 -> 175 | K62: =K52*K61 -> 175 | L62: =L52*L61 -> 200 | M62: =M52*M61 -> 187.5 | N62: =N52*N61 -> 187.5 | P62: FY26 derived from the movement in intangible assets and estimated amortisation.
A63: Amortisation of intangible assets | B63: INR mn | C63: 87.67 | D63: 96.19 | E63: 66.55 | F63: =(E64+F62)*0.22 -> 79.4574 | G63: =(F64+G62)*0.22 -> 108.72677 | H63: =(G64+H62)*0.22 -> 123.30688 | I63: =(H64+I62)*0.22 -> 137.42937 | J63: =(I64+J62)*0.22 -> 145.69491 | K63: =(J64+K62)*0.22 -> 152.14203 | L63: =(K64+L62)*0.22 -> 162.67078 | M63: =(L64+M62)*0.22 -> 168.13321 | N63: =(M64+N62)*0.22 -> 172.3939 | P63: FY24 and FY25 from note 33. FY26 is an ANALYST ESTIMATE within the reported total D&A of 1,668.55. Amortised at ~22% p.a.
A64: Intangible assets - closing | B64: INR mn | C64: 137.73 | D64: 108.56 | E64: 61.17 | F64: =E64+F62-F63 -> 281.7126 | G64: =F64+G62-G63 -> 385.48583 | H64: =G64+H62-H63 -> 437.17895 | I64: =H64+I62-I63 -> 487.24958 | J64: =I64+J62-J63 -> 516.55467 | K64: =J64+K62-K63 -> 539.41264 | L64: =K64+L62-L63 -> 576.74186 | M64: =L64+M62-M63 -> 596.10865 | N64: =M64+N62-N63 -> 611.21475 | P64: FY25 AR p.178 and FY26 audited balance sheet. REPORTED FACT.
A65: 2b. Capital work-in-progress
A66: CWIP - opening | B66: INR mn | D66: =C69 -> 1068.95 | E66: =D69 -> 1244.56 | F66: =E69 -> 2704.53 | G66: =F69 -> 4680 | H66: =G69 -> 2652 | I66: =H69 -> 1842.75 | J66: =I69 -> 1974.375 | K66: =J69 -> 1706.25 | ... N66: =M69 -> 1828.125
A67: + additions (capex excluding intangibles) | B67: INR mn | F67: =F52-F62 -> 11700 | G67: =G52-G62 -> 8287.5 | H67: =H52-H62 -> 6825 | I67: =I52-I62 -> 7312.5 | J67: =J52-J62 -> 6825 | K67: =K52-K62 -> 6825 | L67: =L52-L62 -> 7800 | M67: =M52-M62 -> 7312.5 | N67: =N52-N62 -> 7312.5
A68: CWIP retention (% of the year's additions still in CWIP at year end) | B68: % | F68: 0.4 | G68: 0.32 | H68: 0.27 | I68: 0.27 | J68: 0.25 | K68: 0.25 | L68: 0.25 | M68: 0.25 | N68: 0.25 | P68: ANALYST ASSUMPTION. A brownfield block takes ~18 months to build (Q4FY26 call), so a large share of each year's spend is still uncapitalised at year end. Implied history: 59% FY24, 34% FY25, 44% FY26.
A69: CWIP - closing | B69: INR mn | C69: 1068.95 | D69: 1244.56 | E69: 2704.53 | F69: =F67*F68 -> 4680 | G69: =G67*G68 -> 2652 | H69: =H67*H68 -> 1842.75 | I69: =I67*I68 -> 1974.375 | J69: =J67*J68 -> 1706.25 | K69: =K67*K68 -> 1706.25 | L69: =L67*L68 -> 1950 | M69: =M67*M68 -> 1828.125 | N69: =N67*N68 -> 1828.125 | P69: FY25 AR p.178 and FY26 audited balance sheet. REPORTED FACT.
A70: - capitalised to PP&E | B70: INR mn | F70: =F66+F67-F69 -> 9724.53 | G70: =G66+G67-G69 -> 10315.5 | H70: =H66+H67-H69 -> 7634.25 | I70: =I66+I67-I69 -> 7180.875 | J70: =J66+J67-J69 -> 7093.125 | K70: =K66+K67-K69 -> 6825 | L70: =L66+L67-L69 -> 7556.25 | M70: =M66+M67-M69 -> 7434.375 | N70: =N66+N67-N69 -> 7312.5
A71: 2c. Property, plant and equipment
A72: Net PP&E - opening | B72: INR mn | D72: =C76 -> 9263.55 | E72: =D76 -> 11850.12 | F72: =E76 -> 15344.14 | G72: =F76 -> 23174.474 | H72: =G76 -> 30840.077 | I72: =H76 -> 35236.208 | J72: =I76 -> 38791.205 | K72: =J76 -> 41931.917 | ... N72: =M76 -> 50223.255
A73: Depreciation rate (% of opening net block) | B73: % | F73: 0.093 | G73: 0.093 | H73: 0.093 | I73: 0.093 | J73: 0.093 | K73: 0.093 | L73: 0.093 | M73: 0.093 | N73: 0.093 | P73: Implied history: 9.6% FY25, 9.5% FY26 of opening net PP&E. Half-year convention applied to the year's capitalisations.
A74: Depreciation of PP&E | B74: INR mn | C74: 731.35 | D74: 889.62 | E74: 1124 | F74: =E76*F73+F70*F73/2 -> 1879.1957 | G74: =F76*G73+G70*G73/2 -> 2634.8969 | H74: =G76*H73+H70*H73/2 -> 3223.1198 | I74: =H76*I73+I70*I73/2 -> 3610.878 | J74: =I76*J73+J70*J73/2 -> 3937.4123 | K74: =J76*K73+K70*K73/2 -> 4217.0308 | L74: =K76*L73+L70*L73/2 -> 4492.1801 | M74: =L76*M73+M70*M73/2 -> 4770.0764 | N74: =M76*N73+N70*N73/2 -> 5010.794 | P74: FY24 and FY25 from note 33. FY26 is an ANALYST ESTIMATE within reported total D&A of 1,668.55 (the FY26 annual report is not yet published).
A75: Disposals at net book value | B75: INR mn | C75: 8.43 | D75: 22.88 | E75: 14.81 | F75: 15 | G75: 15 | H75: 15 | I75: 15 | J75: 15 | K75: 15 | L75: 15 | M75: 15 | N75: 15 | P75: Derived from proceeds on sale and the gain/loss recognised in the cash flow statement.
A76: Net PP&E - closing | B76: INR mn | C76: 9263.55 | D76: 11850.12 | E76: 15344.14 | F76: =F72+F70-F74-F75 -> 23174.474 | G76: =G72+G70-G74-G75 -> 30840.077 | H76: =H72+H70-H74-H75 -> 35236.208 | I76: =I72+I70-I74-I75 -> 38791.205 | J76: =J72+J70-J74-J75 -> 41931.917 | K76: =K72+K70-K74-K75 -> 44524.886 | L76: =L72+L70-L74-L75 -> 47573.956 | M76: =M72+M70-M74-M75 -> 50223.255 | N76: =N72+N70-N74-N75 -> 52509.961 | P76: FY25 AR p.178 and FY26 audited balance sheet. REPORTED FACT.
A77: 2d. Right-of-use assets and lease liabilities
A78: ROU additions (% of revenue) | B78: % | F78: 0.013 | G78: 0.013 | H78: 0.013 | I78: 0.013 | J78: 0.013 | K78: 0.013 | L78: 0.013 | M78: 0.013 | N78: 0.013 | P78: ANALYST ASSUMPTION - leased laboratory, office and Boston / Manchester facilities. FY26 implied 1.36% of revenue.
A79: ROU asset additions | B79: INR mn | E79: 297.57 | F79: =F6*F78 -> 327.02724 | G79: =G6*G78 -> 371.24671 | H79: =H6*H78 -> 422.52269 | I79: =I6*I78 -> 476.5739 | J79: =J6*J78 -> 533.46493 | K79: =K6*K78 -> 598.06861 | L79: =L6*L78 -> 666.07072 | M79: =M6*M78 -> 736.96319 | N79: =N6*N78 -> 810.32702
A80: Depreciation of ROU assets | B80: INR mn | C80: 375.34 | D80: 399.92 | E80: 478 | F80: =E81*0.165 -> 452.59665 | G80: =F81*0.165 -> 431.8777 | H80: =G81*0.165 -> 421.87359 | I80: =H81*0.165 -> 421.98069 | J80: =I81*0.165 -> 430.98857 | K80: =J81*0.165 -> 447.89717 | L80: =K81*0.165 -> 472.67546 | M80: =L81*0.165 -> 504.58567 | N80: =M81*0.165 -> 542.92796 | P80: FY24 and FY25 from note 33; FY26 ANALYST ESTIMATE within reported total D&A. ~16.5% of opening ROU assets.
A81: Right-of-use assets - closing | B81: INR mn | C81: 2397.13 | D81: 2923.44 | E81: 2743.01 | F81: =E81+F79-F80 -> 2617.4406 | G81: =F81+G79-G80 -> 2556.8096 | H81: =G81+H79-H80 -> 2557.4587 | I81: =H81+I79-I80 -> 2612.0519 | J81: =I81+J79-J80 -> 2714.5283 | K81: =J81+K79-K80 -> 2864.6997 | L81: =K81+L79-L80 -> 3058.095 | M81: =L81+M79-M80 -> 3290.4725 | N81: =M81+N79-N80 -> 3557.8716 | P81: FY25 AR p.178 and FY26 audited balance sheet. REPORTED FACT.
A82: Lease liabilities - opening | B82: INR mn | D82: =C85 -> 2174.97 | E82: =D85 -> 2237.45 | F82: =E85 -> 1933.27 | G82: =F85 -> 1738.3143 | H82: =G85 -> 1640.2162 | I82: =H85 -> 1619.8805 | J82: =I85 -> 1659.0867 | K82: =J85 -> 1744.5982 | ... N82: =M85 -> 2220.5839
A83: + interest accrued on lease liabilities | B83: INR mn | C83: 253.53 | D83: 248.98 | E83: 232.17 | F83: =F82*0.11 -> 212.6597 | G83: =G82*0.11 -> 191.21458 | H83: =H82*0.11 -> 180.42378 | I83: =I82*0.11 -> 178.18686 | J83: =J82*0.11 -> 182.49953 | K83: =K82*0.11 -> 191.9058 | L83: =L82*0.11 -> 205.87878 | M83: =M82*0.11 -> 223.55929 | N83: =N82*0.11 -> 244.26423 | P83: FY24 / FY25 note 32; FY26 from the consolidated cash flow statement. ~11% implied incremental borrowing rate.
A84: - lease payments (principal portion) | B84: INR mn | C84: 441.05 | D84: 510.64 | E84: 615.52 | F84: =F82*0.27 -> 521.9829 | G84: =G82*0.27 -> 469.34487 | H84: =H82*0.27 -> 442.85837 | I84: =I82*0.27 -> 437.36774 | J84: =J82*0.27 -> 447.9534 | K84: =K82*0.27 -> 471.04151 | L84: =L82*0.27 -> 505.33883 | M84: =M82*0.27 -> 548.73644 | N84: =N82*0.27 -> 599.55766 | P84: Repayment of the principal portion of lease liabilities per the consolidated cash flow statement.
A85: Lease liabilities - closing | B85: INR mn | C85: 2174.97 | D85: 2237.45 | E85: 1933.27 | F85: =F82+F79+F83-F83-F84 -> 1738.3143 | G85: =G82+G79+G83-G83-G84 -> 1640.2162 | H85: =H82+H79+H83-H83-H84 -> 1619.8805 | I85: =I82+I79+I83-I83-I84 -> 1659.0867 | J85: =J82+J79+J83-J83-J84 -> 1744.5982 | K85: =K82+K79+K83-K83-K84 -> 1871.6253 | L85: =L82+L79+L83-L83-L84 -> 2032.3572 | M85: =M82+M79+M83-M83-M84 -> 2220.5839 | N85: =N82+N79+N83-N83-N84 -> 2431.3533 | P85: Non-current plus current lease liabilities. FY25 AR p.178 and FY26 audited balance sheet. REPORTED FACT.
A86: of which: current portion | B86: INR mn | C86: 417.76 | D86: 590.58 | E86: 657.07 | F86: =F85*0.34 -> 591.02688 | G86: =G85*0.34 -> 557.6735 | H86: =H85*0.34 -> 550.75937 | I86: =I85*0.34 -> 564.08947 | J86: =J85*0.34 -> 593.16339 | K86: =K85*0.34 -> 636.3526 | L86: =L85*0.34 -> 691.00144 | M86: =M85*0.34 -> 754.99854 | N86: =N85*0.34 -> 826.66012 | P86: FY26 current portion was 34.0% of total lease liabilities.
A87: 2e. Total depreciation and amortisation
A88: Depreciation and amortisation expense | B88: INR mn | C88: =C74+C80+C63 -> 1194.36 | D88: =D74+D80+D63 -> 1385.73 | E88: =E74+E80+E63 -> 1668.55 | F88: =F74+F80+F63 -> 2411.2497 | G88: =G74+G80+G63 -> 3175.5013 | H88: =H74+H80+H63 -> 3768.3003 | I88: =I74+I80+I63 -> 4170.2881 | J88: =J74+J80+J63 -> 4514.0958 | ... N88: =N74+N80+N63 -> 5726.1158
A89: Reported D&A (history) | B89: INR mn | C89: 1194.36 | D89: 1385.73 | E89: 1668.55 | P89: FY25 AR p.179; FY26 audited results. REPORTED FACT.
A90: check: build vs reported - must be nil | B90: INR mn | C90: =C88-C89 -> 0 | D90: =D88-D89 -> 0 | E90: =E88-E89 -> 0
A91: CROSS-CHECK: revenue per employee | B91: INR mn | C91: =C6/C10 -> 4.3802033 | D91: =D6/D10 -> 4.982564 | E91: =E6/E10 -> 5.7697158 | F91: =F6/F10 -> 6.1058111 | G91: =G6/G10 -> 6.4609592 | H91: =H6/H10 -> 6.9152649 | I91: =I6/I10 -> 7.3910345 | J91: =J6/J10 -> 7.8914931 | ... N91: =N6/N10 -> 10.458531 | P91: Grew 13.8% in FY25 and 15.8% in FY26. The forecast assumes 6-8% - if it runs faster, headcount is too low.
A92: Fixed asset turnover (revenue / net PP&E + CWIP) | B92: x | C92: =C6/(C76+C69) -> 1.4180286 | D92: =D6/(D76+D69) -> 1.2940904 | E92: =E6/(E76+E69) -> 1.2147665 | F92: =F6/(F76+F69) -> 0.90312032 | G92: =G6/(G76+G69) -> 0.85266253 | H92: =H6/(H76+H69) -> 0.87655498 | I92: =I6/(I76+I69) -> 0.89927658 | J92: =J6/(J76+J69) -> 0.94036406 | ... N92: =N6/(N76+N69) -> 1.14713 | P92: Management targets a net asset turn of 1.2x-1.4x through the medium term, with a dip during the investment cycle (Q4FY26 call).
A94: 3. WORKING CAPITAL SCHEDULE
A95: Days are computed on 365. Contract assets (unbilled revenue) are the largest item and the key working capital risk.
A96: Inventory days (on material cost) | B96: days | C96: =C97/C19*365 -> 71.605445 | D96: =D97/D19*365 -> 93.149589 | E96: =E97/E19*365 -> 96.521444 | F96: 95 | G96: 94 | H96: 93 | I96: 92 | J96: 91 | K96: 90 | L96: 90 | M96: 90 | N96: 90 | P96: History: 71.6 / 93.2 / 96.5 days. Elevated versus FY24 on raw-material stocking, longer campaigns and supply-chain diversification.
A97: Inventories | B97: INR mn | C97: 874.43 | D97: 1188.65 | E97: 1509.68 | F97: =F19*F96/365 -> 1750.7388 | G97: =G19*G96/365 -> 1946.1339 | H97: =H19*H96/365 -> 2177.8399 | I97: =I19*I96/365 -> 2435.6353 | J97: =J19*J96/365 -> 2703.888 | K97: =K19*K96/365 -> 3022.4116 | L97: =L19*L96/365 -> 3397.5358 | M97: =M19*M96/365 -> 3791.7404 | N97: =N19*N96/365 -> 4202.3736 | P97: FY25 AR p.178 and FY26 audited balance sheet. REPORTED FACT.
A98: Trade receivable days (on revenue) | B98: days | C98: =C99/C6*365 -> 63.819659 | D98: =D99/D6*365 -> 76.418085 | E98: =E99/E6*365 -> 62.199723 | F98: 62 | G98: 62 | H98: 61 | I98: 61 | J98: 60 | K98: 60 | L98: 60 | M98: 60 | N98: 60 | P98: History: 63.8 / 76.4 / 62.2 days.
A99: Trade receivables | B99: INR mn | C99: 2561.84 | D99: 3547.83 | E99: 3736.23 | F99: =F6*F98/365 -> 4273.0641 | G99: =G6*G98/365 -> 4850.8527 | H99: =H6*H98/365 -> 5431.7985 | I99: =I6*I98/365 -> 6126.6613 | J99: =J6*J98/365 -> 6745.6051 | K99: =K6*K98/365 -> 7562.5114 | L99: =L6*L98/365 -> 8422.3906 | M99: =M6*M98/365 -> 9318.818 | N99: =N6*N98/365 -> 10246.495 | P99: FY25 AR p.178 and FY26 audited balance sheet. REPORTED FACT.
A100: Other current asset days (on revenue) | B100: days | C100: =C101/C6*365 -> 90.481849 | D100: =D101/D6*365 -> 104.97371 | E100: =E101/E6*365 -> 103.89927 | F100: 102 | G100: 100 | H100: 98 | I100: 96 | J100: 95 | K100: 94 | L100: 93 | M100: 92 | N100: 92 | P100: Dominated by contract assets (unbilled revenue): 2,968.16 of 3,632.11 in FY24 and 3,963.24 of 4,873.57 in FY25 (note 13). This is the single largest working capital item and the key WC risk in the model.
A101: Other current assets (mainly contract assets) | B101: INR mn | C101: 3632.11 | D101: 4873.57 | E101: 6241.05 | F101: =F6*F100/365 -> 7029.8796 | G101: =G6*G100/365 -> 7823.956 | H101: =H6*H100/365 -> 8726.4959 | I101: =I6*I100/365 -> 9641.9588 | J101: =J6*J100/365 -> 10680.541 | K101: =K6*K100/365 -> 11847.934 | L101: =L6*L100/365 -> 13054.705 | M101: =M6*M100/365 -> 14288.854 | N101: =N6*N100/365 -> 15711.293 | P101: FY25 AR p.178 and FY26 audited balance sheet. REPORTED FACT.
A102: Other current financial asset days (on revenue) | B102: days | C102: =C103/C6*365 -> 19.798782 | D102: =D103/D6*365 -> 17.150522 | E102: =E103/E6*365 -> 17.308804 | F102: 17 | G102: 17 | H102: 17 | I102: 17 | J102: 17 | K102: 17 | L102: 17 | M102: 17 | N102: 17
A103: Other financial assets (current) | B103: INR mn | C103: 794.76 | D103: 796.24 | E103: 1039.71 | F103: =F6*F102/365 -> 1171.6466 | G103: =G6*G102/365 -> 1330.0725 | H103: =H6*H102/365 -> 1513.7799 | I103: =I6*I102/365 -> 1707.4302 | J103: =J6*J102/365 -> 1911.2548 | K103: =K6*K102/365 -> 2142.7116 | L103: =L6*L102/365 -> 2386.344 | M103: =M6*M102/365 -> 2640.3318 | N103: =N6*N102/365 -> 2903.1737 | P103: FY25 AR p.178 and FY26 audited balance sheet. REPORTED FACT.
A104: Trade payable days (on material cost) | B104: days | C104: =C105/C19*365 -> 113.39051 | D104: =D105/D19*365 -> 252.73619 | E104: =E105/E19*365 -> 182.43095 | F104: 175 | G104: 175 | H104: 175 | I104: 175 | J104: 175 | K104: 175 | L104: 175 | M104: 175 | N104: 175 | P104: History: 113.4 / 252.8 / 182.4 days. FY25 was inflated by year-end purchasing; the forecast reverts toward the FY26 level.
...

Sheet Sources_Checks
A1: SHEET 5 | SOURCES, ASSUMPTION LOG, MOLECULE TABLE AND MODEL CHECKS
A3: A. MODEL INTEGRITY CHECKS (every check must read OK)
A4: Check | B4: What it tests | C4: Worst absolute value | D4: Status
A5: Balance sheet balances | B5: Total assets less total equity and liabilities, every year | C5: =MAX(ABS(Statements!C67),ABS(Statements!D67),ABS(Statements!E67),ABS(Statements!F67),ABS(Statements!G67),ABS(Statements!H67),ABS(Statements!I67),ABS(Statements!J67),ABS(Statements!K67),ABS(Statements!L67),ABS(Statements!M67),ABS(Statements!N67)) -> 0 | D5: =IF(ABS(C5)<0.05,"OK","FAIL") -> OK
A6: Cash flow reconciliation | B6: Cash flow closing cash less balance sheet cash, forecast years | C6: =MAX(ABS(Statements!F102),ABS(Statements!G102),ABS(Statements!H102),ABS(Statements!I102),ABS(Statements!J102),ABS(Statements!K102),ABS(Statements!L102),ABS(Statements!M102),ABS(Statements!N102)) -> 0 | D6: =IF(ABS(C6)<0.05,"OK","FAIL") -> OK
A7: Historical CFO ties to filings | B7: Modelled CFO less reported CFO, FY24-FY26 | C7: =MAX(ABS(Statements!C81),ABS(Statements!D81),ABS(Statements!E81)) -> 0 | D7: =IF(ABS(C7)<0.05,"OK","FAIL") -> OK
A8: Historical PAT ties to filings | B8: Modelled PAT less audited PAT, FY24-FY26 | C8: =MAX(ABS(Statements!C31),ABS(Statements!D31),ABS(Statements!E31)) -> 0 | D8: =IF(ABS(C8)<0.05,"OK","FAIL") -> OK
A9: Historical PBT ties to filings | B9: Cost build reproduces audited PBT, FY24-FY26 | C9: =MAX(ABS(Schedules!C145),ABS(Schedules!D145),ABS(Schedules!E145)) -> 0 | D9: =IF(ABS(C9)<0.05,"OK","FAIL") -> OK
A10: Total revenue reconciliation | B10: CRO plus CDMO plus rounding less audited revenue, FY24-FY26 | C10: =MAX(ABS(Revenue_Model!C57),ABS(Revenue_Model!D57),ABS(Revenue_Model!E57)) -> 0 | D10: =IF(ABS(C10)<0.05,"OK","FAIL") -> OK
A11: CRO engine reconciliation | B11: FTE engine reproduces reported CRO revenue, FY24-FY26 | C11: =MAX(ABS(Revenue_Model!C18),ABS(Revenue_Model!D18),ABS(Revenue_Model!E18)) -> 0 | D11: =IF(ABS(C11)<0.05,"OK","FAIL") -> OK
A12: CDMO bucket reconciliation | B12: Molecule and pipeline buckets sum to reported CDMO revenue, FY24-FY26 | C12: =MAX(ABS(Revenue_Model!C40),ABS(Revenue_Model!D40),ABS(Revenue_Model!E40)) -> 0 | D12: =IF(ABS(C12)<0.05,"OK","FAIL") -> OK
A13: CRO revenue bridge | B13: Volume, utilisation and price bridge foots to CRO revenue, all years | C13: =MAX(ABS(Revenue_Model!D25),ABS(Revenue_Model!E25),ABS(Revenue_Model!F25),ABS(Revenue_Model!J25),ABS(Revenue_Model!N25)) -> 0 | D13: =IF(ABS(C13)<0.05,"OK","FAIL") -> OK
A14: Segment shares sum to 100% | B14: CRO share plus CDMO share of total revenue | C14: =MAX(ABS(Revenue_Model!E55+Revenue_Model!E56-1),ABS(Revenue_Model!J55+Revenue_Model!J56-1),ABS(Revenue_Model!N55+Revenue_Model!N56-1)) -> 0.00022440219 | D14: =IF(ABS(C14)<0.05,"OK","FAIL") -> OK
A15: Capacity feasibility | B15: No forecast year grows commercial revenue per effective KL by more than 10% | C15: =MAX(0,MAX(Revenue_Model!F49,Revenue_Model!G49,Revenue_Model!H49,Revenue_Model!I49,Revenue_Model!J49,Revenue_Model!K49,Revenue_Model!L49,Revenue_Model!M49,Revenue_Model!N49)-0.1) -> 0 | D15: =IF(ABS(C15)<0.05,"OK","FAIL") -> OK
A16: Material cost ties to filings | B16: Driver build reproduces reported material cost | C16: =MAX(ABS(Schedules!C20),ABS(Schedules!D20),ABS(Schedules!E20)) -> 0 | D16: =IF(ABS(C16)<0.05,"OK","FAIL") -> OK
A17: Employee cost ties to filings | B17: Headcount times average cost reproduces reported expense | C17: =MAX(ABS(Schedules!C28),ABS(Schedules!D28),ABS(Schedules!E28)) -> 0 | D17: =IF(ABS(C17)<0.05,"OK","FAIL") -> OK
A18: Other expenses tie to filings | B18: Three-bucket build reproduces reported other expenses | C18: =MAX(ABS(Schedules!C41),ABS(Schedules!D41),ABS(Schedules!E41)) -> 0 | D18: =IF(ABS(C18)<0.05,"OK","FAIL") -> OK
A19: D&A ties to filings | B19: PP&E, ROU and intangible charges sum to reported D&A | C19: =MAX(ABS(Schedules!C90),ABS(Schedules!D90),ABS(Schedules!E90)) -> 0 | D19: =IF(ABS(C19)<0.05,"OK","FAIL") -> OK
A20: Retained earnings roll-forward | B20: Opening equity plus PAT and reserves equals closing equity | C20: =MAX(ABS(Schedules!F168),ABS(Schedules!I168),ABS(Schedules!N168)) -> 1.8189894e-12 | D20: =IF(ABS(C20)<0.05,"OK","FAIL") -> OK
A21: Diluted EPS ties to filings | B21: Modelled EPS less reported diluted EPS, FY24-FY26 | C21: =MAX(ABS(Schedules!C171),ABS(Schedules!D171),ABS(Schedules!E171)) -> 0.00011866642 | D21: =IF(ABS(C21)<0.05,"OK","FAIL") -> OK
A22: MASTER CHECK | B22: All integrity checks pass | C22: =MAX(MAX(C5:C21),-MIN(C5:C21)) -> 0.00022440219 | D22: =IF(COUNTIF(D5:D21,"FAIL")=0,"ALL CHECKS OK","REVIEW FAILURES") -> ALL CHECKS OK
A24: A formula-error sweep is also run outside the workbook: the model is recalculated in full and every cell is scanned for reference, divide-by-zero, value, not-available and undefined-name errors, and for circular references. The model contains no circular references by design - see the note on interest in the Schedules sheet, section 4.
A26: B. MOLECULE TABLE - IDENTIFIED COMMERCIAL AND LATE-STAGE PROGRAMMES
A27: Sai Life Sciences does not disclose molecule names, innovator customers, indications or molecule-level economics, and management explicitly declined to name molecules or clients on the Q4FY26 earnings call. No name has been invented. The revenue model therefore does NOT attempt a bottom-up build of individual molecules - it uses the four portfolio buckets the company actually reports counts for, each as count x revenue per programme, with a single memo line for top-4 concentration. The table below records what IS disclosed and states plainly what is not.
A28: Bucket | B28: Innovator / customer | C28: Indication | D28: Stage | E28: Regulatory status | F28: Innovator sales / TAM | G28: Basis of the estimate in this model | H28: Confidence
A29: Bucket 1 - Base commercial portfolio | B29: 19 of the top 25 global pharma companies are customers; no customer is named | C29: Oncology 15%, metabolic 15%, infectious disease 16%, CNS 25% of CDMO revenue in FY26 | D29: Commercial - the 34 molecules already commercial at FY2026 | E29: USFDA and PMDA approved sites; 100% inspection track record | F29: Not identifiable | G29: Modelled as molecule count x revenue per molecule. Implied FY26 revenue per molecule of ~INR 243mn (FY24 220, FY25 201 - the FY25 dip is the disclosed destocking on a commercial intermediate). The pool rolls forward on exits only. The top-4 share is carried as a single memo line at 40% of commercial revenue, anchored on disclosed FY26 concentration: top-1 customer 12% of group revenue, top-5 37%, top-10 54%. | H29: MEDIUM on the bucket / LOW on the top-4 split
A30: Bucket 2 - New commercial launches | B30: Two additional large-pharma commercial supply qualifications received in FY26 | C30: Predominantly small molecule; management identified one new-modality asset in validation | D30: Commercial - molecules qualified from FY2027 onward | E30: Validation batches then commercial campaigns | F30: Not identifiable | G30: Modelled as cumulative launches x a blended revenue per new molecule that rises as the cohort seasons (INR ~130mn in year one to INR ~540mn at maturity). Management: of the four molecules added in FY26, three should show a 'pretty decent revenue growth trajectory' from FY27. | H30: MEDIUM
A31: Bucket 3 - Late-stage development | B31: Includes large-pharma late-phase work newly transferred to India | C31: Broad; mostly small molecule | D31: Phase III / pre-registration - 11 molecules at FY26, 6 at FY25 | E31: Validation and registration activity underway | F31: Not identifiable | G31: Modelled as programme count x INR 130mn per programme in FY26, escalating 6% p.a. Covers late-phase process development, validation batches, registration and pre-launch supply. | H31: MEDIUM
A32: Bucket 4 - Early phase, process R&D and tech transfer | B32: 300+ active customers; 200+ discovery clients | C32: Broad; 10+ therapy areas | D32: Pre-clinical, Phase I and Phase II - 155 programmes at FY26, 160 at FY25 | E32: Clinical supply under GMP where applicable | F32: Not identifiable | G32: Modelled as programme count x INR ~28.8mn per programme in FY26, escalating 7.5% p.a. Also carries site-to-site technology transfer and the dedicated large-pharma development FTE teams management flagged on the Q4FY26 call. | H32: MEDIUM
A33: New modalities (memo only) | B33: Not disclosed | C33: Peptides, ADC payloads and linkers, oligonucleotide amidites, lipids | D33: Mostly discovery and clinical, not commercial | E33: Peptide process and pilot plants commissioning Sep-26; OEB-6 labs for ADCs | F33: Not identifiable | G33: Tracked as a memo percentage of group revenue: 4% FY22, 3% FY23, 3% FY24, 7% FY25, 4% FY26. Lumpy because the work is campaign-driven. Does NOT drive revenue in the model. | H33: REPORTED (percentage only)
A35: C. ASSUMPTION LOG (classification of every material input)
A36: Area | B36: Assumption | C36: Classification | D36: Basis
A37: Historical financials | B37: FY2024, FY2025 and FY2026 consolidated P&L, balance sheet and cash flow | C37: REPORTED FACT | D37: FY25 Annual Report; audited FY26 consolidated results filed 14-May-2026
A38: Segment revenue | B38: CRO and CDMO revenue for FY2022-FY2026 | C38: REPORTED FACT | D38: Q4FY26 investor presentation pages 21 and 24
A39: Employees | B39: FY2025 3,401 employees and 2,605 scientists; FY2026 3,800+ | C39: REPORTED FACT | D39: FY25 Annual Report pages 6, 33 and 60; Q4FY26 deck page 15
A40: Employees | B40: FY2024 headcount of 3,345 | C40: ANALYST ESTIMATE | D40: Derived from FY24 employee cost divided by FY25 average cost deflated by the disclosed 9.12% salary increase
A41: Scientist allocation | B41: 55% of scientists allocated to Discovery | C41: ANALYST ASSUMPTION | D41: Not disclosed; management declined the split on the Q4FY26 call. Calibrated to a credible FTE rate card
A42: CRO utilisation | B42: 80% to 85% billable ratio | C42: ANALYST ASSUMPTION | D42: Not disclosed. Implies a revenue per billable FTE of ~USD 70k in FY26, inside observed Indian rate cards
A43: Capacity | B43: 700 KL at FY2026, 925 KL at FY2027, 1,150 KL at FY2028 | C43: REPORTED / GUIDED | D43: Q3FY26 deck page 27; Q4FY26 call - 225 KL this year and 225 KL next year
A44: Capacity | B44: Second Hyderabad site adds 200 KL in FY2030 and 250 KL in FY2033 | C44: ANALYST ASSUMPTION | D44: Management has confirmed a second Hyderabad site but has not sized or dated it
A45: Capacity ramp | B45: 30% effective in year one, 75% in year two | C45: ANALYST ASSUMPTION | D45: Reflects qualification, customer audit and validation batches. Not disclosed
A46: Molecule counts | B46: 34 commercial, 11 Phase III / pre-registration, 155 early phase at FY2026 | C46: REPORTED FACT | D46: Q4FY26 deck page 15 and Q4FY26 earnings call
A47: Molecule economics | B47: Top-four commercial molecules carried as a single memo line at 40% of commercial revenue | C47: ANALYST ASSUMPTION - LOW confidence | D47: Anchored on disclosed FY26 concentration: top-1 12%, top-5 37%, top-10 54%. No molecule is named because none is disclosed, and no molecule-level build drives revenue
... A57: Exceptional items | B57: Nil in the forecast | C57: ANALYST ASSUMPTION | D57: FY26 recognised an Rs 80mn charge for the wage-definition change
A59: D. MATERIAL DATA GAPS
A60: - Molecule identities, innovator customers and molecule-level economics. Not disclosed and explicitly declined by management. The top-four commercial buckets are illustrative sizings, not identified revenue.
A61: - The split of scientists between Discovery and CMC. Management declined to provide it on the Q4FY26 call, so the 55% Discovery allocation drives the entire CRO engine and is the single most important undisclosed CRO input.
A62: - The FY2026 annual report has not been published, so the FY2026 notes are unavailable. The split of D&A between PP&E, right-of-use assets and intangibles, and the line-by-line split of other expenses, are analyst estimates that sum exactly to the audited totals.
A63: - FY2024 headcount is not disclosed in the FY2025 annual report and has been derived from employee cost.
A64: - Batch-level and campaign-level volume data, revenue per batch, and pricing. Not disclosed by any Indian CRDMO.
A65: - Segment-level EBITDA. The group reports a single operating segment under Ind AS 108, so CRO and CDMO margins cannot be separated.
A66: - Order book, backlog or revenue visibility metrics. Not disclosed.
A67: - Capacity utilisation percentage. Referenced qualitatively by management but never quantified.
A68: - The dollar value and duration of the dedicated large-pharma FTE development contracts.
A70: E. SOURCE LIST
A71: Document | B71: Used for | C71: Location
A72: Audited consolidated financial results for the year ended 31 March 2026, filed 14-May-2026 | B72: FY2026 and FY2025 income statement, balance sheet and cash flow statement; exceptional items; IPO proceeds utilisation; ESOP grants | C72: BSE filing, scrip 544306
A73: Annual Report 2024-25 (25th/26th Annual Report), audited by Deloitte Haskins & Sells LLP | B73: FY2025 and FY2024 consolidated statements and notes 6-36; headcount and scientist disclosure; other income, other expenses, finance cost and D&A notes; contract asset note 13 | C73: BSE annual report filing / sailife.com investor relations
A74: Q4 FY26 investor presentation, 15-May-2026 | B74: Segment revenue FY22-FY26; molecule counts; capex split; customer mix; therapy mix; new modalities; annexure P&L and balance sheet | C74: BSE / NSE filing
A75: Q4 FY26 earnings call transcript, 15-May-2026 | B75: Revenue and margin guidance; FY27 capex guidance and phasing; capacity commissioning timing; commercial molecule additions; customer concentration; dedicated FTE model; refusal to disclose molecules and customers; asset turn target | C75: sailife.com investor relations
A76: Q3 FY26 investor presentation, 06-Feb-2026 | B76: Capacity timeline 2009-2026; fume hood and process R&D block commissioning dates; peptide, ADC and animal health project timing; FY25 molecule counts; industry data | C76: NSE archives
A77: Q1 FY26 earnings release, 08-Aug-2025 | B77: Bidar Unit IV PB-11 Phase II commissioning of ~91 KL taking capacity to ~700 KL | C77: sailife.com newsroom
A78: FY26 results press release, 14-May-2026 | B78: Headline FY26 revenue, EBITDA, PBT and PAT; FY26 capex of Rs 633 Cr | C78: sailife.com newsroom
A79: Draft Red Herring Prospectus dated 29-July-2024 | B79: Corporate history and capital structure background. NOTE: the copy hosted on the company website sits behind a click-through disclaimer and could not be retrieved programmatically, so nothing in this model depends on it | C79: sailife.com investor relations (disclaimer-gated)
A81: F. KEY MODEL RISKS
A82: - CUSTOMER CONCENTRATION. The top customer is 12% of revenue and the top ten are 54%. A single large-pharma programme loss or in-sourcing decision moves the CDMO forecast more than any driver in this model.
A83: - MOLECULE VARIABILITY. CDMO revenue is campaign-driven. FY2025 carried a destocking hit on a commercial intermediate and FY2026 carried the reversal. Quarterly and even annual revenue is lumpy in a way no driver model fully captures.
A84: - CAPACITY TIMING. The forecast assumes 225 KL lands in H2 FY2027 and a further 225 KL in FY2028. Brownfield construction is roughly 18 months and slippage of two quarters would move revenue between years.
A85: - MARGIN. FY2026's 30.2% is above management's own 28-30% guidance and was helped by an FX gain and a credit-loss reversal. The model assumes neither repeats. Input cost and logistics inflation from the Middle East situation is being passed on with a lag.
A86: - CONTRACT ASSETS. Unbilled revenue is roughly 100 days of sales. FY2025 required a 347mn loss allowance against doubtful contract assets. A repeat would hit both the P&L and cash.
A87: - CAPEX EXECUTION AND RETURNS. Capex roughly doubles in FY2027 and management concedes a two to three year lag before new assets reach target returns. The net asset turn dips before it recovers.
A88: - CRO ENGINE SENSITIVITY. The whole CRO build rests on an undisclosed scientist allocation and utilisation rate. A 5 percentage point error in either moves CRO revenue by roughly 6%.
A89: - AI AND MODALITY DISRUPTION. Management frames AI as a net positive for synthesis demand, but a shift in innovator R&D away from small molecules toward biologics would erode the addressable market over the back half of the forecast.
A90: - FX. Roughly 97% of revenue is exported. The model forecasts no FX gain, but a sustained rupee appreciation would compress reported growth and margin.
A91: - MODELLING CONVENTION. Interest is computed on opening debt to avoid circularity, and the closing cash balance therefore lands slightly away from the minimum-cash target in years of large debt movement. This does not affect the balance sheet check.
