Workbook

Sheet Revenue_Model
A1: GSK India - Product-Level Revenue Model
A2: Underwriting case | B2: Single case | D2: FY26A Revenue | E2: =E54 -> 38330.7 | G2: FY27E Revenue | H2: =J54 -> 43354.735 | J2: FY28E Revenue | K2: =O54 -> 48158.315 | M2: FY31E Revenue | N2: =R54 -> 62428.967 | Q2: FY36E Revenue | R2: =W54 -> 83397.532 | U2: 10Y CAGR | V2: =Y54 -> 0.080838099
D3: FY27 Q1A consolidated | E3: =F54 -> 9634.4 | G3: FY31 new launches + pipeline | H3: =R56 -> 6341.6667 | J3: FY36 new launches + pipeline | K3: =W56 -> 12131.717 | M3: Model basis | N3: Consolidated GSK India; product history estimated within reported totals
A4: INR mn. Annual and quarterly consolidated totals are reported. Product-level history and Q1 FY27 allocations are analyst estimates calibrated to company disclosures and public market data. Forecasts use one underwriting case.
B5: 2023 | C5: 2024 | D5: 2025 | E5: 2026 | F5: 2027 | G5: 2027 | H5: 2027 | I5: 2027 | J5: 2027 | K5: 2028 | L5: 2028 | M5: 2028 | N5: 2028 | O5: 2028 | P5: 2029 | Q5: 2030 | R5: 2031 | S5: 2032 | T5: 2033 | U5: 2034 | V5: 2035 | W5: 2036
A6: Revenue line | B6: FY2023A | C6: FY2024A | D6: FY2025A | E6: FY2026A | F6: Q1 FY27A* | G6: Q2 FY27E | H6: Q3 FY27E | I6: Q4 FY27E | J6: FY2027E | K6: Q1 FY28E | L6: Q2 FY28E | M6: Q3 FY28E | N6: Q4 FY28E | O6: FY2028E | P6: FY2029E | Q6: FY2030E | R6: FY2031E | S6: FY2032E | T6: FY2033E | U6: FY2034E | V6: FY2035E | W6: FY2036E | X6: 5Y CAGR | Y6: 10Y CAGR
A7: GENERAL MEDICINES
A8: Augmentin | B8: 7200 | C8: 7800 | D8: 8500 | E8: 9000 | F8: 2200 | G8: =(J8-F8)*Assumptions_Sources!$C$45/SUM(Assumptions_Sources!$C$45:$E$45) -> 2516.2341 | H8: =(J8-F8)*Assumptions_Sources!$D$45/SUM(Assumptions_Sources!$C$45:$E$45) -> 2516.2341 | I8: =J8-F8-G8-H8 -> 2487.5318 | J8: 9720 | K8: =O8*Assumptions_Sources!$B$45 -> 2225.6856 | L8: =O8*Assumptions_Sources!$C$45 -> 2735.3052 | M8: =O8*Assumptions_Sources!$D$45 -> 2735.3052 | N8: =O8-K8-L8-M8 -> 2704.104 | O8: 10400.4 | P8: =O8*(1+Assumptions_Sources!$D$6) -> 11024.424 | Q8: =P8*(1+Assumptions_Sources!$E$6) -> 11630.767 | R8: =Q8*(1+Assumptions_Sources!$E$6) -> 12270.46 | S8: =R8*(1+Assumptions_Sources!$F$6) -> 12822.63 | T8: =S8*(1+Assumptions_Sources!$F$6) -> 13399.649 | U8: =T8*(1+Assumptions_Sources!$F$6) -> 14002.633 | V8: =U8*(1+Assumptions_Sources!$F$6) -> 14632.751 | W8: =V8*(1+Assumptions_Sources!$F$6) -> 15291.225 | X8: =IF(E8>0,(R8/E8)^(1/5)-1,0) -> 0.063955989 | Y8: =IF(E8>0,(W8/E8)^(1/10)-1,0) -> 0.054435398
A9: Ceftum | B9: 2150 | C9: 2200 | D9: 2250 | E9: 2300 | F9: 600 | G9: =(J9-F9)*Assumptions_Sources!$C$45/SUM(Assumptions_Sources!$C$45:$E$45) -> 615.00509 | H9: =(J9-F9)*Assumptions_Sources!$D$45/SUM(Assumptions_Sources!$C$45:$E$45) -> 615.00509 | I9: =J9-F9-G9-H9 -> 607.98982 | J9: 2438 | K9: =O9*Assumptions_Sources!$B$45 -> 553.03592 | L9: =O9*Assumptions_Sources!$C$45 -> 679.66564 | M9: =O9*Assumptions_Sources!$D$45 -> 679.66564 | N9: =O9-K9-L9-M9 -> 671.9128 | O9: 2584.28 | P9: =O9*(1+Assumptions_Sources!$D$7) -> 2713.494 | Q9: =P9*(1+Assumptions_Sources!$E$7) -> 2835.6012 | R9: =Q9*(1+Assumptions_Sources!$E$7) -> 2963.2033 | S9: =R9*(1+Assumptions_Sources!$F$7) -> 3066.9154 | T9: =S9*(1+Assumptions_Sources!$F$7) -> 3174.2574 | U9: =T9*(1+Assumptions_Sources!$F$7) -> 3285.3564 | V9: =U9*(1+Assumptions_Sources!$F$7) -> 3400.3439 | W9: =V9*(1+Assumptions_Sources!$F$7) -> 3519.356 | X9: =IF(E9>0,(R9/E9)^(1/5)-1,0) -> 0.051978156 | Y9: =IF(E9>0,(W9/E9)^(1/10)-1,0) -> 0.043454547
A10: Calpol | B10: 2800 | C10: 2900 | D10: 3000 | E10: 3100 | F10: 750 | G10: =(J10-F10)*Assumptions_Sources!$C$45/SUM(Assumptions_Sources!$C$45:$E$45) -> 838.18702 | H10: =(J10-F10)*Assumptions_Sources!$D$45/SUM(Assumptions_Sources!$C$45:$E$45) -> 838.18702 | I10: =J10-F10-G10-H10 -> 828.62595 | J10: 3255 | K10: =O10*Assumptions_Sources!$B$45 -> 745.3299 | L10: =O10*Assumptions_Sources!$C$45 -> 915.98955 | M10: =O10*Assumptions_Sources!$D$45 -> 915.98955 | N10: =O10-K10-L10-M10 -> 905.541 | O10: 3482.85 | P10: =O10*(1+Assumptions_Sources!$D$8) -> 3691.821 | Q10: =P10*(1+Assumptions_Sources!$E$8) -> 3876.4121 | R10: =Q10*(1+Assumptions_Sources!$E$8) -> 4070.2327 | S10: =R10*(1+Assumptions_Sources!$F$8) -> 4233.042 | T10: =S10*(1+Assumptions_Sources!$F$8) -> 4402.3636 | U10: =T10*(1+Assumptions_Sources!$F$8) -> 4578.4582 | V10: =U10*(1+Assumptions_Sources!$F$8) -> 4761.5965 | W10: =V10*(1+Assumptions_Sources!$F$8) -> 4952.0604 | X10: =IF(E10>0,(R10/E10)^(1/5)-1,0) -> 0.055969825 | Y10: =IF(E10>0,(W10/E10)^(1/10)-1,0) -> 0.047954492
A11: Eltroxin | B11: 1550 | C11: 1600 | D11: 1650 | E11: 1700 | F11: 430 | G11: =(J11-F11)*Assumptions_Sources!$C$45/SUM(Assumptions_Sources!$C$45:$E$45) -> 453.39059 | H11: =(J11-F11)*Assumptions_Sources!$D$45/SUM(Assumptions_Sources!$C$45:$E$45) -> 453.39059 | I11: =J11-F11-G11-H11 -> 448.21883 | J11: 1785 | K11: =O11*Assumptions_Sources!$B$45 -> 402.99945 | L11: =O11*Assumptions_Sources!$C$45 -> 495.27503 | M11: =O11*Assumptions_Sources!$D$45 -> 495.27503 | N11: =O11-K11-L11-M11 -> 489.6255 | O11: 1883.175 | P11: =O11*(1+Assumptions_Sources!$D$9) -> 1977.3338 | Q11: =P11*(1+Assumptions_Sources!$E$9) -> 2066.3138 | R11: =Q11*(1+Assumptions_Sources!$E$9) -> 2159.2979 | S11: =R11*(1+Assumptions_Sources!$F$9) -> 2245.6698 | T11: =S11*(1+Assumptions_Sources!$F$9) -> 2335.4966 | U11: =T11*(1+Assumptions_Sources!$F$9) -> 2428.9165 | V11: =U11*(1+Assumptions_Sources!$F$9) -> 2526.0731 | W11: =V11*(1+Assumptions_Sources!$F$9) -> 2627.116 | X11: =IF(E11>0,(R11/E11)^(1/5)-1,0) -> 0.048993332 | Y11: =IF(E11>0,(W11/E11)^(1/10)-1,0) -> 0.044486987
A12: Dermatology franchise | B12: 3600 | C12: 3900 | D12: 4200 | E12: 4500 | F12: 1100 | G12: =(J12-F12)*Assumptions_Sources!$C$45/SUM(Assumptions_Sources!$C$45:$E$45) -> 1258.117 | H12: =(J12-F12)*Assumptions_Sources!$D$45/SUM(Assumptions_Sources!$C$45:$E$45) -> 1258.117 | I12: =J12-F12-G12-H12 -> 1243.7659 | J12: 4860 | K12: =O12*Assumptions_Sources!$B$45 -> 1112.8428 | L12: =O12*Assumptions_Sources!$C$45 -> 1367.6526 | M12: =O12*Assumptions_Sources!$D$45 -> 1367.6526 | N12: =O12-K12-L12-M12 -> 1352.052 | O12: 5200.2 | P12: =O12*(1+Assumptions_Sources!$D$10) -> 5512.212 | Q12: =P12*(1+Assumptions_Sources!$E$10) -> 5815.3837 | R12: =Q12*(1+Assumptions_Sources!$E$10) -> 6135.2298 | S12: =R12*(1+Assumptions_Sources!$F$10) -> 6411.3151 | T12: =S12*(1+Assumptions_Sources!$F$10) -> 6699.8243 | U12: =T12*(1+Assumptions_Sources!$F$10) -> 7001.3164 | V12: =U12*(1+Assumptions_Sources!$F$10) -> 7316.3756 | W12: =V12*(1+Assumptions_Sources!$F$10) -> 7645.6125 | X12: =IF(E12>0,(R12/E12)^(1/5)-1,0) -> 0.063955989 | Y12: =IF(E12>0,(W12/E12)^(1/10)-1,0) -> 0.054435398
A13: Vitamins & other general medicines | B13: 9017.2 | C13: 8787.1 | D13: 9430 | E13: 8072.7 | F13: 1553 | G13: =(J13-F13)*Assumptions_Sources!$C$45/SUM(Assumptions_Sources!$C$45:$E$45) -> 2316.5866 | H13: =(J13-F13)*Assumptions_Sources!$D$45/SUM(Assumptions_Sources!$C$45:$E$45) -> 2316.5866 | I13: =J13-F13-G13-H13 -> 2290.1617 | J13: 8476.335 | K13: =O13*Assumptions_Sources!$B$45 -> 1904.6325 | L13: =O13*Assumptions_Sources!$C$45 -> 2340.7399 | M13: =O13*Assumptions_Sources!$D$45 -> 2340.7399 | N13: =O13-K13-L13-M13 -> 2314.0395 | O13: 8900.1518 | P13: =O13*(1+Assumptions_Sources!$D$11) -> 9300.6586 | Q13: =P13*(1+Assumptions_Sources!$E$11) -> 9672.6849 | R13: =Q13*(1+Assumptions_Sources!$E$11) -> 10059.592 | S13: =R13*(1+Assumptions_Sources!$F$11) -> 10411.678 | T13: =S13*(1+Assumptions_Sources!$F$11) -> 10776.087 | U13: =T13*(1+Assumptions_Sources!$F$11) -> 11153.25 | V13: =U13*(1+Assumptions_Sources!$F$11) -> 11543.614 | W13: =V13*(1+Assumptions_Sources!$F$11) -> 11947.64 | X13: =IF(E13>0,(R13/E13)^(1/5)-1,0) -> 0.044990431 | Y13: =IF(E13>0,(W13/E13)^(1/10)-1,0) -> 0.039983219
A14: General Medicines | B14: =SUM(B8:B13) -> 26317.2 | C14: =SUM(C8:C13) -> 27187.1 | D14: =SUM(D8:D13) -> 29030 | E14: =SUM(E8:E13) -> 28672.7 | F14: =SUM(F8:F13) -> 6633 | G14: =SUM(G8:G13) -> 7997.5205 | H14: =SUM(H8:H13) -> 7997.5205 | I14: =SUM(I8:I13) -> 7906.294 | J14: 30534.335 | K14: =SUM(K8:K13) -> 6944.5261 | L14: =SUM(L8:L13) -> 8534.6279 | M14: =SUM(M8:M13) -> 8534.6279 | N14: =SUM(N8:N13) -> 8437.2748 | O14: 32451.057 | P14: =SUM(P8:P13) -> 34219.943 | Q14: =SUM(Q8:Q13) -> 35897.163 | R14: =SUM(R8:R13) -> 37658.015 | S14: =SUM(S8:S13) -> 39191.251 | T14: =SUM(T8:T13) -> 40787.677 | U14: =SUM(U8:U13) -> 42449.93 | V14: =SUM(V8:V13) -> 44180.754 | W14: =SUM(W8:W13) -> 45983.01 | X14: =IF(E14>0,(R14/E14)^(1/5)-1,0) -> 0.056033676 | Y14: =IF(E14>0,(W14/E14)^(1/10)-1,0) -> 0.048365886
A16: VACCINES
A17: Core paediatric vaccines | B17: 3900 | C17: 4300 | D17: 5000 | E17: 5200 | F17: 1500 | G17: =(J17-F17)*Assumptions_Sources!$C$45/SUM(Assumptions_Sources!$C$45:$E$45) -> 1412.0356 | H17: =(J17-F17)*Assumptions_Sources!$D$45/SUM(Assumptions_Sources!$C$45:$E$45) -> 1412.0356 | I17: =J17-F17-G17-H17 -> 1395.9288 | J17: 5720 | K17: =O17*Assumptions_Sources!$B$45 -> 1334.2472 | L17: =O17*Assumptions_Sources!$C$45 -> 1639.7524 | M17: =O17*Assumptions_Sources!$D$45 -> 1639.7524 | N17: =O17-K17-L17-M17 -> 1621.048 | O17: 6234.8 | P17: =O17*(1+Assumptions_Sources!$D$12) -> 6733.584 | Q17: =P17*(1+Assumptions_Sources!$E$12) -> 7204.9349 | R17: =Q17*(1+Assumptions_Sources!$E$12) -> 7709.2803 | S17: =R17*(1+Assumptions_Sources!$F$12) -> 8133.2907 | T17: =S17*(1+Assumptions_Sources!$F$12) -> 8580.6217 | U17: =T17*(1+Assumptions_Sources!$F$12) -> 9052.5559 | V17: =U17*(1+Assumptions_Sources!$F$12) -> 9550.4465 | W17: =V17*(1+Assumptions_Sources!$F$12) -> 10075.721 | X17: =IF(E17>0,(R17/E17)^(1/5)-1,0) -> 0.081937313 | Y17: =IF(E17>0,(W17/E17)^(1/10)-1,0) -> 0.068383763
A18: Seasonal & travel vaccines | B18: 700 | C18: 750 | D18: 800 | E18: 800 | F18: 300 | G18: =(J18-F18)*Assumptions_Sources!$C$45/SUM(Assumptions_Sources!$C$45:$E$45) -> 188.71756 | H18: =(J18-F18)*Assumptions_Sources!$D$45/SUM(Assumptions_Sources!$C$45:$E$45) -> 188.71756 | I18: =J18-F18-G18-H18 -> 186.56489 | J18: 864 | K18: =O18*Assumptions_Sources!$B$45 -> 199.68768 | L18: =O18*Assumptions_Sources!$C$45 -> 245.41056 | M18: =O18*Assumptions_Sources!$D$45 -> 245.41056 | N18: =O18-K18-L18-M18 -> 242.6112 | O18: 933.12 | P18: =O18*(1+Assumptions_Sources!$D$13) -> 998.4384 | Q18: =P18*(1+Assumptions_Sources!$E$13) -> 1058.3447 | R18: =Q18*(1+Assumptions_Sources!$E$13) -> 1121.8454 | S18: =R18*(1+Assumptions_Sources!$F$13) -> 1177.9377 | T18: =S18*(1+Assumptions_Sources!$F$13) -> 1236.8345 | U18: =T18*(1+Assumptions_Sources!$F$13) -> 1298.6763 | V18: =U18*(1+Assumptions_Sources!$F$13) -> 1363.6101 | W18: =V18*(1+Assumptions_Sources!$F$13) -> 1431.7906 | X18: =IF(E18>0,(R18/E18)^(1/5)-1,0) -> 0.069962616 | Y18: =IF(E18>0,(W18/E18)^(1/10)-1,0) -> 0.059934312
A19: Shingrix | B19: 0 | C19: 450 | D19: 650 | E19: 1100 | F19: 280 | G19: =(J19-F19)*Assumptions_Sources!$C$45/SUM(Assumptions_Sources!$C$45:$E$45) -> 440.00636 | H19: =(J19-F19)*Assumptions_Sources!$D$45/SUM(Assumptions_Sources!$C$45:$E$45) -> 440.00636 | I19: =J19-F19-G19-H19 -> 434.98728 | J19: 1595 | K19: =O19*Assumptions_Sources!$B$45 -> 450.5556 | L19: =O19*Assumptions_Sources!$C$45 -> 553.7202 | M19: =O19*Assumptions_Sources!$D$45 -> 553.7202 | N19: =O19-K19-L19-M19 -> 547.404 | O19: 2105.4 | P19: =O19*(1+Assumptions_Sources!$D$14) -> 2610.696 | Q19: =P19*(1+Assumptions_Sources!$E$14) -> 3054.5143 | R19: =Q19*(1+Assumptions_Sources!$E$14) -> 3573.7818 | S19: =R19*(1+Assumptions_Sources!$F$14) -> 3931.1599 | T19: =S19*(1+Assumptions_Sources!$F$14) -> 4324.2759 | U19: =T19*(1+Assumptions_Sources!$F$14) -> 4756.7035 | V19: =U19*(1+Assumptions_Sources!$F$14) -> 5232.3739 | W19: =V19*(1+Assumptions_Sources!$F$14) -> 5755.6113 | X19: =IF(E19>0,(R19/E19)^(1/5)-1,0) -> 0.26574747 | Y19: =IF(E19>0,(W19/E19)^(1/10)-1,0) -> 0.17996704
A20: Other adult vaccines | B20: 200 | C20: 200 | D20: 140 | E20: 215 | F20: 50 | G20: =(J20-F20)*Assumptions_Sources!$C$45/SUM(Assumptions_Sources!$C$45:$E$45) -> 62.403944 | H20: =(J20-F20)*Assumptions_Sources!$D$45/SUM(Assumptions_Sources!$C$45:$E$45) -> 62.403944 | I20: =J20-F20-G20-H20 -> 61.692112 | J20: 236.5 | K20: =O20*Assumptions_Sources!$B$45 -> 55.6721 | L20: =O20*Assumptions_Sources!$C$45 -> 68.41945 | M20: =O20*Assumptions_Sources!$D$45 -> 68.41945 | N20: =O20-K20-L20-M20 -> 67.639 | O20: 260.15 | P20: =O20*(1+Assumptions_Sources!$D$15) -> 280.962 | Q20: =P20*(1+Assumptions_Sources!$E$15) -> 300.62934 | R20: =Q20*(1+Assumptions_Sources!$E$15) -> 321.67339 | S20: =R20*(1+Assumptions_Sources!$F$15) -> 337.75706 | T20: =S20*(1+Assumptions_Sources!$F$15) -> 354.64492 | U20: =T20*(1+Assumptions_Sources!$F$15) -> 372.37716 | V20: =U20*(1+Assumptions_Sources!$F$15) -> 390.99602 | W20: =V20*(1+Assumptions_Sources!$F$15) -> 410.54582 | X20: =IF(E20>0,(R20/E20)^(1/5)-1,0) -> 0.083915274 | Y20: =IF(E20>0,(W20/E20)^(1/10)-1,0) -> 0.066822871
A21: Arexvy | B21: 0 | C21: 0 | D21: 0 | E21: 0 | F21: 0 | G21: =IF(Assumptions_Sources!$C$30=2027,J21*Assumptions_Sources!$H$30,(J21-F21)*Assumptions_Sources!$C$45/SUM(Assumptions_Sources!$C$45:$E$45)) -> 0 | H21: =IF(Assumptions_Sources!$C$30=2027,J21*Assumptions_Sources!$I$30,(J21-F21)*Assumptions_Sources!$D$45/SUM(Assumptions_Sources!$C$45:$E$45)) -> 83.333333 | I21: =J21-F21-G21-H21 -> 125 | J21: 208.33333 | K21: =O21*Assumptions_Sources!$B$45 -> 133.75 | L21: =O21*Assumptions_Sources!$C$45 -> 164.375 | M21: =O21*Assumptions_Sources!$D$45 -> 164.375 | N21: =O21-K21-L21-M21 -> 162.5 | O21: 625 | P21: =IF(2029<Assumptions_Sources!$C$30,0,IF(2029=Assumptions_Sources!$C$30,Assumptions_Sources!$D$30/Assumptions_Sources!$E$30*Assumptions_Sources!$G$30,IF(2029<Assumptions_Sources!$C$30+Assumptions_Sources!$E$30,MIN(Assumptions_Sources!$D$30,Assumptions_Sources!$D$30/Assumptions_Sources!$E$30*(2029-Assumptions_Sources!$C$30+Assumptions_Sources!$G$30)),Assumptions_Sources!$D$30*(1+Assumptions_Sources!$F$30)^(2029-(Assumptions_Sources!$C$30+Assumptions_Sources!$E$30))))) -> 1041.6667 | Q21: =IF(2030<Assumptions_Sources!$C$30,0,IF(2030=Assumptions_Sources!$C$30,Assumptions_Sources!$D$30/Assumptions_Sources!$E$30*Assumptions_Sources!$G$30,IF(2030<Assumptions_Sources!$C$30+Assumptions_Sources!$E$30,MIN(Assumptions_Sources!$D$30,Assumptions_Sources!$D$30/Assumptions_Sources!$E$30*(2030-Assumptions_Sources!$C$30+Assumptions_Sources!$G$30)),Assumptions_Sources!$D$30*(1+Assumptions_Sources!$F$30)^(2030-(Assumptions_Sources!$C$30+Assumptions_Sources!$E$30))))) -> 1458.3333 | R21: =IF(2031<Assumptions_Sources!$C$30,0,IF(2031=Assumptions_Sources!$C$30,Assumptions_Sources!$D$30/Assumptions_Sources!$E$30*Assumptions_Sources!$G$30,IF(2031<Assumptions_Sources!$C$30+Assumptions_Sources!$E$30,MIN(Assumptions_Sources!$D$30,Assumptions_Sources!$D$30/Assumptions_Sources!$E$30*(2031-Assumptions_Sources!$C$30+Assumptions_Sources!$G$30)),Assumptions_Sources!$D$30*(1+Assumptions_Sources!$F$30)^(2031-(Assumptions_Sources!$C$30+Assumptions_Sources!$E$30))))) -> 1875 | S21: =IF(2032<Assumptions_Sources!$C$30,0,IF(2032=Assumptions_Sources!$C$30,Assumptions_Sources!$D$30/Assumptions_Sources!$E$30*Assumptions_Sources!$G$30,IF(2032<Assumptions_Sources!$C$30+Assumptions_Sources!$E$30,MIN(Assumptions_Sources!$D$30,Assumptions_Sources!$D$30/Assumptions_Sources!$E$30*(2032-Assumptions_Sources!$C$30+Assumptions_Sources!$G$30)),Assumptions_Sources!$D$30*(1+Assumptions_Sources!$F$30)^(2032-(Assumptions_Sources!$C$30+Assumptions_Sources!$E$30))))) -> 2291.6667 | T21: =IF(2033<Assumptions_Sources!$C$30,0,IF(2033=Assumptions_Sources!$C$30,Assumptions_Sources!$D$30/Assumptions_Sources!$E$30*Assumptions_Sources!$G$30,IF(2033<Assumptions_Sources!$C$30+Assumptions_Sources!$E$30,MIN(Assumptions_Sources!$D$30,Assumptions_Sources!$D$30/Assumptions_Sources!$E$30*(2033-Assumptions_Sources!$C$30+Assumptions_Sources!$G$30)),Assumptions_Sources!$D$30*(1+Assumptions_Sources!$F$30)^(2033-(Assumptions_Sources!$C$30+Assumptions_Sources!$E$30))))) -> 2500 | U21: =IF(2034<Assumptions_Sources!$C$30,0,IF(2034=Assumptions_Sources!$C$30,Assumptions_Sources!$D$30/Assumptions_Sources!$E$30*Assumptions_Sources!$G$30,IF(2034<Assumptions_Sources!$C$30+Assumptions_Sources!$E$30,MIN(Assumptions_Sources!$D$30,Assumptions_Sources!$D$30/Assumptions_Sources!$E$30*(2034-Assumptions_Sources!$C$30+Assumptions_Sources!$G$30)),Assumptions_Sources!$D$30*(1+Assumptions_Sources!$F$30)^(2034-(Assumptions_Sources!$C$30+Assumptions_Sources!$E$30))))) -> 2575 | V21: =IF(2035<Assumptions_Sources!$C$30,0,IF(2035=Assumptions_Sources!$C$30,Assumptions_Sources!$D$30/Assumptions_Sources!$E$30*Assumptions_Sources!$G$30,IF(2035<Assumptions_Sources!$C$30+Assumptions_Sources!$E$30,MIN(Assumptions_Sources!$D$30,Assumptions_Sources!$D$30/Assumptions_Sources!$E$30*(2035-Assumptions_Sources!$C$30+Assumptions_Sources!$G$30)),Assumptions_Sources!$D$30*(1+Assumptions_Sources!$F$30)^(2035-(Assumptions_Sources!$C$30+Assumptions_Sources!$E$30))))) -> 2652.25 | W21: =IF(2036<Assumptions_Sources!$C$30,0,IF(2036=Assumptions_Sources!$C$30,Assumptions_Sources!$D$30/Assumptions_Sources!$E$30*Assumptions_Sources!$G$30,IF(2036<Assumptions_Sources!$C$30+Assumptions_Sources!$E$30,MIN(Assumptions_Sources!$D$30,Assumptions_Sources!$D$30/Assumptions_Sources!$E$30*(2036-Assumptions_Sources!$C$30+Assumptions_Sources!$G$30)),Assumptions_Sources!$D$30*(1+Assumptions_Sources!$F$30)^(2036-(Assumptions_Sources!$C$30+Assumptions_Sources!$E$30))))) -> 2731.8175 | X21: =IF(E21>0,(R21/E21)^(1/5)-1,0) -> 0 | Y21: =IF(E21>0,(W21/E21)^(1/10)-1,0) -> 0
A22: Vaccines | B22: =SUM(B17:B21) -> 4800 | C22: =SUM(C17:C21) -> 5700 | D22: =SUM(D17:D21) -> 6590 | E22: =SUM(E17:E21) -> 7315 | F22: =SUM(F17:F21) -> 2130 | G22: =SUM(G17:G21) -> 2103.1635 | H22: =SUM(H17:H21) -> 2186.4968 | I22: =SUM(I17:I21) -> 2204.173 | J22: 8623.8333 | K22: =SUM(K17:K21) -> 2173.9126 | L22: =SUM(L17:L21) -> 2671.6776 | M22: =SUM(M17:M21) -> 2671.6776 | N22: =SUM(N17:N21) -> 2641.2022 | O22: 10158.47 | P22: =SUM(P17:P21) -> 11665.347 | Q22: =SUM(Q17:Q21) -> 13076.757 | R22: =SUM(R17:R21) -> 14601.581 | S22: =SUM(S17:S21) -> 15871.812 | T22: =SUM(T17:T21) -> 16996.377 | U22: =SUM(U17:U21) -> 18055.313 | V22: =SUM(V17:V21) -> 19189.676 | W22: =SUM(W17:W21) -> 20405.486 | X22: =IF(E22>0,(R22/E22)^(1/5)-1,0) -> 0.14825173 | Y22: =IF(E22>0,(W22/E22)^(1/10)-1,0) -> 0.10803445
A24: SPECIALTY RESPIRATORY
A25: Trelegy Ellipta | B25: 250 | C25: 400 | D25: 560 | E25: 620 | F25: 75 | G25: =(J25-F25)*Assumptions_Sources!$C$45/SUM(Assumptions_Sources!$C$45:$E$45) -> 219.70204 | H25: =(J25-F25)*Assumptions_Sources!$D$45/SUM(Assumptions_Sources!$C$45:$E$45) -> 219.70204 | I25: =J25-F25-G25-H25 -> 217.19593 | J25: =E25*(1+Assumptions_Sources!$B$16) -> 731.6 | K25: =O25*Assumptions_Sources!$B$45 -> 180.04676 | L25: =O25*Assumptions_Sources!$C$45 -> 221.27242 | M25: =O25*Assumptions_Sources!$D$45 -> 221.27242 | N25: =O25-K25-L25-M25 -> 218.7484 | O25: =J25*(1+Assumptions_Sources!$C$16) -> 841.34 | P25: =O25*(1+Assumptions_Sources!$D$16) -> 942.3008 | Q25: =P25*(1+Assumptions_Sources!$E$16) -> 1036.5309 | R25: =Q25*(1+Assumptions_Sources!$E$16) -> 1140.184 | S25: =R25*(1+Assumptions_Sources!$F$16) -> 1219.9968 | T25: =S25*(1+Assumptions_Sources!$F$16) -> 1305.3966 | U25: =T25*(1+Assumptions_Sources!$F$16) -> 1396.7744 | V25: =U25*(1+Assumptions_Sources!$F$16) -> 1494.5486 | W25: =V25*(1+Assumptions_Sources!$F$16) -> 1599.167 | X25: =IF(E25>0,(R25/E25)^(1/5)-1,0) -> 0.1295791 | Y25: =IF(E25>0,(W25/E25)^(1/10)-1,0) -> 0.099386027
A26: Nucala | B26: 100 | C26: 150 | D26: 200 | E26: 250 | F26: 32 | G26: =(J26-F26)*Assumptions_Sources!$C$45/SUM(Assumptions_Sources!$C$45:$E$45) -> 93.85687 | H26: =(J26-F26)*Assumptions_Sources!$D$45/SUM(Assumptions_Sources!$C$45:$E$45) -> 93.85687 | I26: =J26-F26-G26-H26 -> 92.78626 | J26: =E26*(1+Assumptions_Sources!$B$17) -> 312.5 | K26: =O26*Assumptions_Sources!$B$45 -> 80.25 | L26: =O26*Assumptions_Sources!$C$45 -> 98.625 | M26: =O26*Assumptions_Sources!$D$45 -> 98.625 | N26: =O26-K26-L26-M26 -> 97.5 | O26: =J26*(1+Assumptions_Sources!$C$17) -> 375 | P26: =O26*(1+Assumptions_Sources!$D$17) -> 442.5 | Q26: =P26*(1+Assumptions_Sources!$E$17) -> 504.45 | R26: =Q26*(1+Assumptions_Sources!$E$17) -> 575.073 | S26: =R26*(1+Assumptions_Sources!$F$17) -> 632.5803 | T26: =S26*(1+Assumptions_Sources!$F$17) -> 695.83833 | U26: =T26*(1+Assumptions_Sources!$F$17) -> 765.42216 | V26: =U26*(1+Assumptions_Sources!$F$17) -> 841.96438 | W26: =V26*(1+Assumptions_Sources!$F$17) -> 926.16082 | X26: =IF(E26>0,(R26/E26)^(1/5)-1,0) -> 0.18129018 | Y26: =IF(E26>0,(W26/E26)^(1/10)-1,0) -> 0.1399207
A27: Other respiratory | B27: 750 | C27: 800 | D27: 850 | E27: 930 | F27: 120 | G27: =(J27-F27)*Assumptions_Sources!$C$45/SUM(Assumptions_Sources!$C$45:$E$45) -> 289.70153 | H27: =(J27-F27)*Assumptions_Sources!$D$45/SUM(Assumptions_Sources!$C$45:$E$45) -> 289.70153 | I27: =J27-F27-G27-H27 -> 286.39695 | J27: =E27*(1+Assumptions_Sources!$B$18) -> 985.8 | K27: =O27*Assumptions_Sources!$B$45 -> 223.61887 | L27: =O27*Assumptions_Sources!$C$45 -> 274.82132 | M27: =O27*Assumptions_Sources!$D$45 -> 274.82132 | N27: =O27-K27-L27-M27 -> 271.68648 | O27: =J27*(1+Assumptions_Sources!$C$18) -> 1044.948 | P27: =O27*(1+Assumptions_Sources!$D$18) -> 1097.1954 | Q27: =P27*(1+Assumptions_Sources!$E$18) -> 1141.0832 | R27: =Q27*(1+Assumptions_Sources!$E$18) -> 1186.7265 | S27: =R27*(1+Assumptions_Sources!$F$18) -> 1222.3283 | T27: =S27*(1+Assumptions_Sources!$F$18) -> 1258.9982 | U27: =T27*(1+Assumptions_Sources!$F$18) -> 1296.7681 | V27: =U27*(1+Assumptions_Sources!$F$18) -> 1335.6712 | W27: =V27*(1+Assumptions_Sources!$F$18) -> 1375.7413 | X27: =IF(E27>0,(R27/E27)^(1/5)-1,0) -> 0.049961904 | Y27: =IF(E27>0,(W27/E27)^(1/10)-1,0) -> 0.039933056
A28: Specialty Respiratory | B28: =SUM(B25:B27) -> 1100 | C28: =SUM(C25:C27) -> 1350 | D28: =SUM(D25:D27) -> 1610 | E28: =SUM(E25:E27) -> 1800 | F28: =SUM(F25:F27) -> 227 | G28: =SUM(G25:G27) -> 603.26043 | H28: =SUM(H25:H27) -> 603.26043 | I28: =SUM(I25:I27) -> 596.37913 | ... W28: =SUM(W25:W27) -> 3901.0691
A30: ONCOLOGY
A31: Jemperli | B31: 0 | C31: 0 | D31: 0 | E31: 70 | F31: 180 | G31: =(J31-F31)*Assumptions_Sources!$C$45/SUM(Assumptions_Sources!$C$45:$E$45) -> 207.45547 | H31: =(J31-F31)*Assumptions_Sources!$D$45/SUM(Assumptions_Sources!$C$45:$E$45) -> 207.45547 | I31: =J31-F31-G31-H31 -> 205.08906 | J31: =Assumptions_Sources!$B$22 -> 800 | K31: =O31*Assumptions_Sources!$B$45 -> 214 | L31: =O31*Assumptions_Sources!$C$45 -> 263 | M31: =O31*Assumptions_Sources!$D$45 -> 263 | N31: =O31-K31-L31-M31 -> 260 | O31: =J31*(1+Assumptions_Sources!$C$22) -> 1000 | P31: =O31*(1+Assumptions_Sources!$D$22) -> 1200 | Q31: =P31*(1+Assumptions_Sources!$E$22) -> 1380 | R31: =Q31*(1+Assumptions_Sources!$E$22) -> 1587 | S31: =R31*(1+Assumptions_Sources!$F$22) -> 1713.96 | T31: =S31*(1+Assumptions_Sources!$F$22) -> 1851.0768 | U31: =T31*(1+Assumptions_Sources!$F$22) -> 1999.1629 | V31: =U31*(1+Assumptions_Sources!$F$22) -> 2159.096 | W31: =V31*(1+Assumptions_Sources!$F$22) -> 2331.8237 | X31: =IF(E31>0,(R31/E31)^(1/5)-1,0) -> 0.86679134 | Y31: =IF(E31>0,(W31/E31)^(1/10)-1,0) -> 0.41990656
A32: Zejula | B32: 0 | C32: 0 | D32: 0 | E32: 44 | F32: 70 | G32: =(J32-F32)*Assumptions_Sources!$C$45/SUM(Assumptions_Sources!$C$45:$E$45) -> 110.41985 | H32: =(J32-F32)*Assumptions_Sources!$D$45/SUM(Assumptions_Sources!$C$45:$E$45) -> 110.41985 | I32: =J32-F32-G32-H32 -> 109.16031 | J32: =Assumptions_Sources!$B$23 -> 400 | K32: =O32*Assumptions_Sources!$B$45 -> 98.44 | L32: =O32*Assumptions_Sources!$C$45 -> 120.98 | M32: =O32*Assumptions_Sources!$D$45 -> 120.98 | N32: =O32-K32-L32-M32 -> 119.6 | O32: =J32*(1+Assumptions_Sources!$C$23) -> 460 | P32: =O32*(1+Assumptions_Sources!$D$23) -> 506 | Q32: =P32*(1+Assumptions_Sources!$E$23) -> 531.3 | R32: =Q32*(1+Assumptions_Sources!$E$23) -> 557.865 | S32: =R32*(1+Assumptions_Sources!$F$23) -> 569.0223 | T32: =S32*(1+Assumptions_Sources!$F$23) -> 580.40275 | U32: =T32*(1+Assumptions_Sources!$F$23) -> 592.0108 | V32: =U32*(1+Assumptions_Sources!$F$23) -> 603.85102 | W32: =V32*(1+Assumptions_Sources!$F$23) -> 615.92804 | X32: =IF(E32>0,(R32/E32)^(1/5)-1,0) -> 0.6619398 | Y32: =IF(E32>0,(W32/E32)^(1/10)-1,0) -> 0.30199024
A33: Blenrep | B33: 0 | C33: 0 | D33: 0 | E33: 0 | F33: 0 | G33: =IF(Assumptions_Sources!$C$31=2027,J33*Assumptions_Sources!$H$31,(J33-F33)*Assumptions_Sources!$C$45/SUM(Assumptions_Sources!$C$45:$E$45)) -> 0 | H33: =IF(Assumptions_Sources!$C$31=2027,J33*Assumptions_Sources!$I$31,(J33-F33)*Assumptions_Sources!$D$45/SUM(Assumptions_Sources!$C$45:$E$45)) -> 66.666667 | I33: =J33-F33-G33-H33 -> 100 | J33: =IF(2027<Assumptions_Sources!$C$31,0,IF(2027=Assumptions_Sources!$C$31,Assumptions_Sources!$D$31/Assumptions_Sources!$E$31*Assumptions_Sources!$G$31,IF(2027<Assumptions_Sources!$C$31+Assumptions_Sources!$E$31,MIN(Assumptions_Sources!$D$31,Assumptions_Sources!$D$31/Assumptions_Sources!$E$31*(2027-Assumptions_Sources!$C$31+Assumptions_Sources!$G$31)),Assumptions_Sources!$D$31*(1+Assumptions_Sources!$F$31)^(2027-(Assumptions_Sources!$C$31+Assumptions_Sources!$E$31))))) -> 166.66667 | K33: =O33*Assumptions_Sources!$B$45 -> 107 | L33: =O33*Assumptions_Sources!$C$45 -> 131.5 | M33: =O33*Assumptions_Sources!$D$45 -> 131.5 | N33: =O33-K33-L33-M33 -> 130 | O33: =IF(2028<Assumptions_Sources!$C$31,0,IF(2028=Assumptions_Sources!$C$31,Assumptions_Sources!$D$31/Assumptions_Sources!$E$31*Assumptions_Sources!$G$31,IF(2028<Assumptions_Sources!$C$31+Assumptions_Sources!$E$31,MIN(Assumptions_Sources!$D$31,Assumptions_Sources!$D$31/Assumptions_Sources!$E$31*(2028-Assumptions_Sources!$C$31+Assumptions_Sources!$G$31)),Assumptions_Sources!$D$31*(1+Assumptions_Sources!$F$31)^(2028-(Assumptions_Sources!$C$31+Assumptions_Sources!$E$31))))) -> 500 | P33: =IF(2029<Assumptions_Sources!$C$31,0,IF(2029=Assumptions_Sources!$C$31,Assumptions_Sources!$D$31/Assumptions_Sources!$E$31*Assumptions_Sources!$G$31,IF(2029<Assumptions_Sources!$C$31+Assumptions_Sources!$E$31,MIN(Assumptions_Sources!$D$31,Assumptions_Sources!$D$31/Assumptions_Sources!$E$31*(2029-Assumptions_Sources!$C$31+Assumptions_Sources!$G$31)),Assumptions_Sources!$D$31*(1+Assumptions_Sources!$F$31)^(2029-(Assumptions_Sources!$C$31+Assumptions_Sources!$E$31))))) -> 833.33333 | Q33: =IF(2030<Assumptions_Sources!$C$31,0,IF(2030=Assumptions_Sources!$C$31,Assumptions_Sources!$D$31/Assumptions_Sources!$E$31*Assumptions_Sources!$G$31,IF(2030<Assumptions_Sources!$C$31+Assumptions_Sources!$E$31,MIN(Assumptions_Sources!$D$31,Assumptions_Sources!$D$31/Assumptions_Sources!$E$31*(2030-Assumptions_Sources!$C$31+Assumptions_Sources!$G$31)),Assumptions_Sources!$D$31*(1+Assumptions_Sources!$F$31)^(2030-(Assumptions_Sources!$C$31+Assumptions_Sources!$E$31))))) -> 1166.6667 | R33: =IF(2031<Assumptions_Sources!$C$31,0,IF(2031=Assumptions_Sources!$C$31,Assumptions_Sources!$D$31/Assumptions_Sources!$E$31*Assumptions_Sources!$G$31,IF(2031<Assumptions_Sources!$C$31+Assumptions_Sources!$E$31,MIN(Assumptions_Sources!$D$31,Assumptions_Sources!$D$31/Assumptions_Sources!$E$31*(2031-Assumptions_Sources!$C$31+Assumptions_Sources!$G$31)),Assumptions_Sources!$D$31*(1+Assumptions_Sources!$F$31)^(2031-(Assumptions_Sources!$C$31+Assumptions_Sources!$E$31))))) -> 1500 | S33: =IF(2032<Assumptions_Sources!$C$31,0,IF(2032=Assumptions_Sources!$C$31,Assumptions_Sources!$D$31/Assumptions_Sources!$E$31*Assumptions_Sources!$G$31,IF(2032<Assumptions_Sources!$C$31+Assumptions_Sources!$E$31,MIN(Assumptions_Sources!$D$31,Assumptions_Sources!$D$31/Assumptions_Sources!$E$31*(2032-Assumptions_Sources!$C$31+Assumptions_Sources!$G$31)),Assumptions_Sources!$D$31*(1+Assumptions_Sources!$F$31)^(2032-(Assumptions_Sources!$C$31+Assumptions_Sources!$E$31))))) -> 1833.3333 | T33: =IF(2033<Assumptions_Sources!$C$31,0,IF(2033=Assumptions_Sources!$C$31,Assumptions_Sources!$D$31/Assumptions_Sources!$E$31*Assumptions_Sources!$G$31,IF(2033<Assumptions_Sources!$C$31+Assumptions_Sources!$E$31,MIN(Assumptions_Sources!$D$31,Assumptions_Sources!$D$31/Assumptions_Sources!$E$31*(2033-Assumptions_Sources!$C$31+Assumptions_Sources!$G$31)),Assumptions_Sources!$D$31*(1+Assumptions_Sources!$F$31)^(2033-(Assumptions_Sources!$C$31+Assumptions_Sources!$E$31))))) -> 2000 | U33: =IF(2034<Assumptions_Sources!$C$31,0,IF(2034=Assumptions_Sources!$C$31,Assumptions_Sources!$D$31/Assumptions_Sources!$E$31*Assumptions_Sources!$G$31,IF(2034<Assumptions_Sources!$C$31+Assumptions_Sources!$E$31,MIN(Assumptions_Sources!$D$31,Assumptions_Sources!$D$31/Assumptions_Sources!$E$31*(2034-Assumptions_Sources!$C$31+Assumptions_Sources!$G$31)),Assumptions_Sources!$D$31*(1+Assumptions_Sources!$F$31)^(2034-(Assumptions_Sources!$C$31+Assumptions_Sources!$E$31))))) -> 2040 | V33: =IF(2035<Assumptions_Sources!$C$31,0,IF(2035=Assumptions_Sources!$C$31,Assumptions_Sources!$D$31/Assumptions_Sources!$E$31*Assumptions_Sources!$G$31,IF(2035<Assumptions_Sources!$C$31+Assumptions_Sources!$E$31,MIN(Assumptions_Sources!$D$31,Assumptions_Sources!$D$31/Assumptions_Sources!$E$31*(2035-Assumptions_Sources!$C$31+Assumptions_Sources!$G$31)),Assumptions_Sources!$D$31*(1+Assumptions_Sources!$F$31)^(2035-(Assumptions_Sources!$C$31+Assumptions_Sources!$E$31))))) -> 2080.8 | W33: =IF(2036<Assumptions_Sources!$C$31,0,IF(2036=Assumptions_Sources!$C$31,Assumptions_Sources!$D$31/Assumptions_Sources!$E$31*Assumptions_Sources!$G$31,IF(2036<Assumptions_Sources!$C$31+Assumptions_Sources!$E$31,MIN(Assumptions_Sources!$D$31,Assumptions_Sources!$D$31/Assumptions_Sources!$E$31*(2036-Assumptions_Sources!$C$31+Assumptions_Sources!$G$31)),Assumptions_Sources!$D$31*(1+Assumptions_Sources!$F$31)^(2036-(Assumptions_Sources!$C$31+Assumptions_Sources!$E$31))))) -> 2122.416 | X33: =IF(E33>0,(R33/E33)^(1/5)-1,0) -> 0 | Y33: =IF(E33>0,(W33/E33)^(1/10)-1,0) -> 0
A34: Ojjaara | B34: =SUM(B31:B33) -> 0 | C34: =SUM(C31:C33) -> 0 | D34: =SUM(D31:D33) -> 0 | E34: =SUM(E31:E33) -> 114 | F34: =SUM(F31:F33) -> 250 | G34: =SUM(G31:G33) -> 317.87532 | H34: =SUM(H31:H33) -> 384.54198 | I34: =SUM(I31:I33) -> 414.24936 | J34: =IF(2027<Assumptions_Sources!$C$33,0,IF(2027=Assumptions_Sources!$C$33,Assumptions_Sources!$D$33/Assumptions_Sources!$E$33*Assumptions_Sources!$G$33,IF(2027<Assumptions_Sources!$C$33+Assumptions_Sources!$E$33,MIN(Assumptions_Sources!$D$33,Assumptions_Sources!$D$33/Assumptions_Sources!$E$33*(2027-Assumptions_Sources!$C$33+Assumptions_Sources!$G$33)),Assumptions_Sources!$D$33*(1+Assumptions_Sources!$F$33)^(2027-(Assumptions_Sources!$C$33+Assumptions_Sources!$E$33))))) -> 0 | K34: =O34*Assumptions_Sources!$B$45 -> 0 | L34: =O34*Assumptions_Sources!$C$45 -> 0 | M34: =O34*Assumptions_Sources!$D$45 -> 0 | N34: =O34-K34-L34-M34 -> 0 | O34: =IF(2028<Assumptions_Sources!$C$33,0,IF(2028=Assumptions_Sources!$C$33,Assumptions_Sources!$D$33/Assumptions_Sources!$E$33*Assumptions_Sources!$G$33,IF(2028<Assumptions_Sources!$C$33+Assumptions_Sources!$E$33,MIN(Assumptions_Sources!$D$33,Assumptions_Sources!$D$33/Assumptions_Sources!$E$33*(2028-Assumptions_Sources!$C$33+Assumptions_Sources!$G$33)),Assumptions_Sources!$D$33*(1+Assumptions_Sources!$F$33)^(2028-(Assumptions_Sources!$C$33+Assumptions_Sources!$E$33))))) -> 0 | P34: 125 | Q34: 375 | R34: 625 | S34: 875 | T34: 1125 | U34: 1375 | V34: 1500 | W34: 1530 | X34: =IF(E34>0,(R34/E34)^(1/5)-1,0) -> 0.40538409 | Y34: =IF(E34>0,(W34/E34)^(1/10)-1,0) -> 0.29651832
A35: Oncology | B35: =SUM(B31:B34) -> 0 | C35: =SUM(C31:C34) -> 0 | D35: =SUM(D31:D34) -> 0 | E35: =SUM(E31:E34) -> 228 | F35: =SUM(F31:F34) -> 500 | G35: =SUM(G31:G34) -> 635.75064 | H35: =SUM(H31:H34) -> 769.08397 | I35: =SUM(I31:I34) -> 828.49873 | ... W35: =SUM(W31:W34) -> 6600.1677
A37: INFECTIOUS DISEASE | J37: =SUM(F37:I37) -> 0 | O37: =SUM(K37:N37) -> 0 | X37: =IF(E37>0,(R37/E37)^(1/5)-1,0) -> 0 | Y37: =IF(E37>0,(W37/E37)^(1/10)-1,0) -> 0
A38: Hibsago / Bepirovirsen | B38: 0 | C38: 0 | D38: 0 | E38: 0 | F38: 0 | G38: =IF(Assumptions_Sources!$C$32=2027,J38*Assumptions_Sources!$H$32,(J38-F38)*Assumptions_Sources!$C$45/SUM(Assumptions_Sources!$C$45:$E$45)) -> 0 | H38: =IF(Assumptions_Sources!$C$32=2027,J38*Assumptions_Sources!$I$32,(J38-F38)*Assumptions_Sources!$D$45/SUM(Assumptions_Sources!$C$45:$E$45)) -> 0 | I38: =J38-F38-G38-H38 -> 250 | J38: =SUM(F38:I38) -> 250 | K38: =O38*Assumptions_Sources!$B$45 -> 160.5 | L38: =O38*Assumptions_Sources!$C$45 -> 197.25 | M38: =O38*Assumptions_Sources!$D$45 -> 197.25 | N38: =O38-K38-L38-M38 -> 195 | O38: =SUM(K38:N38) -> 750 | P38: =IF(2029<Assumptions_Sources!$C$32,0,IF(2029=Assumptions_Sources!$C$32,Assumptions_Sources!$D$32/Assumptions_Sources!$E$32*Assumptions_Sources!$G$32,IF(2029<Assumptions_Sources!$C$32+Assumptions_Sources!$E$32,MIN(Assumptions_Sources!$D$32,Assumptions_Sources!$D$32/Assumptions_Sources!$E$32*(2029-Assumptions_Sources!$C$32+Assumptions_Sources!$G$32)),Assumptions_Sources!$D$32*(1+Assumptions_Sources!$F$32)^(2029-(Assumptions_Sources!$C$32+Assumptions_Sources!$E$32))))) -> 1250 | Q38: =IF(2030<Assumptions_Sources!$C$32,0,IF(2030=Assumptions_Sources!$C$32,Assumptions_Sources!$D$32/Assumptions_Sources!$E$32*Assumptions_Sources!$G$32,IF(2030<Assumptions_Sources!$C$32+Assumptions_Sources!$E$32,MIN(Assumptions_Sources!$D$32,Assumptions_Sources!$D$32/Assumptions_Sources!$E$32*(2030-Assumptions_Sources!$C$32+Assumptions_Sources!$G$32)),Assumptions_Sources!$D$32*(1+Assumptions_Sources!$F$32)^(2030-(Assumptions_Sources!$C$32+Assumptions_Sources!$E$32))))) -> 1750 | R38: =IF(2031<Assumptions_Sources!$C$32,0,IF(2031=Assumptions_Sources!$C$32,Assumptions_Sources!$D$32/Assumptions_Sources!$E$32*Assumptions_Sources!$G$32,IF(2031<Assumptions_Sources!$C$32+Assumptions_Sources!$E$32,MIN(Assumptions_Sources!$D$32,Assumptions_Sources!$D$32/Assumptions_Sources!$E$32*(2031-Assumptions_Sources!$C$32+Assumptions_Sources!$G$32)),Assumptions_Sources!$D$32*(1+Assumptions_Sources!$F$32)^(2031-(Assumptions_Sources!$C$32+Assumptions_Sources!$E$32))))) -> 2250 | S38: =IF(2032<Assumptions_Sources!$C$32,0,IF(2032=Assumptions_Sources!$C$32,Assumptions_Sources!$D$32/Assumptions_Sources!$E$32*Assumptions_Sources!$G$32,IF(2032<Assumptions_Sources!$C$32+Assumptions_Sources!$E$32,MIN(Assumptions_Sources!$D$32,Assumptions_Sources!$D$32/Assumptions_Sources!$E$32*(2032-Assumptions_Sources!$C$32+Assumptions_Sources!$G$32)),Assumptions_Sources!$D$32*(1+Assumptions_Sources!$F$32)^(2032-(Assumptions_Sources!$C$32+Assumptions_Sources!$E$32))))) -> 2750 | T38: =IF(2033<Assumptions_Sources!$C$32,0,IF(2033=Assumptions_Sources!$C$32,Assumptions_Sources!$D$32/Assumptions_Sources!$E$32*Assumptions_Sources!$G$32,IF(2033<Assumptions_Sources!$C$32+Assumptions_Sources!$E$32,MIN(Assumptions_Sources!$D$32,Assumptions_Sources!$D$32/Assumptions_Sources!$E$32*(2033-Assumptions_Sources!$C$32+Assumptions_Sources!$G$32)),Assumptions_Sources!$D$32*(1+Assumptions_Sources!$F$32)^(2033-(Assumptions_Sources!$C$32+Assumptions_Sources!$E$32))))) -> 3250 | U38: =IF(2034<Assumptions_Sources!$C$32,0,IF(2034=Assumptions_Sources!$C$32,Assumptions_Sources!$D$32/Assumptions_Sources!$E$32*Assumptions_Sources!$G$32,IF(2034<Assumptions_Sources!$C$32+Assumptions_Sources!$E$32,MIN(Assumptions_Sources!$D$32,Assumptions_Sources!$D$32/Assumptions_Sources!$E$32*(2034-Assumptions_Sources!$C$32+Assumptions_Sources!$G$32)),Assumptions_Sources!$D$32*(1+Assumptions_Sources!$F$32)^(2034-(Assumptions_Sources!$C$32+Assumptions_Sources!$E$32))))) -> 3500 | V38: =IF(2035<Assumptions_Sources!$C$32,0,IF(2035=Assumptions_Sources!$C$32,Assumptions_Sources!$D$32/Assumptions_Sources!$E$32*Assumptions_Sources!$G$32,IF(2035<Assumptions_Sources!$C$32+Assumptions_Sources!$E$32,MIN(Assumptions_Sources!$D$32,Assumptions_Sources!$D$32/Assumptions_Sources!$E$32*(2035-Assumptions_Sources!$C$32+Assumptions_Sources!$G$32)),Assumptions_Sources!$D$32*(1+Assumptions_Sources!$F$32)^(2035-(Assumptions_Sources!$C$32+Assumptions_Sources!$E$32))))) -> 3605 | W38: =IF(2036<Assumptions_Sources!$C$32,0,IF(2036=Assumptions_Sources!$C$32,Assumptions_Sources!$D$32/Assumptions_Sources!$E$32*Assumptions_Sources!$G$32,IF(2036<Assumptions_Sources!$C$32+Assumptions_Sources!$E$32,MIN(Assumptions_Sources!$D$32,Assumptions_Sources!$D$32/Assumptions_Sources!$E$32*(2036-Assumptions_Sources!$C$32+Assumptions_Sources!$G$32)),Assumptions_Sources!$D$32*(1+Assumptions_Sources!$F$32)^(2036-(Assumptions_Sources!$C$32+Assumptions_Sources!$E$32))))) -> 3713.15 | X38: =IF(E38>0,(R38/E38)^(1/5)-1,0) -> 0 | Y38: =IF(E38>0,(W38/E38)^(1/10)-1,0) -> 0
A39: Infectious Disease | B39: =SUM(B38:B38) -> 0 | C39: =SUM(C38:C38) -> 0 | D39: =SUM(D38:D38) -> 0 | E39: =SUM(E38:E38) -> 0 | F39: =SUM(F38:F38) -> 0 | G39: =SUM(G38:G38) -> 0 | H39: =SUM(H38:H38) -> 0 | I39: =SUM(I38:I38) -> 250 | J39: =SUM(F39:I39) -> 250 | K39: =SUM(K38:K38) -> 160.5 | L39: =SUM(L38:L38) -> 197.25 | M39: =SUM(M38:M38) -> 197.25 | N39: =SUM(N38:N38) -> 195 | O39: =SUM(K39:N39) -> 750 | P39: =SUM(P38:P38) -> 1250 | Q39: =SUM(Q38:Q38) -> 1750 | R39: =SUM(R38:R38) -> 2250 | S39: =SUM(S38:S38) -> 2750 | T39: =SUM(T38:T38) -> 3250 | U39: =SUM(U38:U38) -> 3500 | V39: =SUM(V38:V38) -> 3605 | W39: =SUM(W38:W38) -> 3713.15 | X39: =IF(E39>0,(R39/E39)^(1/5)-1,0) -> 0 | Y39: =IF(E39>0,(W39/E39)^(1/10)-1,0) -> 0
J40: =SUM(F40:I40) -> 0 | O40: =SUM(K40:N40) -> 0 | X40: =IF(E40>0,(R40/E40)^(1/5)-1,0) -> 0 | Y40: =IF(E40>0,(W40/E40)^(1/10)-1,0) -> 0
A41: FUTURE PIPELINE (RISK-ADJUSTED) | J41: =SUM(F41:I41) -> 0 | O41: =SUM(K41:N41) -> 0 | X41: =IF(E41>0,(R41/E41)^(1/5)-1,0) -> 0 | Y41: =IF(E41>0,(W41/E41)^(1/10)-1,0) -> 0
A42: Velzatinib | B42: 0 | C42: 0 | D42: 0 | E42: 0 | F42: 0 | G42: =IF(Assumptions_Sources!$C$37=2027,J42*Assumptions_Sources!$H$37,(J42-F42)*Assumptions_Sources!$C$45/SUM(Assumptions_Sources!$C$45:$E$45)) -> 0 | H42: =IF(Assumptions_Sources!$C$37=2027,J42*Assumptions_Sources!$I$37,(J42-F42)*Assumptions_Sources!$D$45/SUM(Assumptions_Sources!$C$45:$E$45)) -> 0 | I42: =J42-F42-G42-H42 -> 0 | J42: =SUM(F42:I42) -> 0 | K42: =O42*Assumptions_Sources!$B$45 -> 0 | L42: =O42*Assumptions_Sources!$C$45 -> 0 | M42: =O42*Assumptions_Sources!$D$45 -> 0 | N42: =O42-K42-L42-M42 -> 0 | O42: =SUM(K42:N42) -> 0 | P42: =IF(2029<Assumptions_Sources!$C$37,0,IF(2029=Assumptions_Sources!$C$37,Assumptions_Sources!$D$37*Assumptions_Sources!$E$37/Assumptions_Sources!$G$37*Assumptions_Sources!$I$37,IF(2029<Assumptions_Sources!$C$37+Assumptions_Sources!$G$37,MIN(Assumptions_Sources!$D$37*Assumptions_Sources!$E$37,Assumptions_Sources!$D$37*Assumptions_Sources!$E$37/Assumptions_Sources!$G$37*(2029-Assumptions_Sources!$C$37+Assumptions_Sources!$I$37)),Assumptions_Sources!$D$37*Assumptions_Sources!$E$37*(1+Assumptions_Sources!$H$37)^(2029-(Assumptions_Sources!$C$37+Assumptions_Sources!$G$37))))) -> 0 | Q42: =IF(2030<Assumptions_Sources!$C$37,0,IF(2030=Assumptions_Sources!$C$37,Assumptions_Sources!$D$37*Assumptions_Sources!$E$37/Assumptions_Sources!$G$37*Assumptions_Sources!$I$37,IF(2030<Assumptions_Sources!$C$37+Assumptions_Sources!$G$37,MIN(Assumptions_Sources!$D$37*Assumptions_Sources!$E$37,Assumptions_Sources!$D$37*Assumptions_Sources!$E$37/Assumptions_Sources!$G$37*(2030-Assumptions_Sources!$C$37+Assumptions_Sources!$I$37)),Assumptions_Sources!$D$37*Assumptions_Sources!$E$37*(1+Assumptions_Sources!$H$37)^(2030-(Assumptions_Sources!$C$37+Assumptions_Sources!$G$37))))) -> 0 | R42: =IF(2031<Assumptions_Sources!$C$37,0,IF(2031=Assumptions_Sources!$C$37,Assumptions_Sources!$D$37*Assumptions_Sources!$E$37/Assumptions_Sources!$G$37*Assumptions_Sources!$I$37,IF(2031<Assumptions_Sources!$C$37+Assumptions_Sources!$G$37,MIN(Assumptions_Sources!$D$37*Assumptions_Sources!$E$37,Assumptions_Sources!$D$37*Assumptions_Sources!$E$37/Assumptions_Sources!$G$37*(2031-Assumptions_Sources!$C$37+Assumptions_Sources!$I$37)),Assumptions_Sources!$D$37*Assumptions_Sources!$E$37*(1+Assumptions_Sources!$H$37)^(2031-(Assumptions_Sources!$C$37+Assumptions_Sources!$G$37))))) -> 0 | S42: =IF(2032<Assumptions_Sources!$C$37,0,IF(2032=Assumptions_Sources!$C$37,Assumptions_Sources!$D$37*Assumptions_Sources!$E$37/Assumptions_Sources!$G$37*Assumptions_Sources!$I$37,IF(2032<Assumptions_Sources!$C$37+Assumptions_Sources!$G$37,MIN(Assumptions_Sources!$D$37*Assumptions_Sources!$E$37,Assumptions_Sources!$D$37*Assumptions_Sources!$E$37/Assumptions_Sources!$G$37*(2032-Assumptions_Sources!$C$37+Assumptions_Sources!$I$37)),Assumptions_Sources!$D$37*Assumptions_Sources!$E$37*(1+Assumptions_Sources!$H$37)^(2032-(Assumptions_Sources!$C$37+Assumptions_Sources!$G$37))))) -> 44 | T42: =IF(2033<Assumptions_Sources!$C$37,0,IF(2033=Assumptions_Sources!$C$37,Assumptions_Sources!$D$37*Assumptions_Sources!$E$37/Assumptions_Sources!$G$37*Assumptions_Sources!$I$37,IF(2033<Assumptions_Sources!$C$37+Assumptions_Sources!$G$37,MIN(Assumptions_Sources!$D$37*Assumptions_Sources!$E$37,Assumptions_Sources!$D$37*Assumptions_Sources!$E$37/Assumptions_Sources!$G$37*(2033-Assumptions_Sources!$C$37+Assumptions_Sources!$I$37)),Assumptions_Sources!$D$37*Assumptions_Sources!$E$37*(1+Assumptions_Sources!$H$37)^(2033-(Assumptions_Sources!$C$37+Assumptions_Sources!$G$37))))) -> 132 | U42: =IF(2034<Assumptions_Sources!$C$37,0,IF(2034=Assumptions_Sources!$C$37,Assumptions_Sources!$D$37*Assumptions_Sources!$E$37/Assumptions_Sources!$G$37*Assumptions_Sources!$I$37,IF(2034<Assumptions_Sources!$C$37+Assumptions_Sources!$G$37,MIN(Assumptions_Sources!$D$37*Assumptions_Sources!$E$37,Assumptions_Sources!$D$37*Assumptions_Sources!$E$37/Assumptions_Sources!$G$37*(2034-Assumptions_Sources!$C$37+Assumptions_Sources!$I$37)),Assumptions_Sources!$D$37*Assumptions_Sources!$E$37*(1+Assumptions_Sources!$H$37)^(2034-(Assumptions_Sources!$C$37+Assumptions_Sources!$G$37))))) -> 220 | V42: =IF(2035<Assumptions_Sources!$C$37,0,IF(2035=Assumptions_Sources!$C$37,Assumptions_Sources!$D$37*Assumptions_Sources!$E$37/Assumptions_Sources!$G$37*Assumptions_Sources!$I$37,IF(2035<Assumptions_Sources!$C$37+Assumptions_Sources!$G$37,MIN(Assumptions_Sources!$D$37*Assumptions_Sources!$E$37,Assumptions_Sources!$D$37*Assumptions_Sources!$E$37/Assumptions_Sources!$G$37*(2035-Assumptions_Sources!$C$37+Assumptions_Sources!$I$37)),Assumptions_Sources!$D$37*Assumptions_Sources!$E$37*(1+Assumptions_Sources!$H$37)^(2035-(Assumptions_Sources!$C$37+Assumptions_Sources!$G$37))))) -> 308 | W42: =IF(2036<Assumptions_Sources!$C$37,0,IF(2036=Assumptions_Sources!$C$37,Assumptions_Sources!$D$37*Assumptions_Sources!$E$37/Assumptions_Sources!$G$37*Assumptions_Sources!$I$37,IF(2036<Assumptions_Sources!$C$37+Assumptions_Sources!$G$37,MIN(Assumptions_Sources!$D$37*Assumptions_Sources!$E$37,Assumptions_Sources!$D$37*Assumptions_Sources!$E$37/Assumptions_Sources!$G$37*(2036-Assumptions_Sources!$C$37+Assumptions_Sources!$I$37)),Assumptions_Sources!$D$37*Assumptions_Sources!$E$37*(1+Assumptions_Sources!$H$37)^(2036-(Assumptions_Sources!$C$37+Assumptions_Sources!$G$37))))) -> 396 | X42: =IF(E42>0,(R42/E42)^(1/5)-1,0) -> 0 | Y42: =IF(E42>0,(W42/E42)^(1/10)-1,0) -> 0
A43: Mocertatug rezetecan (B7-H4) | B43: 0 | C43: 0 | D43: 0 | E43: 0 | F43: 0 | G43: =IF(Assumptions_Sources!$C$38=2027,J43*Assumptions_Sources!$H$38,(J43-F43)*Assumptions_Sources!$C$45/SUM(Assumptions_Sources!$C$45:$E$45)) -> 0 | H43: =IF(Assumptions_Sources!$C$38=2027,J43*Assumptions_Sources!$I$38,(J43-F43)*Assumptions_Sources!$D$45/SUM(Assumptions_Sources!$C$45:$E$45)) -> 0 | I43: =J43-F43-G43-H43 -> 0 | J43: =SUM(F43:I43) -> 0 | K43: =O43*Assumptions_Sources!$B$45 -> 0 | L43: =O43*Assumptions_Sources!$C$45 -> 0 | M43: =O43*Assumptions_Sources!$D$45 -> 0 | N43: =O43-K43-L43-M43 -> 0 | O43: =SUM(K43:N43) -> 0 | P43: =IF(2029<Assumptions_Sources!$C$38,0,IF(2029=Assumptions_Sources!$C$38,Assumptions_Sources!$D$38*Assumptions_Sources!$E$38/Assumptions_Sources!$G$38*Assumptions_Sources!$I$38,IF(2029<Assumptions_Sources!$C$38+Assumptions_Sources!$G$38,MIN(Assumptions_Sources!$D$38*Assumptions_Sources!$E$38,Assumptions_Sources!$D$38*Assumptions_Sources!$E$38/Assumptions_Sources!$G$38*(2029-Assumptions_Sources!$C$38+Assumptions_Sources!$I$38)),Assumptions_Sources!$D$38*Assumptions_Sources!$E$38*(1+Assumptions_Sources!$H$38)^(2029-(Assumptions_Sources!$C$38+Assumptions_Sources!$G$38))))) -> 0 | Q43: =IF(2030<Assumptions_Sources!$C$38,0,IF(2030=Assumptions_Sources!$C$38,Assumptions_Sources!$D$38*Assumptions_Sources!$E$38/Assumptions_Sources!$G$38*Assumptions_Sources!$I$38,IF(2030<Assumptions_Sources!$C$38+Assumptions_Sources!$G$38,MIN(Assumptions_Sources!$D$38*Assumptions_Sources!$E$38,Assumptions_Sources!$D$38*Assumptions_Sources!$E$38/Assumptions_Sources!$G$38*(2030-Assumptions_Sources!$C$38+Assumptions_Sources!$I$38)),Assumptions_Sources!$D$38*Assumptions_Sources!$E$38*(1+Assumptions_Sources!$H$38)^(2030-(Assumptions_Sources!$C$38+Assumptions_Sources!$G$38))))) -> 0 | R43: =IF(2031<Assumptions_Sources!$C$38,0,IF(2031=Assumptions_Sources!$C$38,Assumptions_Sources!$D$38*Assumptions_Sources!$E$38/Assumptions_Sources!$G$38*Assumptions_Sources!$I$38,IF(2031<Assumptions_Sources!$C$38+Assumptions_Sources!$G$38,MIN(Assumptions_Sources!$D$38*Assumptions_Sources!$E$38,Assumptions_Sources!$D$38*Assumptions_Sources!$E$38/Assumptions_Sources!$G$38*(2031-Assumptions_Sources!$C$38+Assumptions_Sources!$I$38)),Assumptions_Sources!$D$38*Assumptions_Sources!$E$38*(1+Assumptions_Sources!$H$38)^(2031-(Assumptions_Sources!$C$38+Assumptions_Sources!$G$38))))) -> 0 | S43: =IF(2032<Assumptions_Sources!$C$38,0,IF(2032=Assumptions_Sources!$C$38,Assumptions_Sources!$D$38*Assumptions_Sources!$E$38/Assumptions_Sources!$G$38*Assumptions_Sources!$I$38,IF(2032<Assumptions_Sources!$C$38+Assumptions_Sources!$G$38,MIN(Assumptions_Sources!$D$38*Assumptions_Sources!$E$38,Assumptions_Sources!$D$38*Assumptions_Sources!$E$38/Assumptions_Sources!$G$38*(2032-Assumptions_Sources!$C$38+Assumptions_Sources!$I$38)),Assumptions_Sources!$D$38*Assumptions_Sources!$E$38*(1+Assumptions_Sources!$H$38)^(2032-(Assumptions_Sources!$C$38+Assumptions_Sources!$G$38))))) -> 0 | T43: =IF(2033<Assumptions_Sources!$C$38,0,IF(2033=Assumptions_Sources!$C$38,Assumptions_Sources!$D$38*Assumptions_Sources!$E$38/Assumptions_Sources!$G$38*Assumptions_Sources!$I$38,IF(2033<Assumptions_Sources!$C$38+Assumptions_Sources!$G$38,MIN(Assumptions_Sources!$D$38*Assumptions_Sources!$E$38,Assumptions_Sources!$D$38*Assumptions_Sources!$E$38/Assumptions_Sources!$G$38*(2033-Assumptions_Sources!$C$38+Assumptions_Sources!$I$38)),Assumptions_Sources!$D$38*Assumptions_Sources!$E$38*(1+Assumptions_Sources!$H$38)^(2033-(Assumptions_Sources!$C$38+Assumptions_Sources!$G$38))))) -> 60 | U43: =IF(2034<Assumptions_Sources!$C$38,0,IF(2034=Assumptions_Sources!$C$38,Assumptions_Sources!$D$38*Assumptions_Sources!$E$38/Assumptions_Sources!$G$38*Assumptions_Sources!$I$38,IF(2034<Assumptions_Sources!$C$38+Assumptions_Sources!$G$38,MIN(Assumptions_Sources!$D$38*Assumptions_Sources!$E$38,Assumptions_Sources!$D$38*Assumptions_Sources!$E$38/Assumptions_Sources!$G$38*(2034-Assumptions_Sources!$C$38+Assumptions_Sources!$I$38)),Assumptions_Sources!$D$38*Assumptions_Sources!$E$38*(1+Assumptions_Sources!$H$38)^(2034-(Assumptions_Sources!$C$38+Assumptions_Sources!$G$38))))) -> 180 | V43: =IF(2035<Assumptions_Sources!$C$38,0,IF(2035=Assumptions_Sources!$C$38,Assumptions_Sources!$D$38*Assumptions_Sources!$E$38/Assumptions_Sources!$G$38*Assumptions_Sources!$I$38,IF(2035<Assumptions_Sources!$C$38+Assumptions_Sources!$G$38,MIN(Assumptions_Sources!$D$38*Assumptions_Sources!$E$38,Assumptions_Sources!$D$38*Assumptions_Sources!$E$38/Assumptions_Sources!$G$38*(2035-Assumptions_Sources!$C$38+Assumptions_Sources!$I$38)),Assumptions_Sources!$D$38*Assumptions_Sources!$E$38*(1+Assumptions_Sources!$H$38)^(2035-(Assumptions_Sources!$C$38+Assumptions_Sources!$G$38))))) -> 300 | W43: =IF(2036<Assumptions_Sources!$C$38,0,IF(2036=Assumptions_Sources!$C$38,Assumptions_Sources!$D$38*Assumptions_Sources!$E$38/Assumptions_Sources!$G$38*Assumptions_Sources!$I$38,IF(2036<Assumptions_Sources!$C$38+Assumptions_Sources!$G$38,MIN(Assumptions_Sources!$D$38*Assumptions_Sources!$E$38,Assumptions_Sources!$D$38*Assumptions_Sources!$E$38/Assumptions_Sources!$G$38*(2036-Assumptions_Sources!$C$38+Assumptions_Sources!$I$38)),Assumptions_Sources!$D$38*Assumptions_Sources!$E$38*(1+Assumptions_Sources!$H$38)^(2036-(Assumptions_Sources!$C$38+Assumptions_Sources!$G$38))))) -> 420 | X43: =IF(E43>0,(R43/E43)^(1/5)-1,0) -> 0 | Y43: =IF(E43>0,(W43/E43)^(1/10)-1,0) -> 0
A44: Efimosfermin | B44: =SUM(B37:B43) -> 0 | C44: =SUM(C37:C43) -> 0 | D44: =SUM(D37:D43) -> 0 | E44: =SUM(E37:E43) -> 0 | F44: =SUM(F37:F43) -> 0 | G44: =SUM(G37:G43) -> 0 | H44: =SUM(H37:H43) -> 0 | I44: =SUM(I37:I43) -> 0 | J44: =SUM(F44:I44) -> 0 | K44: =O44*Assumptions_Sources!$B$45 -> 0 | L44: =O44*Assumptions_Sources!$C$45 -> 0 | M44: =O44*Assumptions_Sources!$D$45 -> 0 | N44: =O44-K44-L44-M44 -> 0 | O44: =SUM(K44:N44) -> 0 | P44: 0 | Q44: 0 | R44: 91.666667 | S44: 275 | T44: 458.33333 | U44: 641.66667 | V44: 825 | W44: 1008.3333 | X44: =IF(E44>0,(R44/E44)^(1/5)-1,0) -> 0 | Y44: =IF(E44>0,(W44/E44)^(1/10)-1,0) -> 0
A45: TSLP (GSK5784283) | B45: 0 | C45: 0 | D45: 0 | E45: 0 | F45: 0 | G45: =IF(Assumptions_Sources!$C$40=2027,J45*Assumptions_Sources!$H$40,(J45-F45)*Assumptions_Sources!$C$45/SUM(Assumptions_Sources!$C$45:$E$45)) -> 0 | H45: =IF(Assumptions_Sources!$C$40=2027,J45*Assumptions_Sources!$I$40,(J45-F45)*Assumptions_Sources!$D$45/SUM(Assumptions_Sources!$C$45:$E$45)) -> 0 | I45: =J45-F45-G45-H45 -> 0 | J45: =IF(2027<Assumptions_Sources!$C$40,0,IF(2027=Assumptions_Sources!$C$40,Assumptions_Sources!$D$40*Assumptions_Sources!$E$40/Assumptions_Sources!$G$40*Assumptions_Sources!$I$40,IF(2027<Assumptions_Sources!$C$40+Assumptions_Sources!$G$40,MIN(Assumptions_Sources!$D$40*Assumptions_Sources!$E$40,Assumptions_Sources!$D$40*Assumptions_Sources!$E$40/Assumptions_Sources!$G$40*(2027-Assumptions_Sources!$C$40+Assumptions_Sources!$I$40)),Assumptions_Sources!$D$40*Assumptions_Sources!$E$40*(1+Assumptions_Sources!$H$40)^(2027-(Assumptions_Sources!$C$40+Assumptions_Sources!$G$40))))) -> 0 | K45: =O45*Assumptions_Sources!$B$45 -> 0 | L45: =O45*Assumptions_Sources!$C$45 -> 0 | M45: =O45*Assumptions_Sources!$D$45 -> 0 | N45: =O45-K45-L45-M45 -> 0 | O45: =IF(2028<Assumptions_Sources!$C$40,0,IF(2028=Assumptions_Sources!$C$40,Assumptions_Sources!$D$40*Assumptions_Sources!$E$40/Assumptions_Sources!$G$40*Assumptions_Sources!$I$40,IF(2028<Assumptions_Sources!$C$40+Assumptions_Sources!$G$40,MIN(Assumptions_Sources!$D$40*Assumptions_Sources!$E$40,Assumptions_Sources!$D$40*Assumptions_Sources!$E$40/Assumptions_Sources!$G$40*(2028-Assumptions_Sources!$C$40+Assumptions_Sources!$I$40)),Assumptions_Sources!$D$40*Assumptions_Sources!$E$40*(1+Assumptions_Sources!$H$40)^(2028-(Assumptions_Sources!$C$40+Assumptions_Sources!$G$40))))) -> 0 | P45: =IF(2029<Assumptions_Sources!$C$40,0,IF(2029=Assumptions_Sources!$C$40,Assumptions_Sources!$D$40*Assumptions_Sources!$E$40/Assumptions_Sources!$G$40*Assumptions_Sources!$I$40,IF(2029<Assumptions_Sources!$C$40+Assumptions_Sources!$G$40,MIN(Assumptions_Sources!$D$40*Assumptions_Sources!$E$40,Assumptions_Sources!$D$40*Assumptions_Sources!$E$40/Assumptions_Sources!$G$40*(2029-Assumptions_Sources!$C$40+Assumptions_Sources!$I$40)),Assumptions_Sources!$D$40*Assumptions_Sources!$E$40*(1+Assumptions_Sources!$H$40)^(2029-(Assumptions_Sources!$C$40+Assumptions_Sources!$G$40))))) -> 0 | Q45: =IF(2030<Assumptions_Sources!$C$40,0,IF(2030=Assumptions_Sources!$C$40,Assumptions_Sources!$D$40*Assumptions_Sources!$E$40/Assumptions_Sources!$G$40*Assumptions_Sources!$I$40,IF(2030<Assumptions_Sources!$C$40+Assumptions_Sources!$G$40,MIN(Assumptions_Sources!$D$40*Assumptions_Sources!$E$40,Assumptions_Sources!$D$40*Assumptions_Sources!$E$40/Assumptions_Sources!$G$40*(2030-Assumptions_Sources!$C$40+Assumptions_Sources!$I$40)),Assumptions_Sources!$D$40*Assumptions_Sources!$E$40*(1+Assumptions_Sources!$H$40)^(2030-(Assumptions_Sources!$C$40+Assumptions_Sources!$G$40))))) -> 0 | R45: =IF(2031<Assumptions_Sources!$C$40,0,IF(2031=Assumptions_Sources!$C$40,Assumptions_Sources!$D$40*Assumptions_Sources!$E$40/Assumptions_Sources!$G$40*Assumptions_Sources!$I$40,IF(2031<Assumptions_Sources!$C$40+Assumptions_Sources!$G$40,MIN(Assumptions_Sources!$D$40*Assumptions_Sources!$E$40,Assumptions_Sources!$D$40*Assumptions_Sources!$E$40/Assumptions_Sources!$G$40*(2031-Assumptions_Sources!$C$40+Assumptions_Sources!$I$40)),Assumptions_Sources!$D$40*Assumptions_Sources!$E$40*(1+Assumptions_Sources!$H$40)^(2031-(Assumptions_Sources!$C$40+Assumptions_Sources!$G$40))))) -> 0 | S45: =IF(2032<Assumptions_Sources!$C$40,0,IF(2032=Assumptions_Sources!$C$40,Assumptions_Sources!$D$40*Assumptions_Sources!$E$40/Assumptions_Sources!$G$40*Assumptions_Sources!$I$40,IF(2032<Assumptions_Sources!$C$40+Assumptions_Sources!$G$40,MIN(Assumptions_Sources!$D$40*Assumptions_Sources!$E$40,Assumptions_Sources!$D$40*Assumptions_Sources!$E$40/Assumptions_Sources!$G$40*(2032-Assumptions_Sources!$C$40+Assumptions_Sources!$I$40)),Assumptions_Sources!$D$40*Assumptions_Sources!$E$40*(1+Assumptions_Sources!$H$40)^(2032-(Assumptions_Sources!$C$40+Assumptions_Sources!$G$40))))) -> 0 | T45: =IF(2033<Assumptions_Sources!$C$40,0,IF(2033=Assumptions_Sources!$C$40,Assumptions_Sources!$D$40*Assumptions_Sources!$E$40/Assumptions_Sources!$G$40*Assumptions_Sources!$I$40,IF(2033<Assumptions_Sources!$C$40+Assumptions_Sources!$G$40,MIN(Assumptions_Sources!$D$40*Assumptions_Sources!$E$40,Assumptions_Sources!$D$40*Assumptions_Sources!$E$40/Assumptions_Sources!$G$40*(2033-Assumptions_Sources!$C$40+Assumptions_Sources!$I$40)),Assumptions_Sources!$D$40*Assumptions_Sources!$E$40*(1+Assumptions_Sources!$H$40)^(2033-(Assumptions_Sources!$C$40+Assumptions_Sources!$G$40))))) -> 0 | U45: =IF(2034<Assumptions_Sources!$C$40,0,IF(2034=Assumptions_Sources!$C$40,Assumptions_Sources!$D$40*Assumptions_Sources!$E$40/Assumptions_Sources!$G$40*Assumptions_Sources!$I$40,IF(2034<Assumptions_Sources!$C$40+Assumptions_Sources!$G$40,MIN(Assumptions_Sources!$D$40*Assumptions_Sources!$E$40,Assumptions_Sources!$D$40*Assumptions_Sources!$E$40/Assumptions_Sources!$G$40*(2034-Assumptions_Sources!$C$40+Assumptions_Sources!$I$40)),Assumptions_Sources!$D$40*Assumptions_Sources!$E$40*(1+Assumptions_Sources!$H$40)^(2034-(Assumptions_Sources!$C$40+Assumptions_Sources!$G$40))))) -> 30 | V45: =IF(2035<Assumptions_Sources!$C$40,0,IF(2035=Assumptions_Sources!$C$40,Assumptions_Sources!$D$40*Assumptions_Sources!$E$40/Assumptions_Sources!$G$40*Assumptions_Sources!$I$40,IF(2035<Assumptions_Sources!$C$40+Assumptions_Sources!$G$40,MIN(Assumptions_Sources!$D$40*Assumptions_Sources!$E$40,Assumptions_Sources!$D$40*Assumptions_Sources!$E$40/Assumptions_Sources!$G$40*(2035-Assumptions_Sources!$C$40+Assumptions_Sources!$I$40)),Assumptions_Sources!$D$40*Assumptions_Sources!$E$40*(1+Assumptions_Sources!$H$40)^(2035-(Assumptions_Sources!$C$40+Assumptions_Sources!$G$40))))) -> 90 | W45: =IF(2036<Assumptions_Sources!$C$40,0,IF(2036=Assumptions_Sources!$C$40,Assumptions_Sources!$D$40*Assumptions_Sources!$E$40/Assumptions_Sources!$G$40*Assumptions_Sources!$I$40,IF(2036<Assumptions_Sources!$C$40+Assumptions_Sources!$G$40,MIN(Assumptions_Sources!$D$40*Assumptions_Sources!$E$40,Assumptions_Sources!$D$40*Assumptions_Sources!$E$40/Assumptions_Sources!$G$40*(2036-Assumptions_Sources!$C$40+Assumptions_Sources!$I$40)),Assumptions_Sources!$D$40*Assumptions_Sources!$E$40*(1+Assumptions_Sources!$H$40)^(2036-(Assumptions_Sources!$C$40+Assumptions_Sources!$G$40))))) -> 150 | X45: =IF(E45>0,(R45/E45)^(1/5)-1,0) -> 0 | Y45: =IF(E45>0,(W45/E45)^(1/10)-1,0) -> 0
A46: Gatuzosiran / GSK4532990 | B46: 0 | C46: 0 | D46: 0 | E46: 0 | F46: 0 | G46: =IF(Assumptions_Sources!$C$41=2027,J46*Assumptions_Sources!$H$41,(J46-F46)*Assumptions_Sources!$C$45/SUM(Assumptions_Sources!$C$45:$E$45)) -> 0 | H46: =IF(Assumptions_Sources!$C$41=2027,J46*Assumptions_Sources!$I$41,(J46-F46)*Assumptions_Sources!$D$45/SUM(Assumptions_Sources!$C$45:$E$45)) -> 0 | I46: =J46-F46-G46-H46 -> 0 | J46: =IF(2027<Assumptions_Sources!$C$41,0,IF(2027=Assumptions_Sources!$C$41,Assumptions_Sources!$D$41*Assumptions_Sources!$E$41/Assumptions_Sources!$G$41*Assumptions_Sources!$I$41,IF(2027<Assumptions_Sources!$C$41+Assumptions_Sources!$G$41,MIN(Assumptions_Sources!$D$41*Assumptions_Sources!$E$41,Assumptions_Sources!$D$41*Assumptions_Sources!$E$41/Assumptions_Sources!$G$41*(2027-Assumptions_Sources!$C$41+Assumptions_Sources!$I$41)),Assumptions_Sources!$D$41*Assumptions_Sources!$E$41*(1+Assumptions_Sources!$H$41)^(2027-(Assumptions_Sources!$C$41+Assumptions_Sources!$G$41))))) -> 0 | K46: =O46*Assumptions_Sources!$B$45 -> 0 | L46: =O46*Assumptions_Sources!$C$45 -> 0 | M46: =O46*Assumptions_Sources!$D$45 -> 0 | N46: =O46-K46-L46-M46 -> 0 | O46: =IF(2028<Assumptions_Sources!$C$41,0,IF(2028=Assumptions_Sources!$C$41,Assumptions_Sources!$D$41*Assumptions_Sources!$E$41/Assumptions_Sources!$G$41*Assumptions_Sources!$I$41,IF(2028<Assumptions_Sources!$C$41+Assumptions_Sources!$G$41,MIN(Assumptions_Sources!$D$41*Assumptions_Sources!$E$41,Assumptions_Sources!$D$41*Assumptions_Sources!$E$41/Assumptions_Sources!$G$41*(2028-Assumptions_Sources!$C$41+Assumptions_Sources!$I$41)),Assumptions_Sources!$D$41*Assumptions_Sources!$E$41*(1+Assumptions_Sources!$H$41)^(2028-(Assumptions_Sources!$C$41+Assumptions_Sources!$G$41))))) -> 0 | P46: =IF(2029<Assumptions_Sources!$C$41,0,IF(2029=Assumptions_Sources!$C$41,Assumptions_Sources!$D$41*Assumptions_Sources!$E$41/Assumptions_Sources!$G$41*Assumptions_Sources!$I$41,IF(2029<Assumptions_Sources!$C$41+Assumptions_Sources!$G$41,MIN(Assumptions_Sources!$D$41*Assumptions_Sources!$E$41,Assumptions_Sources!$D$41*Assumptions_Sources!$E$41/Assumptions_Sources!$G$41*(2029-Assumptions_Sources!$C$41+Assumptions_Sources!$I$41)),Assumptions_Sources!$D$41*Assumptions_Sources!$E$41*(1+Assumptions_Sources!$H$41)^(2029-(Assumptions_Sources!$C$41+Assumptions_Sources!$G$41))))) -> 0 | Q46: =IF(2030<Assumptions_Sources!$C$41,0,IF(2030=Assumptions_Sources!$C$41,Assumptions_Sources!$D$41*Assumptions_Sources!$E$41/Assumptions_Sources!$G$41*Assumptions_Sources!$I$41,IF(2030<Assumptions_Sources!$C$41+Assumptions_Sources!$G$41,MIN(Assumptions_Sources!$D$41*Assumptions_Sources!$E$41,Assumptions_Sources!$D$41*Assumptions_Sources!$E$41/Assumptions_Sources!$G$41*(2030-Assumptions_Sources!$C$41+Assumptions_Sources!$I$41)),Assumptions_Sources!$D$41*Assumptions_Sources!$E$41*(1+Assumptions_Sources!$H$41)^(2030-(Assumptions_Sources!$C$41+Assumptions_Sources!$G$41))))) -> 0 | R46: =IF(2031<Assumptions_Sources!$C$41,0,IF(2031=Assumptions_Sources!$C$41,Assumptions_Sources!$D$41*Assumptions_Sources!$E$41/Assumptions_Sources!$G$41*Assumptions_Sources!$I$41,IF(2031<Assumptions_Sources!$C$41+Assumptions_Sources!$G$41,MIN(Assumptions_Sources!$D$41*Assumptions_Sources!$E$41,Assumptions_Sources!$D$41*Assumptions_Sources!$E$41/Assumptions_Sources!$G$41*(2031-Assumptions_Sources!$C$41+Assumptions_Sources!$I$41)),Assumptions_Sources!$D$41*Assumptions_Sources!$E$41*(1+Assumptions_Sources!$H$41)^(2031-(Assumptions_Sources!$C$41+Assumptions_Sources!$G$41))))) -> 0 | S46: =IF(2032<Assumptions_Sources!$C$41,0,IF(2032=Assumptions_Sources!$C$41,Assumptions_Sources!$D$41*Assumptions_Sources!$E$41/Assumptions_Sources!$G$41*Assumptions_Sources!$I$41,IF(2032<Assumptions_Sources!$C$41+Assumptions_Sources!$G$41,MIN(Assumptions_Sources!$D$41*Assumptions_Sources!$E$41,Assumptions_Sources!$D$41*Assumptions_Sources!$E$41/Assumptions_Sources!$G$41*(2032-Assumptions_Sources!$C$41+Assumptions_Sources!$I$41)),Assumptions_Sources!$D$41*Assumptions_Sources!$E$41*(1+Assumptions_Sources!$H$41)^(2032-(Assumptions_Sources!$C$41+Assumptions_Sources!$G$41))))) -> 0 | T46: =IF(2033<Assumptions_Sources!$C$41,0,IF(2033=Assumptions_Sources!$C$41,Assumptions_Sources!$D$41*Assumptions_Sources!$E$41/Assumptions_Sources!$G$41*Assumptions_Sources!$I$41,IF(2033<Assumptions_Sources!$C$41+Assumptions_Sources!$G$41,MIN(Assumptions_Sources!$D$41*Assumptions_Sources!$E$41,Assumptions_Sources!$D$41*Assumptions_Sources!$E$41/Assumptions_Sources!$G$41*(2033-Assumptions_Sources!$C$41+Assumptions_Sources!$I$41)),Assumptions_Sources!$D$41*Assumptions_Sources!$E$41*(1+Assumptions_Sources!$H$41)^(2033-(Assumptions_Sources!$C$41+Assumptions_Sources!$G$41))))) -> 0 | U46: =IF(2034<Assumptions_Sources!$C$41,0,IF(2034=Assumptions_Sources!$C$41,Assumptions_Sources!$D$41*Assumptions_Sources!$E$41/Assumptions_Sources!$G$41*Assumptions_Sources!$I$41,IF(2034<Assumptions_Sources!$C$41+Assumptions_Sources!$G$41,MIN(Assumptions_Sources!$D$41*Assumptions_Sources!$E$41,Assumptions_Sources!$D$41*Assumptions_Sources!$E$41/Assumptions_Sources!$G$41*(2034-Assumptions_Sources!$C$41+Assumptions_Sources!$I$41)),Assumptions_Sources!$D$41*Assumptions_Sources!$E$41*(1+Assumptions_Sources!$H$41)^(2034-(Assumptions_Sources!$C$41+Assumptions_Sources!$G$41))))) -> 0 | V46: =IF(2035<Assumptions_Sources!$C$41,0,IF(2035=Assumptions_Sources!$C$41,Assumptions_Sources!$D$41*Assumptions_Sources!$E$41/Assumptions_Sources!$G$41*Assumptions_Sources!$I$41,IF(2035<Assumptions_Sources!$C$41+Assumptions_Sources!$G$41,MIN(Assumptions_Sources!$D$41*Assumptions_Sources!$E$41,Assumptions_Sources!$D$41*Assumptions_Sources!$E$41/Assumptions_Sources!$G$41*(2035-Assumptions_Sources!$C$41+Assumptions_Sources!$I$41)),Assumptions_Sources!$D$41*Assumptions_Sources!$E$41*(1+Assumptions_Sources!$H$41)^(2035-(Assumptions_Sources!$C$41+Assumptions_Sources!$G$41))))) -> 20 | W46: =IF(2036<Assumptions_Sources!$C$41,0,IF(2036=Assumptions_Sources!$C$41,Assumptions_Sources!$D$41*Assumptions_Sources!$E$41/Assumptions_Sources!$G$41*Assumptions_Sources!$I$41,IF(2036<Assumptions_Sources!$C$41+Assumptions_Sources!$G$41,MIN(Assumptions_Sources!$D$41*Assumptions_Sources!$E$41,Assumptions_Sources!$D$41*Assumptions_Sources!$E$41/Assumptions_Sources!$G$41*(2036-Assumptions_Sources!$C$41+Assumptions_Sources!$I$41)),Assumptions_Sources!$D$41*Assumptions_Sources!$E$41*(1+Assumptions_Sources!$H$41)^(2036-(Assumptions_Sources!$C$41+Assumptions_Sources!$G$41))))) -> 60 | X46: =IF(E46>0,(R46/E46)^(1/5)-1,0) -> 0 | Y46: =IF(E46>0,(W46/E46)^(1/10)-1,0) -> 0
A47: Camlipixant - RCC | B47: 0 | C47: 0 | D47: 0 | E47: 0 | F47: 0 | G47: =IF(Assumptions_Sources!$C$42=2027,J47*Assumptions_Sources!$H$42,(J47-F47)*Assumptions_Sources!$C$45/SUM(Assumptions_Sources!$C$45:$E$45)) -> 0 | H47: =IF(Assumptions_Sources!$C$42=2027,J47*Assumptions_Sources!$I$42,(J47-F47)*Assumptions_Sources!$D$45/SUM(Assumptions_Sources!$C$45:$E$45)) -> 0 | I47: =J47-F47-G47-H47 -> 0 | J47: =IF(2027<Assumptions_Sources!$C$42,0,IF(2027=Assumptions_Sources!$C$42,Assumptions_Sources!$D$42*Assumptions_Sources!$E$42/Assumptions_Sources!$G$42*Assumptions_Sources!$I$42,IF(2027<Assumptions_Sources!$C$42+Assumptions_Sources!$G$42,MIN(Assumptions_Sources!$D$42*Assumptions_Sources!$E$42,Assumptions_Sources!$D$42*Assumptions_Sources!$E$42/Assumptions_Sources!$G$42*(2027-Assumptions_Sources!$C$42+Assumptions_Sources!$I$42)),Assumptions_Sources!$D$42*Assumptions_Sources!$E$42*(1+Assumptions_Sources!$H$42)^(2027-(Assumptions_Sources!$C$42+Assumptions_Sources!$G$42))))) -> 0 | K47: =O47*Assumptions_Sources!$B$45 -> 0 | L47: =O47*Assumptions_Sources!$C$45 -> 0 | M47: =O47*Assumptions_Sources!$D$45 -> 0 | N47: =O47-K47-L47-M47 -> 0 | O47: =IF(2028<Assumptions_Sources!$C$42,0,IF(2028=Assumptions_Sources!$C$42,Assumptions_Sources!$D$42*Assumptions_Sources!$E$42/Assumptions_Sources!$G$42*Assumptions_Sources!$I$42,IF(2028<Assumptions_Sources!$C$42+Assumptions_Sources!$G$42,MIN(Assumptions_Sources!$D$42*Assumptions_Sources!$E$42,Assumptions_Sources!$D$42*Assumptions_Sources!$E$42/Assumptions_Sources!$G$42*(2028-Assumptions_Sources!$C$42+Assumptions_Sources!$I$42)),Assumptions_Sources!$D$42*Assumptions_Sources!$E$42*(1+Assumptions_Sources!$H$42)^(2028-(Assumptions_Sources!$C$42+Assumptions_Sources!$G$42))))) -> 0 | P47: =IF(2029<Assumptions_Sources!$C$42,0,IF(2029=Assumptions_Sources!$C$42,Assumptions_Sources!$D$42*Assumptions_Sources!$E$42/Assumptions_Sources!$G$42*Assumptions_Sources!$I$42,IF(2029<Assumptions_Sources!$C$42+Assumptions_Sources!$G$42,MIN(Assumptions_Sources!$D$42*Assumptions_Sources!$E$42,Assumptions_Sources!$D$42*Assumptions_Sources!$E$42/Assumptions_Sources!$G$42*(2029-Assumptions_Sources!$C$42+Assumptions_Sources!$I$42)),Assumptions_Sources!$D$42*Assumptions_Sources!$E$42*(1+Assumptions_Sources!$H$42)^(2029-(Assumptions_Sources!$C$42+Assumptions_Sources!$G$42))))) -> 0 | Q47: =IF(2030<Assumptions_Sources!$C$42,0,IF(2030=Assumptions_Sources!$C$42,Assumptions_Sources!$D$42*Assumptions_Sources!$E$42/Assumptions_Sources!$G$42*Assumptions_Sources!$I$42,IF(2030<Assumptions_Sources!$C$42+Assumptions_Sources!$G$42,MIN(Assumptions_Sources!$D$42*Assumptions_Sources!$E$42,Assumptions_Sources!$D$42*Assumptions_Sources!$E$42/Assumptions_Sources!$G$42*(2030-Assumptions_Sources!$C$42+Assumptions_Sources!$I$42)),Assumptions_Sources!$D$42*Assumptions_Sources!$E$42*(1+Assumptions_Sources!$H$42)^(2030-(Assumptions_Sources!$C$42+Assumptions_Sources!$G$42))))) -> 0 | R47: =IF(2031<Assumptions_Sources!$C$42,0,IF(2031=Assumptions_Sources!$C$42,Assumptions_Sources!$D$42*Assumptions_Sources!$E$42/Assumptions_Sources!$G$42*Assumptions_Sources!$I$42,IF(2031<Assumptions_Sources!$C$42+Assumptions_Sources!$G$42,MIN(Assumptions_Sources!$D$42*Assumptions_Sources!$E$42,Assumptions_Sources!$D$42*Assumptions_Sources!$E$42/Assumptions_Sources!$G$42*(2031-Assumptions_Sources!$C$42+Assumptions_Sources!$I$42)),Assumptions_Sources!$D$42*Assumptions_Sources!$E$42*(1+Assumptions_Sources!$H$42)^(2031-(Assumptions_Sources!$C$42+Assumptions_Sources!$G$42))))) -> 0 | S47: =IF(2032<Assumptions_Sources!$C$42,0,IF(2032=Assumptions_Sources!$C$42,Assumptions_Sources!$D$42*Assumptions_Sources!$E$42/Assumptions_Sources!$G$42*Assumptions_Sources!$I$42,IF(2032<Assumptions_Sources!$C$42+Assumptions_Sources!$G$42,MIN(Assumptions_Sources!$D$42*Assumptions_Sources!$E$42,Assumptions_Sources!$D$42*Assumptions_Sources!$E$42/Assumptions_Sources!$G$42*(2032-Assumptions_Sources!$C$42+Assumptions_Sources!$I$42)),Assumptions_Sources!$D$42*Assumptions_Sources!$E$42*(1+Assumptions_Sources!$H$42)^(2032-(Assumptions_Sources!$C$42+Assumptions_Sources!$G$42))))) -> 0 | T47: =IF(2033<Assumptions_Sources!$C$42,0,IF(2033=Assumptions_Sources!$C$42,Assumptions_Sources!$D$42*Assumptions_Sources!$E$42/Assumptions_Sources!$G$42*Assumptions_Sources!$I$42,IF(2033<Assumptions_Sources!$C$42+Assumptions_Sources!$G$42,MIN(Assumptions_Sources!$D$42*Assumptions_Sources!$E$42,Assumptions_Sources!$D$42*Assumptions_Sources!$E$42/Assumptions_Sources!$G$42*(2033-Assumptions_Sources!$C$42+Assumptions_Sources!$I$42)),Assumptions_Sources!$D$42*Assumptions_Sources!$E$42*(1+Assumptions_Sources!$H$42)^(2033-(Assumptions_Sources!$C$42+Assumptions_Sources!$G$42))))) -> 0 | U47: =IF(2034<Assumptions_Sources!$C$42,0,IF(2034=Assumptions_Sources!$C$42,Assumptions_Sources!$D$42*Assumptions_Sources!$E$42/Assumptions_Sources!$G$42*Assumptions_Sources!$I$42,IF(2034<Assumptions_Sources!$C$42+Assumptions_Sources!$G$42,MIN(Assumptions_Sources!$D$42*Assumptions_Sources!$E$42,Assumptions_Sources!$D$42*Assumptions_Sources!$E$42/Assumptions_Sources!$G$42*(2034-Assumptions_Sources!$C$42+Assumptions_Sources!$I$42)),Assumptions_Sources!$D$42*Assumptions_Sources!$E$42*(1+Assumptions_Sources!$H$42)^(2034-(Assumptions_Sources!$C$42+Assumptions_Sources!$G$42))))) -> 0 | V47: =IF(2035<Assumptions_Sources!$C$42,0,IF(2035=Assumptions_Sources!$C$42,Assumptions_Sources!$D$42*Assumptions_Sources!$E$42/Assumptions_Sources!$G$42*Assumptions_Sources!$I$42,IF(2035<Assumptions_Sources!$C$42+Assumptions_Sources!$G$42,MIN(Assumptions_Sources!$D$42*Assumptions_Sources!$E$42,Assumptions_Sources!$D$42*Assumptions_Sources!$E$42/Assumptions_Sources!$G$42*(2035-Assumptions_Sources!$C$42+Assumptions_Sources!$I$42)),Assumptions_Sources!$D$42*Assumptions_Sources!$E$42*(1+Assumptions_Sources!$H$42)^(2035-(Assumptions_Sources!$C$42+Assumptions_Sources!$G$42))))) -> 0 | W47: =IF(2036<Assumptions_Sources!$C$42,0,IF(2036=Assumptions_Sources!$C$42,Assumptions_Sources!$D$42*Assumptions_Sources!$E$42/Assumptions_Sources!$G$42*Assumptions_Sources!$I$42,IF(2036<Assumptions_Sources!$C$42+Assumptions_Sources!$G$42,MIN(Assumptions_Sources!$D$42*Assumptions_Sources!$E$42,Assumptions_Sources!$D$42*Assumptions_Sources!$E$42/Assumptions_Sources!$G$42*(2036-Assumptions_Sources!$C$42+Assumptions_Sources!$I$42)),Assumptions_Sources!$D$42*Assumptions_Sources!$E$42*(1+Assumptions_Sources!$H$42)^(2036-(Assumptions_Sources!$C$42+Assumptions_Sources!$G$42))))) -> 0 | X47: =IF(E47>0,(R47/E47)^(1/5)-1,0) -> 0 | Y47: =IF(E47>0,(W47/E47)^(1/10)-1,0) -> 0
A48: Future Pipeline | B48: =SUM(B42:B47) -> 0 | C48: =SUM(C42:C47) -> 0 | D48: =SUM(D42:D47) -> 0 | E48: =SUM(E42:E47) -> 0 | F48: =SUM(F42:F47) -> 0 | G48: =SUM(G42:G47) -> 0 | H48: =SUM(H42:H47) -> 0 | I48: =SUM(I42:I47) -> 0 | ... W48: =SUM(W42:W47) -> 2034.3333
A50: CONSOLIDATION | B50: =SUM(B14,B22,B28,B34,B44,B48) -> 32217.2 | C50: =SUM(C14,C22,C28,C34,C44,C48) -> 34237.1 | D50: =SUM(D14,D22,D28,D34,D44,D48) -> 37230 | E50: =SUM(E14,E22,E28,E34,E44,E48) -> 37901.7 | F50: =SUM(F14,F22,F28,F34,F44,F48) -> 9240 | G50: =SUM(G14,G22,G28,G34,G44,G48) | H50: =SUM(H14,H22,H28,H34,H44,H48) | I50: =SUM(I14,I22,I28,I34,I44,I48) | P50: =SUM(P14,P22,P28,P34,P44,P48) -> 48492.287 | Q50: =SUM(Q14,Q22,Q28,Q34,Q44,Q48) -> 52030.984 | R50: =SUM(R14,R22,R28,R34,R44,R48) -> 55969.913 | S50: =SUM(S14,S22,S28,S34,S44,S48) -> 59606.968 | T50: =SUM(T14,T22,T28,T34,T44,T48) -> 63277.954 | U50: =SUM(U14,U22,U28,U34,U44,U48) -> 67052.541 | V50: =SUM(V14,V22,V28,V34,V44,V48) -> 70910.615 | W50: =SUM(W14,W22,W28,W34,W44,W48) -> 74862.232
A51: Biddle / consolidation revenue | B51: 300 | C51: 300 | D51: 262.1 | E51: 315 | F51: 144.4 | G51: =(J51-F51)*Assumptions_Sources!$C$45/SUM(Assumptions_Sources!$C$45:$E$45) -> 135.71603 | H51: =(J51-F51)*Assumptions_Sources!$D$45/SUM(Assumptions_Sources!$C$45:$E$45) -> 135.71603 | I51: =J51-F51-G51-H51 -> 134.16794 | J51: 550 | K51: 123.585 | L51: 151.8825 | M51: 151.8825 | N51: 150.15 | O51: 577.5 | P51: 606.375 | Q51: 630.63 | R51: 655.8552 | S51: 675.53086 | T51: 695.79678 | U51: 716.67069 | V51: 738.17081 | W51: 760.31593 | X51: =IF(E51>0,(R51/E51)^(1/5)-1,0) -> 0.1579758 | Y51: =IF(E51>0,(W51/E51)^(1/10)-1,0) -> 0.092114953
A52: Consolidation revenue | B52: =SUM(B51:B51) -> 300 | C52: =SUM(C51:C51) -> 300 | D52: =SUM(D51:D51) -> 262.1 | E52: =SUM(E51:E51) -> 315 | F52: =SUM(F51:F51) -> 144.4 | G52: =SUM(G51:G51) -> 135.71603 | H52: =SUM(H51:H51) -> 135.71603 | I52: =SUM(I51:I51) -> 134.16794 | ... W52: =SUM(W51:W51) -> 760.31593
B53: =IF(B50=0,0,B52/B50) -> 0.0093117962 | C53: =IF(C50=0,0,C52/C50) -> 0.0087624244 | D53: =IF(D50=0,0,D52/D50) -> 0.0070400215 | E53: =IF(E50=0,0,E52/E50) -> 0.0083109729 | F53: =IF(F50=0,0,F52/F50) -> 0.015627706 | G53: =IF(G50=0,0,G52/G50) | H53: =IF(H50=0,0,H52/H50) | I53: =IF(I50=0,0,I52/I50) | ... W53: =IF(W50=0,0,W52/W50) -> 0.010156202
A54: Consolidated revenue | B54: =B14+B22+B28+B35+B39+B48+B52 -> 32517.2 | C54: =C14+C22+C28+C35+C39+C48+C52 -> 34537.1 | D54: =D14+D22+D28+D35+D39+D48+D52 -> 37492.1 | E54: =E14+E22+E28+E35+E39+E48+E52 -> 38330.7 | F54: =F14+F22+F28+F35+F39+F48+F52 -> 9634.4 | G54: =G14+G22+G28+G35+G39+G48+G52 -> 11157.536 | H54: =H14+H22+H28+H35+H39+H48+H52 -> 11307.536 | I54: =I14+I22+I28+I35+I39+I48+I52 -> 11505.263 | ... W54: =W14+W22+W28+W35+W39+W48+W52 -> 83397.532 | X54: =(R54/E54)^(1/5)-1 -> 0.10247279 | Y54: =(W54/E54)^(1/10)-1 -> 0.080838099
A55: YoY growth | C55: =C54/B54-1 -> 0.062117895 | D55: =D54/C54-1 -> 0.085560166 | E55: =E54/D54-1 -> 0.022367379 | F55: =$J$64/$F$64-1 -> 0.16551784 | G55: =G54/$G$64-1 -> 0.13859377 | H55: =H54/$H$64-1 -> 0.085947387 | I55: =I54/$I$64-1 -> 0.15595936 | J55: =J54/E54-1 -> 0.13444476 | K55: =K54/F54-1 -> 0.098192677 | L55: =L54/G54-1 -> 0.13516435 | M55: =M54/H54-1 -> 0.12010583 | N55: =N54/I54-1 -> 0.088298573 | O55: =O54/J54-1 -> 0.11079712 | P55: =P54/O54-1 -> 0.098211082 | Q55: =Q54/P54-1 -> 0.087006236 | R55: =R54/Q54-1 -> 0.085917941 | S55: =S54/R54-1 -> 0.071198486 | T55: =T54/S54-1 -> 0.064645373 | U55: =U54/T54-1 -> 0.057050541 | V55: =V54/U54-1 -> 0.053333537 | W55: =W54/V54-1 -> 0.052035677
A56: Post-FY26 launches + future pipeline | B56: =B21+B33+B34+B38+B48 -> 0 | C56: =C21+C33+C34+C38+C48 -> 0 | D56: =D21+D33+D34+D38+D48 -> 0 | E56: =E21+E33+E34+E38+E48 -> 114 | F56: =F21+F33+F34+F38+F48 -> 250 | G56: =G21+G33+G34+G38+G48 -> 0 | H56: =H21+H33+H34+H38+H48 -> 150 | I56: =I21+I33+I34+I38+I48 -> 475 | ... W56: =W21+W33+W34+W38+W48 -> 12131.717
A57: Innovation + launches as % of revenue | B57: =IF(B54=0,0,(B19+B25+B26+B35+B21+B39+B48)/B54) -> 0.010763534 | C57: =IF(C54=0,0,(C19+C25+C26+C35+C21+C39+C48)/C54) -> 0.028954371 | D57: =IF(D54=0,0,(D19+D25+D26+D35+D21+D39+D48)/D54) -> 0.037607923 | E57: =IF(E54=0,0,(E19+E25+E26+E35+E21+E39+E48)/E54) -> 0.05734307 | F57: =IF(F54=0,0,(F19+F25+F26+F35+F21+F39+F48)/F54) -> 0.09206593 | G57: =IF(G54=0,0,(G19+G25+G26+G35+G21+G39+G48)/G54) -> 0.096028425 | H57: =IF(H54=0,0,(H19+H25+H26+H35+H21+H39+H48)/H54) -> 0.10802005 | I57: =IF(I54=0,0,(I19+I25+I26+I35+I21+I39+I48)/I54) -> 0.1333493 | ... W57: =IF(W54=0,0,(W19+W25+W26+W35+W21+W39+W48)/W54) -> 0.2801091
A59: Reported consolidated revenue | B59: 32517.2 | C59: 34537.1 | D59: 37492.1 | E59: 38216.7
A60: Historical reconciliation difference | B60: =B54-B59 -> 0 | C60: =C54-C59 -> 0 | D60: =D54-D59 -> 0 | E60: =E54-E59 -> 114
A62: RECENT QUARTERLY CONSOLIDATED REVENUE
A63: INR mn | B63: Q1 FY25 | C63: Q2 FY25 | D63: Q3 FY25 | E63: Q4 FY25 | F63: Q1 FY26 | G63: Q2 FY26 | H63: Q3 FY26 | I63: Q4 FY26 | J63: Q1 FY27
A64: Revenue | B64: 8146.5 | C64: 10107.7 | D64: 9494.2 | E64: 9743.7 | F64: 8051.7 | G64: 9799.4 | H64: 10412.6 | I64: 9953 | J64: 9384.4
A66: FY25 quarters difference | B66: =ROUND(SUM(B64:E64)-D54,1) -> 0 | C66: FY26 quarters difference | D66: =ROUND(SUM(F64:I64)-E54,1) -> -114 | E66: FY27 Q1 link difference | F66: =ROUND(J64-F54,1) -> -250

Sheet Assumptions_Sources
A1: GSK India - Single-Case Assumptions, Historical Calibration & Pipeline
A2: As of 14 September 2026. Blue cells are editable analyst assumptions. No bull/base/bear cases are used.
A4: EXISTING PORTFOLIO GROWTH ASSUMPTIONS
A5: Revenue line | B5: FY27E | C5: FY28E | D5: FY29E | E5: FY30-31E | F5: FY32-36E | G5: FY26A basis | H5: Key driver / rationale
A6: Augmentin | B6: 0.08 | C6: 0.07 | D6: 0.06 | E6: 0.055 | F6: 0.045 | G6: Estimated at ₹900cr in FY26 | H6: ₹75-80cr monthly secondary sales reference; price controls and mature volumes cap long-term growth
A7: Ceftum | B7: 0.06 | C7: 0.06 | D7: 0.05 | E7: 0.045 | F7: 0.035 | G7: Estimated within General Medicines | H7: 32.7% represented-market share in Q1 FY27; mature anti-infective
A8: Calpol | B8: 0.05 | C8: 0.07 | D8: 0.06 | E8: 0.05 | F8: 0.04 | G8: Estimated at ₹310cr in FY26 | H8: Q1 FY27 market growth 8.1%; FY27 allows for supply normalisation
A9: Eltroxin | B9: 0.05 | C9: 0.055 | D9: 0.05 | E9: 0.045 | F9: 0.04 | G9: Estimated within General Medicines | H9: Chronic replacement therapy with recurring demand
A10: Dermatology franchise | B10: 0.08 | C10: 0.07 | D10: 0.06 | E10: 0.055 | F10: 0.045 | G10: Includes T-Bact, Betnovate, Tenovate, Neosporin | H10: T-Bact 57.5% represented-market share; category growth and pricing
A11: Vitamins & other general medicines | B11: 0.05 | C11: 0.05 | D11: 0.045 | E11: 0.04 | F11: 0.035 | G11: Residual within reported pharmaceuticals total | H11: Large mature tail; growth below promoted brands
A12: Core paediatric vaccines | B12: 0.1 | C12: 0.09 | D12: 0.08 | E12: 0.07 | F12: 0.055 | G12: Estimated within reported vaccine mix | H12: Private-market leadership; volume-led growth and supply phasing
A13: Seasonal & travel vaccines | B13: 0.08 | C13: 0.08 | D13: 0.07 | E13: 0.06 | F13: 0.05 | G13: Estimated within reported vaccine mix | H13: Influenza/travel seasonality and private immunisation
A14: Shingrix | B14: 0.45 | C14: 0.32 | D14: 0.24 | E14: 0.17 | F14: 0.1 | G14: FY26 estimated at ₹110cr; crossed ₹100cr MAT by Q1 FY27 | H14: Q1 FY27 growth 65%; adult-vaccination category creation fades over time
A15: Other adult vaccines | B15: 0.1 | C15: 0.1 | D15: 0.08 | E15: 0.07 | F15: 0.05 | G15: Residual within reported vaccine mix | H15: Low base; adult immunisation adoption
A16: Trelegy Ellipta | B16: 0.18 | C16: 0.15 | D16: 0.12 | E16: 0.1 | F16: 0.07 | G16: FY26 estimated at ₹62cr | H16: 12% FUV share applied to disclosed ₹513cr SITT market; share and market growth
A17: Nucala | B17: 0.25 | C17: 0.2 | D17: 0.18 | E17: 0.14 | F17: 0.1 | G17: FY26 estimated at ₹25cr | H17: 100-120 new patients per month; severe-asthma diagnosis and affordability
A18: Other respiratory | B18: 0.06 | C18: 0.06 | D18: 0.05 | E18: 0.04 | F18: 0.03 | G18: Residual respiratory portfolio | H18: Mature Seretide/other inhaled portfolio
A20: MARKETED ONCOLOGY AND CONSOLIDATION
A21: Revenue line | B21: FY27E revenue | C21: FY28E growth | D21: FY29E growth | E21: FY30-31E | F21: FY32-36E | G21: Basis | H21: Rationale
A22: Jemperli | B22: 800 | C22: 0.25 | D22: 0.2 | E22: 0.15 | F22: 0.08 | G22: Q1 FY27 oncology run-rate and patient uptake | H22: First-line endometrial cancer; expansion not separately double-counted
A23: Zejula | B23: 400 | C23: 0.15 | D23: 0.1 | E23: 0.05 | F23: 0.02 | G23: Q1 FY27 oncology run-rate and patient uptake | H23: Ovarian maintenance; PARP competition limits long-term growth
A25: Biddle / consolidation revenue | B25: 550 | C25: 0.05 | D25: 0.05 | E25: 0.04 | F25: 0.03 | G25: FY27E annualised from Q1 consolidated less standalone revenue | H25: Keeps subsidiary/consolidation bridge separate from product sales
A28: APPROVED / MANAGEMENT-IDENTIFIED LAUNCHES
A29: Asset | B29: Therapy | C29: Launch FY | D29: Peak India revenue (INR mn) | E29: Ramp years | F29: Post-ramp growth | G29: Launch-year fraction | H29: Q2 share | I29: Q3 share | J29: Basis / status
A30: Arexvy | B30: Adult vaccines | C30: 2027 | D30: 2500 | E30: 6 | F30: 0.03 | G30: 0.5 | H30: 0 | I30: 0.4 | J30: Marketing authorisation received; management indicated launch in coming months
A31: Blenrep | B31: Oncology | C31: 2027 | D31: 2000 | E31: 6 | F31: 0.02 | G31: 0.5 | H31: 0 | I31: 0.4 | J31: CDSCO approved; management guided Q2/Q3 FY27 launch; 7-8k second-line patients
A32: Hibsago / Bepirovirsen | B32: Infectious disease | C32: 2027 | D32: 3500 | E32: 7 | F32: 0.03 | G32: 0.5 | H32: 0 | I32: 0 | J32: Positive Phase III; India launch targeted within three quarters, subject to approvals
A33: Ojjaara | B33: Oncology | C33: 2029 | D33: 1500 | E33: 6 | F33: 0.02 | G33: 0.5 | H33: 0 | I33: 0 | J33: Management-identified upcoming launch over the next 18-24 months
A35: FUTURE PIPELINE - RISK-ADJUSTED REVENUE
A36: Asset | B36: Therapy | C36: Launch FY | D36: Unrisked peak (INR mn) | E36: PoS incl. India rights | F36: Risk-adjusted peak | G36: Ramp years | H36: Post-ramp growth | I36: Launch-year fraction | J36: Rationale
A37: Velzatinib | B37: GIST | C37: 2032 | D37: 800 | E37: 0.55 | F37: =D37*E37 -> 440 | G37: 5 | H37: 0.02 | I37: 0.5 | J37: Phase III; India trial permission supports local development
A38: Mocertatug rezetecan | B38: Ovarian/endometrial cancer | C38: 2033 | D38: 1500 | E38: 0.4 | F38: =D38*E38 -> 600 | G38: 5 | H38: 0.03 | I38: 0.5 | J38: Pivotal program initiated; no India approval
A39: Efimosfermin | B39: MASH / liver disease | C39: 2031 | D39: 2200 | E39: 0.5 | F39: =D39*E39 -> 1100 | G39: 6 | H39: 0.03 | I39: 0.5 | J39: Phase III; potential global launch from 2029, India lag assumed
A40: TSLP (GSK5784283) | B40: Uncontrolled asthma | C40: 2034 | D40: 1000 | E40: 0.3 | F40: =D40*E40 -> 300 | G40: 5 | H40: 0.03 | I40: 0.5 | J40: Phase II; substantial clinical and timing risk
A41: Gatuzosiran / GSK4532990 | B41: Liver disease | C41: 2035 | D41: 1000 | E41: 0.2 | F41: =D41*E41 -> 200 | G41: 5 | H41: 0.03 | I41: 0.5 | J41: Phase II; indication strategy evolving
A42: Camlipixant | B42: Refractory chronic cough | C42: 9999 | D42: 0 | E42: 0 | F42: =D42*E42 -> 0 | G42: 5 | H42: 0 | I42: 0.5 | J42: Development discontinued after Phase III miss; zero revenue
A44: QUARTERLY PHASING
A45: Mature portfolio seasonality (Q1 / Q2 / Q3 / Q4) | B45: 0.214 | C45: 0.263 | D45: 0.263 | E45: 0.26 | F45: Average FY25/FY26 quarterly mix; FY27 Q1 product allocations are estimates constrained to reported totals
A47: FY26 HISTORICAL PRODUCT CALIBRATION
A48: Revenue line | B48: FY26A estimate (INR mn) | C48: Status | D48: Calibration evidence | E48: Reported control | F48: Comment
A49: Augmentin | B49: 9000 | C49: Estimated | D49: Public secondary-sales commentary of ₹75-80cr per month | E49: Reported company total | F49: Secondary sales and company revenue are not identical; estimate normalised
A50: Ceftum | B50: 2300 | C50: Estimated | D50: Q1 FY27 represented-market value share 32.7% | E50: General Medicines total | F50: No audited brand sales disclosed
A51: Calpol | B51: 3100 | C51: Estimated | D51: Public monthly market-sales reference and Q1 FY27 market growth | E51: General Medicines total | F51: No audited brand sales disclosed
A52: Eltroxin | B52: 1700 | C52: Estimated | D52: Chronic brand within promoted portfolio | E52: General Medicines total | F52: No audited brand sales disclosed
A53: Dermatology franchise | B53: 4500 | C53: Estimated | D53: T-Bact 57.5% represented-market value share plus other dermatology brands | E53: General Medicines total | F53: Includes T-Bact, Betnovate, Tenovate, Neosporin and related brands
A54: Vitamins & other general medicines | B54: 8072.7 | C54: Residual estimate | D54: Balances the reported pharmaceutical mix after named products | E54: General Medicines total | F54: Transparent residual, not described as reported brand sales
A55: Core paediatric vaccines | B55: 5200 | C55: Estimated | D55: Private paediatric leadership and portfolio growth disclosures | E55: FY26 vaccines ₹731.5cr | F55: No audited antigen sales disclosed
A56: Seasonal & travel vaccines | B56: 800 | C56: Estimated | D56: Fluarix / Havrix / Menveo portfolio | E56: FY26 vaccines ₹731.5cr | F56: No audited antigen sales disclosed
A57: Shingrix | B57: 1100 | C57: Estimated | D57: Management confirmed >₹100cr MAT by Q1 FY27 | E57: FY26 vaccines ₹731.5cr | F57: Conservative estimate within management floor
A58: Other adult vaccines | B58: 215 | C58: Residual estimate | D58: Balances reported vaccine mix | E58: FY26 vaccines ₹731.5cr | F58: No audited brand sales disclosed
A59: Trelegy Ellipta | B59: 620 | C59: Market-based estimate | D59: 12% FUV share × disclosed ₹513cr SITT market | E59: FY26 pharmaceuticals | F59: Replaces prior ₹170cr overstatement
A60: Nucala | B60: 250 | C60: Patient-based estimate | D60: 100-120 monthly patient additions and 3.5k+ cumulative patients | E60: FY26 pharmaceuticals | F60: Treatment persistence and net pricing remain estimated
... A64: Biddle / consolidation revenue | B64: 315 | C64: Calculated bridge | D64: Consolidated revenue less standalone revenue | E64: FY26 consolidated ₹3,821.7cr | F64: Not other operating revenue and not a balancing product
A67: CLINICAL PIPELINE / CTRI CROSS-CHECK
A68: Asset | B68: Brand / code | C68: Therapy | D68: India indication | E68: Stage / status | F68: India evidence | G68: Expected model launch | H68: Revenue treatment | I68: Key issue | J68: Primary source
A69: Belantamab mafodotin | B69: Blenrep | C69: Oncology | D69: Multiple myeloma | E69: Approved in India | F69: CDSCO approval; company launch preparation | G69: 2027 | H69: Approved launch build | I69: Ocular monitoring and affordability | J69: GSK India Q1 FY27 transcript
A70: Dostarlimab | B70: Jemperli | C70: Oncology | D70: Endometrial cancer | E70: Marketed; expansion trials | F70: India launch and trial permissions | G70: 2026 | H70: Marketed product | I70: Biomarker testing and access | J70: GSK India
A71: Niraparib | B71: Zejula | C71: Oncology | D71: Ovarian maintenance | E71: Marketed | F71: India launch / post-marketing evidence | G71: 2026 | H71: Marketed product | I71: PARP competition | J71: GSK India
A72: Momelotinib | B72: Ojjaara | C72: Oncology | D72: Myelofibrosis | E72: Management-identified launch | F72: Upcoming India launch program | G72: 2029 | H72: Approved/late-stage launch build | I72: India timing and pricing | J72: GSK India Q1 FY27 transcript
A73: Bepirovirsen | B73: Hibsago / GSK3228836 | C73: Infectious disease | D73: Chronic hepatitis B | E73: Phase III positive; filings | F73: Four India trials and company launch roadmap | G73: 2027 | H73: Late-stage launch build | I73: Approval and functional-cure uptake | J73: GSK / CDSCO
A74: Velzatinib | B74: IDRX-42 | C74: Oncology | D74: GIST | E74: Phase III | F74: CDSCO India trial recommendation | G74: 2032 | H74: Risk-adjusted | I74: Clinical success and India rights | J74: CDSCO / GSK
A75: Mocertatug rezetecan | B75: B7-H4 ADC | C75: Oncology | D75: Ovarian/endometrial cancer | E75: Pivotal program | F75: India relevance in disclosed oncology trial bucket | G75: 2033 | H75: Risk-adjusted | I75: Early efficacy must confirm | J75: GSK
A76: Efimosfermin | B76: GSK6519754 | C76: Liver disease | D76: MASH | E76: Phase III | F76: India-relevant global development | G76: 2031 | H76: Risk-adjusted | I76: Large market but affordability | J76: GSK
A77: GSK5784283 | B77: Anti-TSLP | C77: Respiratory | D77: Uncontrolled asthma | E77: Phase II | F77: Global trial / India pipeline disclosure | G77: 2034 | H77: Risk-adjusted | I77: Early stage and competition | J77: GSK / ClinicalTrials.gov
A78: Gatuzosiran | B78: GSK4532990 | C78: Liver disease | D78: MASH / ALD | E78: Phase II | F78: India NASH trial permission | G78: 2035 | H78: Risk-adjusted | I78: Indication strategy evolving | J78: GSK / CDSCO
A80: KEY SOURCES
A81: Data item | B81: Value / conclusion | C81: Source | D81: URL | E81: Class
A82: FY23-FY26 consolidated revenue | B82: Reported annual totals | C82: GSK India annual reports | D82: https://india-pharma.gsk.com/en-in/investors/annual-reports/ | E82: Reported
A83: Q1 FY27 consolidated revenue | B83: ₹938.44cr | C83: GSK India consolidated filing / public release | D83: https://india-pharma.gsk.com/en-in/investors/quarterly-results/ | E83: Reported
A84: Q1 FY27 standalone revenue and innovation mix | B84: ₹924cr; innovation 7% | C84: GSK India Q1 FY27 analyst presentation | D84: https://india-pharma.gsk.com/media/kdghfyzr/analyst-meet-q1-2026-27.pdf | E84: Reported
A85: Launch timing and product commentary | B85: Blenrep, Arexvy, Hibsago, Ojjaara | C85: GSK India Q1 FY27 analyst transcript | D85: https://india-pharma.gsk.com/media/asmha1vh/gsk-q1-fy27-analyst-meet-transcript.pdf | E85: Reported
A86: FY26 mix and 26-trial disclosure | B86: Pharma / vaccines / oncology; trial buckets | C86: GSK India FY26 annual report and May analyst meet | D86: https://india-pharma.gsk.com/media/inhdnswz/analyst-meet-may-2026.pdf | E86: Reported
A87: Augmentin market sales | B87: ₹75-80cr monthly public market-data reference | C87: Economic Times reporting citing market data | D87: https://m.economictimes.com/industry/healthcare/biotech/pharmaceuticals/gsks-antibiotic-drug-augmentin-is-indias-highest-selling-drug/articleshow/118333583.cms | E87: Market data / estimate basis
A88: CTRI access | B88: Registry requires search validation | C88: Clinical Trials Registry - India | D88: https://ctri.nic.in/Clinicaltrials/advancesearchmain.php | E88: Reported limitation
A89: Pipeline revenue | B89: Launch, peak and PoS assumptions | C89: Analyst estimates constrained by company pipeline disclosures | D89: N/A | E89: Estimated
A92: MODEL LIMITATIONS AND UPDATE ITEMS
A93: • Historical brand revenue remains estimated because GSK India does not disclose audited brand sales. Reported consolidated totals and disclosed business mix are the hard controls.
A94: • Q1 FY27 product values are estimates constrained to reported standalone revenue, 7% innovation mix and disclosed market/patient indicators; the consolidated total is reported.
A95: • Secondary-market sales do not equal company-recognised revenue. Replace estimates with IQVIA/PharmaTrac brand sales and channel adjustments when available.
A96: • Approved and management-identified launches are modeled separately from early pipeline. Early pipeline uses probability-adjusted India revenue and should be refreshed after pivotal data, filing, approval, pricing or rights changes.
A97: • The 26-company-disclosed figure is a trial count, not a molecule count. CTRI validation is cross-checked with GSK, CDSCO and global registries where direct record extraction is restricted.
