Workbook

Sheet Revenue_Model
A1: GSK India - Product-Level Revenue Model
A2: Underwriting case | B2: Single case | D2: FY26A Revenue | E2: =E54 -> 38330.7 | G2: FY27E Revenue | H2: =J54 -> 43354.735 | J2: FY28E Revenue | K2: =O54 -> 48158.315 | M2: FY31E Revenue | N2: =R54 -> 62428.967 | Q2: FY36E Revenue | R2: =W54 -> 83397.532 | U2: 10Y CAGR | V2: =Y54 -> 0.080838099
D3: FY27 Q1A consolidated | E3: =F54 -> 9384.4 | G3: FY31 new launches + pipeline | H3: =R56 -> 6341.6667 | J3: FY36 new launches + pipeline | K3: =W56 -> 12131.717 | M3: Model basis | N3: Consolidated GSK India; product history estimated within reported totals
A4: INR mn. Annual and quarterly consolidated totals are reported. Product-level history and Q1 FY27 allocations are analyst estimates calibrated to company disclosures and public market data. Forecasts use one underwriting case.
B5: 2023 | C5: 2024 | D5: 2025 | E5: 2026 | F5: 2027 | G5: 2027 | H5: 2027 | I5: 2027 | J5: 2027 | K5: 2028 | L5: 2028 | M5: 2028 | N5: 2028 | O5: 2028 | P5: 2029 | Q5: 2030 | R5: 2031 | S5: 2032 | T5: 2033 | U5: 2034 | V5: 2035 | W5: 2036
A6: Revenue line | B6: FY2023A | C6: FY2024A | D6: FY2025A | E6: FY2026A | F6: Q1 FY27A* | G6: Q2 FY27E | H6: Q3 FY27E | I6: Q4 FY27E | J6: FY2027E | K6: Q1 FY28E | L6: Q2 FY28E | M6: Q3 FY28E | N6: Q4 FY28E | O6: FY2028E | P6: FY2029E | Q6: FY2030E | R6: FY2031E | S6: FY2032E | T6: FY2033E | U6: FY2034E | V6: FY2035E | W6: FY2036E | X6: 5Y CAGR | Y6: 10Y CAGR
A7: GENERAL MEDICINES
A8: Augmentin | B8: 7200 | C8: 7800 | D8: 8500 | E8: 9000 | F8: 2200 | G8: =(J8-F8)*Assumptions_Sources!$C$45/SUM(Assumptions_Sources!$C$45:$E$45) -> 2516.2341 | H8: =(J8-F8)*Assumptions_Sources!$D$45/SUM(Assumptions_Sources!$C$45:$E$45) -> 2516.2341 | I8: =J8-F8-G8-H8 -> 2487.5318 | J8: 9720 | K8: =O8*Assumptions_Sources!$B$45 -> 2225.6856 | L8: =O8*Assumptions_Sources!$C$45 -> 2735.3052 | M8: =O8*Assumptions_Sources!$D$45 -> 2735.3052 | N8: =O8-K8-L8-M8 -> 2704.104 | O8: 10400.4 | P8: =O8*(1+Assumptions_Sources!$D$6) -> 11024.424 | Q8: =P8*(1+Assumptions_Sources!$E$6) -> 11630.767 | R8: =Q8*(1+Assumptions_Sources!$E$6) -> 12270.46 | S8: =R8*(1+Assumptions_Sources!$F$6) -> 12822.63 | T8: =S8*(1+Assumptions_Sources!$F$6) -> 13399.649 | U8: =T8*(1+Assumptions_Sources!$F$6) -> 14002.633 | V8: =U8*(1+Assumptions_Sources!$F$6) -> 14632.751 | W8: =V8*(1+Assumptions_Sources!$F$6) -> 15291.225 | X8: =IF(E8>0,(R8/E8)^(1/5)-1,0) -> 0.063955989 | Y8: =IF(E8>0,(W8/E8)^(1/10)-1,0) -> 0.054435398
A9: Ceftum | B9: 2150 | C9: 2200 | D9: 2250 | E9: 2300 | F9: 600 | G9: =(J9-F9)*Assumptions_Sources!$C$45/SUM(Assumptions_Sources!$C$45:$E$45) -> 615.00509 | H9: =(J9-F9)*Assumptions_Sources!$D$45/SUM(Assumptions_Sources!$C$45:$E$45) -> 615.00509 | I9: =J9-F9-G9-H9 -> 607.98982 | J9: 2438 | K9: =O9*Assumptions_Sources!$B$45 -> 553.03592 | L9: =O9*Assumptions_Sources!$C$45 -> 679.66564 | M9: =O9*Assumptions_Sources!$D$45 -> 679.66564 | N9: =O9-K9-L9-M9 -> 671.9128 | O9: 2584.28 | P9: =O9*(1+Assumptions_Sources!$D$7) -> 2713.494 | Q9: =P9*(1+Assumptions_Sources!$E$7) -> 2835.6012 | R9: =Q9*(1+Assumptions_Sources!$E$7) -> 2963.2033 | S9: =R9*(1+Assumptions_Sources!$F$7) -> 3066.9154 | T9: =S9*(1+Assumptions_Sources!$F$7) -> 3174.2574 | U9: =T9*(1+Assumptions_Sources!$F$7) -> 3285.3564 | V9: =U9*(1+Assumptions_Sources!$F$7) -> 3400.3439 | W9: =V9*(1+Assumptions_Sources!$F$7) -> 3519.356 | X9: =IF(E9>0,(R9/E9)^(1/5)-1,0) -> 0.051978156 | Y9: =IF(E9>0,(W9/E9)^(1/10)-1,0) -> 0.043454547
A10: Calpol | B10: 2800 | C10: 2900 | D10: 3000 | E10: 3100 | F10: 750 | G10: =(J10-F10)*Assumptions_Sources!$C$45/SUM(Assumptions_Sources!$C$45:$E$45) -> 838.18702 | H10: =(J10-F10)*Assumptions_Sources!$D$45/SUM(Assumptions_Sources!$C$45:$E$45) -> 838.18702 | I10: =J10-F10-G10-H10 -> 828.62595 | J10: 3255 | K10: =O10*Assumptions_Sources!$B$45 -> 745.3299 | L10: =O10*Assumptions_Sources!$C$45 -> 915.98955 | M10: =O10*Assumptions_Sources!$D$45 -> 915.98955 | N10: =O10-K10-L10-M10 -> 905.541 | O10: 3482.85 | P10: =O10*(1+Assumptions_Sources!$D$8) -> 3691.821 | Q10: =P10*(1+Assumptions_Sources!$E$8) -> 3876.412 | R10: =Q10*(1+Assumptions_Sources!$E$8) -> 4070.2327 | S10: =R10*(1+Assumptions_Sources!$F$8) -> 4233.042 | T10: =S10*(1+Assumptions_Sources!$F$8) -> 4402.3636 | U10: =T10*(1+Assumptions_Sources!$F$8) -> 4578.4582 | V10: =U10*(1+Assumptions_Sources!$F$8) -> 4761.5965 | W10: =V10*(1+Assumptions_Sources!$F$8) -> 4952.0604 | X10: =IF(E10>0,(R10/E10)^(1/5)-1,0) -> 0.055969825 | Y10: =IF(E10>0,(W10/E10)^(1/10)-1,0) -> 0.047954492
A11: Eltroxin | B11: 1550 | C11: 1600 | D11: 1650 | E11: 1700 | F11: 430 | G11: =(J11-F11)*Assumptions_Sources!$C$45/SUM(Assumptions_Sources!$C$45:$E$45) -> 453.39059 | H11: =(J11-F11)*Assumptions_Sources!$D$45/SUM(Assumptions_Sources!$C$45:$E$45) -> 453.39059 | I11: =J11-F11-G11-H11 -> 448.21883 | J11: 1785 | K11: =O11*Assumptions_Sources!$B$45 -> 402.99945 | L11: =O11*Assumptions_Sources!$C$45 -> 495.27503 | M11: =O11*Assumptions_Sources!$D$45 -> 495.27503 | N11: =O11-K11-L11-M11 -> 489.6255 | O11: 1883.175 | P11: =O11*(1+Assumptions_Sources!$D$9) -> 1977.3338 | Q11: =P11*(1+Assumptions_Sources!$E$9) -> 2066.3138 | R11: =Q11*(1+Assumptions_Sources!$E$9) -> 2159.2979 | S11: =R11*(1+Assumptions_Sources!$F$9) -> 2245.6698 | T11: =S11*(1+Assumptions_Sources!$F$9) -> 2335.4966 | U11: =T11*(1+Assumptions_Sources!$F$9) -> 2428.9165 | V11: =U11*(1+Assumptions_Sources!$F$9) -> 2526.0731 | W11: =V11*(1+Assumptions_Sources!$F$9) -> 2627.116 | X11: =IF(E11>0,(R11/E11)^(1/5)-1,0) -> 0.048993332 | Y11: =IF(E11>0,(W11/E11)^(1/10)-1,0) -> 0.044486987
A12: Dermatology franchise | B12: 3600 | C12: 3900 | D12: 4200 | E12: 4500 | F12: 1100 | G12: =(J12-F12)*Assumptions_Sources!$C$45/SUM(Assumptions_Sources!$C$45:$E$45) -> 1258.117 | H12: =(J12-F12)*Assumptions_Sources!$D$45/SUM(Assumptions_Sources!$C$45:$E$45) -> 1258.117 | I12: =J12-F12-G12-H12 -> 1243.7659 | J12: 4860 | K12: =O12*Assumptions_Sources!$B$45 -> 1112.8428 | L12: =O12*Assumptions_Sources!$C$45 -> 1367.6526 | M12: =O12*Assumptions_Sources!$D$45 -> 1367.6526 | N12: =O12-K12-L12-M12 -> 1352.052 | O12: 5200.2 | P12: =O12*(1+Assumptions_Sources!$D$10) -> 5512.212 | Q12: =P12*(1+Assumptions_Sources!$E$10) -> 5815.3837 | R12: =Q12*(1+Assumptions_Sources!$E$10) -> 6135.2298 | S12: =R12*(1+Assumptions_Sources!$F$10) -> 6411.3151 | T12: =S12*(1+Assumptions_Sources!$F$10) -> 6699.8243 | U12: =T12*(1+Assumptions_Sources!$F$10) -> 7001.3164 | V12: =U12*(1+Assumptions_Sources!$F$10) -> 7316.3756 | W12: =V12*(1+Assumptions_Sources!$F$10) -> 7645.6125 | X12: =IF(E12>0,(R12/E12)^(1/5)-1,0) -> 0.063955989 | Y12: =IF(E12>0,(W12/E12)^(1/10)-1,0) -> 0.054435398
A13: Vitamins & other general medicines | B13: 9017.2 | C13: 8787.1 | D13: 9430 | E13: 8072.7 | F13: 1553 | G13: =(J13-F13)*Assumptions_Sources!$C$45/SUM(Assumptions_Sources!$C$45:$E$45) -> 2316.5866 | H13: =(J13-F13)*Assumptions_Sources!$D$45/SUM(Assumptions_Sources!$C$45:$E$45) -> 2316.5866 | I13: =J13-F13-G13-H13 -> 2290.1617 | J13: 8476.335 | K13: =O13*Assumptions_Sources!$B$45 -> 1904.6325 | L13: =O13*Assumptions_Sources!$C$45 -> 2340.7399 | M13: =O13*Assumptions_Sources!$D$45 -> 2340.7399 | N13: =O13-K13-L13-M13 -> 2314.0395 | O13: 8900.1518 | P13: =O13*(1+Assumptions_Sources!$D$11) -> 9300.6586 | Q13: =P13*(1+Assumptions_Sources!$E$11) -> 9672.6849 | R13: =Q13*(1+Assumptions_Sources!$E$11) -> 10059.592 | S13: =R13*(1+Assumptions_Sources!$F$11) -> 10411.678 | T13: =S13*(1+Assumptions_Sources!$F$11) -> 10776.087 | U13: =T13*(1+Assumptions_Sources!$F$11) -> 11153.25 | V13: =U13*(1+Assumptions_Sources!$F$11) -> 11543.614 | W13: =V13*(1+Assumptions_Sources!$F$11) -> 11947.64 | X13: =IF(E13>0,(R13/E13)^(1/5)-1,0) -> 0.044990431 | Y13: =IF(E13>0,(W13/E13)^(1/10)-1,0) -> 0.039983219
A14: General Medicines | B14: =SUM(B8:B13) -> 26317.2 | C14: =SUM(C8:C13) -> 27187.1 | D14: =SUM(D8:D13) -> 29030 | E14: =SUM(E8:E13) -> 28672.7 | F14: =SUM(F8:F13) -> 6633 | G14: =SUM(G8:G13) -> 7997.5205 | H14: =SUM(H8:H13) -> 7997.5205 | I14: =SUM(I8:I13) -> 7906.294 | J14: 30534.335 | K14: =SUM(K8:K13) -> 6944.5261 | L14: =SUM(L8:L13) -> 8534.6279 | M14: =SUM(M8:M13) -> 8534.6279 | N14: =SUM(N8:N13) -> 8437.2748 | O14: 32451.057 | P14: =SUM(P8:P13) -> 34219.943 | Q14: =SUM(Q8:Q13) -> 35897.163 | R14: =SUM(R8:R13) -> 37658.015 | S14: =SUM(S8:S13) -> 39191.251 | T14: =SUM(T8:T13) -> 40787.677 | U14: =SUM(U8:U13) -> 42449.93 | V14: =SUM(V8:V13) -> 44180.754 | W14: =SUM(W8:W13) -> 45983.01 | X14: =IF(E14>0,(R14/E14)^(1/5)-1,0) -> 0.056033676 | Y14: =IF(E14>0,(W14/E14)^(1/10)-1,0) -> 0.048365886
A16: VACCINES
A17: Core paediatric vaccines | B17: 3900 | C17: 4300 | D17: 5000 | E17: 5200 | F17: 1500 | G17: =(J17-F17)*Assumptions_Sources!$C$45/SUM(Assumptions_Sources!$C$45:$E$45) -> 1412.0356 | H17: =(J17-F17)*Assumptions_Sources!$D$45/SUM(Assumptions_Sources!$C$45:$E$45) -> 1412.0356 | I17: =J17-F17-G17-H17 -> 1395.9288 | J17: 5720 | K17: =O17*Assumptions_Sources!$B$45 -> 1334.2472 | L17: =O17*Assumptions_Sources!$C$45 -> 1639.7524 | M17: =O17*Assumptions_Sources!$D$45 -> 1639.7524 | N17: =O17-K17-L17-M17 -> 1621.048 | O17: 6234.8 | P17: =O17*(1+Assumptions_Sources!$D$12) -> 6733.584 | Q17: =P17*(1+Assumptions_Sources!$E$12) -> 7204.9349 | R17: =Q17*(1+Assumptions_Sources!$E$12) -> 7709.2803 | S17: =R17*(1+Assumptions_Sources!$F$12) -> 8133.2907 | T17: =S17*(1+Assumptions_Sources!$F$12) -> 8580.6217 | U17: =T17*(1+Assumptions_Sources!$F$12) -> 9052.5559 | V17: =U17*(1+Assumptions_Sources!$F$12) -> 9550.4465 | W17: =V17*(1+Assumptions_Sources!$F$12) -> 10075.721 | X17: =IF(E17>0,(R17/E17)^(1/5)-1,0) -> 0.081937313 | Y17: =IF(E17>0,(W17/E17)^(1/10)-1,0) -> 0.068383763
A18: Seasonal & travel vaccines | B18: 700 | C18: 750 | D18: 800 | E18: 800 | F18: 300 | G18: =(J18-F18)*Assumptions_Sources!$C$45/SUM(Assumptions_Sources!$C$45:$E$45) -> 188.71756 | H18: =(J18-F18)*Assumptions_Sources!$D$45/SUM(Assumptions_Sources!$C$45:$E$45) -> 188.71756 | I18: =J18-F18-G18-H18 -> 186.56489 | J18: 864 | K18: =O18*Assumptions_Sources!$B$45 -> 199.68768 | L18: =O18*Assumptions_Sources!$C$45 -> 245.41056 | M18: =O18*Assumptions_Sources!$D$45 -> 245.41056 | N18: =O18-K18-L18-M18 -> 242.6112 | O18: 933.12 | P18: =O18*(1+Assumptions_Sources!$D$13) -> 998.4384 | Q18: =P18*(1+Assumptions_Sources!$E$13) -> 1058.3447 | R18: =Q18*(1+Assumptions_Sources!$E$13) -> 1121.8454 | S18: =R18*(1+Assumptions_Sources!$F$13) -> 1177.9377 | T18: =S18*(1+Assumptions_Sources!$F$13) -> 1236.8345 | U18: =T18*(1+Assumptions_Sources!$F$13) -> 1298.6763 | V18: =U18*(1+Assumptions_Sources!$F$13) -> 1363.6101 | W18: =V18*(1+Assumptions_Sources!$F$13) -> 1431.7906 | X18: =IF(E18>0,(R18/E18)^(1/5)-1,0) -> 0.069962616 | Y18: =IF(E18>0,(W18/E18)^(1/10)-1,0) -> 0.059934312
A19: Shingrix | B19: 0 | C19: 450 | D19: 650 | E19: 1100 | F19: 280 | G19: =(J19-F19)*Assumptions_Sources!$C$45/SUM(Assumptions_Sources!$C$45:$E$45) -> 440.00636 | H19: =(J19-F19)*Assumptions_Sources!$D$45/SUM(Assumptions_Sources!$C$45:$E$45) -> 440.00636 | I19: =J19-F19-G19-H19 -> 434.98728 | J19: 1595 | K19: =O19*Assumptions_Sources!$B$45 -> 450.5556 | L19: =O19*Assumptions_Sources!$C$45 -> 553.7202 | M19: =O19*Assumptions_Sources!$D$45 -> 553.7202 | N19: =O19-K19-L19-M19 -> 547.404 | O19: 2105.4 | P19: =O19*(1+Assumptions_Sources!$D$14) -> 2610.696 | Q19: =P19*(1+Assumptions_Sources!$E$14) -> 3054.5143 | R19: =Q19*(1+Assumptions_Sources!$E$14) -> 3573.7818 | S19: =R19*(1+Assumptions_Sources!$F$14) -> 3931.1599 | T19: =S19*(1+Assumptions_Sources!$F$14) -> 4324.2759 | U19: =T19*(1+Assumptions_Sources!$F$14) -> 4756.7035 | V19: =U19*(1+Assumptions_Sources!$F$14) -> 5232.3739 | W19: =V19*(1+Assumptions_Sources!$F$14) -> 5755.6113 | X19: =IF(E19>0,(R19/E19)^(1/5)-1,0) -> 0.26574747 | Y19: =IF(E19>0,(W19/E19)^(1/10)-1,0) -> 0.17996704
A20: Other adult vaccines | B20: 200 | C20: 200 | D20: 140 | E20: 215 | F20: 50 | G20: =(J20-F20)*Assumptions_Sources!$C$45/SUM(Assumptions_Sources!$C$45:$E$45) -> 62.403944 | H20: =(J20-F20)*Assumptions_Sources!$D$45/SUM(Assumptions_Sources!$C$45:$E$45) -> 62.403944 | I20: =J20-F20-G20-H20 -> 61.692112 | J20: 236.5 | K20: =O20*Assumptions_Sources!$B$45 -> 55.6721 | L20: =O20*Assumptions_Sources!$C$45 -> 68.41945 | M20: =O20*Assumptions_Sources!$D$45 -> 68.41945 | N20: =O20-K20-L20-M20 -> 67.639 | O20: 260.15 | P20: =O20*(1+Assumptions_Sources!$D$15) -> 280.962 | Q20: =P20*(1+Assumptions_Sources!$E$15) -> 300.62934 | R20: =Q20*(1+Assumptions_Sources!$E$15) -> 321.67339 | S20: =R20*(1+Assumptions_Sources!$F$15) -> 337.75706 | T20: =S20*(1+Assumptions_Sources!$F$15) -> 354.64492 | U20: =T20*(1+Assumptions_Sources!$F$15) -> 372.37716 | V20: =U20*(1+Assumptions_Sources!$F$15) -> 390.99602 | W20: =V20*(1+Assumptions_Sources!$F$15) -> 410.54582 | X20: =IF(E20>0,(R20/E20)^(1/5)-1,0) -> 0.083915274 | Y20: =IF(E20>0,(W20/E20)^(1/10)-1,0) -> 0.066822871
A21: Arexvy | B21: 0 | C21: 0 | D21: 0 | E21: 0 | F21: 0 | G21: =IF(Assumptions_Sources!$C$30=2027,J21*Assumptions_Sources!$H$30,(J21-F21)*Assumptions_Sources!$C$45/SUM(Assumptions_Sources!$C$45:$E$45)) -> 0 | H21: =IF(Assumptions_Sources!$C$30=2027,J21*Assumptions_Sources!$I$30,(J21-F21)*Assumptions_Sources!$D$45/SUM(Assumptions_Sources!$C$45:$E$45)) -> 83.333333 | I21: =J21-F21-G21-H21 -> 125 | J21: 208.33333 | K21: =O21*Assumptions_Sources!$B$45 -> 133.75 | L21: =O21*Assumptions_Sources!$C$45 -> 164.375 | M21: =O21*Assumptions_Sources!$D$45 -> 164.375 | N21: =O21-K21-L21-M21 -> 162.5 | O21: 625 | P21: =IF(2029<Assumptions_Sources!$C$30,0,IF(2029=Assumptions_Sources!$C$30,Assumptions_Sources!$D$30/Assumptions_Sources!$E$30*Assumptions_Sources!$G$30,IF(2029<Assumptions_Sources!$C$30+Assumptions_Sources!$E$30,MIN(Assumptions_Sources!$D$30,Assumptions_Sources!$D$30/Assumptions_Sources!$E$30*(2029-Assumptions_Sources!$C$30+Assumptions_Sources!$G$30)),Assumptions_Sources!$D$30*(1+Assumptions_Sources!$F$30)^(2029-(Assumptions_Sources!$C$30+Assumptions_Sources!$E$30))))) -> 1041.6667 | Q21: =IF(2030<Assumptions_Sources!$C$30,0,IF(2030=Assumptions_Sources!$C$30,Assumptions_Sources!$D$30/Assumptions_Sources!$E$30*Assumptions_Sources!$G$30,IF(2030<Assumptions_Sources!$C$30+Assumptions_Sources!$E$30,MIN(Assumptions_Sources!$D$30,Assumptions_Sources!$D$30/Assumptions_Sources!$E$30*(2030-Assumptions_Sources!$C$30+Assumptions_Sources!$G$30)),Assumptions_Sources!$D$30*(1+Assumptions_Sources!$F$30)^(2030-(Assumptions_Sources!$C$30+Assumptions_Sources!$E$30))))) -> 1458.3333 | R21: =IF(2031<Assumptions_Sources!$C$30,0,IF(2031=Assumptions_Sources!$C$30,Assumptions_Sources!$D$30/Assumptions_Sources!$E$30*Assumptions_Sources!$G$30,IF(2031<Assumptions_Sources!$C$30+Assumptions_Sources!$E$30,MIN(Assumptions_Sources!$D$30,Assumptions_Sources!$D$30/Assumptions_Sources!$E$30*(2031-Assumptions_Sources!$C$30+Assumptions_Sources!$G$30)),Assumptions_Sources!$D$30*(1+Assumptions_Sources!$F$30)^(2031-(Assumptions_Sources!$C$30+Assumptions_Sources!$E$30))))) -> 1875 | S21: =IF(2032<Assumptions_Sources!$C$30,0,IF(2032=Assumptions_Sources!$C$30,Assumptions_Sources!$D$30/Assumptions_Sources!$E$30*Assumptions_Sources!$G$30,IF(2032<Assumptions_Sources!$C$30+Assumptions_Sources!$E$30,MIN(Assumptions_Sources!$D$30,Assumptions_Sources!$D$30/Assumptions_Sources!$E$30*(2032-Assumptions_Sources!$C$30+Assumptions_Sources!$G$30)),Assumptions_Sources!$D$30*(1+Assumptions_Sources!$F$30)^(2032-(Assumptions_Sources!$C$30+Assumptions_Sources!$E$30))))) -> 2291.6667 | T21: =IF(2033<Assumptions_Sources!$C$30,0,IF(2033=Assumptions_Sources!$C$30,Assumptions_Sources!$D$30/Assumptions_Sources!$E$30*Assumptions_Sources!$G$30,IF(2033<Assumptions_Sources!$C$30+Assumptions_Sources!$E$30,MIN(Assumptions_Sources!$D$30,Assumptions_Sources!$D$30/Assumptions_Sources!$E$30*(2033-Assumptions_Sources!$C$30+Assumptions_Sources!$G$30)),Assumptions_Sources!$D$30*(1+Assumptions_Sources!$F$30)^(2033-(Assumptions_Sources!$C$30+Assumptions_Sources!$E$30))))) -> 2500 | U21: =IF(2034<Assumptions_Sources!$C$30,0,IF(2034=Assumptions_Sources!$C$30,Assumptions_Sources!$D$30/Assumptions_Sources!$E$30*Assumptions_Sources!$G$30,IF(2034<Assumptions_Sources!$C$30+Assumptions_Sources!$E$30,MIN(Assumptions_Sources!$D$30,Assumptions_Sources!$D$30/Assumptions_Sources!$E$30*(2034-Assumptions_Sources!$C$30+Assumptions_Sources!$G$30)),Assumptions_Sources!$D$30*(1+Assumptions_Sources!$F$30)^(2034-(Assumptions_Sources!$C$30+Assumptions_Sources!$E$30))))) -> 2575 | V21: =IF(2035<Assumptions_Sources!$C$30,0,IF(2035=Assumptions_Sources!$C$30,Assumptions_Sources!$D$30/Assumptions_Sources!$E$30*Assumptions_Sources!$G$30,IF(2035<Assumptions_Sources!$C$30+Assumptions_Sources!$E$30,MIN(Assumptions_Sources!$D$30,Assumptions_Sources!$D$30/Assumptions_Sources!$E$30*(2035-Assumptions_Sources!$C$30+Assumptions_Sources!$G$30)),Assumptions_Sources!$D$30*(1+Assumptions_Sources!$F$30)^(2035-(Assumptions_Sources!$C$30+Assumptions_Sources!$E$30))))) -> 2652.25 | W21: =IF(2036<Assumptions_Sources!$C$30,0,IF(2036=Assumptions_Sources!$C$30,Assumptions_Sources!$D$30/Assumptions_Sources!$E$30*Assumptions_Sources!$G$30,IF(2036<Assumptions_Sources!$C$30+Assumptions_Sources!$E$30,MIN(Assumptions_Sources!$D$30,Assumptions_Sources!$D$30/Assumptions_Sources!$E$30*(2036-Assumptions_Sources!$C$30+Assumptions_Sources!$G$30)),Assumptions_Sources!$D$30*(1+Assumptions_Sources!$F$30)^(2036-(Assumptions_Sources!$C$30+Assumptions_Sources!$E$30))))) -> 2731.8175 | X21: =IF(E21>0,(R21/E21)^(1/5)-1,0) -> 0 | Y21: =IF(E21>0,(W21/E21)^(1/10)-1,0) -> 0
A22: Vaccines | B22: =SUM(B17:B21) -> 4800 | C22: =SUM(C17:C21) -> 5700 | D22: =SUM(D17:D21) -> 6590 | E22: =SUM(E17:E21) -> 7315 | F22: =SUM(F17:F21) -> 2130 | G22: =SUM(G17:G21) -> 2103.1635 | H22: =SUM(H17:H21) -> 2186.4968 | I22: =SUM(I17:I21) -> 2204.173 | J22: 8623.8333 | K22: =SUM(K17:K21) -> 2173.9126 | L22: =SUM(L17:L21) -> 2671.6776 | M22: =SUM(M17:M21) -> 2671.6776 | N22: =SUM(N17:N21) -> 2641.2022 | O22: 10158.47 | P22: =SUM(P17:P21) -> 11665.347 | Q22: =SUM(Q17:Q21) -> 13076.757 | R22: =SUM(R17:R21) -> 14601.581 | S22: =SUM(S17:S21) -> 15871.812 | T22: =SUM(T17:T21) -> 16996.377 | U22: =SUM(U17:U21) -> 18055.313 | V22: =SUM(V17:V21) -> 19189.676 | W22: =SUM(W17:W21) -> 20405.486 | X22: =IF(E22>0,(R22/E22)^(1/5)-1,0) -> 0.14825173 | Y22: =IF(E22>0,(W22/E22)^(1/10)-1,0) -> 0.10803445
A24: SPECIALTY RESPIRATORY
A25: Trelegy Ellipta | B25: 250 | C25: 400 | D25: 560 | E25: 620 | F25: 75 | G25: =(J25-F25)*Assumptions_Sources!$C$45/SUM(Assumptions_Sources!$C$45:$E$45) -> 219.70204 | H25: =(J25-F25)*Assumptions_Sources!$D$45/SUM(Assumptions_Sources!$C$45:$E$45) -> 219.70204 | I25: =J25-F25-G25-H25 -> 217.19593 | J25: =E25*(1+Assumptions_Sources!$B$16) -> 731.6 | K25: =O25*Assumptions_Sources!$B$45 -> 180.04676 | L25: =O25*Assumptions_Sources!$C$45 -> 221.27242 | M25: =O25*Assumptions_Sources!$D$45 -> 221.27242 | N25: =O25-K25-L25-M25 -> 218.7484 | O25: =J25*(1+Assumptions_Sources!$C$16) -> 841.34 | P25: =O25*(1+Assumptions_Sources!$D$16) -> 942.3008 | Q25: =P25*(1+Assumptions_Sources!$E$16) -> 1036.5309 | R25: =Q25*(1+Assumptions_Sources!$E$16) -> 1140.184 | S25: =R25*(1+Assumptions_Sources!$F$16) -> 1219.9968 | T25: =S25*(1+Assumptions_Sources!$F$16) -> 1305.3966 | U25: =T25*(1+Assumptions_Sources!$F$16) -> 1396.7744 | V25: =U25*(1+Assumptions_Sources!$F$16) -> 1494.5486 | W25: =V25*(1+Assumptions_Sources!$F$16) -> 1599.167 | X25: =IF(E25>0,(R25/E25)^(1/5)-1,0) -> 0.1295791 | Y25: =IF(E25>0,(W25/E25)^(1/10)-1,0) -> 0.099386027
A26: Nucala | B26: 100 | C26: 150 | D26: 200 | E26: 250 | F26: 32 | G26: =(J26-F26)*Assumptions_Sources!$C$45/SUM(Assumptions_Sources!$C$45:$E$45) -> 93.85687 | H26: =(J26-F26)*Assumptions_Sources!$D$45/SUM(Assumptions_Sources!$C$45:$E$45) -> 93.85687 | I26: =J26-F26-G26-H26 -> 92.78626 | J26: =E26*(1+Assumptions_Sources!$B$17) -> 312.5 | K26: =O26*Assumptions_Sources!$B$45 -> 80.25 | L26: =O26*Assumptions_Sources!$C$45 -> 98.625 | M26: =O26*Assumptions_Sources!$D$45 -> 98.625 | N26: =O26-K26-L26-M26 -> 97.5 | O26: =J26*(1+Assumptions_Sources!$C$17) -> 375 | P26: =O26*(1+Assumptions_Sources!$D$17) -> 442.5 | Q26: =P26*(1+Assumptions_Sources!$E$17) -> 504.45 | R26: =Q26*(1+Assumptions_Sources!$E$17) -> 575.073 | S26: =R26*(1+Assumptions_Sources!$F$17) -> 632.5803 | T26: =S26*(1+Assumptions_Sources!$F$17) -> 695.83833 | U26: =T26*(1+Assumptions_Sources!$F$17) -> 765.42216 | V26: =U26*(1+Assumptions_Sources!$F$17) -> 841.96438 | W26: =V26*(1+Assumptions_Sources!$F$17) -> 926.16082 | X26: =IF(E26>0,(R26/E26)^(1/5)-1,0) -> 0.18129018 | Y26: =IF(E26>0,(W26/E26)^(1/10)-1,0) -> 0.1399207
A27: Other respiratory | B27: 750 | C27: 800 | D27: 850 | E27: 930 | F27: 120 | G27: =(J27-F27)*Assumptions_Sources!$C$45/SUM(Assumptions_Sources!$C$45:$E$45) -> 289.70153 | H27: =(J27-F27)*Assumptions_Sources!$D$45/SUM(Assumptions_Sources!$C$45:$E$45) -> 289.70153 | I27: =J27-F27-G27-H27 -> 286.39695 | J27: =E27*(1+Assumptions_Sources!$B$18) -> 985.8 | K27: =O27*Assumptions_Sources!$B$45 -> 223.61887 | L27: =O27*Assumptions_Sources!$C$45 -> 274.82132 | M27: =O27*Assumptions_Sources!$D$45 -> 274.82132 | N27: =O27-K27-L27-M27 -> 271.68648 | O27: =J27*(1+Assumptions_Sources!$C$18) -> 1044.948 | P27: =O27*(1+Assumptions_Sources!$D$18) -> 1097.1954 | Q27: =P27*(1+Assumptions_Sources!$E$18) -> 1141.0832 | R27: =Q27*(1+Assumptions_Sources!$E$18) -> 1186.7265 | S27: =R27*(1+Assumptions_Sources!$F$18) -> 1222.3283 | T27: =S27*(1+Assumptions_Sources!$F$18) -> 1258.9982 | U27: =T27*(1+Assumptions_Sources!$F$18) -> 1296.7681 | V27: =U27*(1+Assumptions_Sources!$F$18) -> 1335.6712 | W27: =V27*(1+Assumptions_Sources!$F$18) -> 1375.7413 | X27: =IF(E27>0,(R27/E27)^(1/5)-1,0) -> 0.049961904 | Y27: =IF(E27>0,(W27/E27)^(1/10)-1,0) -> 0.039933056
A28: Specialty Respiratory | B28: =SUM(B25:B27) -> 1100 | C28: =SUM(C25:C27) -> 1350 | D28: =SUM(D25:D27) -> 1610 | E28: =SUM(E25:E27) -> 1800 | F28: =SUM(F25:F27) -> 227 | G28: =SUM(G25:G27) -> 603.26043 | H28: =SUM(H25:H27) -> 603.26043 | I28: =SUM(I25:I27) -> 596.37913 | ... W28: =SUM(W25:W27) -> 3901.0691
A30: ONCOLOGY
A31: Jemperli | B31: 0 | C31: 0 | D31: 0 | E31: 70 | F31: 180 | G31: =(J31-F31)*Assumptions_Sources!$C$45/SUM(Assumptions_Sources!$C$45:$E$45) -> 207.45547 | H31: =(J31-F31)*Assumptions_Sources!$D$45/SUM(Assumptions_Sources!$C$45:$E$45) -> 207.45547 | I31: =J31-F31-G31-H31 -> 205.08906 | J31: =Assumptions_Sources!$B$22 -> 800 | K31: =O31*Assumptions_Sources!$B$45 -> 214 | L31: =O31*Assumptions_Sources!$C$45 -> 263 | M31: =O31*Assumptions_Sources!$D$45 -> 263 | N31: =O31-K31-L31-M31 -> 260 | O31: =J31*(1+Assumptions_Sources!$C$22) -> 1000 | P31: =O31*(1+Assumptions_Sources!$D$22) -> 1200 | Q31: =P31*(1+Assumptions_Sources!$E$22) -> 1380 | R31: =Q31*(1+Assumptions_Sources!$E$22) -> 1587 | S31: =R31*(1+Assumptions_Sources!$F$22) -> 1713.96 | T31: =S31*(1+Assumptions_Sources!$F$22) -> 1851.0768 | U31: =T31*(1+Assumptions_Sources!$F$22) -> 1999.1629 | V31: =U31*(1+Assumptions_Sources!$F$22) -> 2159.096 | W31: =V31*(1+Assumptions_Sources!$F$22) -> 2331.8237 | X31: =IF(E31>0,(R31/E31)^(1/5)-1,0) -> 0.86679134 | Y31: =IF(E31>0,(W31/E31)^(1/10)-1,0) -> 0.41990656
A32: Zejula | B32: 0 | C32: 0 | D32: 0 | E32: 44 | F32: 70 | G32: =(J32-F32)*Assumptions_Sources!$C$45/SUM(Assumptions_Sources!$C$45:$E$45) -> 110.41985 | H32: =(J32-F32)*Assumptions_Sources!$D$45/SUM(Assumptions_Sources!$C$45:$E$45) -> 110.41985 | I32: =J32-F32-G32-H32 -> 109.16031 | J32: =Assumptions_Sources!$B$23 -> 400 | K32: =O32*Assumptions_Sources!$B$45 -> 98.44 | L32: =O32*Assumptions_Sources!$C$45 -> 120.98 | M32: =O32*Assumptions_Sources!$D$45 -> 120.98 | N32: =O32-K32-L32-M32 -> 119.6 | O32: =J32*(1+Assumptions_Sources!$C$23) -> 460 | P32: =O32*(1+Assumptions_Sources!$D$23) -> 506 | Q32: =P32*(1+Assumptions_Sources!$E$23) -> 531.3 | R32: =Q32*(1+Assumptions_Sources!$E$23) -> 557.865 | S32: =R32*(1+Assumptions_Sources!$F$23) -> 569.0223 | T32: =S32*(1+Assumptions_Sources!$F$23) -> 580.40275 | U32: =T32*(1+Assumptions_Sources!$F$23) -> 592.0108 | V32: =U32*(1+Assumptions_Sources!$F$23) -> 603.85102 | W32: =V32*(1+Assumptions_Sources!$F$23) -> 615.92804 | X32: =IF(E32>0,(R32/E32)^(1/5)-1,0) -> 0.6619398 | Y32: =IF(E32>0,(W32/E32)^(1/10)-1,0) -> 0.30199024
A33: Blenrep | B33: 0 | C33: 0 | D33: 0 | E33: 0 | F33: 0 | G33: =IF(Assumptions_Sources!$C$31=2027,J33*Assumptions_Sources!$H$31,(J33-F33)*Assumptions_Sources!$C$45/SUM(Assumptions_Sources!$C$45:$E$45)) -> 0 | H33: =IF(Assumptions_Sources!$C$31=2027,J33*Assumptions_Sources!$I$31,(J33-F33)*Assumptions_Sources!$D$45/SUM(Assumptions_Sources!$C$45:$E$45)) -> 66.666667 | I33: =J33-F33-G33-H33 -> 100 | J33: =IF(2027<Assumptions_Sources!$C$31,0,IF(2027=Assumptions_Sources!$C$31,Assumptions_Sources!$D$31/Assumptions_Sources!$E$31*Assumptions_Sources!$G$31,IF(2027<Assumptions_Sources!$C$31+Assumptions_Sources!$E$31,MIN(Assumptions_Sources!$D$31,Assumptions_Sources!$D$31/Assumptions_Sources!$E$31*(2027-Assumptions_Sources!$C$31+Assumptions_Sources!$G$31)),Assumptions_Sources!$D$31*(1+Assumptions_Sources!$F$31)^(2027-(Assumptions_Sources!$C$31+Assumptions_Sources!$E$31))))) -> 166.66667 | K33: =O33*Assumptions_Sources!$B$45 -> 107 | L33: =O33*Assumptions_Sources!$C$45 -> 131.5 | M33: =O33*Assumptions_Sources!$D$45 -> 131.5 | N33: =O33-K33-L33-M33 -> 130 | O33: =IF(2028<Assumptions_Sources!$C$31,0,IF(2028=Assumptions_Sources!$C$31,Assumptions_Sources!$D$31/Assumptions_Sources!$E$31*Assumptions_Sources!$G$31,IF(2028<Assumptions_Sources!$C$31+Assumptions_Sources!$E$31,MIN(Assumptions_Sources!$D$31,Assumptions_Sources!$D$31/Assumptions_Sources!$E$31*(2028-Assumptions_Sources!$C$31+Assumptions_Sources!$G$31)),Assumptions_Sources!$D$31*(1+Assumptions_Sources!$F$31)^(2028-(Assumptions_Sources!$C$31+Assumptions_Sources!$E$31))))) -> 500 | P33: =IF(2029<Assumptions_Sources!$C$31,0,IF(2029=Assumptions_Sources!$C$31,Assumptions_Sources!$D$31/Assumptions_Sources!$E$31*Assumptions_Sources!$G$31,IF(2029<Assumptions_Sources!$C$31+Assumptions_Sources!$E$31,MIN(Assumptions_Sources!$D$31,Assumptions_Sources!$D$31/Assumptions_Sources!$E$31*(2029-Assumptions_Sources!$C$31+Assumptions_Sources!$G$31)),Assumptions_Sources!$D$31*(1+Assumptions_Sources!$F$31)^(2029-(Assumptions_Sources!$C$31+Assumptions_Sources!$E$31))))) -> 833.33333 | Q33: =IF(2030<Assumptions_Sources!$C$31,0,IF(2030=Assumptions_Sources!$C$31,Assumptions_Sources!$D$31/Assumptions_Sources!$E$31*Assumptions_Sources!$G$31,IF(2030<Assumptions_Sources!$C$31+Assumptions_Sources!$E$31,MIN(Assumptions_Sources!$D$31,Assumptions_Sources!$D$31/Assumptions_Sources!$E$31*(2030-Assumptions_Sources!$C$31+Assumptions_Sources!$G$31)),Assumptions_Sources!$D$31*(1+Assumptions_Sources!$F$31)^(2030-(Assumptions_Sources!$C$31+Assumptions_Sources!$E$31))))) -> 1166.6667 | R33: =IF(2031<Assumptions_Sources!$C$31,0,IF(2031=Assumptions_Sources!$C$31,Assumptions_Sources!$D$31/Assumptions_Sources!$E$31*Assumptions_Sources!$G$31,IF(2031<Assumptions_Sources!$C$31+Assumptions_Sources!$E$31,MIN(Assumptions_Sources!$D$31,Assumptions_Sources!$D$31/Assumptions_Sources!$E$31*(2031-Assumptions_Sources!$C$31+Assumptions_Sources!$G$31)),Assumptions_Sources!$D$31*(1+Assumptions_Sources!$F$31)^(2031-(Assumptions_Sources!$C$31+Assumptions_Sources!$E$31))))) -> 1500 | S33: =IF(2032<Assumptions_Sources!$C$31,0,IF(2032=Assumptions_Sources!$C$31,Assumptions_Sources!$D$31/Assumptions_Sources!$E$31*Assumptions_Sources!$G$31,IF(2032<Assumptions_Sources!$C$31+Assumptions_Sources!$E$31,MIN(Assumptions_Sources!$D$31,Assumptions_Sources!$D$31/Assumptions_Sources!$E$31*(2032-Assumptions_Sources!$C$31+Assumptions_Sources!$G$31)),Assumptions_Sources!$D$31*(1+Assumptions_Sources!$F$31)^(2032-(Assumptions_Sources!$C$31+Assumptions_Sources!$E$31))))) -> 1833.3333 | T33: =IF(2033<Assumptions_Sources!$C$31,0,IF(2033=Assumptions_Sources!$C$31,Assumptions_Sources!$D$31/Assumptions_Sources!$E$31*Assumptions_Sources!$G$31,IF(2033<Assumptions_Sources!$C$31+Assumptions_Sources!$E$31,MIN(Assumptions_Sources!$D$31,Assumptions_Sources!$D$31/Assumptions_Sources!$E$31*(2033-Assumptions_Sources!$C$31+Assumptions_Sources!$G$31)),Assumptions_Sources!$D$31*(1+Assumptions_Sources!$F$31)^(2033-(Assumptions_Sources!$C$31+Assumptions_Sources!$E$31))))) -> 2000 | U33: =IF(2034<Assumptions_Sources!$C$31,0,IF(2034=Assumptions_Sources!$C$31,Assumptions_Sources!$D$31/Assumptions_Sources!$E$31*Assumptions_Sources!$G$31,IF(2034<Assumptions_Sources!$C$31+Assumptions_Sources!$E$31,MIN(Assumptions_Sources!$D$31,Assumptions_Sources!$D$31/Assumptions_Sources!$E$31*(2034-Assumptions_Sources!$C$31+Assumptions_Sources!$G$31)),Assumptions_Sources!$D$31*(1+Assumptions_Sources!$F$31)^(2034-(Assumptions_Sources!$C$31+Assumptions_Sources!$E$31))))) -> 2040 | V33: =IF(2035<Assumptions_Sources!$C$31,0,IF(2035=Assumptions_Sources!$C$31,Assumptions_Sources!$D$31/Assumptions_Sources!$E$31*Assumptions_Sources!$G$31,IF(2035<Assumptions_Sources!$C$31+Assumptions_Sources!$E$31,MIN(Assumptions_Sources!$D$31,Assumptions_Sources!$D$31/Assumptions_Sources!$E$31*(2035-Assumptions_Sources!$C$31+Assumptions_Sources!$G$31)),Assumptions_Sources!$D$31*(1+Assumptions_Sources!$F$31)^(2035-(Assumptions_Sources!$C$31+Assumptions_Sources!$E$31))))) -> 2080.8 | W33: =IF(2036<Assumptions_Sources!$C$31,0,IF(2036=Assumptions_Sources!$C$31,Assumptions_Sources!$D$31/Assumptions_Sources!$E$31*Assumptions_Sources!$G$31,IF(2036<Assumptions_Sources!$C$31+Assumptions_Sources!$E$31,MIN(Assumptions_Sources!$D$31,Assumptions_Sources!$D$31/Assumptions_Sources!$E$31*(2036-Assumptions_Sources!$C$31+Assumptions_Sources!$G$31)),Assumptions_Sources!$D$31*(1+Assumptions_Sources!$F$31)^(2036-(Assumptions_Sources!$C$31+Assumptions_Sources!$E$31))))) -> 2122.416 | X33: =IF(E33>0,(R33/E33)^(1/5)-1,0) -> 0 | Y33: =IF(E33>0,(W33/E33)^(1/10)-1,0) -> 0
A34: Ojjaara | B34: =SUM(B31:B33) -> 0 | C34: =SUM(C31:C33) -> 0 | D34: =SUM(D31:D33) -> 0 | E34: =SUM(E31:E33) -> 114 | F34: =0 -> 0 | G34: =IF(Assumptions_Sources!$C$33=2027,J34*Assumptions_Sources!$H$33,(J34-F34)*Assumptions_Sources!$C$45/SUM(Assumptions_Sources!$C$45:$E$45)) -> 0 | H34: =IF(Assumptions_Sources!$C$33=2027,J34*Assumptions_Sources!$I$33,(J34-F34)*Assumptions_Sources!$D$45/SUM(Assumptions_Sources!$C$45:$E$45)) -> 0 | I34: =J34-F34-G34-H34 -> 0 | J34: =IF(2027<Assumptions_Sources!$C$33,0,IF(2027=Assumptions_Sources!$C$33,Assumptions_Sources!$D$33/Assumptions_Sources!$E$33*Assumptions_Sources!$G$33,IF(2027<Assumptions_Sources!$C$33+Assumptions_Sources!$E$33,MIN(Assumptions_Sources!$D$33,Assumptions_Sources!$D$33/Assumptions_Sources!$E$33*(2027-Assumptions_Sources!$C$33+Assumptions_Sources!$G$33)),Assumptions_Sources!$D$33*(1+Assumptions_Sources!$F$33)^(2027-(Assumptions_Sources!$C$33+Assumptions_Sources!$E$33))))) -> 0 | K34: =O34*Assumptions_Sources!$B$45 -> 0 | L34: =O34*Assumptions_Sources!$C$45 -> 0 | M34: =O34*Assumptions_Sources!$D$45 -> 0 | N34: =O34-K34-L34-M34 -> 0 | O34: =IF(2028<Assumptions_Sources!$C$33,0,IF(2028=Assumptions_Sources!$C$33,Assumptions_Sources!$D$33/Assumptions_Sources!$E$33*Assumptions_Sources!$G$33,IF(2028<Assumptions_Sources!$C$33+Assumptions_Sources!$E$33,MIN(Assumptions_Sources!$D$33,Assumptions_Sources!$D$33/Assumptions_Sources!$E$33*(2028-Assumptions_Sources!$C$33+Assumptions_Sources!$G$33)),Assumptions_Sources!$D$33*(1+Assumptions_Sources!$F$33)^(2028-(Assumptions_Sources!$C$33+Assumptions_Sources!$E$33))))) -> 0 | P34: 125 | Q34: 375 | R34: 625 | S34: 875 | T34: 1125 | U34: 1375 | V34: 1500 | W34: 1530 | X34: =IF(E34>0,(R34/E34)^(1/5)-1,0) -> 0.40538409 | Y34: =IF(E34>0,(W34/E34)^(1/10)-1,0) -> 0.29651832
A35: Oncology | B35: =SUM(B31:B34) -> 0 | C35: =SUM(C31:C34) -> 0 | D35: =SUM(D31:D34) -> 0 | E35: =SUM(E31:E34) -> 228 | F35: =SUM(F31:F34) -> 250 | G35: =SUM(G31:G34) -> 317.87532 | H35: =SUM(H31:H34) -> 384.54198 | I35: =SUM(I31:I34) -> 414.24936 | ... W35: =SUM(W31:W34) -> 6600.1677
A37: INFECTIOUS DISEASE | J37: =SUM(F37:I37) -> 0 | O37: =SUM(K37:N37) -> 0 | X37: =IF(E37>0,(R37/E37)^(1/5)-1,0) -> 0 | Y37: =IF(E37>0,(W37/E37)^(1/10)-1,0) -> 0
A38: Hibsago / Bepirovirsen | B38: 0 | C38: 0 | D38: 0 | E38: 0 | F38: 0 | G38: =IF(Assumptions_Sources!$C$32=2027,J38*Assumptions_Sources!$H$32,(J38-F38)*Assumptions_Sources!$C$45/SUM(Assumptions_Sources!$C$45:$E$45)) -> 0 | H38: =IF(Assumptions_Sources!$C$32=2027,J38*Assumptions_Sources!$I$32,(J38-F38)*Assumptions_Sources!$D$45/SUM(Assumptions_Sources!$C$45:$E$45)) -> 0 | I38: =J38-F38-G38-H38 -> 250 | J38: =IF(2027<Assumptions_Sources!$C$32,0,IF(2027=Assumptions_Sources!$C$32,Assumptions_Sources!$D$32/Assumptions_Sources!$E$32*Assumptions_Sources!$G$32,IF(2027<Assumptions_Sources!$C$32+Assumptions_Sources!$E$32,MIN(Assumptions_Sources!$D$32,Assumptions_Sources!$D$32/Assumptions_Sources!$E$32*(2027-Assumptions_Sources!$C$32+Assumptions_Sources!$G$32)),Assumptions_Sources!$D$32*(1+Assumptions_Sources!$F$32)^(2027-(Assumptions_Sources!$C$32+Assumptions_Sources!$E$32))))) -> 250 | K38: =O38*Assumptions_Sources!$B$45 -> 160.5 | L38: =O38*Assumptions_Sources!$C$45 -> 197.25 | M38: =O38*Assumptions_Sources!$D$45 -> 197.25 | N38: =O38-K38-L38-M38 -> 195 | O38: =IF(2028<Assumptions_Sources!$C$32,0,IF(2028=Assumptions_Sources!$C$32,Assumptions_Sources!$D$32/Assumptions_Sources!$E$32*Assumptions_Sources!$G$32,IF(2028<Assumptions_Sources!$C$32+Assumptions_Sources!$E$32,MIN(Assumptions_Sources!$D$32,Assumptions_Sources!$D$32/Assumptions_Sources!$E$32*(2028-Assumptions_Sources!$C$32+Assumptions_Sources!$G$32)),Assumptions_Sources!$D$32*(1+Assumptions_Sources!$F$32)^(2028-(Assumptions_Sources!$C$32+Assumptions_Sources!$E$32))))) -> 750 | P38: =IF(2029<Assumptions_Sources!$C$32,0,IF(2029=Assumptions_Sources!$C$32,Assumptions_Sources!$D$32/Assumptions_Sources!$E$32*Assumptions_Sources!$G$32,IF(2029<Assumptions_Sources!$C$32+Assumptions_Sources!$E$32,MIN(Assumptions_Sources!$D$32,Assumptions_Sources!$D$32/Assumptions_Sources!$E$32*(2029-Assumptions_Sources!$C$32+Assumptions_Sources!$G$32)),Assumptions_Sources!$D$32*(1+Assumptions_Sources!$F$32)^(2029-(Assumptions_Sources!$C$32+Assumptions_Sources!$E$32))))) -> 1250 | Q38: =IF(2030<Assumptions_Sources!$C$32,0,IF(2030=Assumptions_Sources!$C$32,Assumptions_Sources!$D$32/Assumptions_Sources!$E$32*Assumptions_Sources!$G$32,IF(2030<Assumptions_Sources!$C$32+Assumptions_Sources!$E$32,MIN(Assumptions_Sources!$D$32,Assumptions_Sources!$D$32/Assumptions_Sources!$E$32*(2030-Assumptions_Sources!$C$32+Assumptions_Sources!$G$32)),Assumptions_Sources!$D$32*(1+Assumptions_Sources!$F$32)^(2030-(Assumptions_Sources!$C$32+Assumptions_Sources!$E$32))))) -> 1750 | R38: =IF(2031<Assumptions_Sources!$C$32,0,IF(2031=Assumptions_Sources!$C$32,Assumptions_Sources!$D$32/Assumptions_Sources!$E$32*Assumptions_Sources!$G$32,IF(2031<Assumptions_Sources!$C$32+Assumptions_Sources!$E$32,MIN(Assumptions_Sources!$D$32,Assumptions_Sources!$D$32/Assumptions_Sources!$E$32*(2031-Assumptions_Sources!$C$32+Assumptions_Sources!$G$32)),Assumptions_Sources!$D$32*(1+Assumptions_Sources!$F$32)^(2031-(Assumptions_Sources!$C$32+Assumptions_Sources!$E$32))))) -> 2250 | S38: =IF(2032<Assumptions_Sources!$C$32,0,IF(2032=Assumptions_Sources!$C$32,Assumptions_Sources!$D$32/Assumptions_Sources!$E$32*Assumptions_Sources!$G$32,IF(2032<Assumptions_Sources!$C$32+Assumptions_Sources!$E$32,MIN(Assumptions_Sources!$D$32,Assumptions_Sources!$D$32/Assumptions_Sources!$E$32*(2032-Assumptions_Sources!$C$32+Assumptions_Sources!$G$32)),Assumptions_Sources!$D$32*(1+Assumptions_Sources!$F$32)^(2032-(Assumptions_Sources!$C$32+Assumptions_Sources!$E$32))))) -> 2750 | T38: =IF(2033<Assumptions_Sources!$C$32,0,IF(2033=Assumptions_Sources!$C$32,Assumptions_Sources!$D$32/Assumptions_Sources!$E$32*Assumptions_Sources!$G$32,IF(2033<Assumptions_Sources!$C$32+Assumptions_Sources!$E$32,MIN(Assumptions_Sources!$D$32,Assumptions_Sources!$D$32/Assumptions_Sources!$E$32*(2033-Assumptions_Sources!$C$32+Assumptions_Sources!$G$32)),Assumptions_Sources!$D$32*(1+Assumptions_Sources!$F$32)^(2033-(Assumptions_Sources!$C$32+Assumptions_Sources!$E$32))))) -> 3250 | U38: =IF(2034<Assumptions_Sources!$C$32,0,IF(2034=Assumptions_Sources!$C$32,Assumptions_Sources!$D$32/Assumptions_Sources!$E$32*Assumptions_Sources!$G$32,IF(2034<Assumptions_Sources!$C$32+Assumptions_Sources!$E$32,MIN(Assumptions_Sources!$D$32,Assumptions_Sources!$D$32/Assumptions_Sources!$E$32*(2034-Assumptions_Sources!$C$32+Assumptions_Sources!$G$32)),Assumptions_Sources!$D$32*(1+Assumptions_Sources!$F$32)^(2034-(Assumptions_Sources!$C$32+Assumptions_Sources!$E$32))))) -> 3500 | V38: =IF(2035<Assumptions_Sources!$C$32,0,IF(2035=Assumptions_Sources!$C$32,Assumptions_Sources!$D$32/Assumptions_Sources!$E$32*Assumptions_Sources!$G$32,IF(2035<Assumptions_Sources!$C$32+Assumptions_Sources!$E$32,MIN(Assumptions_Sources!$D$32,Assumptions_Sources!$D$32/Assumptions_Sources!$E$32*(2035-Assumptions_Sources!$C$32+Assumptions_Sources!$G$32)),Assumptions_Sources!$D$32*(1+Assumptions_Sources!$F$32)^(2035-(Assumptions_Sources!$C$32+Assumptions_Sources!$E$32))))) -> 3605 | W38: =IF(2036<Assumptions_Sources!$C$32,0,IF(2036=Assumptions_Sources!$C$32,Assumptions_Sources!$D$32/Assumptions_Sources!$E$32*Assumptions_Sources!$G$32,IF(2036<Assumptions_Sources!$C$32+Assumptions_Sources!$E$32,MIN(Assumptions_Sources!$D$32,Assumptions_Sources!$D$32/Assumptions_Sources!$E$32*(2036-Assumptions_Sources!$C$32+Assumptions_Sources!$G$32)),Assumptions_Sources!$D$32*(1+Assumptions_Sources!$F$32)^(2036-(Assumptions_Sources!$C$32+Assumptions_Sources!$E$32))))) -> 3713.15 | X38: =IF(E38>0,(R38/E38)^(1/5)-1,0) -> 0 | Y38: =IF(E38>0,(W38/E38)^(1/10)-1,0) -> 0
A39: Infectious Disease | B39: =SUM(B38) -> 0 | C39: =SUM(C38) -> 0 | D39: =SUM(D38) -> 0 | E39: =SUM(E38) -> 0 | F39: =SUM(F38) -> 0 | G39: =SUM(G38) -> 0 | H39: =SUM(H38) -> 0 | I39: =SUM(I38) -> 250 | J39: =SUM(F39:I39) -> 250 | K39: =SUM(K38) -> 160.5 | L39: =SUM(L38) -> 197.25 | M39: =SUM(M38) -> 197.25 | N39: =SUM(N38) -> 195 | O39: =SUM(K39:N39) -> 750 | P39: =SUM(P38) -> 1250 | Q39: =SUM(Q38) -> 1750 | R39: =SUM(R38) -> 2250 | S39: =SUM(S38) -> 2750 | T39: =SUM(T38) -> 3250 | U39: =SUM(U38) -> 3500 | V39: =SUM(V38) -> 3605 | W39: =SUM(W38) -> 3713.15 | X39: =IF(E39>0,(R39/E39)^(1/5)-1,0) -> 0 | Y39: =IF(E39>0,(W39/E39)^(1/10)-1,0) -> 0
J40: =SUM(F40:I40) -> 0 | O40: =SUM(K40:N40) -> 0 | X40: =IF(E40>0,(R40/E40)^(1/5)-1,0) -> 0 | Y40: =IF(E40>0,(W40/E40)^(1/10)-1,0) -> 0
A41: FUTURE PIPELINE (RISK-ADJUSTED) | J41: =SUM(F41:I41) -> 0 | O41: =SUM(K41:N41) -> 0 | X41: =IF(E41>0,(R41/E41)^(1/5)-1,0) -> 0 | Y41: =IF(E41>0,(W41/E41)^(1/10)-1,0) -> 0
A42: Velzatinib | B42: 0 | C42: 0 | D42: 0 | E42: 0 | F42: 0 | G42: =IF(Assumptions_Sources!$C$37=2027,J42*Assumptions_Sources!$H$37,(J42-F42)*Assumptions_Sources!$C$45/SUM(Assumptions_Sources!$C$45:$E$45)) -> 0 | H42: =IF(Assumptions_Sources!$C$37=2027,J42*Assumptions_Sources!$I$37,(J42-F42)*Assumptions_Sources!$D$45/SUM(Assumptions_Sources!$C$45:$E$45)) -> 0 | I42: =J42-F42-G42-H42 -> 0 | J42: =IF(2027<Assumptions_Sources!$C$37,0,IF(2027=Assumptions_Sources!$C$37,Assumptions_Sources!$D$37*Assumptions_Sources!$E$37/Assumptions_Sources!$G$37*Assumptions_Sources!$I$37,IF(2027<Assumptions_Sources!$C$37+Assumptions_Sources!$G$37,MIN(Assumptions_Sources!$D$37*Assumptions_Sources!$E$37,Assumptions_Sources!$D$37*Assumptions_Sources!$E$37/Assumptions_Sources!$G$37*(2027-Assumptions_Sources!$C$37+Assumptions_Sources!$I$37)),Assumptions_Sources!$D$37*Assumptions_Sources!$E$37*(1+Assumptions_Sources!$H$37)^(2027-(Assumptions_Sources!$C$37+Assumptions_Sources!$G$37))))) -> 0 | K42: =O42*Assumptions_Sources!$B$45 -> 0 | L42: =O42*Assumptions_Sources!$C$45 -> 0 | M42: =O42*Assumptions_Sources!$D$45 -> 0 | N42: =O42-K42-L42-M42 -> 0 | O42: =IF(2028<Assumptions_Sources!$C$37,0,IF(2028=Assumptions_Sources!$C$37,Assumptions_Sources!$D$37*Assumptions_Sources!$E$37/Assumptions_Sources!$G$37*Assumptions_Sources!$I$37,IF(2028<Assumptions_Sources!$C$37+Assumptions_Sources!$G$37,MIN(Assumptions_Sources!$D$37*Assumptions_Sources!$E$37,Assumptions_Sources!$D$37*Assumptions_Sources!$E$37/Assumptions_Sources!$G$37*(2028-Assumptions_Sources!$C$37+Assumptions_Sources!$I$37)),Assumptions_Sources!$D$37*Assumptions_Sources!$E$37*(1+Assumptions_Sources!$H$37)^(2028-(Assumptions_Sources!$C$37+Assumptions_Sources!$G$37))))) -> 0 | P42: =IF(2029<Assumptions_Sources!$C$37,0,IF(2029=Assumptions_Sources!$C$37,Assumptions_Sources!$D$37*Assumptions_Sources!$E$37/Assumptions_Sources!$G$37*Assumptions_Sources!$I$37,IF(2029<Assumptions_Sources!$C$37+Assumptions_Sources!$G$37,MIN(Assumptions_Sources!$D$37*Assumptions_Sources!$E$37,Assumptions_Sources!$D$37*Assumptions_Sources!$E$37/Assumptions_Sources!$G$37*(2029-Assumptions_Sources!$C$37+Assumptions_Sources!$I$37)),Assumptions_Sources!$D$37*Assumptions_Sources!$E$37*(1+Assumptions_Sources!$H$37)^(2029-(Assumptions_Sources!$C$37+Assumptions_Sources!$G$37))))) -> 0 | Q42: =IF(2030<Assumptions_Sources!$C$37,0,IF(2030=Assumptions_Sources!$C$37,Assumptions_Sources!$D$37*Assumptions_Sources!$E$37/Assumptions_Sources!$G$37*Assumptions_Sources!$I$37,IF(2030<Assumptions_Sources!$C$37+Assumptions_Sources!$G$37,MIN(Assumptions_Sources!$D$37*Assumptions_Sources!$E$37,Assumptions_Sources!$D$37*Assumptions_Sources!$E$37/Assumptions_Sources!$G$37*(2030-Assumptions_Sources!$C$37+Assumptions_Sources!$I$37)),Assumptions_Sources!$D$37*Assumptions_Sources!$E$37*(1+Assumptions_Sources!$H$37)^(2030-(Assumptions_Sources!$C$37+Assumptions_Sources!$G$37))))) -> 0 | R42: =IF(2031<Assumptions_Sources!$C$37,0,IF(2031=Assumptions_Sources!$C$37,Assumptions_Sources!$D$37*Assumptions_Sources!$E$37/Assumptions_Sources!$G$37*Assumptions_Sources!$I$37,IF(2031<Assumptions_Sources!$C$37+Assumptions_Sources!$G$37,MIN(Assumptions_Sources!$D$37*Assumptions_Sources!$E$37,Assumptions_Sources!$D$37*Assumptions_Sources!$E$37/Assumptions_Sources!$G$37*(2031-Assumptions_Sources!$C$37+Assumptions_Sources!$I$37)),Assumptions_Sources!$D$37*Assumptions_Sources!$E$37*(1+Assumptions_Sources!$H$37)^(2031-(Assumptions_Sources!$C$37+Assumptions_Sources!$G$37))))) -> 0 | S42: =IF(2032<Assumptions_Sources!$C$37,0,IF(2032=Assumptions_Sources!$C$37,Assumptions_Sources!$D$37*Assumptions_Sources!$E$37/Assumptions_Sources!$G$37*Assumptions_Sources!$I$37,IF(2032<Assumptions_Sources!$C$37+Assumptions_Sources!$G$37,MIN(Assumptions_Sources!$D$37*Assumptions_Sources!$E$37,Assumptions_Sources!$D$37*Assumptions_Sources!$E$37/Assumptions_Sources!$G$37*(2032-Assumptions_Sources!$C$37+Assumptions_Sources!$I$37)),Assumptions_Sources!$D$37*Assumptions_Sources!$E$37*(1+Assumptions_Sources!$H$37)^(2032-(Assumptions_Sources!$C$37+Assumptions_Sources!$G$37))))) -> 44 | T42: =IF(2033<Assumptions_Sources!$C$37,0,IF(2033=Assumptions_Sources!$C$37,Assumptions_Sources!$D$37*Assumptions_Sources!$E$37/Assumptions_Sources!$G$37*Assumptions_Sources!$I$37,IF(2033<Assumptions_Sources!$C$37+Assumptions_Sources!$G$37,MIN(Assumptions_Sources!$D$37*Assumptions_Sources!$E$37,Assumptions_Sources!$D$37*Assumptions_Sources!$E$37/Assumptions_Sources!$G$37*(2033-Assumptions_Sources!$C$37+Assumptions_Sources!$I$37)),Assumptions_Sources!$D$37*Assumptions_Sources!$E$37*(1+Assumptions_Sources!$H$37)^(2033-(Assumptions_Sources!$C$37+Assumptions_Sources!$G$37))))) -> 132 | U42: =IF(2034<Assumptions_Sources!$C$37,0,IF(2034=Assumptions_Sources!$C$37,Assumptions_Sources!$D$37*Assumptions_Sources!$E$37/Assumptions_Sources!$G$37*Assumptions_Sources!$I$37,IF(2034<Assumptions_Sources!$C$37+Assumptions_Sources!$G$37,MIN(Assumptions_Sources!$D$37*Assumptions_Sources!$E$37,Assumptions_Sources!$D$37*Assumptions_Sources!$E$37/Assumptions_Sources!$G$37*(2034-Assumptions_Sources!$C$37+Assumptions_Sources!$I$37)),Assumptions_Sources!$D$37*Assumptions_Sources!$E$37*(1+Assumptions_Sources!$H$37)^(2034-(Assumptions_Sources!$C$37+Assumptions_Sources!$G$37))))) -> 220 | V42: =IF(2035<Assumptions_Sources!$C$37,0,IF(2035=Assumptions_Sources!$C$37,Assumptions_Sources!$D$37*Assumptions_Sources!$E$37/Assumptions_Sources!$G$37*Assumptions_Sources!$I$37,IF(2035<Assumptions_Sources!$C$37+Assumptions_Sources!$G$37,MIN(Assumptions_Sources!$D$37*Assumptions_Sources!$E$37,Assumptions_Sources!$D$37*Assumptions_Sources!$E$37/Assumptions_Sources!$G$37*(2035-Assumptions_Sources!$C$37+Assumptions_Sources!$I$37)),Assumptions_Sources!$D$37*Assumptions_Sources!$E$37*(1+Assumptions_Sources!$H$37)^(2035-(Assumptions_Sources!$C$37+Assumptions_Sources!$G$37))))) -> 308 | W42: =IF(2036<Assumptions_Sources!$C$37,0,IF(2036=Assumptions_Sources!$C$37,Assumptions_Sources!$D$37*Assumptions_Sources!$E$37/Assumptions_Sources!$G$37*Assumptions_Sources!$I$37,IF(2036<Assumptions_Sources!$C$37+Assumptions_Sources!$G$37,MIN(Assumptions_Sources!$D$37*Assumptions_Sources!$E$37,Assumptions_Sources!$D$37*Assumptions_Sources!$E$37/Assumptions_Sources!$G$37*(2036-Assumptions_Sources!$C$37+Assumptions_Sources!$I$37)),Assumptions_Sources!$D$37*Assumptions_Sources!$E$37*(1+Assumptions_Sources!$H$37)^(2036-(Assumptions_Sources!$C$37+Assumptions_Sources!$G$37))))) -> 396 | X42: =IF(E42>0,(R42/E42)^(1/5)-1,0) -> 0 | Y42: =IF(E42>0,(W42/E42)^(1/10)-1,0) -> 0
A43: Mocertatug rezetecan (B7-H4) | B43: 0 | C43: 0 | D43: 0 | E43: 0 | F43: 0 | G43: =IF(Assumptions_Sources!$C$38=2027,J43*Assumptions_Sources!$H$38,(J43-F43)*Assumptions_Sources!$C$45/SUM(Assumptions_Sources!$C$45:$E$45)) -> 0 | H43: =IF(Assumptions_Sources!$C$38=2027,J43*Assumptions_Sources!$I$38,(J43-F43)*Assumptions_Sources!$D$45/SUM(Assumptions_Sources!$C$45:$E$45)) -> 0 | I43: =J43-F43-G43-H43 -> 0 | J43: =IF(2027<Assumptions_Sources!$C$38,0,IF(2027=Assumptions_Sources!$C$38,Assumptions_Sources!$D$38*Assumptions_Sources!$E$38/Assumptions_Sources!$G$38*Assumptions_Sources!$I$38,IF(2027<Assumptions_Sources!$C$38+Assumptions_Sources!$G$38,MIN(Assumptions_Sources!$D$38*Assumptions_Sources!$E$38,Assumptions_Sources!$D$38*Assumptions_Sources!$E$38/Assumptions_Sources!$G$38*(2027-Assumptions_Sources!$C$38+Assumptions_Sources!$I$38)),Assumptions_Sources!$D$38*Assumptions_Sources!$E$38*(1+Assumptions_Sources!$H$38)^(2027-(Assumptions_Sources!$C$38+Assumptions_Sources!$G$38))))) -> 0 | K43: =O43*Assumptions_Sources!$B$45 -> 0 | L43: =O43*Assumptions_Sources!$C$45 -> 0 | M43: =O43*Assumptions_Sources!$D$45 -> 0 | N43: =O43-K43-L43-M43 -> 0 | O43: =IF(2028<Assumptions_Sources!$C$38,0,IF(2028=Assumptions_Sources!$C$38,Assumptions_Sources!$D$38*Assumptions_Sources!$E$38/Assumptions_Sources!$G$38*Assumptions_Sources!$I$38,IF(2028<Assumptions_Sources!$C$38+Assumptions_Sources!$G$38,MIN(Assumptions_Sources!$D$38*Assumptions_Sources!$E$38,Assumptions_Sources!$D$38*Assumptions_Sources!$E$38/Assumptions_Sources!$G$38*(2028-Assumptions_Sources!$C$38+Assumptions_Sources!$I$38)),Assumptions_Sources!$D$38*Assumptions_Sources!$E$38*(1+Assumptions_Sources!$H$38)^(2028-(Assumptions_Sources!$C$38+Assumptions_Sources!$G$38))))) -> 0 | P43: =IF(2029<Assumptions_Sources!$C$38,0,IF(2029=Assumptions_Sources!$C$38,Assumptions_Sources!$D$38*Assumptions_Sources!$E$38/Assumptions_Sources!$G$38*Assumptions_Sources!$I$38,IF(2029<Assumptions_Sources!$C$38+Assumptions_Sources!$G$38,MIN(Assumptions_Sources!$D$38*Assumptions_Sources!$E$38,Assumptions_Sources!$D$38*Assumptions_Sources!$E$38/Assumptions_Sources!$G$38*(2029-Assumptions_Sources!$C$38+Assumptions_Sources!$I$38)),Assumptions_Sources!$D$38*Assumptions_Sources!$E$38*(1+Assumptions_Sources!$H$38)^(2029-(Assumptions_Sources!$C$38+Assumptions_Sources!$G$38))))) -> 0 | Q43: =IF(2030<Assumptions_Sources!$C$38,0,IF(2030=Assumptions_Sources!$C$38,Assumptions_Sources!$D$38*Assumptions_Sources!$E$38/Assumptions_Sources!$G$38*Assumptions_Sources!$I$38,IF(2030<Assumptions_Sources!$C$38+Assumptions_Sources!$G$38,MIN(Assumptions_Sources!$D$38*Assumptions_Sources!$E$38,Assumptions_Sources!$D$38*Assumptions_Sources!$E$38/Assumptions_Sources!$G$38*(2030-Assumptions_Sources!$C$38+Assumptions_Sources!$I$38)),Assumptions_Sources!$D$38*Assumptions_Sources!$E$38*(1+Assumptions_Sources!$H$38)^(2030-(Assumptions_Sources!$C$38+Assumptions_Sources!$G$38))))) -> 0 | R43: =IF(2031<Assumptions_Sources!$C$38,0,IF(2031=Assumptions_Sources!$C$38,Assumptions_Sources!$D$38*Assumptions_Sources!$E$38/Assumptions_Sources!$G$38*Assumptions_Sources!$I$38,IF(2031<Assumptions_Sources!$C$38+Assumptions_Sources!$G$38,MIN(Assumptions_Sources!$D$38*Assumptions_Sources!$E$38,Assumptions_Sources!$D$38*Assumptions_Sources!$E$38/Assumptions_Sources!$G$38*(2031-Assumptions_Sources!$C$38+Assumptions_Sources!$I$38)),Assumptions_Sources!$D$38*Assumptions_Sources!$E$38*(1+Assumptions_Sources!$H$38)^(2031-(Assumptions_Sources!$C$38+Assumptions_Sources!$G$38))))) -> 0 | S43: =IF(2032<Assumptions_Sources!$C$38,0,IF(2032=Assumptions_Sources!$C$38,Assumptions_Sources!$D$38*Assumptions_Sources!$E$38/Assumptions_Sources!$G$38*Assumptions_Sources!$I$38,IF(2032<Assumptions_Sources!$C$38+Assumptions_Sources!$G$38,MIN(Assumptions_Sources!$D$38*Assumptions_Sources!$E$38,Assumptions_Sources!$D$38*Assumptions_Sources!$E$38/Assumptions_Sources!$G$38*(2032-Assumptions_Sources!$C$38+Assumptions_Sources!$I$38)),Assumptions_Sources!$D$38*Assumptions_Sources!$E$38*(1+Assumptions_Sources!$H$38)^(2032-(Assumptions_Sources!$C$38+Assumptions_Sources!$G$38))))) -> 0 | T43: =IF(2033<Assumptions_Sources!$C$38,0,IF(2033=Assumptions_Sources!$C$38,Assumptions_Sources!$D$38*Assumptions_Sources!$E$38/Assumptions_Sources!$G$38*Assumptions_Sources!$I$38,IF(2033<Assumptions_Sources!$C$38+Assumptions_Sources!$G$38,MIN(Assumptions_Sources!$D$38*Assumptions_Sources!$E$38,Assumptions_Sources!$D$38*Assumptions_Sources!$E$38/Assumptions_Sources!$G$38*(2033-Assumptions_Sources!$C$38+Assumptions_Sources!$I$38)),Assumptions_Sources!$D$38*Assumptions_Sources!$E$38*(1+Assumptions_Sources!$H$38)^(2033-(Assumptions_Sources!$C$38+Assumptions_Sources!$G$38))))) -> 60 | U43: =IF(2034<Assumptions_Sources!$C$38,0,IF(2034=Assumptions_Sources!$C$38,Assumptions_Sources!$D$38*Assumptions_Sources!$E$38/Assumptions_Sources!$G$38*Assumptions_Sources!$I$38,IF(2034<Assumptions_Sources!$C$38+Assumptions_Sources!$G$38,MIN(Assumptions_Sources!$D$38*Assumptions_Sources!$E$38,Assumptions_Sources!$D$38*Assumptions_Sources!$E$38/Assumptions_Sources!$G$38*(2034-Assumptions_Sources!$C$38+Assumptions_Sources!$I$38)),Assumptions_Sources!$D$38*Assumptions_Sources!$E$38*(1+Assumptions_Sources!$H$38)^(2034-(Assumptions_Sources!$C$38+Assumptions_Sources!$G$38))))) -> 180 | V43: =IF(2035<Assumptions_Sources!$C$38,0,IF(2035=Assumptions_Sources!$C$38,Assumptions_Sources!$D$38*Assumptions_Sources!$E$38/Assumptions_Sources!$G$38*Assumptions_Sources!$I$38,IF(2035<Assumptions_Sources!$C$38+Assumptions_Sources!$G$38,MIN(Assumptions_Sources!$D$38*Assumptions_Sources!$E$38,Assumptions_Sources!$D$38*Assumptions_Sources!$E$38/Assumptions_Sources!$G$38*(2035-Assumptions_Sources!$C$38+Assumptions_Sources!$I$38)),Assumptions_Sources!$D$38*Assumptions_Sources!$E$38*(1+Assumptions_Sources!$H$38)^(2035-(Assumptions_Sources!$C$38+Assumptions_Sources!$G$38))))) -> 300 | W43: =IF(2036<Assumptions_Sources!$C$38,0,IF(2036=Assumptions_Sources!$C$38,Assumptions_Sources!$D$38*Assumptions_Sources!$E$38/Assumptions_Sources!$G$38*Assumptions_Sources!$I$38,IF(2036<Assumptions_Sources!$C$38+Assumptions_Sources!$G$38,MIN(Assumptions_Sources!$D$38*Assumptions_Sources!$E$38,Assumptions_Sources!$D$38*Assumptions_Sources!$E$38/Assumptions_Sources!$G$38*(2036-Assumptions_Sources!$C$38+Assumptions_Sources!$I$38)),Assumptions_Sources!$D$38*Assumptions_Sources!$E$38*(1+Assumptions_Sources!$H$38)^(2036-(Assumptions_Sources!$C$38+Assumptions_Sources!$G$38))))) -> 420 | X43: =IF(E43>0,(R43/E43)^(1/5)-1,0) -> 0 | Y43: =IF(E43>0,(W43/E43)^(1/10)-1,0) -> 0
A44: Efimosfermin | B44: =SUM(B37:B43) -> 0 | C44: =SUM(C37:C43) -> 0 | D44: =SUM(D37:D43) -> 0 | E44: =SUM(E37:E43) -> 0 | F44: =0 -> 0 | G44: =(J44-F44)*Assumptions_Sources!$C$45/SUM(Assumptions_Sources!$C$45:$E$45) -> 0 | H44: =(J44-F44)*Assumptions_Sources!$D$45/SUM(Assumptions_Sources!$C$45:$E$45) -> 0 | I44: =J44-F44-G44-H44 -> 0 | J44: =IF(2027<Assumptions_Sources!$C$39,0,IF(2027=Assumptions_Sources!$C$39,Assumptions_Sources!$D$39*Assumptions_Sources!$E$39/Assumptions_Sources!$G$39*Assumptions_Sources!$I$39,IF(2027<Assumptions_Sources!$C$39+Assumptions_Sources!$G$39,MIN(Assumptions_Sources!$D$39*Assumptions_Sources!$E$39,Assumptions_Sources!$D$39*Assumptions_Sources!$E$39/Assumptions_Sources!$G$39*(2027-Assumptions_Sources!$C$39+Assumptions_Sources!$I$39)),Assumptions_Sources!$D$39*Assumptions_Sources!$E$39*(1+Assumptions_Sources!$H$39)^(2027-(Assumptions_Sources!$C$39+Assumptions_Sources!$G$39))))) -> 0 | K44: =O44*Assumptions_Sources!$B$45 -> 0 | L44: =O44*Assumptions_Sources!$C$45 -> 0 | M44: =O44*Assumptions_Sources!$D$45 -> 0 | N44: =O44-K44-L44-M44 -> 0 | O44: =IF(2028<Assumptions_Sources!$C$39,0,IF(2028=Assumptions_Sources!$C$39,Assumptions_Sources!$D$39*Assumptions_Sources!$E$39/Assumptions_Sources!$G$39*Assumptions_Sources!$I$39,IF(2028<Assumptions_Sources!$C$39+Assumptions_Sources!$G$39,MIN(Assumptions_Sources!$D$39*Assumptions_Sources!$E$39,Assumptions_Sources!$D$39*Assumptions_Sources!$E$39/Assumptions_Sources!$G$39*(2028-Assumptions_Sources!$C$39+Assumptions_Sources!$I$39)),Assumptions_Sources!$D$39*Assumptions_Sources!$E$39*(1+Assumptions_Sources!$H$39)^(2028-(Assumptions_Sources!$C$39+Assumptions_Sources!$G$39))))) -> 0 | P44: 0 | Q44: 0 | R44: 91.666667 | S44: 275 | T44: 458.33333 | U44: 641.66667 | V44: 825 | W44: 1008.3333 | X44: =IF(E44>0,(R44/E44)^(1/5)-1,0) -> 0 | Y44: =IF(E44>0,(W44/E44)^(1/10)-1,0) -> 0
A45: TSLP (GSK5784283) | B45: 0 | C45: 0 | D45: 0 | E45: 0 | F45: 0 | G45: =IF(Assumptions_Sources!$C$40=2027,J45*Assumptions_Sources!$H$40,(J45-F45)*Assumptions_Sources!$C$45/SUM(Assumptions_Sources!$C$45:$E$45)) -> 0 | H45: =IF(Assumptions_Sources!$C$40=2027,J45*Assumptions_Sources!$I$40,(J45-F45)*Assumptions_Sources!$D$45/SUM(Assumptions_Sources!$C$45:$E$45)) -> 0 | I45: =J45-F45-G45-H45 -> 0 | J45: =IF(2027<Assumptions_Sources!$C$40,0,IF(2027=Assumptions_Sources!$C$40,Assumptions_Sources!$D$40*Assumptions_Sources!$E$40/Assumptions_Sources!$G$40*Assumptions_Sources!$I$40,IF(2027<Assumptions_Sources!$C$40+Assumptions_Sources!$G$40,MIN(Assumptions_Sources!$D$40*Assumptions_Sources!$E$40,Assumptions_Sources!$D$40*Assumptions_Sources!$E$40/Assumptions_Sources!$G$40*(2027-Assumptions_Sources!$C$40+Assumptions_Sources!$I$40)),Assumptions_Sources!$D$40*Assumptions_Sources!$E$40*(1+Assumptions_Sources!$H$40)^(2027-(Assumptions_Sources!$C$40+Assumptions_Sources!$G$40))))) -> 0 | K45: =O45*Assumptions_Sources!$B$45 -> 0 | L45: =O45*Assumptions_Sources!$C$45 -> 0 | M45: =O45*Assumptions_Sources!$D$45 -> 0 | N45: =O45-K45-L45-M45 -> 0 | O45: =IF(2028<Assumptions_Sources!$C$40,0,IF(2028=Assumptions_Sources!$C$40,Assumptions_Sources!$D$40*Assumptions_Sources!$E$40/Assumptions_Sources!$G$40*Assumptions_Sources!$I$40,IF(2028<Assumptions_Sources!$C$40+Assumptions_Sources!$G$40,MIN(Assumptions_Sources!$D$40*Assumptions_Sources!$E$40,Assumptions_Sources!$D$40*Assumptions_Sources!$E$40/Assumptions_Sources!$G$40*(2028-Assumptions_Sources!$C$40+Assumptions_Sources!$I$40)),Assumptions_Sources!$D$40*Assumptions_Sources!$E$40*(1+Assumptions_Sources!$H$40)^(2028-(Assumptions_Sources!$C$40+Assumptions_Sources!$G$40))))) -> 0 | P45: =IF(2029<Assumptions_Sources!$C$40,0,IF(2029=Assumptions_Sources!$C$40,Assumptions_Sources!$D$40*Assumptions_Sources!$E$40/Assumptions_Sources!$G$40*Assumptions_Sources!$I$40,IF(2029<Assumptions_Sources!$C$40+Assumptions_Sources!$G$40,MIN(Assumptions_Sources!$D$40*Assumptions_Sources!$E$40,Assumptions_Sources!$D$40*Assumptions_Sources!$E$40/Assumptions_Sources!$G$40*(2029-Assumptions_Sources!$C$40+Assumptions_Sources!$I$40)),Assumptions_Sources!$D$40*Assumptions_Sources!$E$40*(1+Assumptions_Sources!$H$40)^(2029-(Assumptions_Sources!$C$40+Assumptions_Sources!$G$40))))) -> 0 | Q45: =IF(2030<Assumptions_Sources!$C$40,0,IF(2030=Assumptions_Sources!$C$40,Assumptions_Sources!$D$40*Assumptions_Sources!$E$40/Assumptions_Sources!$G$40*Assumptions_Sources!$I$40,IF(2030<Assumptions_Sources!$C$40+Assumptions_Sources!$G$40,MIN(Assumptions_Sources!$D$40*Assumptions_Sources!$E$40,Assumptions_Sources!$D$40*Assumptions_Sources!$E$40/Assumptions_Sources!$G$40*(2030-Assumptions_Sources!$C$40+Assumptions_Sources!$I$40)),Assumptions_Sources!$D$40*Assumptions_Sources!$E$40*(1+Assumptions_Sources!$H$40)^(2030-(Assumptions_Sources!$C$40+Assumptions_Sources!$G$40))))) -> 0 | R45: =IF(2031<Assumptions_Sources!$C$40,0,IF(2031=Assumptions_Sources!$C$40,Assumptions_Sources!$D$40*Assumptions_Sources!$E$40/Assumptions_Sources!$G$40*Assumptions_Sources!$I$40,IF(2031<Assumptions_Sources!$C$40+Assumptions_Sources!$G$40,MIN(Assumptions_Sources!$D$40*Assumptions_Sources!$E$40,Assumptions_Sources!$D$40*Assumptions_Sources!$E$40/Assumptions_Sources!$G$40*(2031-Assumptions_Sources!$C$40+Assumptions_Sources!$I$40)),Assumptions_Sources!$D$40*Assumptions_Sources!$E$40*(1+Assumptions_Sources!$H$40)^(2031-(Assumptions_Sources!$C$40+Assumptions_Sources!$G$40))))) -> 0 | S45: =IF(2032<Assumptions_Sources!$C$40,0,IF(2032=Assumptions_Sources!$C$40,Assumptions_Sources!$D$40*Assumptions_Sources!$E$40/Assumptions_Sources!$G$40*Assumptions_Sources!$I$40,IF(2032<Assumptions_Sources!$C$40+Assumptions_Sources!$G$40,MIN(Assumptions_Sources!$D$40*Assumptions_Sources!$E$40,Assumptions_Sources!$D$40*Assumptions_Sources!$E$40/Assumptions_Sources!$G$40*(2032-Assumptions_Sources!$C$40+Assumptions_Sources!$I$40)),Assumptions_Sources!$D$40*Assumptions_Sources!$E$40*(1+Assumptions_Sources!$H$40)^(2032-(Assumptions_Sources!$C$40+Assumptions_Sources!$G$40))))) -> 0 | T45: =IF(2033<Assumptions_Sources!$C$40,0,IF(2033=Assumptions_Sources!$C$40,Assumptions_Sources!$D$40*Assumptions_Sources!$E$40/Assumptions_Sources!$G$40*Assumptions_Sources!$I$40,IF(2033<Assumptions_Sources!$C$40+Assumptions_Sources!$G$40,MIN(Assumptions_Sources!$D$40*Assumptions_Sources!$E$40,Assumptions_Sources!$D$40*Assumptions_Sources!$E$40/Assumptions_Sources!$G$40*(2033-Assumptions_Sources!$C$40+Assumptions_Sources!$I$40)),Assumptions_Sources!$D$40*Assumptions_Sources!$E$40*(1+Assumptions_Sources!$H$40)^(2033-(Assumptions_Sources!$C$40+Assumptions_Sources!$G$40))))) -> 0 | U45: =IF(2034<Assumptions_Sources!$C$40,0,IF(2034=Assumptions_Sources!$C$40,Assumptions_Sources!$D$40*Assumptions_Sources!$E$40/Assumptions_Sources!$G$40*Assumptions_Sources!$I$40,IF(2034<Assumptions_Sources!$C$40+Assumptions_Sources!$G$40,MIN(Assumptions_Sources!$D$40*Assumptions_Sources!$E$40,Assumptions_Sources!$D$40*Assumptions_Sources!$E$40/Assumptions_Sources!$G$40*(2034-Assumptions_Sources!$C$40+Assumptions_Sources!$I$40)),Assumptions_Sources!$D$40*Assumptions_Sources!$E$40*(1+Assumptions_Sources!$H$40)^(2034-(Assumptions_Sources!$C$40+Assumptions_Sources!$G$40))))) -> 30 | V45: =IF(2035<Assumptions_Sources!$C$40,0,IF(2035=Assumptions_Sources!$C$40,Assumptions_Sources!$D$40*Assumptions_Sources!$E$40/Assumptions_Sources!$G$40*Assumptions_Sources!$I$40,IF(2035<Assumptions_Sources!$C$40+Assumptions_Sources!$G$40,MIN(Assumptions_Sources!$D$40*Assumptions_Sources!$E$40,Assumptions_Sources!$D$40*Assumptions_Sources!$E$40/Assumptions_Sources!$G$40*(2035-Assumptions_Sources!$C$40+Assumptions_Sources!$I$40)),Assumptions_Sources!$D$40*Assumptions_Sources!$E$40*(1+Assumptions_Sources!$H$40)^(2035-(Assumptions_Sources!$C$40+Assumptions_Sources!$G$40))))) -> 90 | W45: =IF(2036<Assumptions_Sources!$C$40,0,IF(2036=Assumptions_Sources!$C$40,Assumptions_Sources!$D$40*Assumptions_Sources!$E$40/Assumptions_Sources!$G$40*Assumptions_Sources!$I$40,IF(2036<Assumptions_Sources!$C$40+Assumptions_Sources!$G$40,MIN(Assumptions_Sources!$D$40*Assumptions_Sources!$E$40,Assumptions_Sources!$D$40*Assumptions_Sources!$E$40/Assumptions_Sources!$G$40*(2036-Assumptions_Sources!$C$40+Assumptions_Sources!$I$40)),Assumptions_Sources!$D$40*Assumptions_Sources!$E$40*(1+Assumptions_Sources!$H$40)^(2036-(Assumptions_Sources!$C$40+Assumptions_Sources!$G$40))))) -> 150 | X45: =IF(E45>0,(R45/E45)^(1/5)-1,0) -> 0 | Y45: =IF(E45>0,(W45/E45)^(1/10)-1,0) -> 0
A46: Gatuzosiran / GSK4532990 | B46: 0 | C46: 0 | D46: 0 | E46: 0 | F46: 0 | G46: =IF(Assumptions_Sources!$C$41=2027,J46*Assumptions_Sources!$H$41,(J46-F46)*Assumptions_Sources!$C$45/SUM(Assumptions_Sources!$C$45:$E$45)) -> 0 | H46: =IF(Assumptions_Sources!$C$41=2027,J46*Assumptions_Sources!$I$41,(J46-F46)*Assumptions_Sources!$D$45/SUM(Assumptions_Sources!$C$45:$E$45)) -> 0 | I46: =J46-F46-G46-H46 -> 0 | J46: =IF(2027<Assumptions_Sources!$C$41,0,IF(2027=Assumptions_Sources!$C$41,Assumptions_Sources!$D$41*Assumptions_Sources!$E$41/Assumptions_Sources!$G$41*Assumptions_Sources!$I$41,IF(2027<Assumptions_Sources!$C$41+Assumptions_Sources!$G$41,MIN(Assumptions_Sources!$D$41*Assumptions_Sources!$E$41,Assumptions_Sources!$D$41*Assumptions_Sources!$E$41/Assumptions_Sources!$G$41*(2027-Assumptions_Sources!$C$41+Assumptions_Sources!$I$41)),Assumptions_Sources!$D$41*Assumptions_Sources!$E$41*(1+Assumptions_Sources!$H$41)^(2027-(Assumptions_Sources!$C$41+Assumptions_Sources!$G$41))))) -> 0 | K46: =O46*Assumptions_Sources!$B$45 -> 0 | L46: =O46*Assumptions_Sources!$C$45 -> 0 | M46: =O46*Assumptions_Sources!$D$45 -> 0 | N46: =O46-K46-L46-M46 -> 0 | O46: =IF(2028<Assumptions_Sources!$C$41,0,IF(2028=Assumptions_Sources!$C$41,Assumptions_Sources!$D$41*Assumptions_Sources!$E$41/Assumptions_Sources!$G$41*Assumptions_Sources!$I$41,IF(2028<Assumptions_Sources!$C$41+Assumptions_Sources!$G$41,MIN(Assumptions_Sources!$D$41*Assumptions_Sources!$E$41,Assumptions_Sources!$D$41*Assumptions_Sources!$E$41/Assumptions_Sources!$G$41*(2028-Assumptions_Sources!$C$41+Assumptions_Sources!$I$41)),Assumptions_Sources!$D$41*Assumptions_Sources!$E$41*(1+Assumptions_Sources!$H$41)^(2028-(Assumptions_Sources!$C$41+Assumptions_Sources!$G$41))))) -> 0 | P46: =IF(2029<Assumptions_Sources!$C$41,0,IF(2029=Assumptions_Sources!$C$41,Assumptions_Sources!$D$41*Assumptions_Sources!$E$41/Assumptions_Sources!$G$41*Assumptions_Sources!$I$41,IF(2029<Assumptions_Sources!$C$41+Assumptions_Sources!$G$41,MIN(Assumptions_Sources!$D$41*Assumptions_Sources!$E$41,Assumptions_Sources!$D$41*Assumptions_Sources!$E$41/Assumptions_Sources!$G$41*(2029-Assumptions_Sources!$C$41+Assumptions_Sources!$I$41)),Assumptions_Sources!$D$41*Assumptions_Sources!$E$41*(1+Assumptions_Sources!$H$41)^(2029-(Assumptions_Sources!$C$41+Assumptions_Sources!$G$41))))) -> 0 | Q46: =IF(2030<Assumptions_Sources!$C$41,0,IF(2030=Assumptions_Sources!$C$41,Assumptions_Sources!$D$41*Assumptions_Sources!$E$41/Assumptions_Sources!$G$41*Assumptions_Sources!$I$41,IF(2030<Assumptions_Sources!$C$41+Assumptions_Sources!$G$41,MIN(Assumptions_Sources!$D$41*Assumptions_Sources!$E$41,Assumptions_Sources!$D$41*Assumptions_Sources!$E$41/Assumptions_Sources!$G$41*(2030-Assumptions_Sources!$C$41+Assumptions_Sources!$I$41)),Assumptions_Sources!$D$41*Assumptions_Sources!$E$41*(1+Assumptions_Sources!$H$41)^(2030-(Assumptions_Sources!$C$41+Assumptions_Sources!$G$41))))) -> 0 | R46: =IF(2031<Assumptions_Sources!$C$41,0,IF(2031=Assumptions_Sources!$C$41,Assumptions_Sources!$D$41*Assumptions_Sources!$E$41/Assumptions_Sources!$G$41*Assumptions_Sources!$I$41,IF(2031<Assumptions_Sources!$C$41+Assumptions_Sources!$G$41,MIN(Assumptions_Sources!$D$41*Assumptions_Sources!$E$41,Assumptions_Sources!$D$41*Assumptions_Sources!$E$41/Assumptions_Sources!$G$41*(2031-Assumptions_Sources!$C$41+Assumptions_Sources!$I$41)),Assumptions_Sources!$D$41*Assumptions_Sources!$E$41*(1+Assumptions_Sources!$H$41)^(2031-(Assumptions_Sources!$C$41+Assumptions_Sources!$G$41))))) -> 0 | S46: =IF(2032<Assumptions_Sources!$C$41,0,IF(2032=Assumptions_Sources!$C$41,Assumptions_Sources!$D$41*Assumptions_Sources!$E$41/Assumptions_Sources!$G$41*Assumptions_Sources!$I$41,IF(2032<Assumptions_Sources!$C$41+Assumptions_Sources!$G$41,MIN(Assumptions_Sources!$D$41*Assumptions_Sources!$E$41,Assumptions_Sources!$D$41*Assumptions_Sources!$E$41/Assumptions_Sources!$G$41*(2032-Assumptions_Sources!$C$41+Assumptions_Sources!$I$41)),Assumptions_Sources!$D$41*Assumptions_Sources!$E$41*(1+Assumptions_Sources!$H$41)^(2032-(Assumptions_Sources!$C$41+Assumptions_Sources!$G$41))))) -> 0 | T46: =IF(2033<Assumptions_Sources!$C$41,0,IF(2033=Assumptions_Sources!$C$41,Assumptions_Sources!$D$41*Assumptions_Sources!$E$41/Assumptions_Sources!$G$41*Assumptions_Sources!$I$41,IF(2033<Assumptions_Sources!$C$41+Assumptions_Sources!$G$41,MIN(Assumptions_Sources!$D$41*Assumptions_Sources!$E$41,Assumptions_Sources!$D$41*Assumptions_Sources!$E$41/Assumptions_Sources!$G$41*(2033-Assumptions_Sources!$C$41+Assumptions_Sources!$I$41)),Assumptions_Sources!$D$41*Assumptions_Sources!$E$41*(1+Assumptions_Sources!$H$41)^(2033-(Assumptions_Sources!$C$41+Assumptions_Sources!$G$41))))) -> 0 | U46: =IF(2034<Assumptions_Sources!$C$41,0,IF(2034=Assumptions_Sources!$C$41,Assumptions_Sources!$D$41*Assumptions_Sources!$E$41/Assumptions_Sources!$G$41*Assumptions_Sources!$I$41,IF(2034<Assumptions_Sources!$C$41+Assumptions_Sources!$G$41,MIN(Assumptions_Sources!$D$41*Assumptions_Sources!$E$41,Assumptions_Sources!$D$41*Assumptions_Sources!$E$41/Assumptions_Sources!$G$41*(2034-Assumptions_Sources!$C$41+Assumptions_Sources!$I$41)),Assumptions_Sources!$D$41*Assumptions_Sources!$E$41*(1+Assumptions_Sources!$H$41)^(2034-(Assumptions_Sources!$C$41+Assumptions_Sources!$G$41))))) -> 0 | V46: =IF(2035<Assumptions_Sources!$C$41,0,IF(2035=Assumptions_Sources!$C$41,Assumptions_Sources!$D$41*Assumptions_Sources!$E$41/Assumptions_Sources!$G$41*Assumptions_Sources!$I$41,IF(2035<Assumptions_Sources!$C$41+Assumptions_Sources!$G$41,MIN(Assumptions_Sources!$D$41*Assumptions_Sources!$E$41,Assumptions_Sources!$D$41*Assumptions_Sources!$E$41/Assumptions_Sources!$G$41*(2035-Assumptions_Sources!$C$41+Assumptions_Sources!$I$41)),Assumptions_Sources!$D$41*Assumptions_Sources!$E$41*(1+Assumptions_Sources!$H$41)^(2035-(Assumptions_Sources!$C$41+Assumptions_Sources!$G$41))))) -> 20 | W46: =IF(2036<Assumptions_Sources!$C$41,0,IF(2036=Assumptions_Sources!$C$41,Assumptions_Sources!$D$41*Assumptions_Sources!$E$41/Assumptions_Sources!$G$41*Assumptions_Sources!$I$41,IF(2036<Assumptions_Sources!$C$41+Assumptions_Sources!$G$41,MIN(Assumptions_Sources!$D$41*Assumptions_Sources!$E$41,Assumptions_Sources!$D$41*Assumptions_Sources!$E$41/Assumptions_Sources!$G$41*(2036-Assumptions_Sources!$C$41+Assumptions_Sources!$I$41)),Assumptions_Sources!$D$41*Assumptions_Sources!$E$41*(1+Assumptions_Sources!$H$41)^(2036-(Assumptions_Sources!$C$41+Assumptions_Sources!$G$41))))) -> 60 | X46: =IF(E46>0,(R46/E46)^(1/5)-1,0) -> 0 | Y46: =IF(E46>0,(W46/E46)^(1/10)-1,0) -> 0
A47: Camlipixant - RCC | B47: 0 | C47: 0 | D47: 0 | E47: 0 | F47: 0 | G47: =IF(Assumptions_Sources!$C$42=2027,J47*Assumptions_Sources!$H$42,(J47-F47)*Assumptions_Sources!$C$45/SUM(Assumptions_Sources!$C$45:$E$45)) -> 0 | H47: =IF(Assumptions_Sources!$C$42=2027,J47*Assumptions_Sources!$I$42,(J47-F47)*Assumptions_Sources!$D$45/SUM(Assumptions_Sources!$C$45:$E$45)) -> 0 | I47: =J47-F47-G47-H47 -> 0 | J47: =IF(2027<Assumptions_Sources!$C$42,0,IF(2027=Assumptions_Sources!$C$42,Assumptions_Sources!$D$42*Assumptions_Sources!$E$42/Assumptions_Sources!$G$42*Assumptions_Sources!$I$42,IF(2027<Assumptions_Sources!$C$42+Assumptions_Sources!$G$42,MIN(Assumptions_Sources!$D$42*Assumptions_Sources!$E$42,Assumptions_Sources!$D$42*Assumptions_Sources!$E$42/Assumptions_Sources!$G$42*(2027-Assumptions_Sources!$C$42+Assumptions_Sources!$I$42)),Assumptions_Sources!$D$42*Assumptions_Sources!$E$42*(1+Assumptions_Sources!$H$42)^(2027-(Assumptions_Sources!$C$42+Assumptions_Sources!$G$42))))) -> 0 | K47: =O47*Assumptions_Sources!$B$45 -> 0 | L47: =O47*Assumptions_Sources!$C$45 -> 0 | M47: =O47*Assumptions_Sources!$D$45 -> 0 | N47: =O47-K47-L47-M47 -> 0 | O47: =IF(2028<Assumptions_Sources!$C$42,0,IF(2028=Assumptions_Sources!$C$42,Assumptions_Sources!$D$42*Assumptions_Sources!$E$42/Assumptions_Sources!$G$42*Assumptions_Sources!$I$42,IF(2028<Assumptions_Sources!$C$42+Assumptions_Sources!$G$42,MIN(Assumptions_Sources!$D$42*Assumptions_Sources!$E$42,Assumptions_Sources!$D$42*Assumptions_Sources!$E$42/Assumptions_Sources!$G$42*(2028-Assumptions_Sources!$C$42+Assumptions_Sources!$I$42)),Assumptions_Sources!$D$42*Assumptions_Sources!$E$42*(1+Assumptions_Sources!$H$42)^(2028-(Assumptions_Sources!$C$42+Assumptions_Sources!$G$42))))) -> 0 | P47: =IF(2029<Assumptions_Sources!$C$42,0,IF(2029=Assumptions_Sources!$C$42,Assumptions_Sources!$D$42*Assumptions_Sources!$E$42/Assumptions_Sources!$G$42*Assumptions_Sources!$I$42,IF(2029<Assumptions_Sources!$C$42+Assumptions_Sources!$G$42,MIN(Assumptions_Sources!$D$42*Assumptions_Sources!$E$42,Assumptions_Sources!$D$42*Assumptions_Sources!$E$42/Assumptions_Sources!$G$42*(2029-Assumptions_Sources!$C$42+Assumptions_Sources!$I$42)),Assumptions_Sources!$D$42*Assumptions_Sources!$E$42*(1+Assumptions_Sources!$H$42)^(2029-(Assumptions_Sources!$C$42+Assumptions_Sources!$G$42))))) -> 0 | Q47: =IF(2030<Assumptions_Sources!$C$42,0,IF(2030=Assumptions_Sources!$C$42,Assumptions_Sources!$D$42*Assumptions_Sources!$E$42/Assumptions_Sources!$G$42*Assumptions_Sources!$I$42,IF(2030<Assumptions_Sources!$C$42+Assumptions_Sources!$G$42,MIN(Assumptions_Sources!$D$42*Assumptions_Sources!$E$42,Assumptions_Sources!$D$42*Assumptions_Sources!$E$42/Assumptions_Sources!$G$42*(2030-Assumptions_Sources!$C$42+Assumptions_Sources!$I$42)),Assumptions_Sources!$D$42*Assumptions_Sources!$E$42*(1+Assumptions_Sources!$H$42)^(2030-(Assumptions_Sources!$C$42+Assumptions_Sources!$G$42))))) -> 0 | R47: =IF(2031<Assumptions_Sources!$C$42,0,IF(2031=Assumptions_Sources!$C$42,Assumptions_Sources!$D$42*Assumptions_Sources!$E$42/Assumptions_Sources!$G$42*Assumptions_Sources!$I$42,IF(2031<Assumptions_Sources!$C$42+Assumptions_Sources!$G$42,MIN(Assumptions_Sources!$D$42*Assumptions_Sources!$E$42,Assumptions_Sources!$D$42*Assumptions_Sources!$E$42/Assumptions_Sources!$G$42*(2031-Assumptions_Sources!$C$42+Assumptions_Sources!$I$42)),Assumptions_Sources!$D$42*Assumptions_Sources!$E$42*(1+Assumptions_Sources!$H$42)^(2031-(Assumptions_Sources!$C$42+Assumptions_Sources!$G$42))))) -> 0 | S47: =IF(2032<Assumptions_Sources!$C$42,0,IF(2032=Assumptions_Sources!$C$42,Assumptions_Sources!$D$42*Assumptions_Sources!$E$42/Assumptions_Sources!$G$42*Assumptions_Sources!$I$42,IF(2032<Assumptions_Sources!$C$42+Assumptions_Sources!$G$42,MIN(Assumptions_Sources!$D$42*Assumptions_Sources!$E$42,Assumptions_Sources!$D$42*Assumptions_Sources!$E$42/Assumptions_Sources!$G$42*(2032-Assumptions_Sources!$C$42+Assumptions_Sources!$I$42)),Assumptions_Sources!$D$42*Assumptions_Sources!$E$42*(1+Assumptions_Sources!$H$42)^(2032-(Assumptions_Sources!$C$42+Assumptions_Sources!$G$42))))) -> 0 | T47: =IF(2033<Assumptions_Sources!$C$42,0,IF(2033=Assumptions_Sources!$C$42,Assumptions_Sources!$D$42*Assumptions_Sources!$E$42/Assumptions_Sources!$G$42*Assumptions_Sources!$I$42,IF(2033<Assumptions_Sources!$C$42+Assumptions_Sources!$G$42,MIN(Assumptions_Sources!$D$42*Assumptions_Sources!$E$42,Assumptions_Sources!$D$42*Assumptions_Sources!$E$42/Assumptions_Sources!$G$42*(2033-Assumptions_Sources!$C$42+Assumptions_Sources!$I$42)),Assumptions_Sources!$D$42*Assumptions_Sources!$E$42*(1+Assumptions_Sources!$H$42)^(2033-(Assumptions_Sources!$C$42+Assumptions_Sources!$G$42))))) -> 0 | U47: =IF(2034<Assumptions_Sources!$C$42,0,IF(2034=Assumptions_Sources!$C$42,Assumptions_Sources!$D$42*Assumptions_Sources!$E$42/Assumptions_Sources!$G$42*Assumptions_Sources!$I$42,IF(2034<Assumptions_Sources!$C$42+Assumptions_Sources!$G$42,MIN(Assumptions_Sources!$D$42*Assumptions_Sources!$E$42,Assumptions_Sources!$D$42*Assumptions_Sources!$E$42/Assumptions_Sources!$G$42*(2034-Assumptions_Sources!$C$42+Assumptions_Sources!$I$42)),Assumptions_Sources!$D$42*Assumptions_Sources!$E$42*(1+Assumptions_Sources!$H$42)^(2034-(Assumptions_Sources!$C$42+Assumptions_Sources!$G$42))))) -> 0 | V47: =IF(2035<Assumptions_Sources!$C$42,0,IF(2035=Assumptions_Sources!$C$42,Assumptions_Sources!$D$42*Assumptions_Sources!$E$42/Assumptions_Sources!$G$42*Assumptions_Sources!$I$42,IF(2035<Assumptions_Sources!$C$42+Assumptions_Sources!$G$42,MIN(Assumptions_Sources!$D$42*Assumptions_Sources!$E$42,Assumptions_Sources!$D$42*Assumptions_Sources!$E$42/Assumptions_Sources!$G$42*(2035-Assumptions_Sources!$C$42+Assumptions_Sources!$I$42)),Assumptions_Sources!$D$42*Assumptions_Sources!$E$42*(1+Assumptions_Sources!$H$42)^(2035-(Assumptions_Sources!$C$42+Assumptions_Sources!$G$42))))) -> 0 | W47: =IF(2036<Assumptions_Sources!$C$42,0,IF(2036=Assumptions_Sources!$C$42,Assumptions_Sources!$D$42*Assumptions_Sources!$E$42/Assumptions_Sources!$G$42*Assumptions_Sources!$I$42,IF(2036<Assumptions_Sources!$C$42+Assumptions_Sources!$G$42,MIN(Assumptions_Sources!$D$42*Assumptions_Sources!$E$42,Assumptions_Sources!$D$42*Assumptions_Sources!$E$42/Assumptions_Sources!$G$42*(2036-Assumptions_Sources!$C$42+Assumptions_Sources!$I$42)),Assumptions_Sources!$D$42*Assumptions_Sources!$E$42*(1+Assumptions_Sources!$H$42)^(2036-(Assumptions_Sources!$C$42+Assumptions_Sources!$G$42))))) -> 0 | X47: =IF(E47>0,(R47/E47)^(1/5)-1,0) -> 0 | Y47: =IF(E47>0,(W47/E47)^(1/10)-1,0) -> 0
A48: Future Pipeline | B48: =SUM(B42:B47) -> 0 | C48: =SUM(C42:C47) -> 0 | D48: =SUM(D42:D47) -> 0 | E48: =SUM(E42:E47) -> 0 | F48: =SUM(F42:F47) -> 0 | G48: =SUM(G42:G47) -> 0 | H48: =SUM(H42:H47) -> 0 | I48: =SUM(I42:I47) -> 0 | ... W48: =SUM(W42:W47) -> 2034.3333
A50: CONSOLIDATION | B50: =SUM(B14,B22,B28,B34,B44,B48) -> 32217.2 | C50: =SUM(C14,C22,C28,C34,C44,C48) -> 34237.1 | D50: =SUM(D14,D22,D28,D34,D44,D48) -> 37230 | E50: =SUM(E14,E22,E28,E34,E44,E48) -> 37901.7 | F50: =SUM(F14,F22,F28,F34,F44,F48) -> 8990 | G50: =SUM(G14,G22,G28,G34,G44,G48) -> 10703.944 | H50: =SUM(H14,H22,H28,H34,H44,H48) -> 10787.278 | I50: =SUM(I14,I22,I28,I34,I44,I48) -> 10706.846 | P50: =SUM(P14,P22,P28,P34,P44,P48) -> 48492.287 | Q50: =SUM(Q14,Q22,Q28,Q34,Q44,Q48) -> 52030.984 | R50: =SUM(R14,R22,R28,R34,R44,R48) -> 55969.913 | S50: =SUM(S14,S22,S28,S34,S44,S48) -> 59606.968 | T50: =SUM(T14,T22,T28,T34,T44,T48) -> 63277.954 | U50: =SUM(U14,U22,U28,U34,U44,U48) -> 67052.541 | V50: =SUM(V14,V22,V28,V34,V44,V48) -> 70910.615 | W50: =SUM(W14,W22,W28,W34,W44,W48) -> 74862.232
A51: Biddle / consolidation revenue | B51: 300 | C51: 300 | D51: 262.1 | E51: 315 | F51: 144.4 | G51: =(J51-F51)*Assumptions_Sources!$C$45/SUM(Assumptions_Sources!$C$45:$E$45) -> 135.71603 | H51: =(J51-F51)*Assumptions_Sources!$D$45/SUM(Assumptions_Sources!$C$45:$E$45) -> 135.71603 | I51: =J51-F51-G51-H51 -> 134.16794 | J51: 550 | K51: 123.585 | L51: 151.8825 | M51: 151.8825 | N51: 150.15 | O51: 577.5 | P51: 606.375 | Q51: 630.63 | R51: 655.8552 | S51: 675.53086 | T51: 695.79678 | U51: 716.67069 | V51: 738.17081 | W51: 760.31593 | X51: =IF(E51>0,(R51/E51)^(1/5)-1,0) -> 0.1579758 | Y51: =IF(E51>0,(W51/E51)^(1/10)-1,0) -> 0.092114953
A52: Consolidation revenue | B52: =SUM(B51) -> 300 | C52: =SUM(C51) -> 300 | D52: =SUM(D51) -> 262.1 | E52: =SUM(E51) -> 315 | F52: =SUM(F51) -> 144.4 | G52: =SUM(G51) -> 135.71603 | H52: =SUM(H51) -> 135.71603 | I52: =SUM(I51) -> 134.16794 | ... W52: =SUM(W51) -> 760.31593
B53: =IF(B50=0,0,B52/B50) -> 0.0093117962 | C53: =IF(C50=0,0,C52/C50) -> 0.0087624244 | D53: =IF(D50=0,0,D52/D50) -> 0.0070400215 | E53: =IF(E50=0,0,E52/E50) -> 0.0083109729 | F53: =IF(F50=0,0,F52/F50) -> 0.016062291 | G53: =IF(G50=0,0,G52/G50) -> 0.012679067 | H53: =IF(H50=0,0,H52/H50) -> 0.01258112 | I53: =IF(I50=0,0,I52/I50) -> 0.012531042 | ... W53: =IF(W50=0,0,W52/W50) -> 0.010156202
A54: Consolidated revenue | B54: =B14+B22+B28+B35+B39+B48+B52 -> 32517.2 | C54: =C14+C22+C28+C35+C39+C48+C52 -> 34537.1 | D54: =D14+D22+D28+D35+D39+D48+D52 -> 37492.1 | E54: =E14+E22+E28+E35+E39+E48+E52 -> 38330.7 | F54: =F14+F22+F28+F35+F39+F48+F52 -> 9384.4 | G54: =G14+G22+G28+G35+G39+G48+G52 -> 11157.536 | H54: =H14+H22+H28+H35+H39+H48+H52 -> 11307.536 | I54: =I14+I22+I28+I35+I39+I48+I52 -> 11505.263 | ... W54: =W14+W22+W28+W35+W39+W48+W52 -> 83397.532 | X54: =(R54/E54)^(1/5)-1 -> 0.10247279 | Y54: =(W54/E54)^(1/10)-1 -> 0.080838099
A55: YoY growth | C55: =C54/B54-1 -> 0.062117895 | D55: =D54/C54-1 -> 0.085560166 | E55: =E54/D54-1 -> 0.022367379 | F55: =$J$64/$F$64-1 -> 0.16551784 | G55: =G54/$G$64-1 -> 0.13859377 | H55: =H54/$H$64-1 -> 0.085947387 | I55: =I54/$I$64-1 -> 0.15595936 | J55: =J54/E54-1 -> 0.13107079 | K55: =K54/F54-1 -> 0.098192677 | L55: =L54/G54-1 -> 0.13516435 | M55: =M54/H54-1 -> 0.12010583 | N55: =N54/I54-1 -> 0.088298573 | O55: =O54/J54-1 -> 0.11079712 | P55: =P54/O54-1 -> 0.098211082 | Q55: =Q54/P54-1 -> 0.087006236 | R55: =R54/Q54-1 -> 0.085917941 | S55: =S54/R54-1 -> 0.071198486 | T55: =T54/S54-1 -> 0.064645373 | U55: =U54/T54-1 -> 0.057050541 | V55: =V54/U54-1 -> 0.053333537 | W55: =W54/V54-1 -> 0.052035677
A56: Post-FY26 launches + future pipeline | B56: =B21+B33+B34+B38+B48 -> 0 | C56: =C21+C33+C34+C38+C48 -> 0 | D56: =D21+D33+D34+D38+D48 -> 0 | E56: =E21+E33+E34+E38+E48 -> 114 | F56: =F21+F33+F34+F38+F48 -> 0 | G56: =G21+G33+G34+G38+G48 -> 0 | H56: =H21+H33+H34+H38+H48 -> 150 | I56: =I21+I33+I34+I38+I48 -> 475 | ... W56: =W21+W33+W34+W38+W48 -> 12131.717
A57: Innovation + launches as % of revenue | B57: =IF(B54=0,0,(B19+B25+B26+B35+B21+B39+B48)/B54) -> 0.010763534 | C57: =IF(C54=0,0,(C19+C25+C26+C35+C21+C39+C48)/C54) -> 0.028954371 | D57: =IF(D54=0,0,(D19+D25+D26+D35+D21+D39+D48)/D54) -> 0.037607923 | E57: =IF(E54=0,0,(E19+E25+E26+E35+E21+E39+E48)/E54) -> 0.05734307 | F57: =IF(F54=0,0,(F19+F25+F26+F35+F21+F39+F48)/F54) -> 0.067878607 | G57: =IF(G54=0,0,(G19+G25+G26+G35+G21+G39+G48)/G54) -> 0.096028425 | H57: =IF(H54=0,0,(H19+H25+H26+H35+H21+H39+H48)/H54) -> 0.10802005 | I57: =IF(I54=0,0,(I19+I25+I26+I35+I21+I39+I48)/I54) -> 0.1333493 | ... W57: =IF(W54=0,0,(W19+W25+W26+W35+W21+W39+W48)/W54) -> 0.2801091
A59: Reported consolidated revenue | B59: 32517.2 | C59: 34537.1 | D59: 37492.1 | E59: 38216.7
A60: Historical reconciliation difference | B60: =B54-B59 -> 0 | C60: =C54-C59 -> 0 | D60: =D54-D59 -> 0 | E60: =E54-E59 -> 114
A62: RECENT QUARTERLY CONSOLIDATED REVENUE
A63: INR mn | B63: Q1 FY25 | C63: Q2 FY25 | D63: Q3 FY25 | E63: Q4 FY25 | F63: Q1 FY26 | G63: Q2 FY26 | H63: Q3 FY26 | I63: Q4 FY26 | J63: Q1 FY27
A64: Revenue | B64: 8146.5 | C64: 10107.7 | D64: 9494.2 | E64: 9743.7 | F64: 8051.7 | G64: 9799.4 | H64: 10412.6 | I64: 9953 | J64: 9384.4
A66: FY25 quarters difference | B66: =ROUND(SUM(B64:E64)-D54,1) -> 0 | C66: FY26 quarters difference | D66: =ROUND(SUM(F64:I64)-E54,1) -> -114 | E66: FY27 Q1 link difference | F66: =ROUND(J64-F54,1) -> 0

Sheet Assumptions_Sources
A1: GSK India - Single-Case Assumptions, Historical Calibration & Pipeline
A2: As of 14 September 2026. Blue cells are editable analyst assumptions. No bull/base/bear cases are used.
A4: EXISTING PORTFOLIO GROWTH ASSUMPTIONS
A5: Revenue line | B5: FY27E | C5: FY28E | D5: FY29E | E5: FY30-31E | F5: FY32-36E | G5: FY26A basis | H5: Key driver / rationale
A6: Augmentin | B6: 0.08 | C6: 0.07 | D6: 0.06 | E6: 0.055 | F6: 0.045 | G6: Estimated at ₹900cr in FY26 | H6: ₹75-80cr monthly secondary sales reference; price controls and mature volumes cap long-term growth
A7: Ceftum | B7: 0.06 | C7: 0.06 | D7: 0.05 | E7: 0.045 | F7: 0.035 | G7: Estimated within General Medicines | H7: 32.7% represented-market share in Q1 FY27; mature anti-infective
A8: Calpol | B8: 0.05 | C8: 0.07 | D8: 0.06 | E8: 0.05 | F8: 0.04 | G8: Estimated at ₹310cr in FY26 | H8: Q1 FY27 market growth 8.1%; FY27 allows for supply normalisation
A9: Eltroxin | B9: 0.05 | C9: 0.055 | D9: 0.05 | E9: 0.045 | F9: 0.04 | G9: Estimated within General Medicines | H9: Chronic replacement therapy with recurring demand
A10: Dermatology franchise | B10: 0.08 | C10: 0.07 | D10: 0.06 | E10: 0.055 | F10: 0.045 | G10: Includes T-Bact, Betnovate, Tenovate, Neosporin | H10: T-Bact 57.5% represented-market share; category growth and pricing
A11: Vitamins & other general medicines | B11: 0.05 | C11: 0.05 | D11: 0.045 | E11: 0.04 | F11: 0.035 | G11: Residual within reported pharmaceuticals total | H11: Large mature tail; growth below promoted brands
A12: Core paediatric vaccines | B12: 0.1 | C12: 0.09 | D12: 0.08 | E12: 0.07 | F12: 0.055 | G12: Estimated within reported vaccine mix | H12: Private-market leadership; volume-led growth and supply phasing
A13: Seasonal & travel vaccines | B13: 0.08 | C13: 0.08 | D13: 0.07 | E13: 0.06 | F13: 0.05 | G13: Estimated within reported vaccine mix | H13: Influenza/travel seasonality and private immunisation
A14: Shingrix | B14: 0.45 | C14: 0.32 | D14: 0.24 | E14: 0.17 | F14: 0.1 | G14: FY26 estimated at ₹110cr; crossed ₹100cr MAT by Q1 FY27 | H14: Q1 FY27 growth 65%; adult-vaccination category creation fades over time
A15: Other adult vaccines | B15: 0.1 | C15: 0.1 | D15: 0.08 | E15: 0.07 | F15: 0.05 | G15: Residual within reported vaccine mix | H15: Low base; adult immunisation adoption
A16: Trelegy Ellipta | B16: 0.18 | C16: 0.15 | D16: 0.12 | E16: 0.1 | F16: 0.07 | G16: FY26 estimated at ₹62cr | H16: 12% FUV share applied to disclosed ₹513cr SITT market; share and market growth
A17: Nucala | B17: 0.25 | C17: 0.2 | D17: 0.18 | E17: 0.14 | F17: 0.1 | G17: FY26 estimated at ₹25cr | H17: 100-120 new patients per month; severe-asthma diagnosis and affordability
A18: Other respiratory | B18: 0.06 | C18: 0.06 | D18: 0.05 | E18: 0.04 | F18: 0.03 | G18: Residual respiratory portfolio | H18: Mature Seretide/other inhaled portfolio
A20: MARKETED ONCOLOGY AND CONSOLIDATION
A21: Revenue line | B21: FY27E revenue | C21: FY28E growth | D21: FY29E growth | E21: FY30-31E | F21: FY32-36E | G21: Basis | H21: Rationale
A22: Jemperli | B22: 800 | C22: 0.25 | D22: 0.2 | E22: 0.15 | F22: 0.08 | G22: Q1 FY27 oncology run-rate and patient uptake | H22: First-line endometrial cancer; expansion not separately double-counted
A23: Zejula | B23: 400 | C23: 0.15 | D23: 0.1 | E23: 0.05 | F23: 0.02 | G23: Q1 FY27 oncology run-rate and patient uptake | H23: Ovarian maintenance; PARP competition limits long-term growth
A25: Biddle / consolidation revenue | B25: 550 | C25: 0.05 | D25: 0.05 | E25: 0.04 | F25: 0.03 | G25: FY27E annualised from Q1 consolidated less standalone revenue | H25: Keeps subsidiary/consolidation bridge separate from product sales
A28: APPROVED / MANAGEMENT-IDENTIFIED LAUNCHES
A29: Asset | B29: Therapy | C29: Launch FY | D29: Peak India revenue (INR mn) | E29: Ramp years | F29: Post-ramp growth | G29: Launch-year fraction | H29: Q2 share | I29: Q3 share | J29: Basis / status
A30: Arexvy | B30: Adult vaccines | C30: 2027 | D30: 2500 | E30: 6 | F30: 0.03 | G30: 0.5 | H30: 0 | I30: 0.4 | J30: Marketing authorisation received; management indicated launch in coming months
A31: Blenrep | B31: Oncology | C31: 2027 | D31: 2000 | E31: 6 | F31: 0.02 | G31: 0.5 | H31: 0 | I31: 0.4 | J31: CDSCO approved; management guided Q2/Q3 FY27 launch; 7-8k second-line patients
A32: Hibsago / Bepirovirsen | B32: Infectious disease | C32: 2027 | D32: 3500 | E32: 7 | F32: 0.03 | G32: 0.5 | H32: 0 | I32: 0 | J32: Positive Phase III; India launch targeted within three quarters, subject to approvals
A33: Ojjaara | B33: Oncology | C33: 2029 | D33: 1500 | E33: 6 | F33: 0.02 | G33: 0.5 | H33: 0 | I33: 0 | J33: Management-identified upcoming launch over the next 18-24 months
A35: FUTURE PIPELINE - RISK-ADJUSTED REVENUE
A36: Asset | B36: Therapy | C36: Launch FY | D36: Unrisked peak (INR mn) | E36: PoS incl. India rights | F36: Risk-adjusted peak | G36: Ramp years | H36: Post-ramp growth | I36: Launch-year fraction | J36: Rationale
A37: Velzatinib | B37: GIST | C37: 2032 | D37: 800 | E37: 0.55 | F37: =D37*E37 -> 440 | G37: 5 | H37: 0.02 | I37: 0.5 | J37: Phase III; India trial permission supports local development
A38: Mocertatug rezetecan | B38: Ovarian/endometrial cancer | C38: 2033 | D38: 1500 | E38: 0.4 | F38: =D38*E38 -> 600 | G38: 5 | H38: 0.03 | I38: 0.5 | J38: Pivotal program initiated; no India approval
A39: Efimosfermin | B39: MASH / liver disease | C39: 2031 | D39: 2200 | E39: 0.5 | F39: =D39*E39 -> 1100 | G39: 6 | H39: 0.03 | I39: 0.5 | J39: Phase III; potential global launch from 2029, India lag assumed
A40: TSLP (GSK5784283) | B40: Uncontrolled asthma | C40: 2034 | D40: 1000 | E40: 0.3 | F40: =D40*E40 -> 300 | G40: 5 | H40: 0.03 | I40: 0.5 | J40: Phase II; substantial clinical and timing risk
A41: Gatuzosiran / GSK4532990 | B41: Liver disease | C41: 2035 | D41: 1000 | E41: 0.2 | F41: =D41*E41 -> 200 | G41: 5 | H41: 0.03 | I41: 0.5 | J41: Phase II; indication strategy evolving
A42: Camlipixant | B42: Refractory chronic cough | C42: 9999 | D42: 0 | E42: 0 | F42: =D42*E42 -> 0 | G42: 5 | H42: 0 | I42: 0.5 | J42: Development discontinued after Phase III miss; zero revenue
A44: QUARTERLY PHASING
A45: Mature portfolio seasonality (Q1 / Q2 / Q3 / Q4) | B45: 0.214 | C45: 0.263 | D45: 0.263 | E45: 0.26 | F45: Average FY25/FY26 quarterly mix; FY27 Q1 product allocations are estimates constrained to reported totals
A47: FY26 HISTORICAL PRODUCT CALIBRATION
A48: Revenue line | B48: FY26A estimate (INR mn) | C48: Status | D48: Calibration evidence | E48: Reported control | F48: Comment
A49: Augmentin | B49: 9000 | C49: Estimated | D49: Public secondary-sales commentary of ₹75-80cr per month | E49: Reported company total | F49: Secondary sales and company revenue are not identical; estimate normalised
A50: Ceftum | B50: 2300 | C50: Estimated | D50: Q1 FY27 represented-market value share 32.7% | E50: General Medicines total | F50: No audited brand sales disclosed
A51: Calpol | B51: 3100 | C51: Estimated | D51: Public monthly market-sales reference and Q1 FY27 market growth | E51: General Medicines total | F51: No audited brand sales disclosed
A52: Eltroxin | B52: 1700 | C52: Estimated | D52: Chronic brand within promoted portfolio | E52: General Medicines total | F52: No audited brand sales disclosed
A53: Dermatology franchise | B53: 4500 | C53: Estimated | D53: T-Bact 57.5% represented-market value share plus other dermatology brands | E53: General Medicines total | F53: Includes T-Bact, Betnovate, Tenovate, Neosporin and related brands
A54: Vitamins & other general medicines | B54: 8072.7 | C54: Residual estimate | D54: Balances the reported pharmaceutical mix after named products | E54: General Medicines total | F54: Transparent residual, not described as reported brand sales
A55: Core paediatric vaccines | B55: 5200 | C55: Estimated | D55: Private paediatric leadership and portfolio growth disclosures | E55: FY26 vaccines ₹731.5cr | F55: No audited antigen sales disclosed
A56: Seasonal & travel vaccines | B56: 800 | C56: Estimated | D56: Fluarix / Havrix / Menveo portfolio | E56: FY26 vaccines ₹731.5cr | F56: No audited antigen sales disclosed
A57: Shingrix | B57: 1100 | C57: Estimated | D57: Management confirmed >₹100cr MAT by Q1 FY27 | E57: FY26 vaccines ₹731.5cr | F57: Conservative estimate within management floor
A58: Other adult vaccines | B58: 215 | C58: Residual estimate | D58: Balances reported vaccine mix | E58: FY26 vaccines ₹731.5cr | F58: No audited brand sales disclosed
A59: Trelegy Ellipta | B59: 620 | C59: Market-based estimate | D59: 12% FUV share × disclosed ₹513cr SITT market | E59: FY26 pharmaceuticals | F59: Replaces prior ₹170cr overstatement
A60: Nucala | B60: 250 | C60: Patient-based estimate | D60: 100-120 monthly patient additions and 3.5k+ cumulative patients | E60: FY26 pharmaceuticals | F60: Treatment persistence and net pricing remain estimated
... A64: Biddle / consolidation revenue | B64: 315 | C64: Calculated bridge | D64: Consolidated revenue less standalone revenue | E64: FY26 consolidated ₹3,821.7cr | F64: Not other operating revenue and not a balancing product
A67: CLINICAL PIPELINE / CTRI CROSS-CHECK
A68: Asset | B68: Brand / code | C68: Therapy | D68: India indication | E68: Stage / status | F68: India evidence | G68: Expected model launch | H68: Revenue treatment | I68: Key issue | J68: Primary source
A69: Belantamab mafodotin | B69: Blenrep | C69: Oncology | D69: Multiple myeloma | E69: Approved in India | F69: CDSCO approval; company launch preparation | G69: 2027 | H69: Approved launch build | I69: Ocular monitoring and affordability | J69: GSK India Q1 FY27 transcript
A70: Dostarlimab | B70: Jemperli | C70: Oncology | D70: Endometrial cancer | E70: Marketed; expansion trials | F70: India launch and trial permissions | G70: 2026 | H70: Marketed product | I70: Biomarker testing and access | J70: GSK India
A71: Niraparib | B71: Zejula | C71: Oncology | D71: Ovarian maintenance | E71: Marketed | F71: India launch / post-marketing evidence | G71: 2026 | H71: Marketed product | I71: PARP competition | J71: GSK India
A72: Momelotinib | B72: Ojjaara | C72: Oncology | D72: Myelofibrosis | E72: Management-identified launch | F72: Upcoming India launch program | G72: 2029 | H72: Approved/late-stage launch build | I72: India timing and pricing | J72: GSK India Q1 FY27 transcript
A73: Bepirovirsen | B73: Hibsago / GSK3228836 | C73: Infectious disease | D73: Chronic hepatitis B | E73: Phase III positive; filings | F73: Four India trials and company launch roadmap | G73: 2027 | H73: Late-stage launch build | I73: Approval and functional-cure uptake | J73: GSK / CDSCO
A74: Velzatinib | B74: IDRX-42 | C74: Oncology | D74: GIST | E74: Phase III | F74: CDSCO India trial recommendation | G74: 2032 | H74: Risk-adjusted | I74: Clinical success and India rights | J74: CDSCO / GSK
A75: Mocertatug rezetecan | B75: B7-H4 ADC | C75: Oncology | D75: Ovarian/endometrial cancer | E75: Pivotal program | F75: India relevance in disclosed oncology trial bucket | G75: 2033 | H75: Risk-adjusted | I75: Early efficacy must confirm | J75: GSK
A76: Efimosfermin | B76: GSK6519754 | C76: Liver disease | D76: MASH | E76: Phase III | F76: India-relevant global development | G76: 2031 | H76: Risk-adjusted | I76: Large market but affordability | J76: GSK
A77: GSK5784283 | B77: Anti-TSLP | C77: Respiratory | D77: Uncontrolled asthma | E77: Phase II | F77: Global trial / India pipeline disclosure | G77: 2034 | H77: Risk-adjusted | I77: Early stage and competition | J77: GSK / ClinicalTrials.gov
A78: Gatuzosiran | B78: GSK4532990 | C78: Liver disease | D78: MASH / ALD | E78: Phase II | F78: India NASH trial permission | G78: 2035 | H78: Risk-adjusted | I78: Indication strategy evolving | J78: GSK / CDSCO
A80: KEY SOURCES
A81: Data item | B81: Value / conclusion | C81: Source | D81: URL | E81: Class
A82: FY23-FY26 consolidated revenue | B82: Reported annual totals | C82: GSK India annual reports | D82: https://india-pharma.gsk.com/en-in/investors/annual-reports/ | E82: Reported
A83: Q1 FY27 consolidated revenue | B83: ₹938.44cr | C83: GSK India consolidated filing / public release | D83: https://india-pharma.gsk.com/en-in/investors/quarterly-results/ | E83: Reported
A84: Q1 FY27 standalone revenue and innovation mix | B84: ₹924cr; innovation 7% | C84: GSK India Q1 FY27 analyst presentation | D84: https://india-pharma.gsk.com/media/kdghfyzr/analyst-meet-q1-2026-27.pdf | E84: Reported
A85: Launch timing and product commentary | B85: Blenrep, Arexvy, Hibsago, Ojjaara | C85: GSK India Q1 FY27 analyst transcript | D85: https://india-pharma.gsk.com/media/asmha1vh/gsk-q1-fy27-analyst-meet-transcript.pdf | E85: Reported
A86: FY26 mix and 26-trial disclosure | B86: Pharma / vaccines / oncology; trial buckets | C86: GSK India FY26 annual report and May analyst meet | D86: https://india-pharma.gsk.com/media/inhdnswz/analyst-meet-may-2026.pdf | E86: Reported
A87: Augmentin market sales | B87: ₹75-80cr monthly public market-data reference | C87: Economic Times reporting citing market data | D87: https://m.economictimes.com/industry/healthcare/biotech/pharmaceuticals/gsks-antibiotic-drug-augmentin-is-indias-highest-selling-drug/articleshow/118333583.cms | E87: Market data / estimate basis
A88: CTRI access | B88: Registry requires search validation | C88: Clinical Trials Registry - India | D88: https://ctri.nic.in/Clinicaltrials/advancesearchmain.php | E88: Reported limitation
A89: Pipeline revenue | B89: Launch, peak and PoS assumptions | C89: Analyst estimates constrained by company pipeline disclosures | D89: N/A | E89: Estimated
A92: MODEL LIMITATIONS AND UPDATE ITEMS
A93: • Historical brand revenue remains estimated because GSK India does not disclose audited brand sales. Reported consolidated totals and disclosed business mix are the hard controls.
A94: • Q1 FY27 product values are estimates constrained to reported standalone revenue, 7% innovation mix and disclosed market/patient indicators; the consolidated total is reported.
A95: • Secondary-market sales do not equal company-recognised revenue. Replace estimates with IQVIA/PharmaTrac brand sales and channel adjustments when available.
A96: • Approved and management-identified launches are modeled separately from early pipeline. Early pipeline uses probability-adjusted India revenue and should be refreshed after pivotal data, filing, approval, pricing or rights changes.
A97: • The 26-company-disclosed figure is a trial count, not a molecule count. CTRI validation is cross-checked with GSK, CDSCO and global registries where direct record extraction is restricted.

Sheet Financial_Assumptions
A1: GSK India - Financial Assumptions
A2: INR million unless stated otherwise | Single forecast case | Blue cells are editable forecast inputs
A4: Forecast assumption anchors
A5: Driver | B5: FY2027E | C5: FY2028E-FY2030E | D5: FY2031E-FY2036E | F5: Rationale / reference
A6: Gross margin | B6: 0.65 | C6: 0.658 | D6: 0.662 | F6: FY23-FY26 gross margin improved materially; only modest additional mix benefit is assumed from specialty, oncology and vaccines.
A7: Employee expenses / revenue | B7: 0.16 | C7: 0.158 | D7: 0.153 | F7: Near-term commercial investment is retained, followed by gradual operating leverage.
A8: Other operating expenses / revenue | B8: 0.147 | C8: 0.144 | D8: 0.14 | F8: Allows launch/royalty/commercial investment near term, then modest operating leverage.
A9: Effective tax rate | B9: 0.263 | C9: 0.263 | D9: 0.263 | F9: Normalized near recent reported effective tax rates; no one-off tax benefit assumed.
A10: Interest rate on borrowings / lease liabilities | B10: 0.08 | C10: 0.08 | D10: 0.08 | F10: Simple effective rate on opening borrowings and lease liabilities.
A11: Yield on opening cash + investments | B11: 0.06 | C11: 0.06 | D11: 0.06 | F11: Conservative yield on opening cash plus financial investments.
A12: Dividend payout ratio | B12: 0.92 | C12: 0.9 | D12: 0.88 | F12: Starts near recent ordinary payout and moderates modestly as growth investment increases.
A13: Capex / revenue | B13: 0.012 | C13: 0.011 | D13: 0.01 | F13: Simple maintenance / reinvestment assumption based on recent low capex intensity.
A14: Inventory days | B14: 124 | C14: 122 | D14: 120 | F14: Normalizes around the recent historical range with modest efficiency.
A15: Receivable days | B15: 27 | C15: 26 | D15: 25 | F15: Stable collections with modest normalization.
A16: Payable days | B16: 158 | C16: 160 | D16: 160 | F16: Modest normalization around recent levels.
A17: Other assets / revenue | B17: 0.13 | C17: 0.128 | D17: 0.125 | F17: Gradual normalization versus recent historical levels.
... A20: Depreciation / opening net fixed assets | B20: 0.2 | C20: 0.195 | D20: 0.19 | F20: Links D&A to the opening fixed-asset base and trends modestly lower over time.
A23: Applied annual assumptions (formula-driven interpolation)
A24: Driver | B24: FY2027E | C24: FY2028E | D24: FY2029E | E24: FY2030E | F24: FY2031E | G24: FY2032E | H24: FY2033E | I24: FY2034E | J24: FY2035E | K24: FY2036E
A25: Gross margin | B25: =$B$6 -> 0.65 | C25: =$B$6+($C$6-$B$6)*1/3 -> 0.65266667 | D25: =$B$6+($C$6-$B$6)*2/3 -> 0.65533333 | E25: =$B$6+($C$6-$B$6)*3/3 -> 0.658 | F25: =$C$6+($D$6-$C$6)*1/6 -> 0.65866667 | G25: =$C$6+($D$6-$C$6)*2/6 -> 0.65933333 | H25: =$C$6+($D$6-$C$6)*3/6 -> 0.66 | I25: =$C$6+($D$6-$C$6)*4/6 -> 0.66066667 | J25: =$C$6+($D$6-$C$6)*5/6 -> 0.66133333 | K25: =$C$6+($D$6-$C$6)*6/6 -> 0.662
A26: Employee expenses / revenue | B26: =$B$7 -> 0.16 | C26: =$B$7+($C$7-$B$7)*1/3 -> 0.15933333 | D26: =$B$7+($C$7-$B$7)*2/3 -> 0.15866667 | E26: =$B$7+($C$7-$B$7)*3/3 -> 0.158 | F26: =$C$7+($D$7-$C$7)*1/6 -> 0.15716667 | G26: =$C$7+($D$7-$C$7)*2/6 -> 0.15633333 | H26: =$C$7+($D$7-$C$7)*3/6 -> 0.1555 | I26: =$C$7+($D$7-$C$7)*4/6 -> 0.15466667 | J26: =$C$7+($D$7-$C$7)*5/6 -> 0.15383333 | K26: =$C$7+($D$7-$C$7)*6/6 -> 0.153
A27: Other operating expenses / revenue | B27: =$B$8 -> 0.147 | C27: =$B$8+($C$8-$B$8)*1/3 -> 0.146 | D27: =$B$8+($C$8-$B$8)*2/3 -> 0.145 | E27: =$B$8+($C$8-$B$8)*3/3 -> 0.144 | F27: =$C$8+($D$8-$C$8)*1/6 -> 0.14333333 | G27: =$C$8+($D$8-$C$8)*2/6 -> 0.14266667 | H27: =$C$8+($D$8-$C$8)*3/6 -> 0.142 | I27: =$C$8+($D$8-$C$8)*4/6 -> 0.14133333 | J27: =$C$8+($D$8-$C$8)*5/6 -> 0.14066667 | K27: =$C$8+($D$8-$C$8)*6/6 -> 0.14
A28: Effective tax rate | B28: =$B$9 -> 0.263 | C28: =$B$9+($C$9-$B$9)*1/3 -> 0.263 | D28: =$B$9+($C$9-$B$9)*2/3 -> 0.263 | E28: =$B$9+($C$9-$B$9)*3/3 -> 0.263 | F28: =$C$9+($D$9-$C$9)*1/6 -> 0.263 | G28: =$C$9+($D$9-$C$9)*2/6 -> 0.263 | H28: =$C$9+($D$9-$C$9)*3/6 -> 0.263 | I28: =$C$9+($D$9-$C$9)*4/6 -> 0.263 | J28: =$C$9+($D$9-$C$9)*5/6 -> 0.263 | K28: =$C$9+($D$9-$C$9)*6/6 -> 0.263
A29: Interest rate on borrowings / lease liabilities | B29: =$B$10 -> 0.08 | C29: =$B$10+($C$10-$B$10)*1/3 -> 0.08 | D29: =$B$10+($C$10-$B$10)*2/3 -> 0.08 | E29: =$B$10+($C$10-$B$10)*3/3 -> 0.08 | F29: =$C$10+($D$10-$C$10)*1/6 -> 0.08 | G29: =$C$10+($D$10-$C$10)*2/6 -> 0.08 | H29: =$C$10+($D$10-$C$10)*3/6 -> 0.08 | I29: =$C$10+($D$10-$C$10)*4/6 -> 0.08 | J29: =$C$10+($D$10-$C$10)*5/6 -> 0.08 | K29: =$C$10+($D$10-$C$10)*6/6 -> 0.08
A30: Yield on opening cash + investments | B30: =$B$11 -> 0.06 | C30: =$B$11+($C$11-$B$11)*1/3 -> 0.06 | D30: =$B$11+($C$11-$B$11)*2/3 -> 0.06 | E30: =$B$11+($C$11-$B$11)*3/3 -> 0.06 | F30: =$C$11+($D$11-$C$11)*1/6 -> 0.06 | G30: =$C$11+($D$11-$C$11)*2/6 -> 0.06 | H30: =$C$11+($D$11-$C$11)*3/6 -> 0.06 | I30: =$C$11+($D$11-$C$11)*4/6 -> 0.06 | J30: =$C$11+($D$11-$C$11)*5/6 -> 0.06 | K30: =$C$11+($D$11-$C$11)*6/6 -> 0.06
A31: Dividend payout ratio | B31: =$B$12 -> 0.92 | C31: =$B$12+($C$12-$B$12)*1/3 -> 0.91333333 | D31: =$B$12+($C$12-$B$12)*2/3 -> 0.90666667 | E31: =$B$12+($C$12-$B$12)*3/3 -> 0.9 | F31: =$C$12+($D$12-$C$12)*1/6 -> 0.89666667 | G31: =$C$12+($D$12-$C$12)*2/6 -> 0.89333333 | H31: =$C$12+($D$12-$C$12)*3/6 -> 0.89 | I31: =$C$12+($D$12-$C$12)*4/6 -> 0.88666667 | J31: =$C$12+($D$12-$C$12)*5/6 -> 0.88333333 | K31: =$C$12+($D$12-$C$12)*6/6 -> 0.88
A32: Capex / revenue | B32: =$B$13 -> 0.012 | C32: =$B$13+($C$13-$B$13)*1/3 -> 0.011666667 | D32: =$B$13+($C$13-$B$13)*2/3 -> 0.011333333 | E32: =$B$13+($C$13-$B$13)*3/3 -> 0.011 | F32: =$C$13+($D$13-$C$13)*1/6 -> 0.010833333 | G32: =$C$13+($D$13-$C$13)*2/6 -> 0.010666667 | H32: =$C$13+($D$13-$C$13)*3/6 -> 0.0105 | I32: =$C$13+($D$13-$C$13)*4/6 -> 0.010333333 | J32: =$C$13+($D$13-$C$13)*5/6 -> 0.010166667 | K32: =$C$13+($D$13-$C$13)*6/6 -> 0.01
A33: Inventory days | B33: =$B$14 -> 124 | C33: =$B$14+($C$14-$B$14)*1/3 -> 123.33333 | D33: =$B$14+($C$14-$B$14)*2/3 -> 122.66667 | E33: =$B$14+($C$14-$B$14)*3/3 -> 122 | F33: =$C$14+($D$14-$C$14)*1/6 -> 121.66667 | G33: =$C$14+($D$14-$C$14)*2/6 -> 121.33333 | H33: =$C$14+($D$14-$C$14)*3/6 -> 121 | I33: =$C$14+($D$14-$C$14)*4/6 -> 120.66667 | J33: =$C$14+($D$14-$C$14)*5/6 -> 120.33333 | K33: =$C$14+($D$14-$C$14)*6/6 -> 120
A34: Receivable days | B34: =$B$15 -> 27 | C34: =$B$15+($C$15-$B$15)*1/3 -> 26.666667 | D34: =$B$15+($C$15-$B$15)*2/3 -> 26.333333 | E34: =$B$15+($C$15-$B$15)*3/3 -> 26 | F34: =$C$15+($D$15-$C$15)*1/6 -> 25.833333 | G34: =$C$15+($D$15-$C$15)*2/6 -> 25.666667 | H34: =$C$15+($D$15-$C$15)*3/6 -> 25.5 | I34: =$C$15+($D$15-$C$15)*4/6 -> 25.333333 | J34: =$C$15+($D$15-$C$15)*5/6 -> 25.166667 | K34: =$C$15+($D$15-$C$15)*6/6 -> 25
A35: Payable days | B35: =$B$16 -> 158 | C35: =$B$16+($C$16-$B$16)*1/3 -> 158.66667 | D35: =$B$16+($C$16-$B$16)*2/3 -> 159.33333 | E35: =$B$16+($C$16-$B$16)*3/3 -> 160 | F35: =$C$16+($D$16-$C$16)*1/6 -> 160 | G35: =$C$16+($D$16-$C$16)*2/6 -> 160 | H35: =$C$16+($D$16-$C$16)*3/6 -> 160 | I35: =$C$16+($D$16-$C$16)*4/6 -> 160 | J35: =$C$16+($D$16-$C$16)*5/6 -> 160 | K35: =$C$16+($D$16-$C$16)*6/6 -> 160
A36: Other assets / revenue | B36: =$B$17 -> 0.13 | C36: =$B$17+($C$17-$B$17)*1/3 -> 0.12933333 | D36: =$B$17+($C$17-$B$17)*2/3 -> 0.12866667 | E36: =$B$17+($C$17-$B$17)*3/3 -> 0.128 | F36: =$C$17+($D$17-$C$17)*1/6 -> 0.1275 | G36: =$C$17+($D$17-$C$17)*2/6 -> 0.127 | H36: =$C$17+($D$17-$C$17)*3/6 -> 0.1265 | I36: =$C$17+($D$17-$C$17)*4/6 -> 0.126 | J36: =$C$17+($D$17-$C$17)*5/6 -> 0.1255 | K36: =$C$17+($D$17-$C$17)*6/6 -> 0.125
A37: Other liabilities + provisions / revenue | B37: =$B$18 -> 0.38 | C37: =$B$18+($C$18-$B$18)*1/3 -> 0.37833333 | D37: =$B$18+($C$18-$B$18)*2/3 -> 0.37666667 | E37: =$B$18+($C$18-$B$18)*3/3 -> 0.375 | F37: =$C$18+($D$18-$C$18)*1/6 -> 0.37416667 | G37: =$C$18+($D$18-$C$18)*2/6 -> 0.37333333 | H37: =$C$18+($D$18-$C$18)*3/6 -> 0.3725 | I37: =$C$18+($D$18-$C$18)*4/6 -> 0.37166667 | J37: =$C$18+($D$18-$C$18)*5/6 -> 0.37083333 | K37: =$C$18+($D$18-$C$18)*6/6 -> 0.37
A38: Borrowings + lease liabilities (INR mn) | B38: =$B$19 -> 332.7 | C38: =$B$19+($C$19-$B$19)*1/3 -> 332.7 | D38: =$B$19+($C$19-$B$19)*2/3 -> 332.7 | E38: =$B$19+($C$19-$B$19)*3/3 -> 332.7 | F38: =$C$19+($D$19-$C$19)*1/6 -> 332.7 | G38: =$C$19+($D$19-$C$19)*2/6 -> 332.7 | H38: =$C$19+($D$19-$C$19)*3/6 -> 332.7 | I38: =$C$19+($D$19-$C$19)*4/6 -> 332.7 | J38: =$C$19+($D$19-$C$19)*5/6 -> 332.7 | K38: =$C$19+($D$19-$C$19)*6/6 -> 332.7
A39: Depreciation / opening net fixed assets | B39: =$B$20 -> 0.2 | C39: =$B$20+($C$20-$B$20)*1/3 -> 0.19833333 | D39: =$B$20+($C$20-$B$20)*2/3 -> 0.19666667 | E39: =$B$20+($C$20-$B$20)*3/3 -> 0.195 | F39: =$C$20+($D$20-$C$20)*1/6 -> 0.19416667 | G39: =$C$20+($D$20-$C$20)*2/6 -> 0.19333333 | H39: =$C$20+($D$20-$C$20)*3/6 -> 0.1925 | I39: =$C$20+($D$20-$C$20)*4/6 -> 0.19166667 | J39: =$C$20+($D$20-$C$20)*5/6 -> 0.19083333 | K39: =$C$20+($D$20-$C$20)*6/6 -> 0.19
A41: Quarterly P&L phasing
A42: FY27 Q1 uses reported consolidated actual P&L line items; Q2-Q4 forecasts allocate the residual FY27 annual target by quarterly revenue / PBT share. FY28 quarterly forecasts phase the existing annual target by quarterly revenue / PBT share. FY27/FY28 annual forecast totals are unchanged.
A43: Historical sources
A44: Document | B44: Reporting period | C44: Relevant page / note | D44: URL
A45: FY2025-26 audited consolidated financial results | B45: Year ended 31 Mar 2026 | C45: Consolidated P&L pp.2-3; balance sheet p.5; cash flow p.6 | D45: https://india-pharma.gsk.com/media/vavjd3ru/outcome-of-board-meeting-13-may-26.pdf
A46: GSK India Annual Report 2024-25 | B46: Year ended 31 Mar 2025 | C46: Consolidated balance sheet p.194; P&L p.195; cash flow p.196 | D46: https://india-pharma.gsk.com/media/a4jaso1n/annual-report-2024-25.pdf
A47: GSK India Annual Report 2023-24 | B47: Year ended 31 Mar 2024 | C47: Consolidated balance sheet p.189; P&L p.190; cash flow pp.191-192 | D47: https://india-pharma.gsk.com/media/4ysjvjwl/annual-report-2023-24.pdf
A48: Existing revenue model | B48: FY2023A-FY2036E | C48: Reported consolidated revenue row 59 (FY23-FY26); Consolidated revenue row 54 (FY27-FY36) | D48: Revenue_Model sheet in this workbook
A49: Q1 FY2026-27 consolidated financial results | B49: Quarter ended 30 Jun 2026 | C49: Consolidated unaudited financial results; INR lakh converted to INR million (divide by 10) | D49: https://india-pharma.gsk.com/en-in/investors/quarterly-results/
A51: Model note: forecast cash is calculated only through the cash-flow statement; debt and investments are explicit assumptions and are never used as balance-sheet plugs.

Sheet Profit_Loss
A1: GSK India - Consolidated Profit & Loss
A2: INR million except per-share data | FY2023A-FY2026A annual actuals | FY27/FY28 quarterly build | FY29E-FY36E annual estimates
A4: Consolidated Profit & Loss
A5: Fiscal period | B5: FY2023A | C5: FY2024A | D5: FY2025A | E5: FY2026A | F5: Q1 FY27A* | G5: Q2 FY27E | H5: Q3 FY27E | I5: Q4 FY27E | J5: FY2027E | K5: Q1 FY28E | L5: Q2 FY28E | M5: Q3 FY28E | N5: Q4 FY28E | O5: FY2028E | P5: FY2029E | Q5: FY2030E | R5: FY2031E | S5: FY2032E | T5: FY2033E | U5: FY2034E | V5: FY2035E | W5: FY2036E
A6: Period | B6: Actual | C6: Actual | D6: Actual | E6: Actual | F6: Actual* | G6: Estimate | H6: Estimate | I6: Estimate | J6: Cumulative E | K6: Estimate | L6: Estimate | M6: Estimate | N6: Estimate | O6: Cumulative E | P6: Estimate | Q6: Estimate | R6: Estimate | S6: Estimate | T6: Estimate | U6: Estimate | V6: Estimate | W6: Estimate
A8: Revenue from operations | B8: =Revenue_Model!B59 -> 32517.2 | C8: =Revenue_Model!C59 -> 34537.1 | D8: =Revenue_Model!D59 -> 37492.1 | E8: =Revenue_Model!E59 -> 38216.7 | F8: =Revenue_Model!F54 -> 9384.4 | G8: =Revenue_Model!G54 -> 11157.536 | H8: =Revenue_Model!H54 -> 11307.536 | I8: =Revenue_Model!I54 -> 11505.263 | J8: =Revenue_Model!J54 -> 43354.735 | K8: =Revenue_Model!K54 -> 10305.879 | L8: =Revenue_Model!L54 -> 12665.637 | M8: =Revenue_Model!M54 -> 12665.637 | ... W8: =Revenue_Model!W54 -> 83397.532
A9: YoY growth | B9: - | C9: =C8/B8-1 -> 0.062117895 | D9: =D8/C8-1 -> 0.085560166 | E9: =E8/D8-1 -> 0.019326738 | F9: =F8/Revenue_Model!F64-1 -> 0.16551784 | G9: =G8/Revenue_Model!G64-1 -> 0.13859377 | H9: =H8/Revenue_Model!H64-1 -> 0.085947387 | I9: =I8/Revenue_Model!I64-1 -> 0.15595936 | J9: =J8/E8-1 -> 0.13444476 | K9: =K8/F8-1 -> 0.098192677 | L9: =L8/G8-1 -> 0.13516435 | M9: =M8/H8-1 -> 0.12010583 | N9: =N8/I8-1 -> 0.088298573 | O9: =O8/J8-1 -> 0.11079712 | P9: =P8/O8-1 -> 0.098211082 | Q9: =Q8/P8-1 -> 0.087006236 | R9: =R8/Q8-1 -> 0.085917941 | S9: =S8/R8-1 -> 0.071198486 | T9: =T8/S8-1 -> 0.064645373 | U9: =U8/T8-1 -> 0.057050541 | V9: =V8/U8-1 -> 0.053333537 | W9: =W8/V8-1 -> 0.052035677
A11: Cost of goods sold | B11: 12848.764 | C11: 13345.266 | D11: 13908.57 | E11: 13510.6 | F11: 3279.4 | G11: =($J11-$F11)*G$8/SUM($G$8:$I$8) -> 3906.8257 | H11: =($J11-$F11)*H$8/SUM($G$8:$I$8) -> 3959.3484 | I11: =($J11-$F11)*I$8/SUM($G$8:$I$8) -> 4028.5831 | J11: =J8*(1-Financial_Assumptions!B$25) -> 15174.157 | K11: =$O11*K$8/$O$8 -> 3579.5754 | L11: =$O11*L$8/$O$8 -> 4399.1978 | M11: =$O11*M$8/$O$8 -> 4399.1978 | N11: =$O11*N$8/$O$8 -> 4349.0169 | O11: =O8*(1-Financial_Assumptions!C$25) -> 16726.988 | P11: =P8*(1-Financial_Assumptions!D$25) -> 18228.729 | Q11: =Q8*(1-Financial_Assumptions!E$25) -> 19661.436 | R11: =R8*(1-Financial_Assumptions!F$25) -> 21309.087 | S11: =S8*(1-Financial_Assumptions!G$25) -> 22781.679 | T11: =T8*(1-Financial_Assumptions!H$25) -> 24206.945 | U11: =U8*(1-Financial_Assumptions!I$25) -> 25537.792 | V11: =V8*(1-Financial_Assumptions!J$25) -> 26846.964 | W11: =W8*(1-Financial_Assumptions!K$25) -> 28188.366
A12: Gross profit | B12: =B8-B11 -> 19668.436 | C12: =C8-C11 -> 21191.834 | D12: =D8-D11 -> 23583.53 | E12: =E8-E11 -> 24706.1 | F12: =F8-F11 -> 6105 | G12: =G8-G11 -> 7250.71 | H12: =H8-H11 -> 7348.1873 | I12: =I8-I11 -> 7476.6804 | ... W12: =W8-W11 -> 55209.166
A13: Gross margin | B13: =B12/B8 -> 0.60486253 | C13: =C12/C8 -> 0.61359622 | D13: =D12/D8 -> 0.62902665 | E13: =E12/E8 -> 0.64647392 | F13: =F12/F8 -> 0.65054772 | G13: =G12/G8 -> 0.64984869 | H13: =H12/H8 -> 0.64984869 | I13: =I12/I8 -> 0.64984869 | ... W13: =W12/W8 -> 0.662
A15: Employee expenses | B15: 5949.857 | C15: 6243.903 | D15: 5797.022 | E15: 6072.5 | F15: 1590.4 | G15: =($J15-$F15)*G$8/SUM($G$8:$I$8) -> 1756.0079 | H15: =($J15-$F15)*H$8/SUM($G$8:$I$8) -> 1779.6154 | I15: =($J15-$F15)*I$8/SUM($G$8:$I$8) -> 1810.7344 | J15: =J8*Financial_Assumptions!B$26 -> 6936.7576 | K15: =$O15*K$8/$O$8 -> 1642.0701 | L15: =$O15*L$8/$O$8 -> 2018.0581 | M15: =$O15*M$8/$O$8 -> 2018.0581 | N15: =$O15*N$8/$O$8 -> 1995.0385 | O15: =O8*Financial_Assumptions!C$26 -> 7673.2248 | P15: =P8*Financial_Assumptions!D$26 -> 8391.5619 | Q15: =Q8*Financial_Assumptions!E$26 -> 9083.3537 | R15: =R8*Financial_Assumptions!F$26 -> 9811.7526 | S15: =S8*Financial_Assumptions!G$26 -> 10454.606 | T15: =T8*Financial_Assumptions!H$26 -> 11071.118 | U15: =U8*Financial_Assumptions!I$26 -> 11640.015 | V15: =V8*Financial_Assumptions!J$26 -> 12194.758 | W15: =W8*Financial_Assumptions!K$26 -> 12759.822
A16: Other operating expenses | B16: 5675.746 | C16: 5861.014 | D16: 6012.88 | E16: 5541.6 | F16: 1559.6 | G16: =($J16-$F16)*G$8/SUM($G$8:$I$8) -> 1581.0063 | H16: =($J16-$F16)*H$8/SUM($G$8:$I$8) -> 1602.261 | I16: =($J16-$F16)*I$8/SUM($G$8:$I$8) -> 1630.2788 | J16: =J8*Financial_Assumptions!B$27 -> 6373.146 | K16: =$O16*K$8/$O$8 -> 1504.6584 | L16: =$O16*L$8/$O$8 -> 1849.183 | M16: =$O16*M$8/$O$8 -> 1849.183 | N16: =$O16*N$8/$O$8 -> 1828.0896 | O16: =O8*Financial_Assumptions!C$27 -> 7031.114 | P16: =P8*Financial_Assumptions!D$27 -> 7668.7593 | Q16: =Q8*Financial_Assumptions!E$27 -> 8278.4996 | R16: =R8*Financial_Assumptions!F$27 -> 8948.1519 | S16: =S8*Financial_Assumptions!G$27 -> 9540.6642 | T16: =T8*Financial_Assumptions!H$27 -> 10109.959 | U16: =U8*Financial_Assumptions!I$27 -> 10636.566 | V16: =V8*Financial_Assumptions!J$27 -> 11151.003 | W16: =W8*Financial_Assumptions!K$27 -> 11675.655
A17: EBITDA | B17: =B12-B15-B16 -> 8042.833 | C17: =C12-C15-C16 -> 9086.917 | D17: =D12-D15-D16 -> 11773.628 | E17: =E12-E15-E16 -> 13092 | F17: =F12-F15-F16 -> 2955 | G17: =G12-G15-G16 -> 3913.6959 | H17: =H12-H15-H16 -> 3966.3109 | I17: =I12-I15-I16 -> 4035.6673 | ... W17: =W12-W15-W16 -> 30773.689
A18: EBITDA margin | B18: =B17/B8 -> 0.24734088 | C18: =C17/C8 -> 0.26310596 | D18: =D17/D8 -> 0.31402957 | E18: =E17/E8 -> 0.34257275 | F18: =F17/F8 -> 0.31488428 | G18: =G17/G8 -> 0.35076705 | H18: =H17/H8 -> 0.35076705 | I18: =I17/I8 -> 0.35076705 | ... W18: =W17/W8 -> 0.369
A20: Depreciation and amortization | B20: 657.672 | C20: 696.796 | D20: 667.925 | E20: 664.4 | F20: 158.4 | G20: =($J20-$F20)*G$8/SUM($G$8:$I$8) -> 154.01649 | H20: =($J20-$F20)*H$8/SUM($G$8:$I$8) -> 156.08706 | I20: =($J20-$F20)*I$8/SUM($G$8:$I$8) -> 158.81645 | J20: =Schedules_Checks!F10 -> 627.32 | K20: =$O20*K$8/$O$8 -> 128.58364 | L20: =$O20*L$8/$O$8 -> 158.02569 | M20: =$O20*M$8/$O$8 -> 158.02569 | N20: =$O20*N$8/$O$8 -> 156.22312 | O20: =Schedules_Checks!G10 -> 600.85814 | P20: =Schedules_Checks!H10 -> 588.13672 | Q20: =Schedules_Checks!I10 -> 585.34832 | R20: =Schedules_Checks!J10 -> 591.97986 | S20: =Schedules_Checks!K10 -> 605.74374 | T20: =Schedules_Checks!L10 -> 623.84134 | U20: =Schedules_Checks!M10 -> 644.85489 | V20: =Schedules_Checks!N10 -> 667.39738 | W20: =Schedules_Checks!O10 -> 690.80558
A21: EBIT | B21: =B17-B20 -> 7385.161 | C21: =C17-C20 -> 8390.121 | D21: =D17-D20 -> 11105.703 | E21: =E17-E20 -> 12427.6 | F21: =F17-F20 -> 2796.6 | G21: =G17-G20 -> 3759.6794 | H21: =H17-H20 -> 3810.2239 | I21: =I17-I20 -> 3876.8508 | ... W21: =W17-W20 -> 30082.884
A22: EBIT margin | B22: =B21/B8 -> 0.22711553 | C22: =C21/C8 -> 0.24293067 | D22: =D21/D8 -> 0.29621448 | E22: =E21/E8 -> 0.32518768 | F22: =F21/F8 -> 0.2980052 | G22: =G21/G8 -> 0.33696324 | H22: =H21/H8 -> 0.33696324 | I22: =I21/I8 -> 0.33696324 | ... W22: =W21/W8 -> 0.36071671
A24: Finance costs | B24: 18.122 | C24: 17.987 | D24: 13.137 | E24: 27.3 | F24: 9.7 | G24: =($J24-$F24)*G$8/SUM($G$8:$I$8) -> 5.5560499 | H24: =($J24-$F24)*H$8/SUM($G$8:$I$8) -> 5.6307444 | I24: =($J24-$F24)*I$8/SUM($G$8:$I$8) -> 5.7292057 | J24: =Balance_Sheet!E22*Financial_Assumptions!B$29 -> 26.616 | K24: =$O24*K$8/$O$8 -> 5.695824 | L24: =$O24*L$8/$O$8 -> 7.000008 | M24: =$O24*M$8/$O$8 -> 7.000008 | N24: =$O24*N$8/$O$8 -> 6.92016 | O24: =Balance_Sheet!F22*Financial_Assumptions!C$29 -> 26.616 | P24: =Balance_Sheet!G22*Financial_Assumptions!D$29 -> 26.616 | Q24: =Balance_Sheet!H22*Financial_Assumptions!E$29 -> 26.616 | R24: =Balance_Sheet!I22*Financial_Assumptions!F$29 -> 26.616 | S24: =Balance_Sheet!J22*Financial_Assumptions!G$29 -> 26.616 | T24: =Balance_Sheet!K22*Financial_Assumptions!H$29 -> 26.616 | U24: =Balance_Sheet!L22*Financial_Assumptions!I$29 -> 26.616 | V24: =Balance_Sheet!M22*Financial_Assumptions!J$29 -> 26.616 | W24: =Balance_Sheet!N22*Financial_Assumptions!K$29 -> 26.616
A25: Other income | B25: 1006.61 | C25: 1225.937 | D25: 1459.295 | E25: 1453.6 | F25: 437.6 | G25: =($J25-$F25)*G$8/SUM($G$8:$I$8) -> 404.68578 | H25: =($J25-$F25)*H$8/SUM($G$8:$I$8) -> 410.1263 | I25: =($J25-$F25)*I$8/SUM($G$8:$I$8) -> 417.29792 | J25: =(Balance_Sheet!E13+Balance_Sheet!E10)*Financial_Assumptions!B$30 -> 1669.71 | K25: =$O25*K$8/$O$8 -> 384.67526 | L25: =$O25*L$8/$O$8 -> 472.75511 | M25: =$O25*M$8/$O$8 -> 472.75511 | N25: =$O25*N$8/$O$8 -> 467.36247 | O25: =(Balance_Sheet!F13+Balance_Sheet!F10)*Financial_Assumptions!C$30 -> 1797.5479 | P25: =(Balance_Sheet!G13+Balance_Sheet!G10)*Financial_Assumptions!D$30 -> 1931.3054 | Q25: =(Balance_Sheet!H13+Balance_Sheet!H10)*Financial_Assumptions!E$30 -> 2075.196 | R25: =(Balance_Sheet!I13+Balance_Sheet!I10)*Financial_Assumptions!F$30 -> 2230.5441 | S25: =(Balance_Sheet!J13+Balance_Sheet!J10)*Financial_Assumptions!G$30 -> 2399.0339 | T25: =(Balance_Sheet!K13+Balance_Sheet!K10)*Financial_Assumptions!H$30 -> 2572.5031 | U25: =(Balance_Sheet!L13+Balance_Sheet!L10)*Financial_Assumptions!I$30 -> 2756.5359 | V25: =(Balance_Sheet!M13+Balance_Sheet!M10)*Financial_Assumptions!J$30 -> 2949.9707 | W25: =(Balance_Sheet!N13+Balance_Sheet!N10)*Financial_Assumptions!K$30 -> 3156.2903
A26: Profit before exceptional items | B26: =B21-B24+B25 -> 8373.649 | C26: =C21-C24+C25 -> 9598.071 | D26: =D21-D24+D25 -> 12551.861 | E26: =E21-E24+E25 -> 13853.9 | F26: =F21-F24+F25 -> 3224.5 | G26: =G21-G24+G25 -> 4158.8091 | H26: =H21-H24+H25 -> 4214.7194 | I26: =I21-I24+I25 -> 4288.4196 | ... W26: =W21-W24+W25 -> 33212.558
A27: Exceptional items | B27: -9.679 | C27: -1436.154 | D27: 46.919 | E27: 206.2 | F27: =0 -> 0 | G27: =0 -> 0 | H27: =0 -> 0 | I27: =0 -> 0 | J27: =0 -> 0 | K27: =0 -> 0 | L27: =0 -> 0 | M27: =0 -> 0 | ... W27: =0 -> 0
A28: Profit before tax | B28: =B26+B27 -> 8363.97 | C28: =C26+C27 -> 8161.917 | D28: =D26+D27 -> 12598.78 | E28: =E26+E27 -> 14060.1 | F28: =F26+F27 -> 3224.5 | G28: =G26+G27 -> 4158.8091 | H28: =H26+H27 -> 4214.7194 | I28: =I26+I27 -> 4288.4196 | ... W28: =W26+W27 -> 33212.558
A30: Tax expense | B30: 2287.578 | C30: 2262.269 | D30: 3322.955 | E30: 3700.3 | F30: 852.7 | G30: =($J30-$F30)*G28/SUM($G$28:$I$28) -> 1092.2374 | H30: =($J30-$F30)*H28/SUM($G$28:$I$28) -> 1106.9212 | I30: =($J30-$F30)*I28/SUM($G$28:$I$28) -> 1126.2773 | J30: =J28*Financial_Assumptions!B$28 -> 4178.1359 | K30: =$O$30*K28/$O$28 -> 1007.2824 | L30: =$O$30*L28/$O$28 -> 1237.9219 | M30: =$O$30*M28/$O$28 -> 1237.9219 | N30: =$O$30*N28/$O$28 -> 1223.8011 | O30: =O28*Financial_Assumptions!C$28 -> 4706.9273 | P30: =P28*Financial_Assumptions!D$28 -> 5237.7758 | Q30: =Q28*Financial_Assumptions!E$28 -> 5767.4644 | R30: =R28*Financial_Assumptions!F$28 -> 6304.6158 | S30: =S28*Financial_Assumptions!G$28 -> 6802.1107 | T30: =T28*Financial_Assumptions!H$28 -> 7293.2322 | U30: =U28*Financial_Assumptions!I$28 -> 7766.2351 | V30: =V28*Financial_Assumptions!J$28 -> 8241.3061 | W30: =W28*Financial_Assumptions!K$28 -> 8734.9028
A31: Effective tax rate | B31: =B30/B28 -> 0.27350385 | C31: =C30/C28 -> 0.27717373 | D31: =D30/D28 -> 0.26375213 | E31: =E30/E28 -> 0.26317736 | F31: =F30/F28 -> 0.2644441 | G31: =G30/G28 -> 0.26263224 | H31: =H30/H28 -> 0.26263224 | I31: =I30/I28 -> 0.26263224 | ... W31: =W30/W28 -> 0.263
A32: Profit after tax | B32: =B28-B30 -> 6076.392 | C32: =C28-C30 -> 5899.648 | D32: =D28-D30 -> 9275.825 | E32: =E28-E30 -> 10359.8 | F32: =F28-F30 -> 2371.8 | G32: =G28-G30 -> 3066.5717 | H32: =H28-H30 -> 3107.7982 | I32: =I28-I30 -> 3162.1423 | ... W32: =W28-W30 -> 24477.655
A33: PAT margin | B33: =B32/B8 -> 0.18686701 | C33: =C32/C8 -> 0.1708206 | D33: =D32/D8 -> 0.24740745 | E33: =E32/E8 -> 0.27108044 | F33: =F32/F8 -> 0.25273859 | G33: =G32/G8 -> 0.2748431 | H33: =H32/H8 -> 0.2748431 | I33: =I32/I8 -> 0.2748431 | ... W33: =W32/W8 -> 0.29350575
A35: Non-controlling interest | B35: 0 | C35: 0 | D35: 0 | E35: 0 | F35: =0 -> 0 | G35: =0 -> 0 | H35: =0 -> 0 | I35: =0 -> 0 | J35: =0 -> 0 | K35: =0 -> 0 | L35: =0 -> 0 | M35: =0 -> 0 | ... W35: =0 -> 0
A36: PAT attributable to shareholders | B36: =B32-B35 -> 6076.392 | C36: =C32-C35 -> 5899.648 | D36: =D32-D35 -> 9275.825 | E36: =E32-E35 -> 10359.8 | F36: =F32-F35 -> 2371.8 | G36: =G32-G35 -> 3066.5717 | H36: =H32-H35 -> 3107.7982 | I36: =I32-I35 -> 3162.1423 | ... W36: =W32-W35 -> 24477.655
A38: Diluted shares outstanding (mn) | B38: 169.406 | C38: 169.406 | D38: 169.406 | E38: 169.406 | F38: 169.406 | G38: =$J38 -> 169.406 | H38: =$J38 -> 169.406 | I38: =$J38 -> 169.406 | J38: =E38 -> 169.406 | K38: =$O38 -> 169.406 | L38: =$O38 -> 169.406 | M38: =$O38 -> 169.406 | N38: =$O38 -> 169.406 | O38: =J38 -> 169.406 | P38: =$O38 -> 169.406 | Q38: =$O38 -> 169.406 | R38: =$O38 -> 169.406 | S38: =$O38 -> 169.406 | T38: =$O38 -> 169.406 | U38: =$O38 -> 169.406 | V38: =$O38 -> 169.406 | W38: =$O38 -> 169.406
A39: Diluted EPS (INR) | B39: =B36/B38 -> 35.868812 | C39: =C36/C38 -> 34.825496 | D39: =D36/D38 -> 54.754997 | E39: =E36/E38 -> 61.153678 | F39: =F36/F38 -> 14.000685 | G39: =G36/G38 -> 18.101907 | H39: =H36/H38 -> 18.345266 | I39: =I36/I38 -> 18.666059 | ... W39: =W36/W38 -> 144.49108
A40: * Q1 FY27 revenue and P&L line items are reported consolidated actuals. Q2-Q4 FY27 forecasts bridge to the unchanged FY27 annual model; FY28 quarterly forecasts phase the unchanged FY28 annual model.

Sheet Balance_Sheet
A1: GSK India - Consolidated Balance Sheet
A2: INR million | Annual FY2023A-FY2036E | Forecast cash is linked from the cash-flow statement
A4: Simplified Consolidated Balance Sheet
A5: Fiscal year | B5: FY2023A | C5: FY2024A | D5: FY2025A | E5: FY2026A | F5: FY2027E | G5: FY2028E | H5: FY2029E | I5: FY2030E | J5: FY2031E | K5: FY2032E | L5: FY2033E | M5: FY2034E | N5: FY2035E | O5: FY2036E
A6: Period | B6: Actual | C6: Actual | D6: Actual | E6: Actual | F6: Estimate | G6: Estimate | H6: Estimate | I6: Estimate | J6: Estimate | K6: Estimate | L6: Estimate | M6: Estimate | N6: Estimate | O6: Estimate
A8: Assets
A9: Net property, plant & equipment / ROU / intangibles | B9: 3502.714 | C9: 3352.037 | D9: 2979.737 | E9: 3136.6 | F9: =Schedules_Checks!F12 -> 3029.5368 | G9: =Schedules_Checks!G12 -> 2990.5257 | H9: =Schedules_Checks!H12 -> 3001.7862 | I9: =Schedules_Checks!I12 -> 3048.8233 | J9: =Schedules_Checks!J12 -> 3133.1573 | K9: =Schedules_Checks!K12 -> 3240.7342 | L9: =Schedules_Checks!L12 -> 3364.4603 | M9: =Schedules_Checks!M12 -> 3497.2788 | ... O9: =Schedules_Checks!O12 -> 3778.9886
A10: Financial investments | B10: 17092.763 | C10: 18122.701 | D10: 19829.148 | E10: 16808 | F10: =E10 -> 16808 | G10: =F10 -> 16808 | H10: =G10 -> 16808 | I10: =H10 -> 16808 | J10: =I10 -> 16808 | K10: =J10 -> 16808 | L10: =K10 -> 16808 | M10: =L10 -> 16808 | ... O10: =N10 -> 16808
A11: Inventories | B11: 4599.704 | C11: 5250.482 | D11: 4817.368 | E11: 4575.5 | F11: =Financial_Assumptions!B$33*Profit_Loss!J11/365 -> 5155.0562 | G11: =Financial_Assumptions!C$33*Profit_Loss!O11/365 -> 5652.0416 | H11: =Financial_Assumptions!D$33*Profit_Loss!P11/365 -> 6126.1847 | I11: =Financial_Assumptions!E$33*Profit_Loss!Q11/365 -> 6571.7678 | J11: =Financial_Assumptions!F$33*Profit_Loss!R11/365 -> 7103.0291 | K11: =Financial_Assumptions!G$33*Profit_Loss!S11/365 -> 7573.088 | L11: =Financial_Assumptions!H$33*Profit_Loss!T11/365 -> 8024.7681 | M11: =Financial_Assumptions!I$33*Profit_Loss!U11/365 -> 8442.6307 | N11: =Financial_Assumptions!J$33*Profit_Loss!V11/365 -> 8850.917 | O11: =Financial_Assumptions!K$33*Profit_Loss!W11/365 -> 9267.408
A12: Trade receivables | B12: 1923.75 | C12: 2220.571 | D12: 2925.491 | E12: 2731.1 | F12: =Financial_Assumptions!B$34*Profit_Loss!J8/365 -> 3207.0626 | G12: =Financial_Assumptions!C$34*Profit_Loss!O8/365 -> 3518.4157 | H12: =Financial_Assumptions!D$34*Profit_Loss!P8/365 -> 3815.6636 | I12: =Financial_Assumptions!E$34*Profit_Loss!Q8/365 -> 4095.1482 | J12: =Financial_Assumptions!F$34*Profit_Loss!R8/365 -> 4418.4885 | K12: =Financial_Assumptions!G$34*Profit_Loss!S8/365 -> 4702.5422 | L12: =Financial_Assumptions!H$34*Profit_Loss!T8/365 -> 4974.0298 | M12: =Financial_Assumptions!I$34*Profit_Loss!U8/365 -> 5223.4362 | N12: =Financial_Assumptions!J$34*Profit_Loss!V8/365 -> 5465.823 | O12: =Financial_Assumptions!K$34*Profit_Loss!W8/365 -> 5712.1597
A13: Cash and cash equivalents | B13: 349.409 | C13: 641.712 | D13: 5388.477 | E13: 11020.5 | F13: =Cash_Flow!F28 -> 13151.132 | G13: =Cash_Flow!G28 -> 15380.423 | H13: =Cash_Flow!H28 -> 17778.6 | I13: =Cash_Flow!I28 -> 20367.735 | J13: =Cash_Flow!J28 -> 23175.898 | K13: =Cash_Flow!K28 -> 26067.052 | L13: =Cash_Flow!L28 -> 29134.265 | M13: =Cash_Flow!M28 -> 32358.178 | ... O13: =Cash_Flow!O28 -> 39500.371
A14: Other assets | B14: 5797.508 | C14: 5978.672 | D14: 5140.434 | E14: 4967 | F14: =Financial_Assumptions!B$36*Profit_Loss!J8 -> 5636.1156 | G14: =Financial_Assumptions!C$36*Profit_Loss!O8 -> 6228.4754 | H14: =Financial_Assumptions!D$36*Profit_Loss!P8 -> 6804.922 | I14: =Financial_Assumptions!E$36*Profit_Loss!Q8 -> 7358.6663 | J14: =Financial_Assumptions!F$36*Profit_Loss!R8 -> 7959.6932 | K14: =Financial_Assumptions!G$36*Profit_Loss!S8 -> 8492.9744 | L14: =Financial_Assumptions!H$36*Profit_Loss!T8 -> 9006.4075 | M14: =Financial_Assumptions!I$36*Profit_Loss!U8 -> 9482.5986 | N14: =Financial_Assumptions!J$36*Profit_Loss!V8 -> 9948.7028 | O14: =Financial_Assumptions!K$36*Profit_Loss!W8 -> 10424.692
A15: Total assets | B15: =SUM(B9:B14) -> 33265.848 | C15: =SUM(C9:C14) -> 35566.175 | D15: =SUM(D9:D14) -> 41080.655 | E15: =SUM(E9:E14) -> 43238.7 | F15: =SUM(F9:F14) -> 46986.904 | G15: =SUM(G9:G14) -> 50577.881 | H15: =SUM(H9:H14) -> 54335.157 | I15: =SUM(I9:I14) -> 58250.141 | ... O15: =SUM(O9:O14) -> 85491.619
A17: Equity and liabilities
A18: Share capital | B18: 1694.06 | C18: 1694.06 | D18: 1694.06 | E18: 1694.1 | F18: =E18 -> 1694.1 | G18: =F18 -> 1694.1 | H18: =G18 -> 1694.1 | I18: =H18 -> 1694.1 | J18: =I18 -> 1694.1 | K18: =J18 -> 1694.1 | L18: =K18 -> 1694.1 | M18: =L18 -> 1694.1 | ... O18: =N18 -> 1694.1
A19: Other equity and retained earnings | B19: 15718.67 | C19: 16082.337 | D19: 17819.047 | E19: 20980.1 | F19: =Schedules_Checks!F24 -> 21916.765 | G19: =Schedules_Checks!G24 -> 23059.91 | H19: =Schedules_Checks!H24 -> 24429.831 | I19: =Schedules_Checks!I24 -> 26046.036 | J19: =Schedules_Checks!J24 -> 27871.658 | K19: =Schedules_Checks!K24 -> 29904.877 | L19: =Schedules_Checks!L24 -> 32153.023 | M19: =Schedules_Checks!M24 -> 34619.516 | ... O19: =Schedules_Checks!O24 -> 40251.188
A20: Total shareholders' equity | B20: =SUM(B18:B19) -> 17412.73 | C20: =SUM(C18:C19) -> 17776.397 | D20: =SUM(D18:D19) -> 19513.107 | E20: =SUM(E18:E19) -> 22674.2 | F20: =SUM(F18:F19) -> 23610.865 | G20: =SUM(G18:G19) -> 24754.01 | H20: =SUM(H18:H19) -> 26123.931 | I20: =SUM(I18:I19) -> 27740.136 | ... O20: =SUM(O18:O19) -> 41945.288
A22: Borrowings and lease liabilities | B22: 155.392 | C22: 186.65 | D22: 99.512 | E22: 332.7 | F22: =Financial_Assumptions!B$38 -> 332.7 | G22: =Financial_Assumptions!C$38 -> 332.7 | H22: =Financial_Assumptions!D$38 -> 332.7 | I22: =Financial_Assumptions!E$38 -> 332.7 | J22: =Financial_Assumptions!F$38 -> 332.7 | K22: =Financial_Assumptions!G$38 -> 332.7 | L22: =Financial_Assumptions!H$38 -> 332.7 | M22: =Financial_Assumptions!I$38 -> 332.7 | ... O22: =Financial_Assumptions!K$38 -> 332.7
A23: Trade payables | B23: 4277.887 | C23: 6254.097 | D23: 7082.486 | E23: 5702.2 | F23: =Financial_Assumptions!B$35*Profit_Loss!J11/365 -> 6568.5393 | G23: =Financial_Assumptions!C$35*Profit_Loss!O11/365 -> 7271.2751 | H23: =Financial_Assumptions!D$35*Profit_Loss!P11/365 -> 7957.3812 | I23: =Financial_Assumptions!E$35*Profit_Loss!Q11/365 -> 8618.7119 | J23: =Financial_Assumptions!F$35*Profit_Loss!R11/365 -> 9340.9698 | K23: =Financial_Assumptions!G$35*Profit_Loss!S11/365 -> 9986.4896 | L23: =Financial_Assumptions!H$35*Profit_Loss!T11/365 -> 10611.264 | M23: =Financial_Assumptions!I$35*Profit_Loss!U11/365 -> 11194.648 | N23: =Financial_Assumptions!J$35*Profit_Loss!V11/365 -> 11768.532 | O23: =Financial_Assumptions!K$35*Profit_Loss!W11/365 -> 12356.544
A24: Other liabilities and provisions | B24: 11419.839 | C24: 11349.031 | D24: 14385.55 | E24: 14529.6 | F24: =Financial_Assumptions!B$37*Profit_Loss!J8 -> 16474.799 | G24: =Financial_Assumptions!C$37*Profit_Loss!O8 -> 18219.896 | H24: =Financial_Assumptions!D$37*Profit_Loss!P8 -> 19921.145 | I24: =Financial_Assumptions!E$37*Profit_Loss!Q8 -> 21558.593 | J24: =Financial_Assumptions!F$37*Profit_Loss!R8 -> 23358.838 | K24: =Financial_Assumptions!G$37*Profit_Loss!S8 -> 24966.224 | L24: =Financial_Assumptions!H$37*Profit_Loss!T8 -> 26520.844 | M24: =Financial_Assumptions!I$37*Profit_Loss!U8 -> 27971.157 | N24: =Financial_Assumptions!J$37*Profit_Loss!V8 -> 29396.897 | O24: =Financial_Assumptions!K$37*Profit_Loss!W8 -> 30857.087
A25: Total liabilities | B25: =SUM(B22:B24) -> 15853.118 | C25: =SUM(C22:C24) -> 17789.778 | D25: =SUM(D22:D24) -> 21567.548 | E25: =SUM(E22:E24) -> 20564.5 | F25: =SUM(F22:F24) -> 23376.039 | G25: =SUM(G22:G24) -> 25823.871 | H25: =SUM(H22:H24) -> 28211.226 | I25: =SUM(I22:I24) -> 30510.004 | ... O25: =SUM(O22:O24) -> 43546.331
A26: Total equity and liabilities | B26: =B20+B25 -> 33265.848 | C26: =C20+C25 -> 35566.175 | D26: =D20+D25 -> 41080.655 | E26: =E20+E25 -> 43238.7 | F26: =F20+F25 -> 46986.904 | G26: =G20+G25 -> 50577.881 | H26: =H20+H25 -> 54335.157 | I26: =I20+I25 -> 58250.141 | ... O26: =O20+O25 -> 85491.619
A28: Balance-sheet check | B28: =ROUND(B15-B26,6) -> 0 | C28: =ROUND(C15-C26,6) -> 0 | D28: =ROUND(D15-D26,6) -> 0 | E28: =ROUND(E15-E26,6) -> 0 | F28: =ROUND(F15-F26,6) -> 0 | G28: =ROUND(G15-G26,6) -> 0 | H28: =ROUND(H15-H26,6) -> 0 | I28: =ROUND(I15-I26,6) -> 0 | ... O28: =ROUND(O15-O26,6) -> 0
A29: Historical balances are consolidated reported figures; forecast balances are driven by the centralized assumptions and linked annual P&L / cash-flow statements.

Sheet Cash_Flow
A1: GSK India - Consolidated Cash Flow Statement
A2: INR million | Simplified indirect method | Annual FY2023A-FY2036E
A4: Simplified Consolidated Cash Flow Statement
A5: Fiscal year | B5: FY2023A | C5: FY2024A | D5: FY2025A | E5: FY2026A | F5: FY2027E | G5: FY2028E | H5: FY2029E | I5: FY2030E | J5: FY2031E | K5: FY2032E | L5: FY2033E | M5: FY2034E | N5: FY2035E | O5: FY2036E
A6: Period | B6: Actual | C6: Actual | D6: Actual | E6: Actual | F6: Estimate | G6: Estimate | H6: Estimate | I6: Estimate | J6: Estimate | K6: Estimate | L6: Estimate | M6: Estimate | N6: Estimate | O6: Estimate
A8: Profit after tax | B8: =Profit_Loss!B32 -> 6076.392 | C8: =Profit_Loss!C32 -> 5899.648 | D8: =Profit_Loss!D32 -> 9275.825 | E8: =Profit_Loss!E32 -> 10359.8 | F8: =Profit_Loss!J32 -> 11708.312 | G8: =Profit_Loss!O32 -> 13190.135 | H8: =Profit_Loss!P32 -> 14677.722 | I8: =Profit_Loss!Q32 -> 16162.058 | J8: =Profit_Loss!R32 -> 17667.307 | K8: =Profit_Loss!S32 -> 19061.428 | L8: =Profit_Loss!T32 -> 20437.689 | M8: =Profit_Loss!U32 -> 21763.176 | N8: =Profit_Loss!V32 -> 23094.458 | O8: =Profit_Loss!W32 -> 24477.655
A9: Add: depreciation and amortization | B9: =Profit_Loss!B20 -> 657.672 | C9: =Profit_Loss!C20 -> 696.796 | D9: =Profit_Loss!D20 -> 667.925 | E9: =Profit_Loss!E20 -> 664.4 | F9: =Profit_Loss!J20 -> 627.32 | G9: =Profit_Loss!O20 -> 600.85814 | H9: =Profit_Loss!P20 -> 588.13672 | I9: =Profit_Loss!Q20 -> 585.34832 | J9: =Profit_Loss!R20 -> 591.97986 | K9: =Profit_Loss!S20 -> 605.74374 | L9: =Profit_Loss!T20 -> 623.84134 | M9: =Profit_Loss!U20 -> 644.85489 | N9: =Profit_Loss!V20 -> 667.39738 | O9: =Profit_Loss!W20 -> 690.80558
A10: Inventory change (cash impact) | B10: 0 | C10: =Balance_Sheet!B11-Balance_Sheet!C11 -> -650.778 | D10: =Balance_Sheet!C11-Balance_Sheet!D11 -> 433.114 | E10: =Balance_Sheet!D11-Balance_Sheet!E11 -> 241.868 | F10: =Balance_Sheet!E11-Balance_Sheet!F11 -> -579.55616 | G10: =Balance_Sheet!F11-Balance_Sheet!G11 -> -496.98544 | H10: =Balance_Sheet!G11-Balance_Sheet!H11 -> -474.14309 | I10: =Balance_Sheet!H11-Balance_Sheet!I11 -> -445.58311 | J10: =Balance_Sheet!I11-Balance_Sheet!J11 -> -531.26129 | ... O10: =Balance_Sheet!N11-Balance_Sheet!O11 -> -416.49097
A11: Receivables change (cash impact) | B11: 0 | C11: =Balance_Sheet!B12-Balance_Sheet!C12 -> -296.821 | D11: =Balance_Sheet!C12-Balance_Sheet!D12 -> -704.92 | E11: =Balance_Sheet!D12-Balance_Sheet!E12 -> 194.391 | F11: =Balance_Sheet!E12-Balance_Sheet!F12 -> -475.96259 | G11: =Balance_Sheet!F12-Balance_Sheet!G12 -> -311.3531 | H11: =Balance_Sheet!G12-Balance_Sheet!H12 -> -297.24787 | I11: =Balance_Sheet!H12-Balance_Sheet!I12 -> -279.48462 | J11: =Balance_Sheet!I12-Balance_Sheet!J12 -> -323.34032 | ... O11: =Balance_Sheet!N12-Balance_Sheet!O12 -> -246.33674
A12: Other assets change (cash impact) | B12: 0 | C12: =Balance_Sheet!B14-Balance_Sheet!C14 -> -181.164 | D12: =Balance_Sheet!C14-Balance_Sheet!D14 -> 838.238 | E12: =Balance_Sheet!D14-Balance_Sheet!E14 -> 173.434 | F12: =Balance_Sheet!E14-Balance_Sheet!F14 -> -669.11555 | G12: =Balance_Sheet!F14-Balance_Sheet!G14 -> -592.35982 | H12: =Balance_Sheet!G14-Balance_Sheet!H14 -> -576.44664 | I12: =Balance_Sheet!H14-Balance_Sheet!I14 -> -553.74426 | J12: =Balance_Sheet!I14-Balance_Sheet!J14 -> -601.02697 | ... O12: =Balance_Sheet!N14-Balance_Sheet!O14 -> -475.98872
A13: Trade payables change (cash impact) | B13: 0 | C13: =Balance_Sheet!C23-Balance_Sheet!B23 -> 1976.21 | D13: =Balance_Sheet!D23-Balance_Sheet!C23 -> 828.389 | E13: =Balance_Sheet!E23-Balance_Sheet!D23 -> -1380.286 | F13: =Balance_Sheet!F23-Balance_Sheet!E23 -> 866.3393 | G13: =Balance_Sheet!G23-Balance_Sheet!F23 -> 702.73584 | H13: =Balance_Sheet!H23-Balance_Sheet!G23 -> 686.10606 | I13: =Balance_Sheet!I23-Balance_Sheet!H23 -> 661.33066 | J13: =Balance_Sheet!J23-Balance_Sheet!I23 -> 722.2579 | ... O13: =Balance_Sheet!O23-Balance_Sheet!N23 -> 588.01166
A14: Other liabilities and provisions change (cash impact) | B14: 0 | C14: =Balance_Sheet!C24-Balance_Sheet!B24 -> -70.808 | D14: =Balance_Sheet!D24-Balance_Sheet!C24 -> 3036.519 | E14: =Balance_Sheet!E24-Balance_Sheet!D24 -> 144.05 | F14: =Balance_Sheet!F24-Balance_Sheet!E24 -> 1945.1993 | G14: =Balance_Sheet!G24-Balance_Sheet!F24 -> 1745.0964 | H14: =Balance_Sheet!H24-Balance_Sheet!G24 -> 1701.249 | I14: =Balance_Sheet!I24-Balance_Sheet!H24 -> 1637.4479 | J14: =Balance_Sheet!J24-Balance_Sheet!I24 -> 1800.2458 | ... O14: =Balance_Sheet!O24-Balance_Sheet!N24 -> 1460.1895
A15: Cash flow from operations | B15: =SUM(B8:B14) -> 6734.064 | C15: =SUM(C8:C14) -> 7373.083 | D15: =SUM(D8:D14) -> 14375.09 | E15: =SUM(E8:E14) -> 10397.657 | F15: =SUM(F8:F14) -> 13422.537 | G15: =SUM(G8:G14) -> 14838.127 | H15: =SUM(H8:H14) -> 16305.376 | I15: =SUM(I8:I14) -> 17767.373 | ... O15: =SUM(O8:O14) -> 26077.846
A17: Capital expenditure | B17: -440.391 | C17: -312.215 | D17: -230.216 | E17: -552.8 | F17: =-Schedules_Checks!F9 -> -520.25682 | G17: =-Schedules_Checks!G9 -> -561.84701 | H17: =-Schedules_Checks!H9 -> -599.39728 | I17: =-Schedules_Checks!I9 -> -632.38538 | J17: =-Schedules_Checks!J9 -> -676.31381 | K17: =-Schedules_Checks!K9 -> -713.32069 | L17: =-Schedules_Checks!L9 -> -747.56742 | M17: =-Schedules_Checks!M9 -> -777.67343 | ... O17: =-Schedules_Checks!O9 -> -833.97532
A18: Change in financial investments | B18: 0 | C18: =-(Balance_Sheet!C10-Balance_Sheet!B10) -> -1029.938 | D18: =-(Balance_Sheet!D10-Balance_Sheet!C10) -> -1706.447 | E18: =-(Balance_Sheet!E10-Balance_Sheet!D10) -> 3021.148 | F18: =-(Balance_Sheet!F10-Balance_Sheet!E10) -> 0 | G18: =-(Balance_Sheet!G10-Balance_Sheet!F10) -> 0 | H18: =-(Balance_Sheet!H10-Balance_Sheet!G10) -> 0 | I18: =-(Balance_Sheet!I10-Balance_Sheet!H10) -> 0 | J18: =-(Balance_Sheet!J10-Balance_Sheet!I10) -> 0 | ... O18: =-(Balance_Sheet!O10-Balance_Sheet!N10) -> 0
A19: Cash flow from investing | B19: =SUM(B17:B18) -> -440.391 | C19: =SUM(C17:C18) -> -1342.153 | D19: =SUM(D17:D18) -> -1936.663 | E19: =SUM(E17:E18) -> 2468.348 | F19: =SUM(F17:F18) -> -520.25682 | G19: =SUM(G17:G18) -> -561.84701 | H19: =SUM(H17:H18) -> -599.39728 | I19: =SUM(I17:I18) -> -632.38538 | ... O19: =SUM(O17:O18) -> -833.97532
A21: Dividends paid | B21: -15254.999 | C21: -5415.729 | D21: -7493.8 | E21: -7139.7 | F21: =-Schedules_Checks!F22 -> -10771.647 | G21: =-Schedules_Checks!G22 -> -12046.99 | H21: =-Schedules_Checks!H22 -> -13307.801 | I21: =-Schedules_Checks!I22 -> -14545.852 | J21: =-Schedules_Checks!J22 -> -15841.686 | K21: =-Schedules_Checks!K22 -> -17028.209 | L21: =-Schedules_Checks!L22 -> -18189.543 | M21: =-Schedules_Checks!M22 -> -19296.683 | ... O21: =-Schedules_Checks!O22 -> -21540.337
A22: Change in borrowings and lease liabilities | B22: 0 | C22: =Balance_Sheet!C22-Balance_Sheet!B22 -> 31.258 | D22: =Balance_Sheet!D22-Balance_Sheet!C22 -> -87.138 | E22: =Balance_Sheet!E22-Balance_Sheet!D22 -> 233.188 | F22: =Balance_Sheet!F22-Balance_Sheet!E22 -> 0 | G22: =Balance_Sheet!G22-Balance_Sheet!F22 -> 0 | H22: =Balance_Sheet!H22-Balance_Sheet!G22 -> 0 | I22: =Balance_Sheet!I22-Balance_Sheet!H22 -> 0 | J22: =Balance_Sheet!J22-Balance_Sheet!I22 -> 0 | ... O22: =Balance_Sheet!O22-Balance_Sheet!N22 -> 0
A23: Other financing / historical cash-flow reconciliation | B23: 6448.864 | C23: -354.156 | D23: -110.724 | E23: -327.47 | F23: =0 -> 0 | G23: =0 -> 0 | H23: =0 -> 0 | I23: =0 -> 0 | J23: =0 -> 0 | K23: =0 -> 0 | L23: =0 -> 0 | M23: =0 -> 0 | ... O23: =0 -> 0
A24: Cash flow from financing | B24: =SUM(B21:B23) -> -8806.135 | C24: =SUM(C21:C23) -> -5738.627 | D24: =SUM(D21:D23) -> -7691.662 | E24: =SUM(E21:E23) -> -7233.982 | F24: =SUM(F21:F23) -> -10771.647 | G24: =SUM(G21:G23) -> -12046.99 | H24: =SUM(H21:H23) -> -13307.801 | I24: =SUM(I21:I23) -> -14545.852 | ... O24: =SUM(O21:O23) -> -21540.337
A26: Net change in cash | B26: =B15+B19+B24 -> -2512.462 | C26: =C15+C19+C24 -> 292.303 | D26: =D15+D19+D24 -> 4746.765 | E26: =E15+E19+E24 -> 5632.023 | F26: =F15+F19+F24 -> 2130.6325 | G26: =G15+G19+G24 -> 2229.29 | H26: =H15+H19+H24 -> 2398.1776 | I26: =I15+I19+I24 -> 2589.1352 | ... O26: =O15+O19+O24 -> 3703.5336
A27: Opening cash | B27: 2861.871 | C27: 349.409 | D27: 641.712 | E27: 5388.477 | F27: =Balance_Sheet!E13 -> 11020.5 | G27: =Balance_Sheet!F13 -> 13151.132 | H27: =Balance_Sheet!G13 -> 15380.423 | I27: =Balance_Sheet!H13 -> 17778.6 | J27: =Balance_Sheet!I13 -> 20367.735 | K27: =Balance_Sheet!J13 -> 23175.898 | L27: =Balance_Sheet!K13 -> 26067.052 | M27: =Balance_Sheet!L13 -> 29134.265 | ... O27: =Balance_Sheet!N13 -> 35796.838
A28: Closing cash | B28: =B27+B26 -> 349.409 | C28: =C27+C26 -> 641.712 | D28: =D27+D26 -> 5388.477 | E28: =E27+E26 -> 11020.5 | F28: =F27+F26 -> 13151.132 | G28: =G27+G26 -> 15380.423 | H28: =H27+H26 -> 17778.6 | I28: =I27+I26 -> 20367.735 | ... O28: =O27+O26 -> 39500.371
A30: Closing cash BS less CFS | B30: =ROUND(Balance_Sheet!B13-B28,6) -> 0 | C30: =ROUND(Balance_Sheet!C13-C28,6) -> 0 | D30: =ROUND(Balance_Sheet!D13-D28,6) -> 0 | E30: =ROUND(Balance_Sheet!E13-E28,6) -> 0 | F30: =ROUND(Balance_Sheet!F13-F28,6) -> 0 | G30: =ROUND(Balance_Sheet!G13-G28,6) -> 0 | H30: =ROUND(Balance_Sheet!H13-H28,6) -> 0 | I30: =ROUND(Balance_Sheet!I13-I28,6) -> 0 | ... O30: =ROUND(Balance_Sheet!O13-O28,6) -> 0
A31: Historical cash flow retains the transparent reconciliation line from the prior QC model; all forecast reconciliation items are zero.

Sheet Schedules_Checks
A1: GSK India - Supporting Schedules & Model Checks
A2: INR million unless stated otherwise | Annual FY2023A-FY2036E
A4: Fiscal year | B4: FY2023A | C4: FY2024A | D4: FY2025A | E4: FY2026A | F4: FY2027E | G4: FY2028E | H4: FY2029E | I4: FY2030E | J4: FY2031E | K4: FY2032E | L4: FY2033E | M4: FY2034E | N4: FY2035E | O4: FY2036E
A5: Period | B5: Actual | C5: Actual | D5: Actual | E5: Actual | F5: Estimate | G5: Estimate | H5: Estimate | I5: Estimate | J5: Estimate | K5: Estimate | L5: Estimate | M5: Estimate | N5: Estimate | O5: Estimate
A7: Net fixed-asset roll-forward
A8: Opening net fixed assets | B8: =Balance_Sheet!B9-B9+B10 -> 3719.995 | C8: =Balance_Sheet!B9 -> 3502.714 | D8: =Balance_Sheet!C9 -> 3352.037 | E8: =Balance_Sheet!D9 -> 2979.737 | F8: =E12 -> 3136.6 | G8: =F12 -> 3029.5368 | H8: =G12 -> 2990.5257 | I8: =H12 -> 3001.7862 | J8: =I12 -> 3048.8233 | K8: =J12 -> 3133.1573 | L8: =K12 -> 3240.7342 | M8: =L12 -> 3364.4603 | ... O8: =N12 -> 3635.8189
A9: Capital expenditure | B9: 440.391 | C9: 312.215 | D9: 230.216 | E9: 552.8 | F9: =Profit_Loss!J8*Financial_Assumptions!B$32 -> 520.25682 | G9: =Profit_Loss!O8*Financial_Assumptions!C$32 -> 561.84701 | H9: =Profit_Loss!P8*Financial_Assumptions!D$32 -> 599.39728 | I9: =Profit_Loss!Q8*Financial_Assumptions!E$32 -> 632.38538 | J9: =Profit_Loss!R8*Financial_Assumptions!F$32 -> 676.31381 | K9: =Profit_Loss!S8*Financial_Assumptions!G$32 -> 713.32069 | L9: =Profit_Loss!T8*Financial_Assumptions!H$32 -> 747.56742 | M9: =Profit_Loss!U8*Financial_Assumptions!I$32 -> 777.67343 | N9: =Profit_Loss!V8*Financial_Assumptions!J$32 -> 805.93741 | O9: =Profit_Loss!W8*Financial_Assumptions!K$32 -> 833.97532
A10: Depreciation and amortization | B10: =Profit_Loss!B20 -> 657.672 | C10: =Profit_Loss!C20 -> 696.796 | D10: =Profit_Loss!D20 -> 667.925 | E10: =Profit_Loss!E20 -> 664.4 | F10: =F8*Financial_Assumptions!B$39 -> 627.32 | G10: =G8*Financial_Assumptions!C$39 -> 600.85814 | H10: =H8*Financial_Assumptions!D$39 -> 588.13672 | I10: =I8*Financial_Assumptions!E$39 -> 585.34832 | J10: =J8*Financial_Assumptions!F$39 -> 591.97986 | K10: =K8*Financial_Assumptions!G$39 -> 605.74374 | L10: =L8*Financial_Assumptions!H$39 -> 623.84134 | M10: =M8*Financial_Assumptions!I$39 -> 644.85489 | ... O10: =O8*Financial_Assumptions!K$39 -> 690.80558
A11: Other historical asset movements | B11: =Balance_Sheet!B9-(B8+B9-B10) -> 0 | C11: =Balance_Sheet!C9-(C8+C9-C10) -> 233.904 | D11: =Balance_Sheet!D9-(D8+D9-D10) -> 65.409 | E11: =Balance_Sheet!E9-(E8+E9-E10) -> 268.463 | F11: =0 -> 0 | G11: =0 -> 0 | H11: =0 -> 0 | I11: =0 -> 0 | J11: =0 -> 0 | K11: =0 -> 0 | L11: =0 -> 0 | M11: =0 -> 0 | ... O11: =0 -> 0
A12: Closing net fixed assets | B12: =B8+B9-B10+B11 -> 3502.714 | C12: =C8+C9-C10+C11 -> 3352.037 | D12: =D8+D9-D10+D11 -> 2979.737 | E12: =E8+E9-E10+E11 -> 3136.6 | F12: =F8+F9-F10+F11 -> 3029.5368 | G12: =G8+G9-G10+G11 -> 2990.5257 | H12: =H8+H9-H10+H11 -> 3001.7862 | I12: =I8+I9-I10+I11 -> 3048.8233 | ... O12: =O8+O9-O10+O11 -> 3778.9886
A14: Net working-capital schedule
A15: Inventory days | B15: =Balance_Sheet!B11/Profit_Loss!B11*365 -> 130.66564 | C15: =Balance_Sheet!C11/Profit_Loss!C11*365 -> 143.60343 | D15: =Balance_Sheet!D11/Profit_Loss!D11*365 -> 126.42129 | E15: =Balance_Sheet!E11/Profit_Loss!E11*365 -> 123.61091 | F15: =Balance_Sheet!F11/Profit_Loss!J11*365 -> 124 | G15: =Balance_Sheet!G11/Profit_Loss!O11*365 -> 123.33333 | H15: =Balance_Sheet!H11/Profit_Loss!P11*365 -> 122.66667 | I15: =Balance_Sheet!I11/Profit_Loss!Q11*365 -> 122 | J15: =Balance_Sheet!J11/Profit_Loss!R11*365 -> 121.66667 | K15: =Balance_Sheet!K11/Profit_Loss!S11*365 -> 121.33333 | L15: =Balance_Sheet!L11/Profit_Loss!T11*365 -> 121 | M15: =Balance_Sheet!M11/Profit_Loss!U11*365 -> 120.66667 | N15: =Balance_Sheet!N11/Profit_Loss!V11*365 -> 120.33333 | O15: =Balance_Sheet!O11/Profit_Loss!W11*365 -> 120
A16: Receivable days | B16: =Balance_Sheet!B12/Profit_Loss!B8*365 -> 21.593764 | C16: =Balance_Sheet!C12/Profit_Loss!C8*365 -> 23.467761 | D16: =Balance_Sheet!D12/Profit_Loss!D8*365 -> 28.480779 | E16: =Balance_Sheet!E12/Profit_Loss!E8*365 -> 26.084186 | F16: =Balance_Sheet!F12/Profit_Loss!J8*365 -> 27 | G16: =Balance_Sheet!G12/Profit_Loss!O8*365 -> 26.666667 | H16: =Balance_Sheet!H12/Profit_Loss!P8*365 -> 26.333333 | I16: =Balance_Sheet!I12/Profit_Loss!Q8*365 -> 26 | J16: =Balance_Sheet!J12/Profit_Loss!R8*365 -> 25.833333 | K16: =Balance_Sheet!K12/Profit_Loss!S8*365 -> 25.666667 | L16: =Balance_Sheet!L12/Profit_Loss!T8*365 -> 25.5 | M16: =Balance_Sheet!M12/Profit_Loss!U8*365 -> 25.333333 | N16: =Balance_Sheet!N12/Profit_Loss!V8*365 -> 25.166667 | O16: =Balance_Sheet!O12/Profit_Loss!W8*365 -> 25
A17: Payable days | B17: =Balance_Sheet!B23/Profit_Loss!B11*365 -> 121.52365 | C17: =Balance_Sheet!C23/Profit_Loss!C11*365 -> 171.05282 | D17: =Balance_Sheet!D23/Profit_Loss!D11*365 -> 185.86435 | E17: =Balance_Sheet!E23/Profit_Loss!E11*365 -> 154.04964 | F17: =Balance_Sheet!F23/Profit_Loss!J11*365 -> 158 | G17: =Balance_Sheet!G23/Profit_Loss!O11*365 -> 158.66667 | H17: =Balance_Sheet!H23/Profit_Loss!P11*365 -> 159.33333 | I17: =Balance_Sheet!I23/Profit_Loss!Q11*365 -> 160 | J17: =Balance_Sheet!J23/Profit_Loss!R11*365 -> 160 | K17: =Balance_Sheet!K23/Profit_Loss!S11*365 -> 160 | L17: =Balance_Sheet!L23/Profit_Loss!T11*365 -> 160 | M17: =Balance_Sheet!M23/Profit_Loss!U11*365 -> 160 | N17: =Balance_Sheet!N23/Profit_Loss!V11*365 -> 160 | O17: =Balance_Sheet!O23/Profit_Loss!W11*365 -> 160
A19: Retained-earnings roll-forward
A20: Opening other equity / retained earnings | B20: 24935.498 | C20: =Balance_Sheet!B19 -> 15718.67 | D20: =Balance_Sheet!C19 -> 16082.337 | E20: =Balance_Sheet!D19 -> 17819.047 | F20: =Balance_Sheet!E19 -> 20980.1 | G20: =F24 -> 21916.765 | H20: =G24 -> 23059.91 | I20: =H24 -> 24429.831 | J20: =I24 -> 26046.036 | K20: =J24 -> 27871.658 | L20: =K24 -> 29904.877 | M20: =L24 -> 32153.023 | N20: =M24 -> 34619.516 | O20: =N24 -> 37313.87
A21: PAT attributable to shareholders | B21: =Profit_Loss!B36 -> 6076.392 | C21: =Profit_Loss!C36 -> 5899.648 | D21: =Profit_Loss!D36 -> 9275.825 | E21: =Profit_Loss!E36 -> 10359.8 | F21: =Profit_Loss!J36 -> 11708.312 | G21: =Profit_Loss!O36 -> 13190.135 | H21: =Profit_Loss!P36 -> 14677.722 | I21: =Profit_Loss!Q36 -> 16162.058 | J21: =Profit_Loss!R36 -> 17667.307 | K21: =Profit_Loss!S36 -> 19061.428 | L21: =Profit_Loss!T36 -> 20437.689 | M21: =Profit_Loss!U36 -> 21763.176 | N21: =Profit_Loss!V36 -> 23094.458 | O21: =Profit_Loss!W36 -> 24477.655
A22: Dividends | B22: 15254.999 | C22: 5415.729 | D22: 7493.8 | E22: 7139.7 | F22: =F21*Financial_Assumptions!B$31 -> 10771.647 | G22: =G21*Financial_Assumptions!C$31 -> 12046.99 | H22: =H21*Financial_Assumptions!D$31 -> 13307.801 | I22: =I21*Financial_Assumptions!E$31 -> 14545.852 | J22: =J21*Financial_Assumptions!F$31 -> 15841.686 | K22: =K21*Financial_Assumptions!G$31 -> 17028.209 | L22: =L21*Financial_Assumptions!H$31 -> 18189.543 | M22: =M21*Financial_Assumptions!I$31 -> 19296.683 | ... O22: =O21*Financial_Assumptions!K$31 -> 21540.337
A23: Other historical equity movements | B23: =Balance_Sheet!B19-(B20+B21-B22) -> -38.221 | C23: =Balance_Sheet!C19-(C20+C21-C22) -> -120.252 | D23: =Balance_Sheet!D19-(D20+D21-D22) -> -45.315 | E23: =Balance_Sheet!E19-(E20+E21-E22) -> -59.047 | F23: =0 -> 0 | G23: =0 -> 0 | H23: =0 -> 0 | I23: =0 -> 0 | J23: =0 -> 0 | K23: =0 -> 0 | L23: =0 -> 0 | M23: =0 -> 0 | ... O23: =0 -> 0
A24: Closing other equity / retained earnings | B24: =B20+B21-B22+B23 -> 15718.67 | C24: =C20+C21-C22+C23 -> 16082.337 | D24: =D20+D21-D22+D23 -> 17819.047 | E24: =E20+E21-E22+E23 -> 20980.1 | F24: =F20+F21-F22+F23 -> 21916.765 | G24: =G20+G21-G22+G23 -> 23059.91 | H24: =H20+H21-H22+H23 -> 24429.831 | I24: =I20+I21-I22+I23 -> 26046.036 | ... O24: =O20+O21-O22+O23 -> 40251.188
A26: Cash roll-forward
A27: Opening cash | B27: =Cash_Flow!B27 -> 2861.871 | C27: =Cash_Flow!C27 -> 349.409 | D27: =Cash_Flow!D27 -> 641.712 | E27: =Cash_Flow!E27 -> 5388.477 | F27: =Cash_Flow!F27 -> 11020.5 | G27: =Cash_Flow!G27 -> 13151.132 | H27: =Cash_Flow!H27 -> 15380.423 | I27: =Cash_Flow!I27 -> 17778.6 | ... O27: =Cash_Flow!O27 -> 35796.838
A28: Net change in cash | B28: =Cash_Flow!B26 -> -2512.462 | C28: =Cash_Flow!C26 -> 292.303 | D28: =Cash_Flow!D26 -> 4746.765 | E28: =Cash_Flow!E26 -> 5632.023 | F28: =Cash_Flow!F26 -> 2130.6325 | G28: =Cash_Flow!G26 -> 2229.29 | H28: =Cash_Flow!H26 -> 2398.1776 | I28: =Cash_Flow!I26 -> 2589.1352 | ... O28: =Cash_Flow!O26 -> 3703.5336
A29: Closing cash | B29: =Cash_Flow!B28 -> 349.409 | C29: =Cash_Flow!C28 -> 641.712 | D29: =Cash_Flow!D28 -> 5388.477 | E29: =Cash_Flow!E28 -> 11020.5 | F29: =Cash_Flow!F28 -> 13151.132 | G29: =Cash_Flow!G28 -> 15380.423 | H29: =Cash_Flow!H28 -> 17778.6 | I29: =Cash_Flow!I28 -> 20367.735 | ... O29: =Cash_Flow!O28 -> 39500.371
A31: Model checks (all numerical differences should equal 0.0)
A32: Historical revenue vs Revenue_Model | B32: =ROUND(Profit_Loss!B8-Revenue_Model!B59,6) -> 0 | C32: =ROUND(Profit_Loss!C8-Revenue_Model!C59,6) -> 0 | D32: =ROUND(Profit_Loss!D8-Revenue_Model!D59,6) -> 0 | E32: =ROUND(Profit_Loss!E8-Revenue_Model!E59,6) -> 0 | F32: =0 -> 0 | G32: =0 -> 0 | H32: =0 -> 0 | I32: =0 -> 0 | J32: =0 -> 0 | K32: =0 -> 0 | L32: =0 -> 0 | M32: =0 -> 0 | ... O32: =0 -> 0
A33: Forecast revenue vs Revenue_Model | B33: =0 -> 0 | C33: =0 -> 0 | D33: =0 -> 0 | E33: =0 -> 0 | F33: =ROUND(Profit_Loss!J8-Revenue_Model!J54,6) -> 0 | G33: =ROUND(Profit_Loss!O8-Revenue_Model!O54,6) -> 0 | H33: =ROUND(Profit_Loss!P8-Revenue_Model!P54,6) -> 0 | I33: =ROUND(Profit_Loss!Q8-Revenue_Model!Q54,6) -> 0 | J33: =ROUND(Profit_Loss!R8-Revenue_Model!R54,6) -> 0 | K33: =ROUND(Profit_Loss!S8-Revenue_Model!S54,6) -> 0 | L33: =ROUND(Profit_Loss!T8-Revenue_Model!T54,6) -> 0 | M33: =ROUND(Profit_Loss!U8-Revenue_Model!U54,6) -> 0 | N33: =ROUND(Profit_Loss!V8-Revenue_Model!V54,6) -> 0 | O33: =ROUND(Profit_Loss!W8-Revenue_Model!W54,6) -> 0
A34: Balance-sheet check | B34: =ROUND(Balance_Sheet!B15-Balance_Sheet!B26,6) -> 0 | C34: =ROUND(Balance_Sheet!C15-Balance_Sheet!C26,6) -> 0 | D34: =ROUND(Balance_Sheet!D15-Balance_Sheet!D26,6) -> 0 | E34: =ROUND(Balance_Sheet!E15-Balance_Sheet!E26,6) -> 0 | F34: =ROUND(Balance_Sheet!F15-Balance_Sheet!F26,6) -> 0 | G34: =ROUND(Balance_Sheet!G15-Balance_Sheet!G26,6) -> 0 | H34: =ROUND(Balance_Sheet!H15-Balance_Sheet!H26,6) -> 0 | I34: =ROUND(Balance_Sheet!I15-Balance_Sheet!I26,6) -> 0 | ... O34: =ROUND(Balance_Sheet!O15-Balance_Sheet!O26,6) -> 0
A35: Closing cash BS less CFS | B35: =ROUND(Balance_Sheet!B13-Cash_Flow!B28,6) -> 0 | C35: =ROUND(Balance_Sheet!C13-Cash_Flow!C28,6) -> 0 | D35: =ROUND(Balance_Sheet!D13-Cash_Flow!D28,6) -> 0 | E35: =ROUND(Balance_Sheet!E13-Cash_Flow!E28,6) -> 0 | F35: =ROUND(Balance_Sheet!F13-Cash_Flow!F28,6) -> 0 | G35: =ROUND(Balance_Sheet!G13-Cash_Flow!G28,6) -> 0 | H35: =ROUND(Balance_Sheet!H13-Cash_Flow!H28,6) -> 0 | I35: =ROUND(Balance_Sheet!I13-Cash_Flow!I28,6) -> 0 | ... O35: =ROUND(Balance_Sheet!O13-Cash_Flow!O28,6) -> 0
A36: Net fixed-asset roll-forward check | B36: =ROUND(Balance_Sheet!B9-B12,6) -> 0 | C36: =ROUND(Balance_Sheet!C9-C12,6) -> 0 | D36: =ROUND(Balance_Sheet!D9-D12,6) -> 0 | E36: =ROUND(Balance_Sheet!E9-E12,6) -> 0 | F36: =ROUND(Balance_Sheet!F9-F12,6) -> 0 | G36: =ROUND(Balance_Sheet!G9-G12,6) -> 0 | H36: =ROUND(Balance_Sheet!H9-H12,6) -> 0 | I36: =ROUND(Balance_Sheet!I9-I12,6) -> 0 | ... O36: =ROUND(Balance_Sheet!O9-O12,6) -> 0
A37: Retained-earnings roll-forward check | B37: =ROUND(Balance_Sheet!B19-B24,6) -> 0 | C37: =ROUND(Balance_Sheet!C19-C24,6) -> 0 | D37: =ROUND(Balance_Sheet!D19-D24,6) -> 0 | E37: =ROUND(Balance_Sheet!E19-E24,6) -> 0 | F37: =ROUND(Balance_Sheet!F19-F24,6) -> 0 | G37: =ROUND(Balance_Sheet!G19-G24,6) -> 0 | H37: =ROUND(Balance_Sheet!H19-H24,6) -> 0 | I37: =ROUND(Balance_Sheet!I19-I24,6) -> 0 | ... O37: =ROUND(Balance_Sheet!O19-O24,6) -> 0
A38: FY27 quarterly revenue aggregation | B38: =0 -> 0 | C38: =0 -> 0 | D38: =0 -> 0 | E38: =0 -> 0 | F38: =ROUND(Profit_Loss!J8-SUM(Profit_Loss!F8:I8),6) -> 0 | G38: =0 -> 0 | H38: =0 -> 0 | I38: =0 -> 0 | J38: =0 -> 0 | K38: =0 -> 0 | L38: =0 -> 0 | M38: =0 -> 0 | N38: =0 -> 0 | O38: =0 -> 0
A39: FY27 quarterly EBITDA aggregation | B39: =0 -> 0 | C39: =0 -> 0 | D39: =0 -> 0 | E39: =0 -> 0 | F39: =ROUND(Profit_Loss!J17-SUM(Profit_Loss!F17:I17),6) -> 0 | G39: =0 -> 0 | H39: =0 -> 0 | I39: =0 -> 0 | J39: =0 -> 0 | K39: =0 -> 0 | L39: =0 -> 0 | M39: =0 -> 0 | N39: =0 -> 0 | O39: =0 -> 0
A40: FY27 quarterly PAT aggregation | B40: =0 -> 0 | C40: =0 -> 0 | D40: =0 -> 0 | E40: =0 -> 0 | F40: =ROUND(Profit_Loss!J32-SUM(Profit_Loss!F32:I32),6) -> 0 | G40: =0 -> 0 | H40: =0 -> 0 | I40: =0 -> 0 | J40: =0 -> 0 | K40: =0 -> 0 | L40: =0 -> 0 | M40: =0 -> 0 | N40: =0 -> 0 | O40: =0 -> 0
A41: FY28 quarterly revenue aggregation | B41: =0 -> 0 | C41: =0 -> 0 | D41: =0 -> 0 | E41: =0 -> 0 | F41: =0 -> 0 | G41: =ROUND(Profit_Loss!O8-SUM(Profit_Loss!K8:N8),6) -> 0 | H41: =0 -> 0 | I41: =0 -> 0 | J41: =0 -> 0 | K41: =0 -> 0 | L41: =0 -> 0 | M41: =0 -> 0 | N41: =0 -> 0 | O41: =0 -> 0
A42: FY28 quarterly EBITDA aggregation | B42: =0 -> 0 | C42: =0 -> 0 | D42: =0 -> 0 | E42: =0 -> 0 | F42: =0 -> 0 | G42: =ROUND(Profit_Loss!O17-SUM(Profit_Loss!K17:N17),6) -> 0 | H42: =0 -> 0 | I42: =0 -> 0 | J42: =0 -> 0 | K42: =0 -> 0 | L42: =0 -> 0 | M42: =0 -> 0 | N42: =0 -> 0 | O42: =0 -> 0
A43: FY28 quarterly PAT aggregation | B43: =0 -> 0 | C43: =0 -> 0 | D43: =0 -> 0 | E43: =0 -> 0 | F43: =0 -> 0 | G43: =ROUND(Profit_Loss!O32-SUM(Profit_Loss!K32:N32),6) -> 0 | H43: =0 -> 0 | I43: =0 -> 0 | J43: =0 -> 0 | K43: =0 -> 0 | L43: =0 -> 0 | M43: =0 -> 0 | N43: =0 -> 0 | O43: =0 -> 0
A44: Formula-error scan (workbook count) | B44: =SUMPRODUCT(--ISERROR(Profit_Loss!B8:W39))+SUMPRODUCT(--ISERROR(Balance_Sheet!B9:O28))+SUMPRODUCT(--ISERROR(Cash_Flow!B8:O30))+SUMPRODUCT(--ISERROR(Schedules_Checks!B8:O43)) -> 0 | C44: =0 -> 0 | D44: =0 -> 0 | E44: =0 -> 0 | F44: =0 -> 0 | G44: =0 -> 0 | H44: =0 -> 0 | I44: =0 -> 0 | J44: =0 -> 0 | ... O44: =0 -> 0
