Workbook

Sheet Revenue Model
A2: Pfizer Limited bottoms-up revenue model
A3: INR million. FY23-FY26 are historical estimates reconciled to reported totals. FY27 Q1 is reported at company level and estimated by product.
S4: Blue: hardcodes | T4: Black: formulas | U4: Green: cross-sheet
A6: Company revenue summary
A7: Therapy / line item | B7: Brand | C7: FY23A | D7: FY24A | E7: FY25A | F7: FY26A | G7: Q1 FY27 | H7: Q2 FY27E | I7: Q3 FY27E | J7: Q4 FY27E | K7: FY27E | L7: Q1 FY28E | M7: Q2 FY28E | N7: Q3 FY28E | O7: Q4 FY28E | P7: FY28E | Q7: FY29E | R7: FY30E | S7: FY31E | T7: FY32E | U7: FY33E | V7: FY34E | W7: FY35E
A8: Product revenue | C8: =C81 -> 23376.3 | D8: =D81 -> 20810.4 | E8: =E81 -> 21283.6 | F8: =F81 -> 23771.1 | G8: =G81 -> 6175.35 | H8: =H81 -> 6277.5878 | I8: =I81 -> 6016.672 | J8: =J81 -> 6142.8538 | ... W8: =W81 -> 44680.883
A9: Service revenue | C9: =C83 -> 846.9 | D9: =D83 -> 1116.5 | E9: =E83 -> 1526.4 | F9: =F83 -> 1421.6 | G9: =G83 -> 355.4 | H9: =H83 -> 355.4 | I9: =I83 -> 355.4 | J9: =J83 -> 355.4 | ... W9: =W83 -> 1421.6
A10: Other operating revenue | C10: =C84 -> 24.4 | D10: =D84 -> 4.8 | E10: =E84 -> 3.5 | F10: =F84 -> 3.8 | G10: =G84 -> 0.95 | H10: =H84 -> 0.95 | I10: =I84 -> 0.95 | J10: =J84 -> 0.95 | ... W10: =W84 -> 3.8
A11: Revenue from operations | C11: =C85 -> 24247.6 | D11: =D85 -> 21931.7 | E11: =E85 -> 22813.5 | F11: =F85 -> 25196.5 | G11: =G85 -> 6531.7 | H11: =H85 -> 6633.9378 | I11: =I85 -> 6373.022 | J11: =J85 -> 6499.2038 | ... W11: =W85 -> 46106.283
A12: Growth | D12: =D11/C11-1 -> -0.095510484 | E12: =E11/D11-1 -> 0.040206642 | F12: =F11/E11-1 -> 0.1044557 | K12: =K11/F11-1 -> 0.033392081 | P12: =P11/K11-1 -> 0.05652046 | Q12: =Q11/P11-1 -> 0.10384958 | R12: =R11/Q11-1 -> 0.11444217 | S12: =S11/R11-1 -> 0.063270599 | T12: =T11/S11-1 -> 0.063624621 | U12: =U11/T11-1 -> 0.063215444 | V12: =V11/U11-1 -> 0.063274806 | W12: =W11/V11-1 -> 0.065639787
A15: Product revenue by therapy and brand
A16: Therapy / line item | B16: Brand | C16: FY23A | D16: FY24A | E16: FY25A | F16: FY26A | G16: Q1 FY27 | H16: Q2 FY27E | I16: Q3 FY27E | J16: Q4 FY27E | K16: FY27E | L16: Q1 FY28E | M16: Q2 FY28E | N16: Q3 FY28E | O16: Q4 FY28E | P16: FY28E | Q16: FY29E | R16: FY30E | S16: FY31E | T16: FY32E | U16: FY33E | V16: FY34E | W16: FY35E
A17: Vaccines
B18: Prevenar 13 | C18: 2350 | D18: 2450 | E18: 2600 | F18: 2760 | G18: =Assumptions!$G$16 -> 681.46069 | H18: =(($F18*(1+Assumptions!$C$16)*Assumptions!$E$16)-$G18)*Assumptions!$J$16/SUM(Assumptions!$J$16:$L$16) -> 636.88311 | I18: =(($F18*(1+Assumptions!$C$16)*Assumptions!$E$16)-$G18)*Assumptions!$K$16/SUM(Assumptions!$J$16:$L$16) -> 692.26425 | J18: =(($F18*(1+Assumptions!$C$16)*Assumptions!$E$16)-$G18)*Assumptions!$L$16/SUM(Assumptions!$J$16:$L$16) -> 775.33596 | K18: =SUM(G18:J18) -> 2785.944 | L18: =($K18*(1+Assumptions!$C$16)*Assumptions!$F$16)*Assumptions!$I$16 -> 674.91165 | M18: =($K18*(1+Assumptions!$C$16)*Assumptions!$F$16)*Assumptions!$J$16 -> 646.79033 | N18: =($K18*(1+Assumptions!$C$16)*Assumptions!$F$16)*Assumptions!$K$16 -> 703.03297 | O18: =($K18*(1+Assumptions!$C$16)*Assumptions!$F$16)*Assumptions!$L$16 -> 787.39692 | P18: =SUM(L18:O18) -> 2812.1319 | Q18: =$P18*(1+Assumptions!$C$16)*Assumptions!$F$16 -> 2838.5659 | R18: =$Q18*(1+Assumptions!$C$16)*Assumptions!$F$16 -> 2865.2484 | S18: =$R18*(1+Assumptions!$D$16)*Assumptions!$F$16 -> 2819.4045 | T18: =$S18*(1+Assumptions!$D$16)*Assumptions!$F$16 -> 2774.294 | U18: =$T18*(1+Assumptions!$D$16)*Assumptions!$F$16 -> 2729.9053 | V18: =$U18*(1+Assumptions!$D$16)*Assumptions!$F$16 -> 2686.2268 | W18: =$V18*(1+Assumptions!$D$16)*Assumptions!$F$16 -> 2643.2472
B19: Prevenar 20 | C19: 0 | D19: 0 | E19: 0 | F19: 820 | G19: =Assumptions!$G$17 -> 278.90306 | H19: =(($F19*(1+Assumptions!$C$17)*Assumptions!$E$17)-$G19)*Assumptions!$J$17/SUM(Assumptions!$J$17:$L$17) -> 260.65868 | I19: =(($F19*(1+Assumptions!$C$17)*Assumptions!$E$17)-$G19)*Assumptions!$K$17/SUM(Assumptions!$J$17:$L$17) -> 283.32465 | J19: =(($F19*(1+Assumptions!$C$17)*Assumptions!$E$17)-$G19)*Assumptions!$L$17/SUM(Assumptions!$J$17:$L$17) -> 317.32361 | K19: =SUM(G19:J19) -> 1140.21 | L19: =($K19*(1+Assumptions!$C$17)*Assumptions!$F$17)*Assumptions!$I$17 -> 380.51088 | M19: =($K19*(1+Assumptions!$C$17)*Assumptions!$F$17)*Assumptions!$J$17 -> 364.65626 | N19: =($K19*(1+Assumptions!$C$17)*Assumptions!$F$17)*Assumptions!$K$17 -> 396.3655 | O19: =($K19*(1+Assumptions!$C$17)*Assumptions!$F$17)*Assumptions!$L$17 -> 443.92936 | P19: =SUM(L19:O19) -> 1585.462 | Q19: =$P19*(1+Assumptions!$C$17)*Assumptions!$F$17 -> 2204.5849 | R19: =$Q19*(1+Assumptions!$C$17)*Assumptions!$F$17 -> 3065.4753 | S19: =$R19*(1+Assumptions!$D$17)*Assumptions!$F$17 -> 3519.1657 | T19: =$S19*(1+Assumptions!$D$17)*Assumptions!$F$17 -> 4040.0022 | U19: =$T19*(1+Assumptions!$D$17)*Assumptions!$F$17 -> 4637.9225 | V19: =$U19*(1+Assumptions!$D$17)*Assumptions!$F$17 -> 5324.3351 | W19: =$V19*(1+Assumptions!$D$17)*Assumptions!$F$17 -> 6112.3366
B20: Other vaccines | C20: 130 | D20: 125 | E20: 120 | F20: 120 | G20: =Assumptions!$G$18 -> 30.838061 | H20: =(($F20*(1+Assumptions!$C$18)*Assumptions!$E$18)-$G20)*Assumptions!$J$18/SUM(Assumptions!$J$18:$L$18) -> 28.820797 | I20: =(($F20*(1+Assumptions!$C$18)*Assumptions!$E$18)-$G20)*Assumptions!$K$18/SUM(Assumptions!$J$18:$L$18) -> 31.326953 | J20: =(($F20*(1+Assumptions!$C$18)*Assumptions!$E$18)-$G20)*Assumptions!$L$18/SUM(Assumptions!$J$18:$L$18) -> 35.086188 | K20: =SUM(G20:J20) -> 126.072 | L20: =($K20*(1+Assumptions!$C$18)*Assumptions!$F$18)*Assumptions!$I$18 -> 31.788298 | M20: =($K20*(1+Assumptions!$C$18)*Assumptions!$F$18)*Assumptions!$J$18 -> 30.463786 | N20: =($K20*(1+Assumptions!$C$18)*Assumptions!$F$18)*Assumptions!$K$18 -> 33.112811 | O20: =($K20*(1+Assumptions!$C$18)*Assumptions!$F$18)*Assumptions!$L$18 -> 37.086348 | P20: =SUM(L20:O20) -> 132.45124 | Q20: =$P20*(1+Assumptions!$C$18)*Assumptions!$F$18 -> 139.15328 | R20: =$Q20*(1+Assumptions!$C$18)*Assumptions!$F$18 -> 146.19443 | S20: =$R20*(1+Assumptions!$D$18)*Assumptions!$F$18 -> 151.34779 | T20: =$S20*(1+Assumptions!$D$18)*Assumptions!$F$18 -> 156.6828 | U20: =$T20*(1+Assumptions!$D$18)*Assumptions!$F$18 -> 162.20586 | V20: =$U20*(1+Assumptions!$D$18)*Assumptions!$F$18 -> 167.92362 | W20: =$V20*(1+Assumptions!$D$18)*Assumptions!$F$18 -> 173.84293
B21: Abrysvo (pipeline) | C21: 0 | D21: 0 | E21: 0 | F21: 0 | G21: 0 | H21: 0 | I21: 0 | J21: 0 | K21: 0 | L21: 0 | M21: 0 | N21: 0 | O21: 0 | P21: 0 | Q21: =Assumptions!$C$72*Assumptions!$D$72 -> 162 | R21: =Assumptions!$C$72*Assumptions!$E$72 -> 364.5 | S21: =Assumptions!$C$72*Assumptions!$F$72 -> 567 | T21: =Assumptions!$C$72*Assumptions!$G$72 -> 729 | U21: =Assumptions!$C$72*Assumptions!$H$72 -> 810 | V21: =Assumptions!$C$72*Assumptions!$I$72 -> 810 | W21: =Assumptions!$C$72*Assumptions!$J$72 -> 810
A22: Vaccines | B22: Subtotal | C22: =SUM(C18:C21) -> 2480 | D22: =SUM(D18:D21) -> 2575 | E22: =SUM(E18:E21) -> 2720 | F22: =SUM(F18:F21) -> 3700 | G22: =SUM(G18:G21) -> 991.20181 | H22: =SUM(H18:H21) -> 926.36258 | I22: =SUM(I18:I21) -> 1006.9159 | J22: =SUM(J18:J21) -> 1127.7458 | ... W22: =SUM(W18:W21) -> 9739.4267
A24: Anti-infectives and hospital products
B25: Magnex | C25: 1700 | D25: 650 | E25: 1050 | F25: 1400 | G25: =Assumptions!$G$20 -> 379.09153 | H25: =(($F25*(1+Assumptions!$C$20)*Assumptions!$E$20)-$G25)*Assumptions!$J$20/SUM(Assumptions!$J$20:$L$20) -> 385.10147 | I25: =(($F25*(1+Assumptions!$C$20)*Assumptions!$E$20)-$G25)*Assumptions!$K$20/SUM(Assumptions!$J$20:$L$20) -> 385.10147 | J25: =(($F25*(1+Assumptions!$C$20)*Assumptions!$E$20)-$G25)*Assumptions!$L$20/SUM(Assumptions!$J$20:$L$20) -> 400.50553 | K25: =SUM(G25:J25) -> 1549.8 | L25: =($K25*(1+Assumptions!$C$20)*Assumptions!$F$20)*Assumptions!$I$20 -> 411.75086 | M25: =($K25*(1+Assumptions!$C$20)*Assumptions!$F$20)*Assumptions!$J$20 -> 428.90715 | N25: =($K25*(1+Assumptions!$C$20)*Assumptions!$F$20)*Assumptions!$K$20 -> 428.90715 | O25: =($K25*(1+Assumptions!$C$20)*Assumptions!$F$20)*Assumptions!$L$20 -> 446.06344 | P25: =SUM(L25:O25) -> 1715.6286 | Q25: =$P25*(1+Assumptions!$C$20)*Assumptions!$F$20 -> 1899.2009 | R25: =$Q25*(1+Assumptions!$C$20)*Assumptions!$F$20 -> 2102.4154 | S25: =$R25*(1+Assumptions!$D$20)*Assumptions!$F$20 -> 2251.6868 | T25: =$S25*(1+Assumptions!$D$20)*Assumptions!$F$20 -> 2411.5566 | U25: =$T25*(1+Assumptions!$D$20)*Assumptions!$F$20 -> 2582.7771 | V25: =$U25*(1+Assumptions!$D$20)*Assumptions!$F$20 -> 2766.1543 | W25: =$V25*(1+Assumptions!$D$20)*Assumptions!$F$20 -> 2962.5513
B26: Meronem | C26: 880 | D26: 820 | E26: 870 | F26: 920 | G26: =Assumptions!$G$21 -> 242.19737 | H26: =(($F26*(1+Assumptions!$C$21)*Assumptions!$E$21)-$G26)*Assumptions!$J$21/SUM(Assumptions!$J$21:$L$21) -> 246.03705 | I26: =(($F26*(1+Assumptions!$C$21)*Assumptions!$E$21)-$G26)*Assumptions!$K$21/SUM(Assumptions!$J$21:$L$21) -> 246.03705 | J26: =(($F26*(1+Assumptions!$C$21)*Assumptions!$E$21)-$G26)*Assumptions!$L$21/SUM(Assumptions!$J$21:$L$21) -> 255.87853 | K26: =SUM(G26:J26) -> 990.15 | L26: =($K26*(1+Assumptions!$C$21)*Assumptions!$F$21)*Assumptions!$I$21 -> 255.75575 | M26: =($K26*(1+Assumptions!$C$21)*Assumptions!$F$21)*Assumptions!$J$21 -> 266.41223 | N26: =($K26*(1+Assumptions!$C$21)*Assumptions!$F$21)*Assumptions!$K$21 -> 266.41223 | O26: =($K26*(1+Assumptions!$C$21)*Assumptions!$F$21)*Assumptions!$L$21 -> 277.06872 | P26: =SUM(L26:O26) -> 1065.6489 | Q26: =$P26*(1+Assumptions!$C$21)*Assumptions!$F$21 -> 1146.9047 | R26: =$Q26*(1+Assumptions!$C$21)*Assumptions!$F$21 -> 1234.3561 | S26: =$R26*(1+Assumptions!$D$21)*Assumptions!$F$21 -> 1296.8146 | T26: =$S26*(1+Assumptions!$D$21)*Assumptions!$F$21 -> 1362.4334 | U26: =$T26*(1+Assumptions!$D$21)*Assumptions!$F$21 -> 1431.3725 | V26: =$U26*(1+Assumptions!$D$21)*Assumptions!$F$21 -> 1503.8 | W26: =$V26*(1+Assumptions!$D$21)*Assumptions!$F$21 -> 1579.8922
B27: Zavicefta | C27: 650 | D27: 720 | E27: 800 | F27: 880 | G27: =Assumptions!$G$22 -> 238.28611 | H27: =(($F27*(1+Assumptions!$C$22)*Assumptions!$E$22)-$G27)*Assumptions!$J$22/SUM(Assumptions!$J$22:$L$22) -> 242.06378 | I27: =(($F27*(1+Assumptions!$C$22)*Assumptions!$E$22)-$G27)*Assumptions!$K$22/SUM(Assumptions!$J$22:$L$22) -> 242.06378 | J27: =(($F27*(1+Assumptions!$C$22)*Assumptions!$E$22)-$G27)*Assumptions!$L$22/SUM(Assumptions!$J$22:$L$22) -> 251.74633 | K27: =SUM(G27:J27) -> 974.16 | L27: =($K27*(1+Assumptions!$C$22)*Assumptions!$F$22)*Assumptions!$I$22 -> 258.81483 | M27: =($K27*(1+Assumptions!$C$22)*Assumptions!$F$22)*Assumptions!$J$22 -> 269.59878 | N27: =($K27*(1+Assumptions!$C$22)*Assumptions!$F$22)*Assumptions!$K$22 -> 269.59878 | O27: =($K27*(1+Assumptions!$C$22)*Assumptions!$F$22)*Assumptions!$L$22 -> 280.38273 | P27: =SUM(L27:O27) -> 1078.3951 | Q27: =$P27*(1+Assumptions!$C$22)*Assumptions!$F$22 -> 1193.7834 | R27: =$Q27*(1+Assumptions!$C$22)*Assumptions!$F$22 -> 1321.5182 | S27: =$R27*(1+Assumptions!$D$22)*Assumptions!$F$22 -> 1415.346 | T27: =$S27*(1+Assumptions!$D$22)*Assumptions!$F$22 -> 1515.8356 | U27: =$T27*(1+Assumptions!$D$22)*Assumptions!$F$22 -> 1623.4599 | V27: =$U27*(1+Assumptions!$D$22)*Assumptions!$F$22 -> 1738.7256 | W27: =$V27*(1+Assumptions!$D$22)*Assumptions!$F$22 -> 1862.1751
B28: Zithromax | C28: 350 | D28: 330 | E28: 315 | F28: 300 | G28: =Assumptions!$G$23 -> 75.216574 | H28: =(($F28*(1+Assumptions!$C$23)*Assumptions!$E$23)-$G28)*Assumptions!$J$23/SUM(Assumptions!$J$23:$L$23) -> 76.409022 | I28: =(($F28*(1+Assumptions!$C$23)*Assumptions!$E$23)-$G28)*Assumptions!$K$23/SUM(Assumptions!$J$23:$L$23) -> 76.409022 | J28: =(($F28*(1+Assumptions!$C$23)*Assumptions!$E$23)-$G28)*Assumptions!$L$23/SUM(Assumptions!$J$23:$L$23) -> 79.465383 | K28: =SUM(G28:J28) -> 307.5 | L28: =($K28*(1+Assumptions!$C$23)*Assumptions!$F$23)*Assumptions!$I$23 -> 75.645 | M28: =($K28*(1+Assumptions!$C$23)*Assumptions!$F$23)*Assumptions!$J$23 -> 78.796875 | N28: =($K28*(1+Assumptions!$C$23)*Assumptions!$F$23)*Assumptions!$K$23 -> 78.796875 | O28: =($K28*(1+Assumptions!$C$23)*Assumptions!$F$23)*Assumptions!$L$23 -> 81.94875 | P28: =SUM(L28:O28) -> 315.1875 | Q28: =$P28*(1+Assumptions!$C$23)*Assumptions!$F$23 -> 323.06719 | R28: =$Q28*(1+Assumptions!$C$23)*Assumptions!$F$23 -> 331.14387 | S28: =$R28*(1+Assumptions!$D$23)*Assumptions!$F$23 -> 331.01141 | T28: =$S28*(1+Assumptions!$D$23)*Assumptions!$F$23 -> 330.87901 | U28: =$T28*(1+Assumptions!$D$23)*Assumptions!$F$23 -> 330.74665 | V28: =$U28*(1+Assumptions!$D$23)*Assumptions!$F$23 -> 330.61435 | W28: =$V28*(1+Assumptions!$D$23)*Assumptions!$F$23 -> 330.48211
B29: Emblaveo | C29: 0 | D29: 0 | E29: 0 | F29: 180 | G29: =Assumptions!$G$24 -> 65.438419 | H29: =(($F29*(1+Assumptions!$C$24)*Assumptions!$E$24)-$G29)*Assumptions!$J$24/SUM(Assumptions!$J$24:$L$24) -> 66.475849 | I29: =(($F29*(1+Assumptions!$C$24)*Assumptions!$E$24)-$G29)*Assumptions!$K$24/SUM(Assumptions!$J$24:$L$24) -> 66.475849 | J29: =(($F29*(1+Assumptions!$C$24)*Assumptions!$E$24)-$G29)*Assumptions!$L$24/SUM(Assumptions!$J$24:$L$24) -> 69.134883 | K29: =SUM(G29:J29) -> 267.525 | L29: =($K29*(1+Assumptions!$C$24)*Assumptions!$F$24)*Assumptions!$I$24 -> 95.426167 | M29: =($K29*(1+Assumptions!$C$24)*Assumptions!$F$24)*Assumptions!$J$24 -> 99.402258 | N29: =($K29*(1+Assumptions!$C$24)*Assumptions!$F$24)*Assumptions!$K$24 -> 99.402258 | O29: =($K29*(1+Assumptions!$C$24)*Assumptions!$F$24)*Assumptions!$L$24 -> 103.37835 | P29: =SUM(L29:O29) -> 397.60903 | Q29: =$P29*(1+Assumptions!$C$24)*Assumptions!$F$24 -> 590.94642 | R29: =$Q29*(1+Assumptions!$C$24)*Assumptions!$F$24 -> 878.29412 | S29: =$R29*(1+Assumptions!$D$24)*Assumptions!$F$24 -> 1030.239 | T29: =$S29*(1+Assumptions!$D$24)*Assumptions!$F$24 -> 1208.4704 | U29: =$T29*(1+Assumptions!$D$24)*Assumptions!$F$24 -> 1417.5357 | V29: =$U29*(1+Assumptions!$D$24)*Assumptions!$F$24 -> 1662.7694 | W29: =$V29*(1+Assumptions!$D$24)*Assumptions!$F$24 -> 1950.4285
B30: Other hospital and anti-infective products | C30: 680 | D30: 480 | E30: 540 | F30: 600 | G30: =Assumptions!$G$25 -> 154.94614 | H30: =(($F30*(1+Assumptions!$C$25)*Assumptions!$E$25)-$G30)*Assumptions!$J$25/SUM(Assumptions!$J$25:$L$25) -> 157.40258 | I30: =(($F30*(1+Assumptions!$C$25)*Assumptions!$E$25)-$G30)*Assumptions!$K$25/SUM(Assumptions!$J$25:$L$25) -> 157.40258 | J30: =(($F30*(1+Assumptions!$C$25)*Assumptions!$E$25)-$G30)*Assumptions!$L$25/SUM(Assumptions!$J$25:$L$25) -> 163.69869 | K30: =SUM(G30:J30) -> 633.45 | L30: =($K30*(1+Assumptions!$C$25)*Assumptions!$F$25)*Assumptions!$I$25 -> 160.50356 | M30: =($K30*(1+Assumptions!$C$25)*Assumptions!$F$25)*Assumptions!$J$25 -> 167.19121 | N30: =($K30*(1+Assumptions!$C$25)*Assumptions!$F$25)*Assumptions!$K$25 -> 167.19121 | O30: =($K30*(1+Assumptions!$C$25)*Assumptions!$F$25)*Assumptions!$L$25 -> 173.87886 | P30: =SUM(L30:O30) -> 668.76484 | Q30: =$P30*(1+Assumptions!$C$25)*Assumptions!$F$25 -> 706.04848 | R30: =$Q30*(1+Assumptions!$C$25)*Assumptions!$F$25 -> 745.41068 | S30: =$R30*(1+Assumptions!$D$25)*Assumptions!$F$25 -> 775.52527 | T30: =$S30*(1+Assumptions!$D$25)*Assumptions!$F$25 -> 806.85649 | U30: =$T30*(1+Assumptions!$D$25)*Assumptions!$F$25 -> 839.45349 | V30: =$U30*(1+Assumptions!$D$25)*Assumptions!$F$25 -> 873.36742 | W30: =$V30*(1+Assumptions!$D$25)*Assumptions!$F$25 -> 908.65146
A31: Anti-infectives and hospital products | B31: Subtotal | C31: =SUM(C25:C30) -> 4260 | D31: =SUM(D25:D30) -> 3000 | E31: =SUM(E25:E30) -> 3575 | F31: =SUM(F25:F30) -> 4280 | G31: =SUM(G25:G30) -> 1155.1761 | H31: =SUM(H25:H30) -> 1173.4898 | I31: =SUM(I25:I30) -> 1173.4898 | J31: =SUM(J25:J30) -> 1220.4293 | ... W31: =SUM(W25:W30) -> 9594.1807
A33: Cardiovascular and anticoagulation
B34: Eliquis | C34: 1150 | D34: 1300 | E34: 1446 | F34: 1880 | G34: =Assumptions!$G$26 -> 527.92006 | H34: =(($F34*(1+Assumptions!$C$26)*Assumptions!$E$26)-$G34)*Assumptions!$J$26/SUM(Assumptions!$J$26:$L$26) -> 536.28945 | I34: =(($F34*(1+Assumptions!$C$26)*Assumptions!$E$26)-$G34)*Assumptions!$K$26/SUM(Assumptions!$J$26:$L$26) -> 536.28945 | J34: =(($F34*(1+Assumptions!$C$26)*Assumptions!$E$26)-$G34)*Assumptions!$L$26/SUM(Assumptions!$J$26:$L$26) -> 557.74103 | K34: =SUM(G34:J34) -> 2158.24 | L34: =($K34*(1+Assumptions!$C$26)*Assumptions!$F$26)*Assumptions!$I$26 -> 594.63828 | M34: =($K34*(1+Assumptions!$C$26)*Assumptions!$F$26)*Assumptions!$J$26 -> 619.41488 | N34: =($K34*(1+Assumptions!$C$26)*Assumptions!$F$26)*Assumptions!$K$26 -> 619.41488 | O34: =($K34*(1+Assumptions!$C$26)*Assumptions!$F$26)*Assumptions!$L$26 -> 644.19148 | P34: =SUM(L34:O34) -> 2477.6595 | Q34: =$P34*(1+Assumptions!$C$26)*Assumptions!$F$26 -> 2844.3531 | R34: =$Q34*(1+Assumptions!$C$26)*Assumptions!$F$26 -> 3265.3174 | S34: =$R34*(1+Assumptions!$D$26)*Assumptions!$F$26 -> 3530.4612 | T34: =$S34*(1+Assumptions!$D$26)*Assumptions!$F$26 -> 3817.1346 | U34: =$T34*(1+Assumptions!$D$26)*Assumptions!$F$26 -> 4127.0859 | V34: =$U34*(1+Assumptions!$D$26)*Assumptions!$F$26 -> 4462.2053 | W34: =$V34*(1+Assumptions!$D$26)*Assumptions!$F$26 -> 4824.5364
B35: Minipress XL | C35: 1400 | D35: 1500 | E35: 1600 | F35: 1725 | G35: =Assumptions!$G$27 -> 445.47016 | H35: =(($F35*(1+Assumptions!$C$27)*Assumptions!$E$27)-$G35)*Assumptions!$J$27/SUM(Assumptions!$J$27:$L$27) -> 341.46914 | I35: =(($F35*(1+Assumptions!$C$27)*Assumptions!$E$27)-$G35)*Assumptions!$K$27/SUM(Assumptions!$J$27:$L$27) -> 0 | J35: =(($F35*(1+Assumptions!$C$27)*Assumptions!$E$27)-$G35)*Assumptions!$L$27/SUM(Assumptions!$J$27:$L$27) -> 0 | K35: =SUM(G35:J35) -> 786.9393 | L35: =($K35*(1+Assumptions!$C$27)*Assumptions!$F$27)*Assumptions!$I$27 -> 0 | M35: =($K35*(1+Assumptions!$C$27)*Assumptions!$F$27)*Assumptions!$J$27 -> 0 | N35: =($K35*(1+Assumptions!$C$27)*Assumptions!$F$27)*Assumptions!$K$27 -> 0 | O35: =($K35*(1+Assumptions!$C$27)*Assumptions!$F$27)*Assumptions!$L$27 -> 0 | P35: =SUM(L35:O35) -> 0 | Q35: =$P35*(1+Assumptions!$C$27)*Assumptions!$F$27 -> 0 | R35: =$Q35*(1+Assumptions!$C$27)*Assumptions!$F$27 -> 0 | S35: =$R35*(1+Assumptions!$D$27)*Assumptions!$F$27 -> 0 | T35: =$S35*(1+Assumptions!$D$27)*Assumptions!$F$27 -> 0 | U35: =$T35*(1+Assumptions!$D$27)*Assumptions!$F$27 -> 0 | V35: =$U35*(1+Assumptions!$D$27)*Assumptions!$F$27 -> 0 | W35: =$V35*(1+Assumptions!$D$27)*Assumptions!$F$27 -> 0
B36: Amlogard | C36: 250 | D36: 0 | E36: 0 | F36: 0 | G36: =Assumptions!$G$28 -> 0 | H36: =(($F36*(1+Assumptions!$C$28)*Assumptions!$E$28)-$G36)*Assumptions!$J$28/SUM(Assumptions!$J$28:$L$28) -> 0 | I36: =(($F36*(1+Assumptions!$C$28)*Assumptions!$E$28)-$G36)*Assumptions!$K$28/SUM(Assumptions!$J$28:$L$28) -> 0 | J36: =(($F36*(1+Assumptions!$C$28)*Assumptions!$E$28)-$G36)*Assumptions!$L$28/SUM(Assumptions!$J$28:$L$28) -> 0 | K36: =SUM(G36:J36) -> 0 | L36: =($K36*(1+Assumptions!$C$28)*Assumptions!$F$28)*Assumptions!$I$28 -> 0 | M36: =($K36*(1+Assumptions!$C$28)*Assumptions!$F$28)*Assumptions!$J$28 -> 0 | N36: =($K36*(1+Assumptions!$C$28)*Assumptions!$F$28)*Assumptions!$K$28 -> 0 | O36: =($K36*(1+Assumptions!$C$28)*Assumptions!$F$28)*Assumptions!$L$28 -> 0 | P36: =SUM(L36:O36) -> 0 | Q36: =$P36*(1+Assumptions!$C$28)*Assumptions!$F$28 -> 0 | R36: =$Q36*(1+Assumptions!$C$28)*Assumptions!$F$28 -> 0 | S36: =$R36*(1+Assumptions!$D$28)*Assumptions!$F$28 -> 0 | T36: =$S36*(1+Assumptions!$D$28)*Assumptions!$F$28 -> 0 | U36: =$T36*(1+Assumptions!$D$28)*Assumptions!$F$28 -> 0 | V36: =$U36*(1+Assumptions!$D$28)*Assumptions!$F$28 -> 0 | W36: =$V36*(1+Assumptions!$D$28)*Assumptions!$F$28 -> 0
B37: Other cardiovascular products | C37: 350 | D37: 320 | E37: 310 | F37: 300 | G37: =Assumptions!$G$29 -> 76.720905 | H37: =(($F37*(1+Assumptions!$C$29)*Assumptions!$E$29)-$G37)*Assumptions!$J$29/SUM(Assumptions!$J$29:$L$29) -> 77.937202 | I37: =(($F37*(1+Assumptions!$C$29)*Assumptions!$E$29)-$G37)*Assumptions!$K$29/SUM(Assumptions!$J$29:$L$29) -> 77.937202 | J37: =(($F37*(1+Assumptions!$C$29)*Assumptions!$E$29)-$G37)*Assumptions!$L$29/SUM(Assumptions!$J$29:$L$29) -> 81.05469 | K37: =SUM(G37:J37) -> 313.65 | L37: =($K37*(1+Assumptions!$C$29)*Assumptions!$F$29)*Assumptions!$I$29 -> 78.701058 | M37: =($K37*(1+Assumptions!$C$29)*Assumptions!$F$29)*Assumptions!$J$29 -> 81.980269 | N37: =($K37*(1+Assumptions!$C$29)*Assumptions!$F$29)*Assumptions!$K$29 -> 81.980269 | O37: =($K37*(1+Assumptions!$C$29)*Assumptions!$F$29)*Assumptions!$L$29 -> 85.259479 | P37: =SUM(L37:O37) -> 327.92107 | Q37: =$P37*(1+Assumptions!$C$29)*Assumptions!$F$29 -> 342.84148 | R37: =$Q37*(1+Assumptions!$C$29)*Assumptions!$F$29 -> 358.44077 | S37: =$R37*(1+Assumptions!$D$29)*Assumptions!$F$29 -> 369.26568 | T37: =$S37*(1+Assumptions!$D$29)*Assumptions!$F$29 -> 380.41751 | U37: =$T37*(1+Assumptions!$D$29)*Assumptions!$F$29 -> 391.90612 | V37: =$U37*(1+Assumptions!$D$29)*Assumptions!$F$29 -> 403.74168 | W37: =$V37*(1+Assumptions!$D$29)*Assumptions!$F$29 -> 415.93468
A38: Cardiovascular and anticoagulation | B38: Subtotal | C38: =SUM(C34:C37) -> 3150 | D38: =SUM(D34:D37) -> 3120 | E38: =SUM(E34:E37) -> 3356 | F38: =SUM(F34:F37) -> 3905 | G38: =SUM(G34:G37) -> 1050.1111 | H38: =SUM(H34:H37) -> 955.6958 | I38: =SUM(I34:I37) -> 614.22666 | J38: =SUM(J34:J37) -> 638.79572 | ... W38: =SUM(W34:W37) -> 5240.4711
A40: Vitamins and nutritional products
B41: Becosules | C41: 1900 | D41: 1980 | E41: 2100 | F41: 2230 | G41: =Assumptions!$G$30 -> 565.34871 | H41: =(($F41*(1+Assumptions!$C$30)*Assumptions!$E$30)-$G41)*Assumptions!$J$30/SUM(Assumptions!$J$30:$L$30) -> 623.45849 | I41: =(($F41*(1+Assumptions!$C$30)*Assumptions!$E$30)-$G41)*Assumptions!$K$30/SUM(Assumptions!$J$30:$L$30) -> 623.45849 | J41: =(($F41*(1+Assumptions!$C$30)*Assumptions!$E$30)-$G41)*Assumptions!$L$30/SUM(Assumptions!$J$30:$L$30) -> 599.47931 | K41: =SUM(G41:J41) -> 2411.745 | L41: =($K41*(1+Assumptions!$C$30)*Assumptions!$F$30)*Assumptions!$I$30 -> 599.90951 | M41: =($K41*(1+Assumptions!$C$30)*Assumptions!$F$30)*Assumptions!$J$30 -> 678.15858 | N41: =($K41*(1+Assumptions!$C$30)*Assumptions!$F$30)*Assumptions!$K$30 -> 678.15858 | O41: =($K41*(1+Assumptions!$C$30)*Assumptions!$F$30)*Assumptions!$L$30 -> 652.07555 | P41: =SUM(L41:O41) -> 2608.3022 | Q41: =$P41*(1+Assumptions!$C$30)*Assumptions!$F$30 -> 2820.8788 | R41: =$Q41*(1+Assumptions!$C$30)*Assumptions!$F$30 -> 3050.7805 | S41: =$R41*(1+Assumptions!$D$30)*Assumptions!$F$30 -> 3220.8615 | T41: =$S41*(1+Assumptions!$D$30)*Assumptions!$F$30 -> 3400.4245 | U41: =$T41*(1+Assumptions!$D$30)*Assumptions!$F$30 -> 3589.9982 | V41: =$U41*(1+Assumptions!$D$30)*Assumptions!$F$30 -> 3790.1406 | W41: =$V41*(1+Assumptions!$D$30)*Assumptions!$F$30 -> 4001.4409
B42: Other nutritional products | C42: 170 | D42: 160 | E42: 155 | F42: 150 | G42: =Assumptions!$G$31 -> 36.941428 | H42: =(($F42*(1+Assumptions!$C$31)*Assumptions!$E$31)-$G42)*Assumptions!$J$31/SUM(Assumptions!$J$31:$L$31) -> 40.738479 | I42: =(($F42*(1+Assumptions!$C$31)*Assumptions!$E$31)-$G42)*Assumptions!$K$31/SUM(Assumptions!$J$31:$L$31) -> 40.738479 | J42: =(($F42*(1+Assumptions!$C$31)*Assumptions!$E$31)-$G42)*Assumptions!$L$31/SUM(Assumptions!$J$31:$L$31) -> 39.171614 | K42: =SUM(G42:J42) -> 157.59 | L42: =($K42*(1+Assumptions!$C$31)*Assumptions!$F$31)*Assumptions!$I$31 -> 38.079732 | M42: =($K42*(1+Assumptions!$C$31)*Assumptions!$F$31)*Assumptions!$J$31 -> 43.046654 | N42: =($K42*(1+Assumptions!$C$31)*Assumptions!$F$31)*Assumptions!$K$31 -> 43.046654 | O42: =($K42*(1+Assumptions!$C$31)*Assumptions!$F$31)*Assumptions!$L$31 -> 41.391014 | P42: =SUM(L42:O42) -> 165.56405 | Q42: =$P42*(1+Assumptions!$C$31)*Assumptions!$F$31 -> 173.9416 | R42: =$Q42*(1+Assumptions!$C$31)*Assumptions!$F$31 -> 182.74304 | S42: =$R42*(1+Assumptions!$D$31)*Assumptions!$F$31 -> 189.18473 | T42: =$S42*(1+Assumptions!$D$31)*Assumptions!$F$31 -> 195.85349 | U42: =$T42*(1+Assumptions!$D$31)*Assumptions!$F$31 -> 202.75733 | V42: =$U42*(1+Assumptions!$D$31)*Assumptions!$F$31 -> 209.90453 | W42: =$V42*(1+Assumptions!$D$31)*Assumptions!$F$31 -> 217.30366
A43: Vitamins and nutritional products | B43: Subtotal | C43: =SUM(C41:C42) -> 2070 | D43: =SUM(D41:D42) -> 2140 | E43: =SUM(E41:E42) -> 2255 | F43: =SUM(F41:F42) -> 2380 | G43: =SUM(G41:G42) -> 602.29014 | H43: =SUM(H41:H42) -> 664.19697 | I43: =SUM(I41:I42) -> 664.19697 | J43: =SUM(J41:J42) -> 638.65093 | ... W43: =SUM(W41:W42) -> 4218.7446
A45: Gastrointestinal
B46: Mucaine | C46: 1100 | D46: 1150 | E46: 1220 | F46: 1310 | G46: =Assumptions!$G$32 -> 332.11068 | H46: =(($F46*(1+Assumptions!$C$32)*Assumptions!$E$32)-$G46)*Assumptions!$J$32/SUM(Assumptions!$J$32:$L$32) -> 366.24691 | I46: =(($F46*(1+Assumptions!$C$32)*Assumptions!$E$32)-$G46)*Assumptions!$K$32/SUM(Assumptions!$J$32:$L$32) -> 366.24691 | J46: =(($F46*(1+Assumptions!$C$32)*Assumptions!$E$32)-$G46)*Assumptions!$L$32/SUM(Assumptions!$J$32:$L$32) -> 352.16049 | K46: =SUM(G46:J46) -> 1416.765 | L46: =($K46*(1+Assumptions!$C$32)*Assumptions!$F$32)*Assumptions!$I$32 -> 352.41321 | M46: =($K46*(1+Assumptions!$C$32)*Assumptions!$F$32)*Assumptions!$J$32 -> 398.38015 | N46: =($K46*(1+Assumptions!$C$32)*Assumptions!$F$32)*Assumptions!$K$32 -> 398.38015 | O46: =($K46*(1+Assumptions!$C$32)*Assumptions!$F$32)*Assumptions!$L$32 -> 383.05784 | P46: =SUM(L46:O46) -> 1532.2313 | Q46: =$P46*(1+Assumptions!$C$32)*Assumptions!$F$32 -> 1657.1082 | R46: =$Q46*(1+Assumptions!$C$32)*Assumptions!$F$32 -> 1792.1625 | S46: =$R46*(1+Assumptions!$D$32)*Assumptions!$F$32 -> 1892.0756 | T46: =$S46*(1+Assumptions!$D$32)*Assumptions!$F$32 -> 1997.5588 | U46: =$T46*(1+Assumptions!$D$32)*Assumptions!$F$32 -> 2108.9227 | V46: =$U46*(1+Assumptions!$D$32)*Assumptions!$F$32 -> 2226.4951 | W46: =$V46*(1+Assumptions!$D$32)*Assumptions!$F$32 -> 2350.6222
B47: Gelusil-MPS | C47: 800 | D47: 820 | E47: 850 | F47: 900 | G47: =Assumptions!$G$33 -> 225.99462 | H47: =(($F47*(1+Assumptions!$C$33)*Assumptions!$E$33)-$G47)*Assumptions!$J$33/SUM(Assumptions!$J$33:$L$33) -> 249.22364 | I47: =(($F47*(1+Assumptions!$C$33)*Assumptions!$E$33)-$G47)*Assumptions!$K$33/SUM(Assumptions!$J$33:$L$33) -> 249.22364 | J47: =(($F47*(1+Assumptions!$C$33)*Assumptions!$E$33)-$G47)*Assumptions!$L$33/SUM(Assumptions!$J$33:$L$33) -> 239.63811 | K47: =SUM(G47:J47) -> 964.08 | L47: =($K47*(1+Assumptions!$C$33)*Assumptions!$F$33)*Assumptions!$I$33 -> 237.52617 | M47: =($K47*(1+Assumptions!$C$33)*Assumptions!$F$33)*Assumptions!$J$33 -> 268.50785 | N47: =($K47*(1+Assumptions!$C$33)*Assumptions!$F$33)*Assumptions!$K$33 -> 268.50785 | O47: =($K47*(1+Assumptions!$C$33)*Assumptions!$F$33)*Assumptions!$L$33 -> 258.18062 | P47: =SUM(L47:O47) -> 1032.7225 | Q47: =$P47*(1+Assumptions!$C$33)*Assumptions!$F$33 -> 1106.2523 | R47: =$Q47*(1+Assumptions!$C$33)*Assumptions!$F$33 -> 1185.0175 | S47: =$R47*(1+Assumptions!$D$33)*Assumptions!$F$33 -> 1238.9358 | T47: =$S47*(1+Assumptions!$D$33)*Assumptions!$F$33 -> 1295.3074 | U47: =$T47*(1+Assumptions!$D$33)*Assumptions!$F$33 -> 1354.2439 | V47: =$U47*(1+Assumptions!$D$33)*Assumptions!$F$33 -> 1415.862 | W47: =$V47*(1+Assumptions!$D$33)*Assumptions!$F$33 -> 1480.2837
B48: Neksium | C48: 360 | D48: 350 | E48: 345 | F48: 350 | G48: =Assumptions!$G$34 -> 83.053022 | H48: =(($F48*(1+Assumptions!$C$34)*Assumptions!$E$34)-$G48)*Assumptions!$J$34/SUM(Assumptions!$J$34:$L$34) -> 91.589686 | I48: =(($F48*(1+Assumptions!$C$34)*Assumptions!$E$34)-$G48)*Assumptions!$K$34/SUM(Assumptions!$J$34:$L$34) -> 91.589686 | J48: =(($F48*(1+Assumptions!$C$34)*Assumptions!$E$34)-$G48)*Assumptions!$L$34/SUM(Assumptions!$J$34:$L$34) -> 88.067006 | K48: =SUM(G48:J48) -> 354.2994 | L48: =($K48*(1+Assumptions!$C$34)*Assumptions!$F$34)*Assumptions!$I$34 -> 90.64821 | M48: =($K48*(1+Assumptions!$C$34)*Assumptions!$F$34)*Assumptions!$J$34 -> 102.47189 | N48: =($K48*(1+Assumptions!$C$34)*Assumptions!$F$34)*Assumptions!$K$34 -> 102.47189 | O48: =($K48*(1+Assumptions!$C$34)*Assumptions!$F$34)*Assumptions!$L$34 -> 98.530663 | P48: =SUM(L48:O48) -> 394.12265 | Q48: =$P48*(1+Assumptions!$C$34)*Assumptions!$F$34 -> 438.42204 | R48: =$Q48*(1+Assumptions!$C$34)*Assumptions!$F$34 -> 487.70068 | S48: =$R48*(1+Assumptions!$D$34)*Assumptions!$F$34 -> 519.88892 | T48: =$S48*(1+Assumptions!$D$34)*Assumptions!$F$34 -> 554.20159 | U48: =$T48*(1+Assumptions!$D$34)*Assumptions!$F$34 -> 590.77889 | V48: =$U48*(1+Assumptions!$D$34)*Assumptions!$F$34 -> 629.7703 | W48: =$V48*(1+Assumptions!$D$34)*Assumptions!$F$34 -> 671.33514
B49: Other gastrointestinal products | C49: 190 | D49: 180 | E49: 175 | F49: 180 | G49: =Assumptions!$G$35 -> 44.329713 | H49: =(($F49*(1+Assumptions!$C$35)*Assumptions!$E$35)-$G49)*Assumptions!$J$35/SUM(Assumptions!$J$35:$L$35) -> 48.886175 | I49: =(($F49*(1+Assumptions!$C$35)*Assumptions!$E$35)-$G49)*Assumptions!$K$35/SUM(Assumptions!$J$35:$L$35) -> 48.886175 | J49: =(($F49*(1+Assumptions!$C$35)*Assumptions!$E$35)-$G49)*Assumptions!$L$35/SUM(Assumptions!$J$35:$L$35) -> 47.005937 | K49: =SUM(G49:J49) -> 189.108 | L49: =($K49*(1+Assumptions!$C$35)*Assumptions!$F$35)*Assumptions!$I$35 -> 45.695679 | M49: =($K49*(1+Assumptions!$C$35)*Assumptions!$F$35)*Assumptions!$J$35 -> 51.655985 | N49: =($K49*(1+Assumptions!$C$35)*Assumptions!$F$35)*Assumptions!$K$35 -> 51.655985 | O49: =($K49*(1+Assumptions!$C$35)*Assumptions!$F$35)*Assumptions!$L$35 -> 49.669216 | P49: =SUM(L49:O49) -> 198.67686 | Q49: =$P49*(1+Assumptions!$C$35)*Assumptions!$F$35 -> 208.72991 | R49: =$Q49*(1+Assumptions!$C$35)*Assumptions!$F$35 -> 219.29165 | S49: =$R49*(1+Assumptions!$D$35)*Assumptions!$F$35 -> 227.02168 | T49: =$S49*(1+Assumptions!$D$35)*Assumptions!$F$35 -> 235.02419 | U49: =$T49*(1+Assumptions!$D$35)*Assumptions!$F$35 -> 243.3088 | V49: =$U49*(1+Assumptions!$D$35)*Assumptions!$F$35 -> 251.88543 | W49: =$V49*(1+Assumptions!$D$35)*Assumptions!$F$35 -> 260.76439
A50: Gastrointestinal | B50: Subtotal | C50: =SUM(C46:C49) -> 2450 | D50: =SUM(D46:D49) -> 2500 | E50: =SUM(E46:E49) -> 2590 | F50: =SUM(F46:F49) -> 2740 | G50: =SUM(G46:G49) -> 685.48803 | H50: =SUM(H46:H49) -> 755.94641 | I50: =SUM(I46:I49) -> 755.94641 | J50: =SUM(J46:J49) -> 726.87155 | ... W50: =SUM(W46:W49) -> 4763.0055
A52: Respiratory and cough
B53: Corex DX | C53: 520 | D53: 510 | E53: 500 | F53: 500 | G53: =Assumptions!$G$36 -> 118.64717 | H53: =(($F53*(1+Assumptions!$C$36)*Assumptions!$E$36)-$G53)*Assumptions!$J$36/SUM(Assumptions!$J$36:$L$36) -> 130.84241 | I53: =(($F53*(1+Assumptions!$C$36)*Assumptions!$E$36)-$G53)*Assumptions!$K$36/SUM(Assumptions!$J$36:$L$36) -> 130.84241 | J53: =(($F53*(1+Assumptions!$C$36)*Assumptions!$E$36)-$G53)*Assumptions!$L$36/SUM(Assumptions!$J$36:$L$36) -> 125.81001 | K53: =SUM(G53:J53) -> 506.142 | L53: =($K53*(1+Assumptions!$C$36)*Assumptions!$F$36)*Assumptions!$I$36 -> 129.49744 | M53: =($K53*(1+Assumptions!$C$36)*Assumptions!$F$36)*Assumptions!$J$36 -> 146.38841 | N53: =($K53*(1+Assumptions!$C$36)*Assumptions!$F$36)*Assumptions!$K$36 -> 146.38841 | O53: =($K53*(1+Assumptions!$C$36)*Assumptions!$F$36)*Assumptions!$L$36 -> 140.75809 | P53: =SUM(L53:O53) -> 563.03236 | Q53: =$P53*(1+Assumptions!$C$36)*Assumptions!$F$36 -> 626.3172 | R53: =$Q53*(1+Assumptions!$C$36)*Assumptions!$F$36 -> 696.71525 | S53: =$R53*(1+Assumptions!$D$36)*Assumptions!$F$36 -> 742.69846 | T53: =$S53*(1+Assumptions!$D$36)*Assumptions!$F$36 -> 791.71656 | U53: =$T53*(1+Assumptions!$D$36)*Assumptions!$F$36 -> 843.96985 | V53: =$U53*(1+Assumptions!$D$36)*Assumptions!$F$36 -> 899.67186 | W53: =$V53*(1+Assumptions!$D$36)*Assumptions!$F$36 -> 959.0502
B54: Corex LS | C54: 360 | D54: 370 | E54: 380 | F54: 400 | G54: =Assumptions!$G$37 -> 94.917739 | H54: =(($F54*(1+Assumptions!$C$37)*Assumptions!$E$37)-$G54)*Assumptions!$J$37/SUM(Assumptions!$J$37:$L$37) -> 104.67393 | I54: =(($F54*(1+Assumptions!$C$37)*Assumptions!$E$37)-$G54)*Assumptions!$K$37/SUM(Assumptions!$J$37:$L$37) -> 104.67393 | J54: =(($F54*(1+Assumptions!$C$37)*Assumptions!$E$37)-$G54)*Assumptions!$L$37/SUM(Assumptions!$J$37:$L$37) -> 100.64801 | K54: =SUM(G54:J54) -> 404.9136 | L54: =($K54*(1+Assumptions!$C$37)*Assumptions!$F$37)*Assumptions!$I$37 -> 103.59795 | M54: =($K54*(1+Assumptions!$C$37)*Assumptions!$F$37)*Assumptions!$J$37 -> 117.11073 | N54: =($K54*(1+Assumptions!$C$37)*Assumptions!$F$37)*Assumptions!$K$37 -> 117.11073 | O54: =($K54*(1+Assumptions!$C$37)*Assumptions!$F$37)*Assumptions!$L$37 -> 112.60647 | P54: =SUM(L54:O54) -> 450.42589 | Q54: =$P54*(1+Assumptions!$C$37)*Assumptions!$F$37 -> 501.05376 | R54: =$Q54*(1+Assumptions!$C$37)*Assumptions!$F$37 -> 557.3722 | S54: =$R54*(1+Assumptions!$D$37)*Assumptions!$F$37 -> 594.15877 | T54: =$S54*(1+Assumptions!$D$37)*Assumptions!$F$37 -> 633.37324 | U54: =$T54*(1+Assumptions!$D$37)*Assumptions!$F$37 -> 675.17588 | V54: =$U54*(1+Assumptions!$D$37)*Assumptions!$F$37 -> 719.73749 | W54: =$V54*(1+Assumptions!$D$37)*Assumptions!$F$37 -> 767.24016
B55: Other respiratory products | C55: 120 | D55: 110 | E55: 100 | F55: 100 | G55: =Assumptions!$G$38 -> 24.627618 | H55: =(($F55*(1+Assumptions!$C$38)*Assumptions!$E$38)-$G55)*Assumptions!$J$38/SUM(Assumptions!$J$38:$L$38) -> 27.158986 | I55: =(($F55*(1+Assumptions!$C$38)*Assumptions!$E$38)-$G55)*Assumptions!$K$38/SUM(Assumptions!$J$38:$L$38) -> 27.158986 | J55: =(($F55*(1+Assumptions!$C$38)*Assumptions!$E$38)-$G55)*Assumptions!$L$38/SUM(Assumptions!$J$38:$L$38) -> 26.11441 | K55: =SUM(G55:J55) -> 105.06 | L55: =($K55*(1+Assumptions!$C$38)*Assumptions!$F$38)*Assumptions!$I$38 -> 25.386488 | M55: =($K55*(1+Assumptions!$C$38)*Assumptions!$F$38)*Assumptions!$J$38 -> 28.697769 | N55: =($K55*(1+Assumptions!$C$38)*Assumptions!$F$38)*Assumptions!$K$38 -> 28.697769 | O55: =($K55*(1+Assumptions!$C$38)*Assumptions!$F$38)*Assumptions!$L$38 -> 27.594009 | P55: =SUM(L55:O55) -> 110.37604 | Q55: =$P55*(1+Assumptions!$C$38)*Assumptions!$F$38 -> 115.96106 | R55: =$Q55*(1+Assumptions!$C$38)*Assumptions!$F$38 -> 121.82869 | S55: =$R55*(1+Assumptions!$D$38)*Assumptions!$F$38 -> 126.12315 | T55: =$S55*(1+Assumptions!$D$38)*Assumptions!$F$38 -> 130.569 | U55: =$T55*(1+Assumptions!$D$38)*Assumptions!$F$38 -> 135.17155 | V55: =$U55*(1+Assumptions!$D$38)*Assumptions!$F$38 -> 139.93635 | W55: =$V55*(1+Assumptions!$D$38)*Assumptions!$F$38 -> 144.86911
A56: Respiratory and cough | B56: Subtotal | C56: =SUM(C53:C55) -> 1000 | D56: =SUM(D53:D55) -> 990 | E56: =SUM(E53:E55) -> 980 | F56: =SUM(F53:F55) -> 1000 | G56: =SUM(G53:G55) -> 238.19253 | H56: =SUM(H53:H55) -> 262.67532 | I56: =SUM(I53:I55) -> 262.67532 | J56: =SUM(J53:J55) -> 252.57242 | ... W56: =SUM(W53:W55) -> 1871.1595
A58: Pain, inflammation and immunology
B59: Dolonex | C59: 380 | D59: 370 | E59: 360 | F59: 350 | G59: =Assumptions!$G$39 -> 81.119299 | H59: =(($F59*(1+Assumptions!$C$39)*Assumptions!$E$39)-$G59)*Assumptions!$J$39/SUM(Assumptions!$J$39:$L$39) -> 89.457204 | I59: =(($F59*(1+Assumptions!$C$39)*Assumptions!$E$39)-$G59)*Assumptions!$K$39/SUM(Assumptions!$J$39:$L$39) -> 89.457204 | J59: =(($F59*(1+Assumptions!$C$39)*Assumptions!$E$39)-$G59)*Assumptions!$L$39/SUM(Assumptions!$J$39:$L$39) -> 86.016543 | K59: =SUM(G59:J59) -> 346.05025 | L59: =($K59*(1+Assumptions!$C$39)*Assumptions!$F$39)*Assumptions!$I$39 -> 86.476227 | M59: =($K59*(1+Assumptions!$C$39)*Assumptions!$F$39)*Assumptions!$J$39 -> 97.755735 | N59: =($K59*(1+Assumptions!$C$39)*Assumptions!$F$39)*Assumptions!$K$39 -> 97.755735 | O59: =($K59*(1+Assumptions!$C$39)*Assumptions!$F$39)*Assumptions!$L$39 -> 93.995899 | P59: =SUM(L59:O59) -> 375.9836 | Q59: =$P59*(1+Assumptions!$C$39)*Assumptions!$F$39 -> 408.50618 | R59: =$Q59*(1+Assumptions!$C$39)*Assumptions!$F$39 -> 443.84196 | S59: =$R59*(1+Assumptions!$D$39)*Assumptions!$F$39 -> 466.30037 | T59: =$S59*(1+Assumptions!$D$39)*Assumptions!$F$39 -> 489.89516 | U59: =$T59*(1+Assumptions!$D$39)*Assumptions!$F$39 -> 514.68386 | V59: =$U59*(1+Assumptions!$D$39)*Assumptions!$F$39 -> 540.72686 | W59: =$V59*(1+Assumptions!$D$39)*Assumptions!$F$39 -> 568.08764
B60: Enbrel | C60: 600 | D60: 590 | E60: 570 | F60: 550 | G60: =Assumptions!$G$40 -> 135.13911 | H60: =(($F60*(1+Assumptions!$C$40)*Assumptions!$E$40)-$G60)*Assumptions!$J$40/SUM(Assumptions!$J$40:$L$40) -> 137.28154 | I60: =(($F60*(1+Assumptions!$C$40)*Assumptions!$E$40)-$G60)*Assumptions!$K$40/SUM(Assumptions!$J$40:$L$40) -> 137.28154 | J60: =(($F60*(1+Assumptions!$C$40)*Assumptions!$E$40)-$G60)*Assumptions!$L$40/SUM(Assumptions!$J$40:$L$40) -> 142.7728 | K60: =SUM(G60:J60) -> 552.475 | L60: =($K60*(1+Assumptions!$C$40)*Assumptions!$F$40)*Assumptions!$I$40 -> 133.19067 | M60: =($K60*(1+Assumptions!$C$40)*Assumptions!$F$40)*Assumptions!$J$40 -> 138.74028 | N60: =($K60*(1+Assumptions!$C$40)*Assumptions!$F$40)*Assumptions!$K$40 -> 138.74028 | O60: =($K60*(1+Assumptions!$C$40)*Assumptions!$F$40)*Assumptions!$L$40 -> 144.2899 | P60: =SUM(L60:O60) -> 554.96114 | Q60: =$P60*(1+Assumptions!$C$40)*Assumptions!$F$40 -> 557.45846 | R60: =$Q60*(1+Assumptions!$C$40)*Assumptions!$F$40 -> 559.96703 | S60: =$R60*(1+Assumptions!$D$40)*Assumptions!$F$40 -> 554.03138 | T60: =$S60*(1+Assumptions!$D$40)*Assumptions!$F$40 -> 548.15864 | U60: =$T60*(1+Assumptions!$D$40)*Assumptions!$F$40 -> 542.34816 | V60: =$U60*(1+Assumptions!$D$40)*Assumptions!$F$40 -> 536.59927 | W60: =$V60*(1+Assumptions!$D$40)*Assumptions!$F$40 -> 530.91132
B61: Betrecep | C61: 0 | D61: 100 | E61: 180 | F61: 250 | G61: =Assumptions!$G$41 -> 70.202135 | H61: =(($F61*(1+Assumptions!$C$41)*Assumptions!$E$41)-$G61)*Assumptions!$J$41/SUM(Assumptions!$J$41:$L$41) -> 71.315087 | I61: =(($F61*(1+Assumptions!$C$41)*Assumptions!$E$41)-$G61)*Assumptions!$K$41/SUM(Assumptions!$J$41:$L$41) -> 71.315087 | J61: =(($F61*(1+Assumptions!$C$41)*Assumptions!$E$41)-$G61)*Assumptions!$L$41/SUM(Assumptions!$J$41:$L$41) -> 74.16769 | K61: =SUM(G61:J61) -> 287 | L61: =($K61*(1+Assumptions!$C$41)*Assumptions!$F$41)*Assumptions!$I$41 -> 79.07424 | M61: =($K61*(1+Assumptions!$C$41)*Assumptions!$F$41)*Assumptions!$J$41 -> 82.369 | N61: =($K61*(1+Assumptions!$C$41)*Assumptions!$F$41)*Assumptions!$K$41 -> 82.369 | O61: =($K61*(1+Assumptions!$C$41)*Assumptions!$F$41)*Assumptions!$L$41 -> 85.66376 | P61: =SUM(L61:O61) -> 329.476 | Q61: =$P61*(1+Assumptions!$C$41)*Assumptions!$F$41 -> 378.23845 | R61: =$Q61*(1+Assumptions!$C$41)*Assumptions!$F$41 -> 434.21774 | S61: =$R61*(1+Assumptions!$D$41)*Assumptions!$F$41 -> 465.0472 | T61: =$S61*(1+Assumptions!$D$41)*Assumptions!$F$41 -> 498.06555 | U61: =$T61*(1+Assumptions!$D$41)*Assumptions!$F$41 -> 533.4282 | V61: =$U61*(1+Assumptions!$D$41)*Assumptions!$F$41 -> 571.30161 | W61: =$V61*(1+Assumptions!$D$41)*Assumptions!$F$41 -> 611.86402
B62: Other pain and immunology products | C62: 220 | D62: 230 | E62: 240 | F62: 250 | G62: =Assumptions!$G$42 -> 66.441307 | H62: =(($F62*(1+Assumptions!$C$42)*Assumptions!$E$42)-$G62)*Assumptions!$J$42/SUM(Assumptions!$J$42:$L$42) -> 67.494636 | I62: =(($F62*(1+Assumptions!$C$42)*Assumptions!$E$42)-$G62)*Assumptions!$K$42/SUM(Assumptions!$J$42:$L$42) -> 67.494636 | J62: =(($F62*(1+Assumptions!$C$42)*Assumptions!$E$42)-$G62)*Assumptions!$L$42/SUM(Assumptions!$J$42:$L$42) -> 70.194421 | K62: =SUM(G62:J62) -> 271.625 | L62: =($K62*(1+Assumptions!$C$42)*Assumptions!$F$42)*Assumptions!$I$42 -> 70.828935 | M62: =($K62*(1+Assumptions!$C$42)*Assumptions!$F$42)*Assumptions!$J$42 -> 73.780141 | N62: =($K62*(1+Assumptions!$C$42)*Assumptions!$F$42)*Assumptions!$K$42 -> 73.780141 | O62: =($K62*(1+Assumptions!$C$42)*Assumptions!$F$42)*Assumptions!$L$42 -> 76.731346 | P62: =SUM(L62:O62) -> 295.12056 | Q62: =$P62*(1+Assumptions!$C$42)*Assumptions!$F$42 -> 320.64849 | R62: =$Q62*(1+Assumptions!$C$42)*Assumptions!$F$42 -> 348.38459 | S62: =$R62*(1+Assumptions!$D$42)*Assumptions!$F$42 -> 366.01285 | T62: =$S62*(1+Assumptions!$D$42)*Assumptions!$F$42 -> 384.5331 | U62: =$T62*(1+Assumptions!$D$42)*Assumptions!$F$42 -> 403.99047 | V62: =$U62*(1+Assumptions!$D$42)*Assumptions!$F$42 -> 424.43239 | W62: =$V62*(1+Assumptions!$D$42)*Assumptions!$F$42 -> 445.90867
A63: Pain, inflammation and immunology | B63: Subtotal | C63: =SUM(C59:C62) -> 1200 | D63: =SUM(D59:D62) -> 1290 | E63: =SUM(E59:E62) -> 1350 | F63: =SUM(F59:F62) -> 1400 | G63: =SUM(G59:G62) -> 352.90185 | H63: =SUM(H59:H62) -> 365.54847 | I63: =SUM(I59:I62) -> 365.54847 | J63: =SUM(J59:J62) -> 373.15146 | ... W63: =SUM(W59:W62) -> 2156.7716
A65: Women's health and endocrine
B66: Premarin franchise | C66: 330 | D66: 320 | E66: 310 | F66: 300 | G66: =Assumptions!$G$43 -> 75.583484 | H66: =(($F66*(1+Assumptions!$C$43)*Assumptions!$E$43)-$G66)*Assumptions!$J$43/SUM(Assumptions!$J$43:$L$43) -> 76.781749 | I66: =(($F66*(1+Assumptions!$C$43)*Assumptions!$E$43)-$G66)*Assumptions!$K$43/SUM(Assumptions!$J$43:$L$43) -> 76.781749 | J66: =(($F66*(1+Assumptions!$C$43)*Assumptions!$E$43)-$G66)*Assumptions!$L$43/SUM(Assumptions!$J$43:$L$43) -> 79.853019 | K66: =SUM(G66:J66) -> 309 | L66: =($K66*(1+Assumptions!$C$43)*Assumptions!$F$43)*Assumptions!$I$43 -> 76.3848 | M66: =($K66*(1+Assumptions!$C$43)*Assumptions!$F$43)*Assumptions!$J$43 -> 79.5675 | N66: =($K66*(1+Assumptions!$C$43)*Assumptions!$F$43)*Assumptions!$K$43 -> 79.5675 | O66: =($K66*(1+Assumptions!$C$43)*Assumptions!$F$43)*Assumptions!$L$43 -> 82.7502 | P66: =SUM(L66:O66) -> 318.27 | Q66: =$P66*(1+Assumptions!$C$43)*Assumptions!$F$43 -> 327.8181 | R66: =$Q66*(1+Assumptions!$C$43)*Assumptions!$F$43 -> 337.65264 | S66: =$R66*(1+Assumptions!$D$43)*Assumptions!$F$43 -> 342.63302 | T66: =$S66*(1+Assumptions!$D$43)*Assumptions!$F$43 -> 347.68686 | U66: =$T66*(1+Assumptions!$D$43)*Assumptions!$F$43 -> 352.81524 | V66: =$U66*(1+Assumptions!$D$43)*Assumptions!$F$43 -> 358.01926 | W66: =$V66*(1+Assumptions!$D$43)*Assumptions!$F$43 -> 363.30005
B67: Folvite / folic-acid combinations | C67: 580 | D67: 600 | E67: 620 | F67: 650 | G67: =Assumptions!$G$44 -> 171.95243 | H67: =(($F67*(1+Assumptions!$C$44)*Assumptions!$E$44)-$G67)*Assumptions!$J$44/SUM(Assumptions!$J$44:$L$44) -> 174.67848 | I67: =(($F67*(1+Assumptions!$C$44)*Assumptions!$E$44)-$G67)*Assumptions!$K$44/SUM(Assumptions!$J$44:$L$44) -> 174.67848 | J67: =(($F67*(1+Assumptions!$C$44)*Assumptions!$E$44)-$G67)*Assumptions!$L$44/SUM(Assumptions!$J$44:$L$44) -> 181.66562 | K67: =SUM(G67:J67) -> 702.975 | L67: =($K67*(1+Assumptions!$C$44)*Assumptions!$F$44)*Assumptions!$I$44 -> 182.46419 | M67: =($K67*(1+Assumptions!$C$44)*Assumptions!$F$44)*Assumptions!$J$44 -> 190.06687 | N67: =($K67*(1+Assumptions!$C$44)*Assumptions!$F$44)*Assumptions!$K$44 -> 190.06687 | O67: =($K67*(1+Assumptions!$C$44)*Assumptions!$F$44)*Assumptions!$L$44 -> 197.66954 | P67: =SUM(L67:O67) -> 760.26746 | Q67: =$P67*(1+Assumptions!$C$44)*Assumptions!$F$44 -> 822.22926 | R67: =$Q67*(1+Assumptions!$C$44)*Assumptions!$F$44 -> 889.24095 | S67: =$R67*(1+Assumptions!$D$44)*Assumptions!$F$44 -> 938.81613 | T67: =$S67*(1+Assumptions!$D$44)*Assumptions!$F$44 -> 991.15513 | U67: =$T67*(1+Assumptions!$D$44)*Assumptions!$F$44 -> 1046.412 | V67: =$U67*(1+Assumptions!$D$44)*Assumptions!$F$44 -> 1104.7495 | W67: =$V67*(1+Assumptions!$D$44)*Assumptions!$F$44 -> 1166.3393
B68: Oral contraceptive brands | C68: 400 | D68: 410 | E68: 430 | F68: 450 | G68: =Assumptions!$G$45 -> 117.91023 | H68: =(($F68*(1+Assumptions!$C$45)*Assumptions!$E$45)-$G68)*Assumptions!$J$45/SUM(Assumptions!$J$45:$L$45) -> 119.77953 | I68: =(($F68*(1+Assumptions!$C$45)*Assumptions!$E$45)-$G68)*Assumptions!$K$45/SUM(Assumptions!$J$45:$L$45) -> 119.77953 | J68: =(($F68*(1+Assumptions!$C$45)*Assumptions!$E$45)-$G68)*Assumptions!$L$45/SUM(Assumptions!$J$45:$L$45) -> 124.57071 | K68: =SUM(G68:J68) -> 482.04 | L68: =($K68*(1+Assumptions!$C$45)*Assumptions!$F$45)*Assumptions!$I$45 -> 123.9267 | M68: =($K68*(1+Assumptions!$C$45)*Assumptions!$F$45)*Assumptions!$J$45 -> 129.09031 | N68: =($K68*(1+Assumptions!$C$45)*Assumptions!$F$45)*Assumptions!$K$45 -> 129.09031 | O68: =($K68*(1+Assumptions!$C$45)*Assumptions!$F$45)*Assumptions!$L$45 -> 134.25392 | P68: =SUM(L68:O68) -> 516.36125 | Q68: =$P68*(1+Assumptions!$C$45)*Assumptions!$F$45 -> 553.12617 | R68: =$Q68*(1+Assumptions!$C$45)*Assumptions!$F$45 -> 592.50875 | S68: =$R68*(1+Assumptions!$D$45)*Assumptions!$F$45 -> 619.4679 | T68: =$S68*(1+Assumptions!$D$45)*Assumptions!$F$45 -> 647.65369 | U68: =$T68*(1+Assumptions!$D$45)*Assumptions!$F$45 -> 677.12193 | V68: =$U68*(1+Assumptions!$D$45)*Assumptions!$F$45 -> 707.93098 | W68: =$V68*(1+Assumptions!$D$45)*Assumptions!$F$45 -> 740.14184
B69: Other women’s-health products | C69: 140 | D69: 145 | E69: 145 | F69: 150 | G69: =Assumptions!$G$46 -> 38.547577 | H69: =(($F69*(1+Assumptions!$C$46)*Assumptions!$E$46)-$G69)*Assumptions!$J$46/SUM(Assumptions!$J$46:$L$46) -> 39.158692 | I69: =(($F69*(1+Assumptions!$C$46)*Assumptions!$E$46)-$G69)*Assumptions!$K$46/SUM(Assumptions!$J$46:$L$46) -> 39.158692 | J69: =(($F69*(1+Assumptions!$C$46)*Assumptions!$E$46)-$G69)*Assumptions!$L$46/SUM(Assumptions!$J$46:$L$46) -> 40.72504 | K69: =SUM(G69:J69) -> 157.59 | L69: =($K69*(1+Assumptions!$C$46)*Assumptions!$F$46)*Assumptions!$I$46 -> 39.735373 | M69: =($K69*(1+Assumptions!$C$46)*Assumptions!$F$46)*Assumptions!$J$46 -> 41.391014 | N69: =($K69*(1+Assumptions!$C$46)*Assumptions!$F$46)*Assumptions!$K$46 -> 41.391014 | O69: =($K69*(1+Assumptions!$C$46)*Assumptions!$F$46)*Assumptions!$L$46 -> 43.046654 | P69: =SUM(L69:O69) -> 165.56405 | Q69: =$P69*(1+Assumptions!$C$46)*Assumptions!$F$46 -> 173.9416 | R69: =$Q69*(1+Assumptions!$C$46)*Assumptions!$F$46 -> 182.74304 | S69: =$R69*(1+Assumptions!$D$46)*Assumptions!$F$46 -> 189.18473 | T69: =$S69*(1+Assumptions!$D$46)*Assumptions!$F$46 -> 195.85349 | U69: =$T69*(1+Assumptions!$D$46)*Assumptions!$F$46 -> 202.75733 | V69: =$U69*(1+Assumptions!$D$46)*Assumptions!$F$46 -> 209.90453 | W69: =$V69*(1+Assumptions!$D$46)*Assumptions!$F$46 -> 217.30366
A70: Women's health and endocrine | B70: Subtotal | C70: =SUM(C66:C69) -> 1450 | D70: =SUM(D66:D69) -> 1475 | E70: =SUM(E66:E69) -> 1505 | F70: =SUM(F66:F69) -> 1550 | G70: =SUM(G66:G69) -> 403.99372 | H70: =SUM(H66:H69) -> 410.39845 | I70: =SUM(I66:I69) -> 410.39845 | J70: =SUM(J66:J69) -> 426.81438 | ... W70: =SUM(W66:W69) -> 2487.0848
A72: CNS and migraine
B73: Nurtec | C73: 0 | D73: 0 | E73: 0 | F73: 80 | G73: =Assumptions!$G$47 -> 31.089517 | H73: =(($F73*(1+Assumptions!$C$47)*Assumptions!$E$47)-$G73)*Assumptions!$J$47/SUM(Assumptions!$J$47:$L$47) -> 31.582396 | I73: =(($F73*(1+Assumptions!$C$47)*Assumptions!$E$47)-$G73)*Assumptions!$K$47/SUM(Assumptions!$J$47:$L$47) -> 31.582396 | J73: =(($F73*(1+Assumptions!$C$47)*Assumptions!$E$47)-$G73)*Assumptions!$L$47/SUM(Assumptions!$J$47:$L$47) -> 32.845692 | K73: =SUM(G73:J73) -> 127.1 | L73: =($K73*(1+Assumptions!$C$47)*Assumptions!$F$47)*Assumptions!$I$47 -> 48.46323 | M73: =($K73*(1+Assumptions!$C$47)*Assumptions!$F$47)*Assumptions!$J$47 -> 50.482531 | N73: =($K73*(1+Assumptions!$C$47)*Assumptions!$F$47)*Assumptions!$K$47 -> 50.482531 | O73: =($K73*(1+Assumptions!$C$47)*Assumptions!$F$47)*Assumptions!$L$47 -> 52.501832 | P73: =SUM(L73:O73) -> 201.93012 | Q73: =$P73*(1+Assumptions!$C$47)*Assumptions!$F$47 -> 320.81649 | R73: =$Q73*(1+Assumptions!$C$47)*Assumptions!$F$47 -> 509.69719 | S73: =$R73*(1+Assumptions!$D$47)*Assumptions!$F$47 -> 597.87481 | T73: =$S73*(1+Assumptions!$D$47)*Assumptions!$F$47 -> 701.30715 | U73: =$T73*(1+Assumptions!$D$47)*Assumptions!$F$47 -> 822.63328 | V73: =$U73*(1+Assumptions!$D$47)*Assumptions!$F$47 -> 964.94884 | W73: =$V73*(1+Assumptions!$D$47)*Assumptions!$F$47 -> 1131.885
B74: Other CNS products | C74: 80 | D74: 75 | E74: 70 | F74: 70 | G74: =Assumptions!$G$48 -> 17.901545 | H74: =(($F74*(1+Assumptions!$C$48)*Assumptions!$E$48)-$G74)*Assumptions!$J$48/SUM(Assumptions!$J$48:$L$48) -> 18.185347 | I74: =(($F74*(1+Assumptions!$C$48)*Assumptions!$E$48)-$G74)*Assumptions!$K$48/SUM(Assumptions!$J$48:$L$48) -> 18.185347 | J74: =(($F74*(1+Assumptions!$C$48)*Assumptions!$E$48)-$G74)*Assumptions!$L$48/SUM(Assumptions!$J$48:$L$48) -> 18.912761 | K74: =SUM(G74:J74) -> 73.185 | L74: =($K74*(1+Assumptions!$C$48)*Assumptions!$F$48)*Assumptions!$I$48 -> 18.36358 | M74: =($K74*(1+Assumptions!$C$48)*Assumptions!$F$48)*Assumptions!$J$48 -> 19.128729 | N74: =($K74*(1+Assumptions!$C$48)*Assumptions!$F$48)*Assumptions!$K$48 -> 19.128729 | O74: =($K74*(1+Assumptions!$C$48)*Assumptions!$F$48)*Assumptions!$L$48 -> 19.893879 | P74: =SUM(L74:O74) -> 76.514917 | Q74: =$P74*(1+Assumptions!$C$48)*Assumptions!$F$48 -> 79.996346 | R74: =$Q74*(1+Assumptions!$C$48)*Assumptions!$F$48 -> 83.63618 | S74: =$R74*(1+Assumptions!$D$48)*Assumptions!$F$48 -> 86.161993 | T74: =$S74*(1+Assumptions!$D$48)*Assumptions!$F$48 -> 88.764085 | U74: =$T74*(1+Assumptions!$D$48)*Assumptions!$F$48 -> 91.44476 | V74: =$U74*(1+Assumptions!$D$48)*Assumptions!$F$48 -> 94.206392 | W74: =$V74*(1+Assumptions!$D$48)*Assumptions!$F$48 -> 97.051425
A75: CNS and migraine | B75: Subtotal | C75: =SUM(C73:C74) -> 80 | D75: =SUM(D73:D74) -> 75 | E75: =SUM(E73:E74) -> 70 | F75: =SUM(F73:F74) -> 150 | G75: =SUM(G73:G74) -> 48.991062 | H75: =SUM(H73:H74) -> 49.767743 | I75: =SUM(I73:I74) -> 49.767743 | J75: =SUM(J73:J74) -> 51.758453 | ... W75: =SUM(W73:W74) -> 1228.9364
A77: Other established products
B78: Other established products | C78: 5236.3 | D78: 3645.4 | E78: 2882.6 | F78: 2666.1 | G78: =Assumptions!$G$49 -> 647.0036 | H78: =(($F78*(1+Assumptions!$C$49)*Assumptions!$E$49)-$G78)*Assumptions!$J$49/SUM(Assumptions!$J$49:$L$49) -> 713.50633 | I78: =(($F78*(1+Assumptions!$C$49)*Assumptions!$E$49)-$G78)*Assumptions!$K$49/SUM(Assumptions!$J$49:$L$49) -> 713.50633 | J78: =(($F78*(1+Assumptions!$C$49)*Assumptions!$E$49)-$G78)*Assumptions!$L$49/SUM(Assumptions!$J$49:$L$49) -> 686.06378 | K78: =SUM(G78:J78) -> 2760.08 | L78: =($K78*(1+Assumptions!$C$49)*Assumptions!$F$49)*Assumptions!$I$49 -> 657.19575 | M78: =($K78*(1+Assumptions!$C$49)*Assumptions!$F$49)*Assumptions!$J$49 -> 742.91694 | N78: =($K78*(1+Assumptions!$C$49)*Assumptions!$F$49)*Assumptions!$K$49 -> 742.91694 | O78: =($K78*(1+Assumptions!$C$49)*Assumptions!$F$49)*Assumptions!$L$49 -> 714.34321 | P78: =SUM(L78:O78) -> 2857.3728 | Q78: =$P78*(1+Assumptions!$C$49)*Assumptions!$F$49 -> 2958.0952 | R78: =$Q78*(1+Assumptions!$C$49)*Assumptions!$F$49 -> 3062.3681 | S78: =$R78*(1+Assumptions!$D$49)*Assumptions!$F$49 -> 3123.6155 | T78: =$S78*(1+Assumptions!$D$49)*Assumptions!$F$49 -> 3186.0878 | U78: =$T78*(1+Assumptions!$D$49)*Assumptions!$F$49 -> 3249.8095 | V78: =$U78*(1+Assumptions!$D$49)*Assumptions!$F$49 -> 3314.8057 | W78: =$V78*(1+Assumptions!$D$49)*Assumptions!$F$49 -> 3381.1018
A79: Other established products | B79: Subtotal | C79: =SUM(C78:C78) -> 5236.3 | D79: =SUM(D78:D78) -> 3645.4 | E79: =SUM(E78:E78) -> 2882.6 | F79: =SUM(F78:F78) -> 2666.1 | G79: =SUM(G78:G78) -> 647.0036 | H79: =SUM(H78:H78) -> 713.50633 | I79: =SUM(I78:I78) -> 713.50633 | J79: =SUM(J78:J78) -> 686.06378 | ... W79: =SUM(W78:W78) -> 3381.1018
A81: Total pharmaceutical product revenue | C81: =SUM(C22,C31,C38,C43,C50,C56,C63,C70,C75,C79) -> 23376.3 | D81: =SUM(D22,D31,D38,D43,D50,D56,D63,D70,D75,D79) -> 20810.4 | E81: =SUM(E22,E31,E38,E43,E50,E56,E63,E70,E75,E79) -> 21283.6 | F81: =SUM(F22,F31,F38,F43,F50,F56,F63,F70,F75,F79) -> 23771.1 | G81: =SUM(G22,G31,G38,G43,G50,G56,G63,G70,G75,G79) -> 6175.35 | H81: =SUM(H22,H31,H38,H43,H50,H56,H63,H70,H75,H79) -> 6277.5878 | I81: =SUM(I22,I31,I38,I43,I50,I56,I63,I70,I75,I79) -> 6016.672 | J81: =SUM(J22,J31,J38,J43,J50,J56,J63,J70,J75,J79) -> 6142.8538 | ... W81: =SUM(W22,W31,W38,W43,W50,W56,W63,W70,W75,W79) -> 44680.883
A83: Service revenue | C83: 846.9 | D83: 1116.5 | E83: 1526.4 | F83: 1421.6 | G83: =Assumptions!$C$66 -> 355.4 | H83: =($F83*(1+Assumptions!$B$66)-$G83)/3 -> 355.4 | I83: =H83 -> 355.4 | J83: =H83 -> 355.4 | K83: =SUM(G83:J83) -> 1421.6 | L83: =$K83*(1+Assumptions!$B$66)/4 -> 355.4 | M83: =L83 -> 355.4 | N83: =L83 -> 355.4 | O83: =L83 -> 355.4 | P83: =SUM(L83:O83) -> 1421.6 | Q83: =$P83*(1+Assumptions!$B$66) -> 1421.6 | R83: =$Q83*(1+Assumptions!$B$66) -> 1421.6 | S83: =$R83*(1+Assumptions!$B$66) -> 1421.6 | T83: =$S83*(1+Assumptions!$B$66) -> 1421.6 | U83: =$T83*(1+Assumptions!$B$66) -> 1421.6 | V83: =$U83*(1+Assumptions!$B$66) -> 1421.6 | W83: =$V83*(1+Assumptions!$B$66) -> 1421.6
A84: Other operating revenue | C84: 24.4 | D84: 4.8 | E84: 3.5 | F84: 3.8 | G84: =Assumptions!$C$67 -> 0.95 | H84: =($F84*(1+Assumptions!$B$67)-$G84)/3 -> 0.95 | I84: =H84 -> 0.95 | J84: =H84 -> 0.95 | K84: =SUM(G84:J84) -> 3.8 | L84: =$K84*(1+Assumptions!$B$67)/4 -> 0.95 | M84: =L84 -> 0.95 | N84: =L84 -> 0.95 | O84: =L84 -> 0.95 | P84: =SUM(L84:O84) -> 3.8 | Q84: =$P84*(1+Assumptions!$B$67) -> 3.8 | R84: =$Q84*(1+Assumptions!$B$67) -> 3.8 | S84: =$R84*(1+Assumptions!$B$67) -> 3.8 | T84: =$S84*(1+Assumptions!$B$67) -> 3.8 | U84: =$T84*(1+Assumptions!$B$67) -> 3.8 | V84: =$U84*(1+Assumptions!$B$67) -> 3.8 | W84: =$V84*(1+Assumptions!$B$67) -> 3.8
A85: Revenue from operations | C85: =SUM(C81,C83,C84) -> 24247.6 | D85: =SUM(D81,D83,D84) -> 21931.7 | E85: =SUM(E81,E83,E84) -> 22813.5 | F85: =SUM(F81,F83,F84) -> 25196.5 | G85: =SUM(G81,G83,G84) -> 6531.7 | H85: =SUM(H81,H83,H84) -> 6633.9378 | I85: =SUM(I81,I83,I84) -> 6373.022 | J85: =SUM(J81,J83,J84) -> 6499.2038 | ... W85: =SUM(W81,W83,W84) -> 46106.283
A88: Model checks
A89: Historical product-revenue difference | C89: =ROUND(C81-Assumptions!B9,2) -> 0 | D89: =ROUND(D81-Assumptions!C9,2) -> 0 | E89: =ROUND(E81-Assumptions!D9,2) -> 0 | F89: =ROUND(F81-Assumptions!E9,2) -> 0
A90: FY27 annual less quarters | K90: =ROUND(K85-SUM(G85:J85),2) -> 0
A91: FY28 annual less quarters | P91: =ROUND(P85-SUM(L85:O85),2) -> 0
A92: PPIPL products included | C92: 0

Sheet Assumptions
A2: Pfizer Limited revenue assumptions
A3: INR million unless stated. Blue font and pale-yellow fill are editable inputs. Black cells are same-sheet formulas.
A5: Legend | B5: Hardcode | C5: Formula | D5: Cross-sheet link
A7: Reported company revenue anchors
A8: Metric | B8: FY23A | C8: FY24A | D8: FY25A | E8: FY26A
A9: Product revenue | B9: 23376.3 | C9: 20810.4 | D9: 21283.6 | E9: 23771.1
A10: Service revenue | B10: 846.9 | C10: 1116.5 | D10: 1526.4 | E10: 1421.6
A11: Other operating revenue | B11: 24.4 | C11: 4.8 | D11: 3.5 | E11: 3.8
A12: Revenue from operations | B12: 24247.6 | C12: 21931.7 | D12: 22813.5 | E12: 25196.5
A14: Product forecast drivers
A15: Therapy | B15: Brand | C15: Net growth FY27-FY30 | D15: Net growth FY31-FY35 | E15: FY27 factor | F15: FY28+ factor | G15: FY27 Q1 estimate | H15: Quarterly profile | I15: Q1 % | J15: Q2 % | K15: Q3 % | L15: Q4 % | M15: Rationale
A16: Vaccines | B16: Prevenar 13 | C16: 0.0094 | D16: -0.016 | E16: 1 | F16: 1 | G16: 681.46069 | H16: Vaccines | I16: =$B$56 -> 0.24 | J16: =$C$56 -> 0.23 | K16: =$D$56 -> 0.25 | L16: =$E$56 -> 0.28 | M16: Mature PCV franchise; modelled with cannibalisation from Prevenar 20.
A17: Vaccines | B17: Prevenar 20 | C17: 0.3905 | D17: 0.148 | E17: 1 | F17: 1 | G17: 278.90306 | H17: Vaccines | I17: =$B$56 -> 0.24 | J17: =$C$56 -> 0.23 | K17: =$D$56 -> 0.25 | L17: =$E$56 -> 0.28 | M17: Launch ramp; adult immunisation, affordability and internal franchise cannibalisation.
A18: Vaccines | B18: Other vaccines | C18: 0.0506 | D18: 0.03525 | E18: 1 | F18: 1 | G18: 30.838061 | H18: Vaccines | I18: =$B$56 -> 0.24 | J18: =$C$56 -> 0.23 | K18: =$D$56 -> 0.25 | L18: =$E$56 -> 0.28 | M18: Residual vaccine portfolio.
A19: Vaccines | B19: Abrysvo (pipeline) | C19: 0.03 | D19: 0.025 | E19: 0 | F19: 0 | G19: 0 | H19: Vaccines | I19: =$B$56 -> 0.24 | J19: =$C$56 -> 0.23 | K19: =$D$56 -> 0.25 | L19: =$E$56 -> 0.28 | M19: Only future pipeline line included in the base case; linked to the pipeline assumptions below.
A20: Anti-infectives and hospital products | B20: Magnex | C20: 0.107 | D20: 0.071 | E20: 1 | F20: 1 | G20: 379.09153 | H20: Hospital | I20: =$B$57 -> 0.24 | J20: =$C$57 -> 0.25 | K20: =$D$57 -> 0.25 | L20: =$E$57 -> 0.26 | M20: FY24 historical estimate reflects voluntary recall/supply disruption; subsequent recovery.
A21: Anti-infectives and hospital products | B21: Meronem | C21: 0.07625 | D21: 0.0506 | E21: 1 | F21: 1 | G21: 242.19737 | H21: Hospital | I21: =$B$57 -> 0.24 | J21: =$C$57 -> 0.25 | K21: =$D$57 -> 0.25 | L21: =$E$57 -> 0.26 | M21: Hospital anti-infective; institutional exposure.
A22: Anti-infectives and hospital products | B22: Zavicefta | C22: 0.107 | D22: 0.071 | E22: 1 | F22: 1 | G22: 238.28611 | H22: Hospital | I22: =$B$57 -> 0.24 | J22: =$C$57 -> 0.25 | K22: =$D$57 -> 0.25 | L22: =$E$57 -> 0.26 | M22: 42% market share MAT Mar-26 in represented ceftazidime-avibactam market.
A23: Anti-infectives and hospital products | B23: Zithromax | C23: 0.025 | D23: -0.0004 | E23: 1 | F23: 1 | G23: 75.216574 | H23: Hospital | I23: =$B$57 -> 0.24 | J23: =$C$57 -> 0.25 | K23: =$D$57 -> 0.25 | L23: =$E$57 -> 0.26 | M23: Mature anti-infective; generic pressure. Azithromycin formulations are scheduled under NLEM 2022, limiting unrestricted price/mix.
A24: Anti-infectives and hospital products | B24: Emblaveo | C24: 0.48625 | D24: 0.173 | E24: 1 | F24: 1 | G24: 65.438419 | H24: Hospital | I24: =$B$57 -> 0.24 | J24: =$C$57 -> 0.25 | K24: =$D$57 -> 0.25 | L24: =$E$57 -> 0.26 | M24: ICU launch ramp; MDR Gram-negative infections.
A25: Anti-infectives and hospital products | B25: Other hospital and anti-infective products | C25: 0.05575 | D25: 0.0404 | E25: 1 | F25: 1 | G25: 154.94614 | H25: Hospital | I25: =$B$57 -> 0.24 | J25: =$C$57 -> 0.25 | K25: =$D$57 -> 0.25 | L25: =$E$57 -> 0.26 | M25: Residual hospital portfolio; includes smaller anti-infectives.
A26: Cardiovascular and anticoagulation | B26: Eliquis | C26: 0.148 | D26: 0.0812 | E26: 1 | F26: 1 | G26: 527.92006 | H26: Chronic | I26: =$B$58 -> 0.24 | J26: =$C$58 -> 0.25 | K26: =$D$58 -> 0.25 | L26: =$E$58 -> 0.26 | M26: FY26 estimate anchored to company-disclosed 30% YoY growth; post-2022 LOE/generic pressure incorporated in forecast.
A27: Cardiovascular and anticoagulation | B27: Minipress XL | C27: 0.05575 | D27: 0.02 | E27: 0.43210674 | F27: 0 | G27: 445.47016 | H27: Exit | I27: =$B$61 -> 0 | J27: =$C$61 -> 1 | K27: =$D$61 -> 0 | L27: =$E$61 -> 0 | M27: FY27 Q2 prorated to 7-Sep-26; zero from FY28. Compensation excluded from operating revenue.
A28: Cardiovascular and anticoagulation | B28: Amlogard | C28: 0.025 | D28: 0.02 | E28: 0 | F28: 0 | G28: 0 | H28: Chronic | I28: =$B$58 -> 0.24 | J28: =$C$58 -> 0.25 | K28: =$D$58 -> 0.25 | L28: =$E$58 -> 0.26 | M28: Historical FY23 estimate covers only Apr-Jul 2022 pre-transfer; no revenue thereafter.
A29: Cardiovascular and anticoagulation | B29: Other cardiovascular products | C29: 0.0455 | D29: 0.0302 | E29: 1 | F29: 1 | G29: 76.720905 | H29: Chronic | I29: =$B$58 -> 0.24 | J29: =$C$58 -> 0.25 | K29: =$D$58 -> 0.25 | L29: =$E$58 -> 0.26 | M29: Residual listed-company cardiovascular portfolio.
A30: Vitamins and nutritional products | B30: Becosules | C30: 0.0815 | D30: 0.05575 | E30: 1 | F30: 1 | G30: 565.34871 | H30: Primary | I30: =$B$59 -> 0.23 | J30: =$C$59 -> 0.26 | K30: =$D$59 -> 0.26 | L30: =$E$59 -> 0.25 | M30: Mature brand with distribution/packaging support; no innovation-like growth.
A31: Vitamins and nutritional products | B31: Other nutritional products | C31: 0.0506 | D31: 0.03525 | E31: 1 | F31: 1 | G31: 36.941428 | H31: Primary | I31: =$B$59 -> 0.23 | J31: =$C$59 -> 0.26 | K31: =$D$59 -> 0.26 | L31: =$E$59 -> 0.25 | M31: Residual nutritional portfolio.
A32: Gastrointestinal | B32: Mucaine | C32: 0.0815 | D32: 0.05575 | E32: 1 | F32: 1 | G32: 332.11068 | H32: Primary | I32: =$B$59 -> 0.23 | J32: =$C$59 -> 0.26 | K32: =$D$59 -> 0.26 | L32: =$E$59 -> 0.25 | M32: Mature GI franchise.
A33: Gastrointestinal | B33: Gelusil-MPS | C33: 0.0712 | D33: 0.0455 | E33: 1 | F33: 1 | G33: 225.99462 | H33: Primary | I33: =$B$59 -> 0.23 | J33: =$C$59 -> 0.26 | K33: =$D$59 -> 0.26 | L33: =$E$59 -> 0.25 | M33: Mature OTC-oriented GI brand.
A34: Gastrointestinal | B34: Neksium | C34: 0.1124 | D34: 0.066 | E34: 0.91 | F34: 1 | G34: 83.053022 | H34: Primary | I34: =$B$59 -> 0.23 | J34: =$C$59 -> 0.26 | K34: =$D$59 -> 0.26 | L34: =$E$59 -> 0.25 | M34: Cipla transition factor applied in FY27; volume growth assumption captures broader reach.
A35: Gastrointestinal | B35: Other gastrointestinal products | C35: 0.0506 | D35: 0.03525 | E35: 1 | F35: 1 | G35: 44.329713 | H35: Primary | I35: =$B$59 -> 0.23 | J35: =$C$59 -> 0.26 | K35: =$D$59 -> 0.26 | L35: =$E$59 -> 0.25 | M35: Residual listed-company GI portfolio.
A36: Respiratory and cough | B36: Corex DX | C36: 0.1124 | D36: 0.066 | E36: 0.91 | F36: 1 | G36: 118.64717 | H36: Primary | I36: =$B$59 -> 0.23 | J36: =$C$59 -> 0.26 | K36: =$D$59 -> 0.26 | L36: =$E$59 -> 0.25 | M36: Cipla transition factor applied in FY27.
A37: Respiratory and cough | B37: Corex LS | C37: 0.1124 | D37: 0.066 | E37: 0.91 | F37: 1 | G37: 94.917739 | H37: Primary | I37: =$B$59 -> 0.23 | J37: =$C$59 -> 0.26 | K37: =$D$59 -> 0.26 | L37: =$E$59 -> 0.25 | M37: Cipla transition factor applied in FY27.
A38: Respiratory and cough | B38: Other respiratory products | C38: 0.0506 | D38: 0.03525 | E38: 1 | F38: 1 | G38: 24.627618 | H38: Primary | I38: =$B$59 -> 0.23 | J38: =$C$59 -> 0.26 | K38: =$D$59 -> 0.26 | L38: =$E$59 -> 0.25 | M38: Residual respiratory portfolio.
A39: Pain, inflammation and immunology | B39: Dolonex | C39: 0.0865 | D39: 0.0506 | E39: 0.91 | F39: 1 | G39: 81.119299 | H39: Primary | I39: =$B$59 -> 0.23 | J39: =$C$59 -> 0.26 | K39: =$D$59 -> 0.26 | L39: =$E$59 -> 0.25 | M39: Cipla transition factor applied in FY27.
A40: Pain, inflammation and immunology | B40: Enbrel | C40: 0.0045 | D40: -0.0106 | E40: 1 | F40: 1 | G40: 135.13911 | H40: Chronic | I40: =$B$58 -> 0.24 | J40: =$C$58 -> 0.25 | K40: =$D$58 -> 0.25 | L40: =$E$58 -> 0.26 | M40: Mature TNF inhibitor with competitive/biosimilar pressure.
A41: Pain, inflammation and immunology | B41: Betrecep | C41: 0.148 | D41: 0.071 | E41: 1 | F41: 1 | G41: 70.202135 | H41: Chronic | I41: =$B$58 -> 0.24 | J41: =$C$58 -> 0.25 | K41: =$D$58 -> 0.25 | L41: =$E$58 -> 0.26 | M41: India-specific access launch; ranked #6 in >85-brand market MAT Mar-26.
A42: Pain, inflammation and immunology | B42: Other pain and immunology products | C42: 0.0865 | D42: 0.0506 | E42: 1 | F42: 1 | G42: 66.441307 | H42: Chronic | I42: =$B$58 -> 0.24 | J42: =$C$58 -> 0.25 | K42: =$D$58 -> 0.25 | L42: =$E$58 -> 0.26 | M42: Includes smaller listed-company I&I/pain products; Cibinqo is not separately material in available data.
A43: Women's health and endocrine | B43: Premarin franchise | C43: 0.03 | D43: 0.01475 | E43: 1 | F43: 1 | G43: 75.583484 | H43: Chronic | I43: =$B$58 -> 0.24 | J43: =$C$58 -> 0.25 | K43: =$D$58 -> 0.25 | L43: =$E$58 -> 0.26 | M43: Mature women’s-health franchise.
A44: Women's health and endocrine | B44: Folvite / folic-acid combinations | C44: 0.0815 | D44: 0.05575 | E44: 1 | F44: 1 | G44: 171.95243 | H44: Chronic | I44: =$B$58 -> 0.24 | J44: =$C$58 -> 0.25 | K44: =$D$58 -> 0.25 | L44: =$E$58 -> 0.26 | M44: Market-leading represented folic-acid category positioning.
A45: Women's health and endocrine | B45: Oral contraceptive brands | C45: 0.0712 | D45: 0.0455 | E45: 1 | F45: 1 | G45: 117.91023 | H45: Chronic | I45: =$B$58 -> 0.24 | J45: =$C$58 -> 0.25 | K45: =$D$58 -> 0.25 | L45: =$E$58 -> 0.26 | M45: Ovral L plus other listed-company oral contraceptives.
A46: Women's health and endocrine | B46: Other women’s-health products | C46: 0.0506 | D46: 0.03525 | E46: 1 | F46: 1 | G46: 38.547577 | H46: Chronic | I46: =$B$58 -> 0.24 | J46: =$C$58 -> 0.25 | K46: =$D$58 -> 0.25 | L46: =$E$58 -> 0.26 | M46: Residual women’s-health portfolio.
A47: CNS and migraine | B47: Nurtec | C47: 0.58875 | D47: 0.173 | E47: 1 | F47: 1 | G47: 31.089517 | H47: Chronic | I47: =$B$58 -> 0.24 | J47: =$C$58 -> 0.25 | K47: =$D$58 -> 0.25 | L47: =$E$58 -> 0.26 | M47: FY26 launch; specialist adoption ramp from low base.
A48: CNS and migraine | B48: Other CNS products | C48: 0.0455 | D48: 0.0302 | E48: 1 | F48: 1 | G48: 17.901545 | H48: Chronic | I48: =$B$58 -> 0.24 | J48: =$C$58 -> 0.25 | K48: =$D$58 -> 0.25 | L48: =$E$58 -> 0.26 | M48: Residual CNS products; excludes transferred Upjohn brands after Aug-22.
A49: Other established products | B49: Other established products | C49: 0.03525 | D49: 0.02 | E49: 1 | F49: 1 | G49: 647.0036 | H49: Primary | I49: =$B$59 -> 0.23 | J49: =$C$59 -> 0.26 | K49: =$D$59 -> 0.26 | L49: =$E$59 -> 0.25 | M49: Balancing row captures >150-product long tail and pre-Aug-22 Upjohn revenue in FY23; historical formula reconciles exactly to audited product revenue.
A54: Quarterly profiles
A55: Profile | B55: Q1 | C55: Q2 | D55: Q3 | E55: Q4
A56: Vaccines | B56: 0.24 | C56: 0.23 | D56: 0.25 | E56: 0.28
A57: Hospital | B57: 0.24 | C57: 0.25 | D57: 0.25 | E57: 0.26
A58: Chronic | B58: 0.24 | C58: 0.25 | D58: 0.25 | E58: 0.26
A59: Primary | B59: 0.23 | C59: 0.26 | D59: 0.26 | E59: 0.25
A60: Services | B60: 0.25 | C60: 0.25 | D60: 0.25 | E60: 0.25
A61: Exit | B61: 0 | C61: 1 | D61: 0 | E61: 0
A64: Service and other operating revenue
A65: Line item | B65: FY27-FY35 growth | C65: FY27 Q1 estimate | D65: Quarterly profile
A66: Service revenue | B66: 0 | C66: 355.4 | D66: Services
A67: Other operating revenue | B67: 0 | C67: 0.95 | D67: Services
A70: Pipeline included in the base case
A71: Candidate | B71: Launch year | C71: Risk-adjusted peak sales | D71: FY29 | E71: FY30 | F71: FY31 | G71: FY32 | H71: FY33 | I71: FY34 | J71: FY35 | K71: Listed economics probability | L71: Basis
A72: Abrysvo | B72: 2029 | C72: 810 | D72: 0.2 | E72: 0.45 | F72: 0.7 | G72: 0.9 | H72: 1 | I72: 1 | J72: 1 | K72: 0.9 | L72: India Phase 3 sponsored by Pfizer Limited; launch timing remains an analyst estimate.
A75: Key sources and modelling conventions
A76: Source | B76: Use in model | M76: Reference
A77: FY26 Annual Report | B77: Audited product, service and operating revenue; product launches and portfolio commentary. | M77: https://www.pfizerltd.co.in/files/Pfizer_Limited_-_Annual_Report_FY_2026.pdf
A78: Q1 FY27 result | B78: Reported revenue from operations of INR6,531.7 million. | M78: https://www.pfizerltd.co.in/files/Stock_Exchange_Intimation_-Outcome_of_the_Board_Meeting_28072026_final.pdf
A79: IQVIA MAT June 2026 | B79: Market sell-out anchors. Brand revenue is converted to estimated manufacturer net revenue and reconciled to audited totals. | M79: Uploaded / task-provided market data
A80: Minipress filing | B80: Marketing discontinued from 7 September 2026. Compensation is excluded from operating revenue. | M80: https://www.pfizerltd.co.in/files/Stock_Exchange_Intimation_-_Outcome_of_the_Board_Meeting_07092026.pdf
A81: Cipla arrangement | B81: Corex DX, Corex LS, Dolonex and Neksium remain in listed-company supply economics under an undisclosed commercial structure. | M81: Pfizer FY26 Annual Report and Cipla filing dated 19 December 2025
A82: Pipeline rule | B82: Only products with credible listed-company economics enter the model. PPIPL products and uncertain global assets are excluded. | M82: CTRI, CDSCO, ClinicalTrials.gov and Pfizer disclosures

Sheet Drug Primer
A2: Pfizer India drug primer
A3: Reference sheet only. It does not feed the revenue model. Listed and private-entity products are separated below.
A5: Products included in the listed-company model
A6: Therapy | B6: Brand | C6: Molecule | D6: What it is | E6: What it treats | F6: Typical prescriber / patient | G6: Use | H6: Channel | I6: Portfolio role | J6: Ownership note
A7: Vaccines | B7: Prevenar 13 | C7: 13-valent pneumococcal conjugate vaccine | D7: Conjugate vaccine covering 13 pneumococcal serotypes | E7: Pneumococcal disease prevention | F7: Paediatricians and physicians; children and adults | G7: Short vaccination schedule | H7: Private clinics and hospitals | I7: Mature vaccine franchise | J7: Listed Pfizer marketer
A8: Vaccines | B8: Prevenar 20 | C8: 20-valent pneumococcal conjugate vaccine | D8: Broader-valency pneumococcal conjugate vaccine | E8: Pneumococcal disease prevention | F8: Physicians; mainly adult private-pay patients | G8: Short vaccination schedule | H8: Private clinics and hospitals | I8: Core vaccine growth product | J8: Listed Pfizer launch
A9: Vaccines | B9: Other vaccines | C9: Multiple | D9: Portfolio line or residual grouping | E9: Products within Vaccines | F9: Varies by product | G9: Varies | H9: Retail and/or hospitals | I9: Residual portfolio | J9: Included in listed-company model
A10: Vaccines | B10: Abrysvo (pipeline) | C10: RSV prefusion F vaccine | D10: Bivalent RSV prefusion F protein vaccine | E10: RSV lower-respiratory-tract disease prevention | F10: Adult physicians; older and at-risk adults | G10: Single vaccination course | H10: Private clinics and hospitals | I10: Risk-adjusted pipeline | J10: Listed economics plausible but unconfirmed
A11: Anti-infectives and hospital products | B11: Magnex | C11: Cefoperazone + sulbactam | D11: Injectable cephalosporin plus beta-lactamase inhibitor | E11: Serious bacterial infections | F11: Hospital physicians; admitted patients | G11: Acute | H11: Hospitals | I11: Hospital growth franchise | J11: Listed Pfizer marketer
A12: Anti-infectives and hospital products | B12: Meronem | C12: Meropenem | D12: Broad-spectrum carbapenem antibiotic | E12: Serious and resistant bacterial infections | F12: Intensivists and hospital physicians | G12: Acute | H12: Hospitals | I12: Established hospital brand | J12: Listed Pfizer marketer
A13: Anti-infectives and hospital products | B13: Zavicefta | C13: Ceftazidime + avibactam | D13: Cephalosporin plus beta-lactamase inhibitor | E13: Resistant Gram-negative infections | F13: Intensivists and infectious-disease specialists | G13: Acute | H13: Hospitals | I13: Higher-value hospital growth brand | J13: Listed Pfizer marketer
A14: Anti-infectives and hospital products | B14: Zithromax | C14: Azithromycin | D14: Macrolide antibiotic | E14: Selected bacterial respiratory and other infections | F14: General physicians and specialists | G14: Acute | H14: Retail and hospitals | I14: Mature anti-infective | J14: Listed Pfizer marketer
A15: Anti-infectives and hospital products | B15: Emblaveo | C15: Aztreonam + avibactam | D15: Monobactam plus beta-lactamase inhibitor | E15: Difficult multidrug-resistant Gram-negative infections | F15: Infectious-disease specialists and intensivists | G15: Acute | H15: Tertiary hospitals | I15: New hospital launch | J15: Listed Pfizer launch
A16: Anti-infectives and hospital products | B16: Other hospital and anti-infective products | C16: Multiple | D16: Portfolio line or residual grouping | E16: Products within Anti-infectives and hospital products | F16: Varies by product | G16: Varies | H16: Retail and/or hospitals | I16: Residual portfolio | J16: Included in listed-company model
A17: Cardiovascular and anticoagulation | B17: Eliquis | C17: Apixaban | D17: Oral factor Xa anticoagulant | E17: Atrial fibrillation and venous thromboembolism | F17: Cardiologists and physicians; chronic patients | G17: Chronic | H17: Retail and hospitals | I17: Core cardiovascular growth brand | J17: Listed Pfizer marketer
... A40: Other established products | B40: Other established products | C40: Multiple | D40: Portfolio line or residual grouping | E40: Products within Other established products | F40: Varies by product | G40: Varies | H40: Retail and/or hospitals | I40: Residual portfolio | J40: Included in listed-company model
A43: Private-entity products excluded from the listed-company model
A44: Therapy | B44: Brand | C44: Molecule | D44: What it is | E44: What it treats | F44: Typical prescriber / patient | G44: Use | H44: Channel | I44: Portfolio role | J44: Ownership note
A45: Oncology | B45: Palbace | C45: Palbociclib | D45: Oral CDK4/6 inhibitor | E45: HR-positive, HER2-negative advanced breast cancer | F45: Oncologists; biomarker-selected patients | G45: Chronic cycles | H45: Oncology | I45: Established targeted therapy | J45: PPIPL; excluded
A46: Hospital / inflammation | B46: Solu-Medrol | C46: Methylprednisolone sodium succinate | D46: Intravenous corticosteroid | E46: Severe inflammatory, allergic and autoimmune conditions | F46: Hospital physicians | G46: Acute | H46: Hospitals | I46: Established hospital product | J46: PPIPL; excluded
A47: Rare disease | B47: Xyntha | C47: Recombinant factor VIII | D47: Clotting-factor replacement | E47: Haemophilia A | F47: Haematologists; haemophilia patients | G47: Repeated prophylaxis or on demand | H47: Specialty hospitals | I47: Rare-disease product | J47: PPIPL; excluded
A48: Anti-infectives | B48: Dalacin C | C48: Clindamycin | D48: Lincosamide antibiotic | E48: Susceptible bacterial infections | F48: General physicians and specialists | G48: Acute | H48: Retail and hospitals | I48: Cipla-commercialised private brand | J48: PPIPL; excluded
A49: Endocrine | B49: Genotropin | C49: Somatropin | D49: Recombinant human growth hormone | E49: Growth-hormone deficiency and related conditions | F49: Paediatric endocrinologists | G49: Chronic | H49: Specialty retail | I49: Rare endocrine product | J49: PPIPL; excluded
A50: Anti-infectives | B50: VFEND | C50: Voriconazole | D50: Triazole antifungal | E50: Serious invasive fungal infections | F50: Infectious-disease specialists | G50: Acute or extended | H50: Hospitals | I50: Specialty hospital product | J50: PPIPL; excluded
A51: Oncology | B51: Crizalk | C51: Crizotinib | D51: ALK and ROS1 tyrosine-kinase inhibitor | E51: Molecularly selected lung cancer | F51: Oncologists | G51: Chronic | H51: Oncology | I51: Targeted therapy | J51: PPIPL; excluded
A52: Oncology | B52: Inlyta | C52: Axitinib | D52: VEGFR tyrosine-kinase inhibitor | E52: Advanced renal-cell carcinoma | F52: Oncologists | G52: Chronic | H52: Oncology | I52: Targeted therapy | J52: PPIPL; excluded
A53: Inflammation | B53: Depo-Medrol | C53: Methylprednisolone acetate | D53: Depot corticosteroid injection | E53: Inflammatory and allergic conditions | F53: Physicians and specialists | G53: Acute or episodic | H53: Clinics and hospitals | I53: Established injectable | J53: PPIPL; excluded
A54: Rare disease / hospital | B54: Atgam | C54: Equine antithymocyte globulin | D54: Polyclonal immunosuppressive antibody | E54: Severe aplastic anaemia and selected transplant use | F54: Haematologists and transplant specialists | G54: Acute course | H54: Tertiary hospitals | I54: Rare hospital therapy | J54: PPIPL; excluded
